Workbook
Name __MIN2016: #REF!
Name __PRC1: #REF!
Name _20EURRATE: #REF!
Name _20EURRATE: #REF!
Name _CRN1: [6]Dimensions!#REF!
Name _CRN2: [6]Dimensions!#REF!
Name _DAT4: '[7]Tab 01'!#REF!
Name _LCP2: #REF!
Name _LinkPic_45022E3A814A4CCE8C24E4AE23F9E450: #REF!
Name _ric2: #REF!
Name _ric3: #REF!
Name _TVA1098: #REF!
Name Account_codes: [10]Descriptions!$D$1:$H$787
Name Account_codes: [11]Descriptions!$D$1:$H$787
Name ACE: #REF!
Name AEngagHB: #REF!
Name Andep: [12]GEFFGL!$H$2
Name ANNEE: [13]Feuil1!$B$1
Name Année2: [14]Hypothèses!$E$8
Name Année3: [14]Hypothèses!$E$9
Name ANNEEbis: [13]Feuil1!$B$1
Name archCost: #REF!
Name archCost: #REF!
Name AREP: #REF!
Name AshfordLeaseAssetCfProfile: '[15]nfm-f670-d158 (GreenSpeed)'!#REF!
Name AshfordLeaseAssetCfProfile: '[16]nfm-f670-d158 (GreenSpeed)'!#REF!
Name AshfordLeaseAssetCfProfile: '[16]nfm-f670-d158 (GreenSpeed)'!#REF!
Name AshfordLeaseCurrentAssetCfProfile: '[15]nfm-f670-d158 (GreenSpeed)'!#REF!
Name AshfordLeaseCurrentAssetCfProfile: '[16]nfm-f670-d158 (GreenSpeed)'!#REF!
Name AshfordLeaseCurrentAssetCfProfile: '[16]nfm-f670-d158 (GreenSpeed)'!#REF!
Name AshfordLeaseLongTermCreditorCfProfile: '[15]nfm-f670-d158 (GreenSpeed)'!#REF!
Name AshfordLeaseLongTermCreditorCfProfile: '[16]nfm-f670-d158 (GreenSpeed)'!#REF!
Name AshfordLeaseLongTermCreditorCfProfile: '[16]nfm-f670-d158 (GreenSpeed)'!#REF!
Name AshfordLeaseNonCurrentAssetCfProfile: '[15]nfm-f670-d158 (GreenSpeed)'!#REF!
Name AshfordLeaseNonCurrentAssetCfProfile: '[16]nfm-f670-d158 (GreenSpeed)'!#REF!
Name AshfordLeaseNonCurrentAssetCfProfile: '[16]nfm-f670-d158 (GreenSpeed)'!#REF!
Name AshfordLeaseShortTermCreditorCfProfile: '[15]nfm-f670-d158 (GreenSpeed)'!#REF!
Name AshfordLeaseShortTermCreditorCfProfile: '[16]nfm-f670-d158 (GreenSpeed)'!#REF!
Name AuditFailsStructural: [17]Audit!$F$19
Name AuditFailsStructural: [18]Audit!$F$19
Name axedoc: '[19]passage ca soc-conso'!#REF!
Name azds: [13]Feuil1!$B$1
Name azeas: #REF!
Name azsz: #REF!
Name b: [20]PowerPoint!$D$16
Name Base2: #REF!
Name BaseScenarios: #REF!
Name bb: [21]PowerPoint!$D$16
Name bd: #REF!
Name BELALL1: [22]offre!$K$11
Name BELALL2: [22]offre!$K$12
Name BF_CAVA_PBA_01: '[23]Trains Week'!$C$92
Name BF_CAVA_PBA_02: '[23]Trains Week'!$D$92
Name BF_CAVA_PBA_03: '[23]Trains Week'!$E$92
Name BF_CAVB_MLV_01: '[23]Trains Week'!$C$116
Name BF_CAVB_MLV_02: '[23]Trains Week'!$D$116
Name BF_CAVB_MLV_03: '[23]Trains Week'!$E$116
Name BF_CAVB_PB_01: '[23]Trains Week'!$C$44
Name BF_CAVB_PB_02: '[23]Trains Week'!$D$44
Name BF_CAVB_PB_03: '[23]Trains Week'!$E$44

Sheet Contents
C3: 1 | D3: Budget 2026 Overview | E3: Overview of budget 2026
C4: 2.1 | D4: EIL Opex Costs | E4: Detail of opex in EIL for budget 2026 downloaded directly from financial system.
C5: 2.2 | D5: EIL Cost of Sales | E5: Detail of Cost of sales in EIL for budget 2026 downloaded directly from financial system.
C6: 2.3 | D6: EIL Capex | E6: Detail of Capex in EIL for budget 2026 downloaded directly from financial system.
C7: 3.1 | D7: THIF Opex Costs | E7: Detail of opex in THIF for budget 2026 downloaded directly from financial system.
C8: 3.2 | D8: THIF Cost of Sales | E8: Detail of Cost of sales in THIF for budget 2026 downloaded directly from financial system.
C9: 3.3 | D9: THIF Capex | E9: Detail of Capex in THIF for budget 2026 downloaded directly from financial system.
C10: 4.1 | D10: Simplify Savings | E10: Detail of any simplify savings included in budget 2026 (where applicable)
C11: 4.2 | D11: Simplify Investments | E11: Detail of any simplify investments included in budget 2026 (where applicable)
C12: 5 | D12: FX Rates

Sheet 1. Budget Overview (EUR)
C3: 2026 Budget (excluding simplify) | D3: EIL Budget (excluding simplify) | E3: THIF Budget (excluding simplify) | F3: Simplify savings | G3: EIL Simplify savings | H3: THIF Simplify savings | I3: Simplify investments | J3: 2026 Budget | K3: EIL | L3: THIF | N3: 2026 Budget (2025 rates)
B4: Revenue | O4: n/a - no revenue in budget 2026
B5: Cost of Sales | C5: =SUM(D5:E5) -> 17397371 | D5: ='2.2 EIL COS'!Z3 -> 13274936 | E5: ='3.2 THIF COS'!S1 -> 4122434.5 | J5: =C5+F5+I5 -> 17397371 | K5: =D5+G5+I5 -> 13274936 | L5: =H5+E5 -> 4122434.5 | O5: n/a - no cost of sales in budget 2026
B6: Opex (excluding staff costs) | C6: =SUM(D6:E6) -> 42678201 | D6: ='2.1 EIL Opex'!AB3 -> 22117348 | E6: ='3.1 THIF Opex'!S1 -> 20560853 | F6: =SUM(G6:H6) -> -4356483.2 | G6: ='4.2 Simplify Savings'!AB1 -> -2533219.1 | H6: ='4.2 Simplify Savings'!AB47 -> -1823264 | I6: ='4.1 Simplify Investments '!AB1-I8 -> 466500 | J6: =C6+F6+I6 -> 38788218 | K6: =D6+G6+I6 -> 20050629 | L6: =H6+E6 -> 18737589 | M6: << opex excluding FTE related staff costs | N6: =SUM('[73]8. Group Opex Detail (€ 2025)'!S3:S7) -> 531381.65
B7: Staff costs | C7: =SUM(D7:E7) -> 14577171 | D7: =SUM('Report Data'!C34:C44,'Report Data'!D45)-'4.2 Simplify Savings'!AB3 -> 12081201 | E7: =SUM('Report Data'!C23:C33) -> 2495969.6 | F7: =SUM(G7:H7) -> -125583.48 | G7: ='4.2 Simplify Savings'!AB3 -> -125583.48 | J7: =C7+F7+I7 -> 14451588 | M7: << staff costs are shown net of FTE related simplify savings | O7: << total wageroll cost to be added (post simplify)
B8: Capex | C8: =SUM(D8:E8) -> 31261811 | D8: ='2.3 EIL Capex '!AP3 -> 26992811 | E8: ='3.3 THIF Capex'!F2 -> 4269000 | I8: =SUM('4.1 Simplify Investments '!AB8:AB12) -> 466500 | J8: =C8+F8+I8 -> 31728311 | K8: =D8+G8+I8 -> 27459311 | L8: =H8+E8 -> 4269000 | O8: n/a - no capex in budget 2026

Sheet 2.1 EIL Opex
AA3: Total | AB3: =SUBTOTAL(9,AB5:AB184) -> 22117348 | AC3: =SUBTOTAL(9,AC5:AC184) -> -2533219.1 | AD3: =SUBTOTAL(9,AD5:AD184) -> 19584129
A4: Cost center manager | B4: Is Split Child Row | C4: Level Code | D4: Level Name | E4: Account Code Code | F4: Account Code Name | G4: Counterparty Code | H4: Counterparty Name | I4: Project Code | J4: Project Name | K4: Details (Free Text) | L4: Supplier (Free Text) | M4: Version (Free Text) | N4: Currency | O4: Jan-2026 | P4: Feb-2026 | Q4: Mar-2026 | R4: Apr-2026 | S4: May-2026 | T4: Jun-2026 | U4: Jul-2026 | V4: Aug-2026 | W4: Sep-2026 | X4: Oct-2026 | Y4: Nov-2026 | Z4: Dec-2026 | AA4: FY2026 | AB4: cost in euros | AC4: Simplify savings | AD4: Total after Simplify | AF4: << Column AA and AB are net of Simplify savings and show the allowable spend for budget 2026. Column AD is the budget before simplify with column AC showing the effort to be made per line.
A5: =_xlfn.XLOOKUP(B5*1,'Reference '!I:I,'Reference '!K:K) -> Paolo Rodeghiero | B5: =LEFT(C5,3) -> 608 | C5: 608_Data & Middleware_EIL_EUR | D5: 608_Data & Middleware_EIL_EUR | E5: 305001 - Agency staff & contractors (STATIONS ONLY) | F5: 305001 - Agency staff & contractors (STATIONS ONLY) | G5: 000000_Default | H5: 000000_Default | I5: 0000_Default | J5: 0000_Default | K5: BI Center of Excellence | M5: Budget 2026 | N5: EUR | O5: 23333 | P5: 23333 | Q5: 23333 | R5: 23333 | S5: 23333 | T5: 23333 | U5: 23333 | V5: 23333 | W5: 23333 | X5: 23333 | Y5: 23333 | Z5: 23333 | AA5: 279996 | AB5: =IF(N5="EUR",AA5,IF(N5="GBP",AA5/Rate!$C$3,AA5/Rate!$C$5)) -> 279996 | AC5: =IFERROR(VLOOKUP(K5,'4.2 Simplify Savings'!K:AB,19,0),0) -> 0 | AD5: =SUM(AB5:AC5) -> 279996
A6: =_xlfn.XLOOKUP(B6*1,'Reference '!I:I,'Reference '!K:K) -> Ben Gbeve | B6: =LEFT(C6,3) -> 601 | C6: 601_IS Service Delivery_EIL_GBP | D6: 601_IS Service Delivery_EIL_GBP | E6: 307001 - Staff entertainment | F6: 307001 - Staff entertainment | G6: 000000_Default | H6: 000000_Default | I6: 0000_Default | J6: 0000_Default | K6: Expenses | L6: Various | M6: Budget 2026 | N6: GBP | O6: 150 | P6: 150 | Q6: 150 | R6: 150 | S6: 150 | T6: 150 | U6: 150 | V6: 150 | W6: 150 | X6: 150 | Y6: 150 | Z6: 150 | AA6: 1800 | AB6: =IF(N6="EUR",AA6,IF(N6="GBP",AA6/Rate!$C$3,AA6/Rate!$C$5)) -> 2068.9655 | AC6: =IFERROR(VLOOKUP(K6,'4.2 Simplify Savings'!K:AB,18,0),0) -> 0 | AD6: =SUM(AB6:AC6) -> 2068.9655
A7: =_xlfn.XLOOKUP(B7*1,'Reference '!I:I,'Reference '!K:K) -> Laurent Bellan | B7: =LEFT(C7,3) -> 600 | C7: 600_CIO_EIL_EUR | D7: 600_CIO_EIL_EUR | E7: 307200 - Training | F7: 307200 - Training | G7: 000000_Default | H7: 000000_Default | I7: 0000_Default | J7: 0000_Default | K7: Training | M7: Budget 2026 | N7: EUR | O7: 8443.06 | P7: 8443.06 | Q7: 8443.06 | R7: 8443.06 | S7: 8443.06 | T7: 8443.06 | U7: 8443.06 | V7: 8443.06 | W7: 8443.06 | X7: 8443.06 | Y7: 8443.06 | Z7: 8443.06 | AA7: 101316.72 | AB7: =IF(N7="EUR",AA7,IF(N7="GBP",AA7/Rate!$C$3,AA7/Rate!$C$5)) -> 101316.72 | AC7: =IFERROR(VLOOKUP(K7,'4.2 Simplify Savings'!K:AB,18,0),0) -> 0 | AD7: =SUM(AB7:AC7) -> 101316.72
A8: =_xlfn.XLOOKUP(B8*1,'Reference '!I:I,'Reference '!K:K) -> Ben Gbeve | B8: =LEFT(C8,3) -> 601 | C8: 601_IS Service Delivery_EIL_GBP | D8: 601_IS Service Delivery_EIL_GBP | E8: 307200 - Training | F8: 307200 - Training | G8: 000000_Default | H8: 000000_Default | I8: 0000_Default | J8: 0000_Default | K8: Training | L8: Various | M8: Budget 2026 | N8: GBP | O8: 1000 | P8: 1000 | Q8: 1000 | R8: 1000 | S8: 1000 | T8: 1000 | U8: 1000 | V8: 1000 | W8: 1000 | X8: 1000 | Y8: 1000 | Z8: 1000 | AA8: 12000 | AB8: =IF(N8="EUR",AA8,IF(N8="GBP",AA8/Rate!$C$3,AA8/Rate!$C$5)) -> 13793.103 | AC8: =IFERROR(VLOOKUP(K8,'4.2 Simplify Savings'!K:AB,18,0),0) -> 0 | AD8: =SUM(AB8:AC8) -> 13793.103
A9: =_xlfn.XLOOKUP(B9*1,'Reference '!I:I,'Reference '!K:K) -> Xavier Romanet | B9: =LEFT(C9,3) -> 605 | C9: 605_IS Sales System_EIL_GBP | D9: 605_IS Sales System_EIL_GBP | E9: 307200 - Training | F9: 307200 - Training | G9: 000000_Default | H9: 000000_Default | I9: 0000_Default | J9: 0000_Default | K9: Training budget for increased team-wide knowledge | L9: Various | M9: 5+7 2024 & Budget 25 | N9: GBP | Y9: 833 | Z9: 833 | AA9: 1666 | AB9: =IF(N9="EUR",AA9,IF(N9="GBP",AA9/Rate!$C$3,AA9/Rate!$C$5)) -> 1914.9425 | AC9: =IFERROR(VLOOKUP(K9,'4.2 Simplify Savings'!K:AB,18,0),0) -> 0 | AD9: =SUM(AB9:AC9) -> 1914.9425
A10: =_xlfn.XLOOKUP(B10*1,'Reference '!I:I,'Reference '!K:K) -> Ben Gbeve | B10: =LEFT(C10,3) -> 601 | C10: 601_IS Service Delivery_EIL_GBP | D10: 601_IS Service Delivery_EIL_GBP | E10: 340001 - Local Area Network (LAN) | F10: 340001 - Local Area Network (LAN) | G10: 000000_Default | H10: 000000_Default | I10: 0000_Default | J10: 0000_Default | K10: SPI Terminal Wi-Fi | L10: WIFI METROPOLIS BV | M10: Budget 2026 | N10: GBP | O10: 2175 | P10: 2175 | Q10: 2175 | R10: 2175 | S10: 2175 | T10: 2175 | U10: 2175 | V10: 2175 | W10: 2175 | X10: 2175 | Y10: 2175 | Z10: 2175 | AA10: 26100 | AB10: =IF(N10="EUR",AA10,IF(N10="GBP",AA10/Rate!$C$3,AA10/Rate!$C$5)) -> 30000 | AC10: =IFERROR(VLOOKUP(K10,'4.2 Simplify Savings'!K:AB,18,0),0) -> 0 | AD10: =SUM(AB10:AC10) -> 30000
A11: =_xlfn.XLOOKUP(B11*1,'Reference '!I:I,'Reference '!K:K) -> Ben Gbeve | B11: =LEFT(C11,3) -> 601 | C11: 601_IS Service Delivery_EIL_GBP | D11: 601_IS Service Delivery_EIL_GBP | E11: 340001 - Local Area Network (LAN) | F11: 340001 - Local Area Network (LAN) | G11: 000000_Default | H11: 000000_Default | I11: 0000_Default | J11: 0000_Default | K11: New Amsterdam Terminal Wi-Fi | L11: Natilik | M11: Budget 2026 | N11: GBP | O11: 670 | P11: 670 | Q11: 670 | R11: 670 | S11: 670 | T11: 670 | U11: 670 | V11: 670 | W11: 670 | X11: 670 | Y11: 670 | Z11: 670 | AA11: 8040 | AB11: =IF(N11="EUR",AA11,IF(N11="GBP",AA11/Rate!$C$3,AA11/Rate!$C$5)) -> 9241.3793 | AC11: =IFERROR(VLOOKUP(K11,'4.2 Simplify Savings'!K:AB,18,0),0) -> 0 | AD11: =SUM(AB11:AC11) -> 9241.3793
A12: =_xlfn.XLOOKUP(B12*1,'Reference '!I:I,'Reference '!K:K) -> Ben Gbeve | B12: =LEFT(C12,3) -> 601 | C12: 601_IS Service Delivery_EIL_GBP | D12: 601_IS Service Delivery_EIL_GBP | E12: 340001 - Local Area Network (LAN) | F12: 340001 - Local Area Network (LAN) | G12: 000000_Default | H12: 000000_Default | I12: 0000_Default | J12: 0000_Default | K12: Network swtiches at all locations | L12: Meraki and Others | M12: Budget 2026 | N12: GBP | O12: 6350 | P12: 6350 | Q12: 6350 | R12: 6350 | S12: 6350 | T12: 6350 | U12: 6350 | V12: 6350 | W12: 6350 | X12: 6350 | Y12: 6350 | Z12: 6350 | AA12: 76200 | AB12: =IF(N12="EUR",AA12,IF(N12="GBP",AA12/Rate!$C$3,AA12/Rate!$C$5)) -> 87586.207 | AC12: =IFERROR(VLOOKUP(K12,'4.2 Simplify Savings'!K:AB,18,0),0) -> 0 | AD12: =SUM(AB12:AC12) -> 87586.207
A13: =_xlfn.XLOOKUP(B13*1,'Reference '!I:I,'Reference '!K:K) -> Ben Gbeve | B13: =LEFT(C13,3) -> 601 | C13: 601_IS Service Delivery_EIL_GBP | D13: 601_IS Service Delivery_EIL_GBP | E13: 340001 - Local Area Network (LAN) | F13: 340001 - Local Area Network (LAN) | G13: 000000_Default | H13: 000000_Default | I13: 0000_Default | J13: 0000_Default | K13: Firewall including Phsical/Cloud Palo Alto Support | L13: BYTES | M13: Budget 2026 | N13: GBP | O13: 6917 | P13: 6917 | Q13: 6917 | R13: 6917 | S13: 6917 | T13: 6917 | U13: 6917 | V13: 6917 | W13: 6917 | X13: 6917 | Y13: 6917 | Z13: 6917 | AA13: 83004 | AB13: =IF(N13="EUR",AA13,IF(N13="GBP",AA13/Rate!$C$3,AA13/Rate!$C$5)) -> 95406.897 | AC13: =IFERROR(VLOOKUP(K13,'4.2 Simplify Savings'!K:AB,18,0),0) -> -40860 | AD13: =SUM(AB13:AC13) -> 54546.897
A14: =_xlfn.XLOOKUP(B14*1,'Reference '!I:I,'Reference '!K:K) -> Ben Gbeve | B14: =LEFT(C14,3) -> 601 | C14: 601_IS Service Delivery_EIL_GBP | D14: 601_IS Service Delivery_EIL_GBP | E14: 340001 - Local Area Network (LAN) | F14: 340001 - Local Area Network (LAN) | G14: 000000_Default | H14: 000000_Default | I14: 0000_Default | J14: 0000_Default | K14: ClearPass Wi-Fi Controllers & Aruba - Now replaced by licences for Cisco ISE | L14: ASP | M14: Budget 2026 | N14: GBP | O14: 4000 | P14: 4000 | Q14: 4000 | R14: 4000 | S14: 4000 | T14: 4000 | U14: 4000 | V14: 4000 | W14: 4000 | X14: 4000 | Y14: 4000 | Z14: 4000 | AA14: 48000 | AB14: =IF(N14="EUR",AA14,IF(N14="GBP",AA14/Rate!$C$3,AA14/Rate!$C$5)) -> 55172.414 | AC14: =IFERROR(VLOOKUP(K14,'4.2 Simplify Savings'!K:AB,18,0),0) -> -27240 | AD14: =SUM(AB14:AC14) -> 27932.414
A15: =_xlfn.XLOOKUP(B15*1,'Reference '!I:I,'Reference '!K:K) -> Ben Gbeve | B15: =LEFT(C15,3) -> 601 | C15: 601_IS Service Delivery_EIL_GBP | D15: 601_IS Service Delivery_EIL_GBP | E15: 340100 - Communication rooms | F15: 340100 - Communication rooms | G15: 000000_Default | H15: 000000_Default | I15: 0000_Default | J15: 0000_Default | K15: Provision to maitain comms rooms (UPS, disposals, etc) | L15: SECURE POWER / Others | M15: Budget 2026 | N15: GBP | O15: 2500 | P15: 2500 | Q15: 2500 | R15: 2500 | S15: 2500 | T15: 2500 | U15: 2500 | V15: 2500 | W15: 2500 | X15: 2500 | Y15: 2500 | Z15: 2500 | AA15: 30000 | AB15: =IF(N15="EUR",AA15,IF(N15="GBP",AA15/Rate!$C$3,AA15/Rate!$C$5)) -> 34482.759 | AC15: =IFERROR(VLOOKUP(K15,'4.2 Simplify Savings'!K:AB,18,0),0) -> 0 | AD15: =SUM(AB15:AC15) -> 34482.759
A16: =_xlfn.XLOOKUP(B16*1,'Reference '!I:I,'Reference '!K:K) -> Ben Gbeve | B16: =LEFT(C16,3) -> 601 | C16: 601_IS Service Delivery_EIL_GBP | D16: 601_IS Service Delivery_EIL_GBP | E16: 340200 - Computer / NIIT | F16: 340200 - Computer / NIIT | G16: 000000_Default | H16: 000000_Default | I16: 0000_Default | J16: 0000_Default | K16: Managed Service Provider - Amsterdam Coverage | L16: HEXAWARE | M16: Budget 2026 | N16: GBP | O16: 5416.67 | P16: 5416.67 | Q16: 5416.67 | R16: 5416.67 | S16: 5416.67 | T16: 5416.67 | U16: 5416.67 | V16: 5416.67 | W16: 5416.67 | X16: 5416.67 | Y16: 5416.67 | Z16: 5416.67 | AA16: 65000.04 | AB16: =IF(N16="EUR",AA16,IF(N16="GBP",AA16/Rate!$C$3,AA16/Rate!$C$5)) -> 74712.69 | AC16: =IFERROR(VLOOKUP(K16,'4.2 Simplify Savings'!K:AB,18,0),0) -> 0 | AD16: =SUM(AB16:AC16) -> 74712.69
A17: =_xlfn.XLOOKUP(B17*1,'Reference '!I:I,'Reference '!K:K) -> Ben Gbeve | B17: =LEFT(C17,3) -> 601 | C17: 601_IS Service Delivery_EIL_GBP | D17: 601_IS Service Delivery_EIL_GBP | E17: 340200 - Computer / NIIT | F17: 340200 - Computer / NIIT | G17: 000000_Default | H17: 000000_Default | I17: 0000_Default | J17: 0000_Default | K17: Managed Service Provider - Arc/Rcs variations | L17: HEXAWARE | M17: Budget 2026 | N17: GBP | O17: 8333.33 | P17: 8333.33 | Q17: 8333.33 | R17: 8333.33 | S17: 8333.33 | T17: 8333.33 | U17: 8333.33 | V17: 8333.33 | W17: 8333.33 | X17: 8333.33 | Y17: 8333.33 | Z17: 8333.33 | AA17: 99999.96 | AB17: =IF(N17="EUR",AA17,IF(N17="GBP",AA17/Rate!$C$3,AA17/Rate!$C$5)) -> 114942.48 | AC17: =IFERROR(VLOOKUP(K17,'4.2 Simplify Savings'!K:AB,18,0),0) -> 0 | AD17: =SUM(AB17:AC17) -> 114942.48
A18: =_xlfn.XLOOKUP(B18*1,'Reference '!I:I,'Reference '!K:K) -> Ben Gbeve | B18: =LEFT(C18,3) -> 601 | C18: 601_IS Service Delivery_EIL_GBP | D18: 601_IS Service Delivery_EIL_GBP | E18: 340200 - Computer / NIIT | F18: 340200 - Computer / NIIT | G18: 000000_Default | H18: 000000_Default | I18: 0000_Default | J18: 0000_Default | K18: Managed Service Provider - Core Service Charge (BAU & Tx) | L18: HEXAWARE | M18: Budget 2026 | N18: GBP | O18: 149382 | P18: 149382 | Q18: 149382 | R18: 149382 | S18: 149382 | T18: 149382 | U18: 149382 | V18: 149382 | W18: 149382 | X18: 149382 | Y18: 149382 | Z18: 149382 | AA18: 1792584 | AB18: =IF(N18="EUR",AA18,IF(N18="GBP",AA18/Rate!$C$3,AA18/Rate!$C$5)) -> 2060441.4 | AC18: ='4.2 Simplify Savings'!$AB$5 -> -135757.32 | AD18: =SUM(AB18:AC18) -> 1924684.1
A19: =_xlfn.XLOOKUP(B19*1,'Reference '!I:I,'Reference '!K:K) -> Ben Gbeve | B19: =LEFT(C19,3) -> 601 | C19: 601_IS Service Delivery_EIL_GBP | D19: 601_IS Service Delivery_EIL_GBP | E19: 340200 - Computer / NIIT | F19: 340200 - Computer / NIIT | G19: 000000_Default | H19: 000000_Default | I19: 0000_Default | J19: 0000_Default | K19: Managed Service Provider - Non BAU | L19: HEXAWARE | M19: Budget 2026 | N19: GBP | O19: 11250 | P19: 11250 | Q19: 11250 | R19: 11250 | S19: 11250 | T19: 11250 | U19: 11250 | V19: 11250 | W19: 11250 | X19: 11250 | Y19: 11250 | Z19: 11250 | AA19: 135000 | AB19: =IF(N19="EUR",AA19,IF(N19="GBP",AA19/Rate!$C$3,AA19/Rate!$C$5)) -> 155172.41 | AC19: =IFERROR(VLOOKUP(K19,'4.2 Simplify Savings'!K:AB,18,0),0) -> 0 | AD19: =SUM(AB19:AC19) -> 155172.41
A20: =_xlfn.XLOOKUP(B20*1,'Reference '!I:I,'Reference '!K:K) -> Ben Gbeve | B20: =LEFT(C20,3) -> 601 | C20: 601_IS Service Delivery_EIL_GBP | D20: 601_IS Service Delivery_EIL_GBP | E20: 340200 - Computer / NIIT | F20: 340200 - Computer / NIIT | G20: 000000_Default | H20: 000000_Default | I20: 0000_Default | J20: 0000_Default | K20: Managed Service Provider - TUPE Provision | L20: HEXAWARE | M20: Budget 2026 | N20: GBP | O20: 7900 | P20: 7900 | Q20: 7900 | R20: 7900 | S20: 7900 | T20: 7900 | U20: 7900 | V20: 7900 | W20: 7900 | X20: 7900 | Y20: 7900 | Z20: 7900 | AA20: 94800 | AB20: =IF(N20="EUR",AA20,IF(N20="GBP",AA20/Rate!$C$3,AA20/Rate!$C$5)) -> 108965.52 | AC20: =IFERROR(VLOOKUP(K20,'4.2 Simplify Savings'!K:AB,18,0),0) -> 0 | AD20: =SUM(AB20:AC20) -> 108965.52
A21: =_xlfn.XLOOKUP(B21*1,'Reference '!I:I,'Reference '!K:K) -> Ben Gbeve | B21: =LEFT(C21,3) -> 601 | C21: 601_IS Service Delivery_EIL_GBP | D21: 601_IS Service Delivery_EIL_GBP | E21: 340200 - Computer / NIIT | F21: 340200 - Computer / NIIT | G21: 000000_Default | H21: 000000_Default | I21: 0000_Default | J21: 0000_Default | K21: Managed Service Provider - Application Support | L21: COFORGE U.K. LIMITED- | M21: Budget 2026 | N21: GBP | O21: 2900 | P21: 2900 | Q21: 2900 | R21: 2900 | S21: 2900 | T21: 2900 | U21: 2900 | V21: 2900 | W21: 2900 | X21: 2900 | Y21: 2900 | Z21: 2900 | AA21: 34800 | AB21: =IF(N21="EUR",AA21,IF(N21="GBP",AA21/Rate!$C$3,AA21/Rate!$C$5)) -> 40000 | AC21: =IFERROR(VLOOKUP(K21,'4.2 Simplify Savings'!K:AB,18,0),0) -> 0 | AD21: =SUM(AB21:AC21) -> 40000
A22: =_xlfn.XLOOKUP(B22*1,'Reference '!I:I,'Reference '!K:K) -> Ben Gbeve | B22: =LEFT(C22,3) -> 601 | C22: 601_IS Service Delivery_EIL_GBP | D22: 601_IS Service Delivery_EIL_GBP | E22: 340300 - IS consumables | F22: 340300 - IS consumables | G22: 000000_Default | H22: 000000_Default | I22: 0000_Default | J22: 0000_Default | K22: Hardware and consumables | L22: Various | M22: Budget 2026 | N22: GBP | O22: 9000 | P22: 9000 | Q22: 9000 | R22: 9000 | S22: 9000 | T22: 9000 | U22: 9000 | V22: 9000 | W22: 9000 | X22: 9000 | Y22: 9000 | Z22: 9000 | AA22: 108000 | AB22: =IF(N22="EUR",AA22,IF(N22="GBP",AA22/Rate!$C$3,AA22/Rate!$C$5)) -> 124137.93 | AC22: =IFERROR(VLOOKUP(K22,'4.2 Simplify Savings'!K:AB,18,0),0) -> 0 | AD22: =SUM(AB22:AC22) -> 124137.93
A23: =_xlfn.XLOOKUP(B23*1,'Reference '!I:I,'Reference '!K:K) -> Ben Gbeve | B23: =LEFT(C23,3) -> 601 | C23: 601_IS Service Delivery_EIL_GBP | D23: 601_IS Service Delivery_EIL_GBP | E23: 340400 - IS Hardware maintenance & support | F23: 340400 - IS Hardware maintenance & support | G23: 000000_Default | H23: 000000_Default | I23: 0000_Default | J23: 0000_Default | K23: Call out & repair of display / meeting room systems | L23: SOLUTIONS AUDIO VISUAL LIMITED | M23: Budget 2026 | N23: GBP | O23: 3230 | P23: 3230 | Q23: 3230 | R23: 3230 | S23: 3230 | T23: 3230 | U23: 3230 | V23: 3230 | W23: 3230 | X23: 3230 | Y23: 3230 | Z23: 3230 | AA23: 38760 | AB23: =IF(N23="EUR",AA23,IF(N23="GBP",AA23/Rate!$C$3,AA23/Rate!$C$5)) -> 44551.724 | AC23: =IFERROR(VLOOKUP(K23,'4.2 Simplify Savings'!K:AB,18,0),0) -> 0 | AD23: =SUM(AB23:AC23) -> 44551.724
A24: =_xlfn.XLOOKUP(B24*1,'Reference '!I:I,'Reference '!K:K) -> Ben Gbeve | B24: =LEFT(C24,3) -> 601 | C24: 601_IS Service Delivery_EIL_GBP | D24: 601_IS Service Delivery_EIL_GBP | E24: 340400 - IS Hardware maintenance & support | F24: 340400 - IS Hardware maintenance & support | G24: 000000_Default | H24: 000000_Default | I24: 0000_Default | J24: 0000_Default | K24: Stand alone printer | L24: Printer Support | M24: Budget 2026 | N24: GBP | O24: 495.42 | P24: 495.42 | Q24: 495.42 | R24: 495.42 | S24: 495.42 | T24: 495.42 | U24: 495.42 | V24: 495.42 | W24: 495.42 | X24: 495.42 | Y24: 495.42 | Z24: 495.42 | AA24: 5945.04 | AB24: =IF(N24="EUR",AA24,IF(N24="GBP",AA24/Rate!$C$3,AA24/Rate!$C$5)) -> 6833.3793 | AC24: =IFERROR(VLOOKUP(K24,'4.2 Simplify Savings'!K:AB,18,0),0) -> 0 | AD24: =SUM(AB24:AC24) -> 6833.3793
A25: =_xlfn.XLOOKUP(B25*1,'Reference '!I:I,'Reference '!K:K) -> Ben Gbeve | B25: =LEFT(C25,3) -> 601 | C25: 601_IS Service Delivery_EIL_GBP | D25: 601_IS Service Delivery_EIL_GBP | E25: 340400 - IS Hardware maintenance & support | F25: 340400 - IS Hardware maintenance & support | G25: 000000_Default | H25: 000000_Default | I25: 0000_Default | J25: 0000_Default | K25: Teleohony at TMI (Siemens PBX) | L25: ELITETELE.COM PLC T/A ELITE GROUP | M25: Budget 2026 | N25: GBP | O25: 583.33 | P25: 583.33 | Q25: 583.33 | R25: 583.33 | S25: 583.33 | T25: 583.33 | U25: 583.33 | V25: 583.33 | W25: 583.33 | X25: 583.33 | Y25: 583.33 | Z25: 583.33 | AA25: 6999.96 | AB25: =IF(N25="EUR",AA25,IF(N25="GBP",AA25/Rate!$C$3,AA25/Rate!$C$5)) -> 8045.931 | AC25: =IFERROR(VLOOKUP(K25,'4.2 Simplify Savings'!K:AB,18,0),0) -> 0 | AD25: =SUM(AB25:AC25) -> 8045.931
A26: =_xlfn.XLOOKUP(B26*1,'Reference '!I:I,'Reference '!K:K) -> Ben Gbeve | B26: =LEFT(C26,3) -> 601 | C26: 601_IS Service Delivery_EIL_GBP | D26: 601_IS Service Delivery_EIL_GBP | E26: 340400 - IS Hardware maintenance & support | F26: 340400 - IS Hardware maintenance & support | G26: 000000_Default | H26: 000000_Default | I26: 0000_Default | J26: 0000_Default | K26: SST Payement Devices at stations | L26: ADYEN N.V | M26: Budget 2026 | N26: GBP | O26: 436 | P26: 436 | Q26: 436 | R26: 436 | S26: 436 | T26: 436 | U26: 436 | V26: 436 | W26: 436 | X26: 436 | Y26: 436 | Z26: 436 | AA26: 5232 | AB26: =IF(N26="EUR",AA26,IF(N26="GBP",AA26/Rate!$C$3,AA26/Rate!$C$5)) -> 6013.7931 | AC26: =IFERROR(VLOOKUP(K26,'4.2 Simplify Savings'!K:AB,18,0),0) -> 0 | AD26: =SUM(AB26:AC26) -> 6013.7931
A27: =_xlfn.XLOOKUP(B27*1,'Reference '!I:I,'Reference '!K:K) -> Mael Delmas | B27: =LEFT(C27,3) -> 604 | C27: 604_IS Customer Systems_EIL_GBP | D27: 604_IS Customer Systems_EIL_GBP | E27: 340400 - IS Hardware maintenance & support | F27: 340400 - IS Hardware maintenance & support | G27: 000000_Default | H27: 000000_Default | I27: 0000_Default | J27: 0000_Default | K27: [Stations] - Borders - SAS Parafe - maintenance | L27: Thales | M27: Budget 2026 | N27: GBP | O27: 13000 | P27: 13000 | Q27: 13000 | R27: 13000 | S27: 13000 | T27: 13000 | U27: 13000 | V27: 13000 | W27: 13000 | X27: 13000 | Y27: 13000 | Z27: 13000 | AA27: 156000 | AB27: =IF(N27="EUR",AA27,IF(N27="GBP",AA27/Rate!$C$3,AA27/Rate!$C$5)) -> 179310.34 | AC27: =IFERROR(VLOOKUP(K27,'4.2 Simplify Savings'!K:AB,18,0),0) -> 0 | AD27: =SUM(AB27:AC27) -> 179310.34
A28: =_xlfn.XLOOKUP(B28*1,'Reference '!I:I,'Reference '!K:K) -> Mael Delmas | B28: =LEFT(C28,3) -> 604 | C28: 604_IS Customer Systems_EIL_GBP | D28: 604_IS Customer Systems_EIL_GBP | E28: 340400 - IS Hardware maintenance & support | F28: 340400 - IS Hardware maintenance & support | G28: 000000_Default | H28: 000000_Default | I28: 0000_Default | J28: 0000_Default | K28: [Stations] - Ticket Gates maintenance | L28: IER/EASIER | M28: Budget 2026 | N28: GBP | O28: 2600 | P28: 2600 | Q28: 2600 | R28: 2600 | S28: 2600 | T28: 2600 | U28: 2600 | V28: 2600 | W28: 2600 | X28: 2600 | Y28: 2600 | Z28: 2600 | AA28: 31200 | AB28: =IF(N28="EUR",AA28,IF(N28="GBP",AA28/Rate!$C$3,AA28/Rate!$C$5)) -> 35862.069 | AC28: =IFERROR(VLOOKUP(K28,'4.2 Simplify Savings'!K:AB,18,0),0) -> 0 | AD28: =SUM(AB28:AC28) -> 35862.069
A29: =_xlfn.XLOOKUP(B29*1,'Reference '!I:I,'Reference '!K:K) -> Ben Gbeve | B29: =LEFT(C29,3) -> 601 | C29: 601_IS Service Delivery_EIL_EUR | D29: 601_IS Service Delivery_EIL_EUR | E29: 341001 - Global Wide Area Network (GWAN) | F29: 341001 - Global Wide Area Network (GWAN) | G29: 000000_Default | H29: 000000_Default | I29: 0000_Default | J29: 0000_Default | K29: Connection to Tigre for TMI dedicated PCs | L29: HERMES INFORMATION TECHNOLOGY RAIL (HIT RAIL) BV | M29: Budget 2026 | N29: EUR | O29: 4356.25 | P29: 4356.25 | Q29: 4356.25 | R29: 4356.25 | S29: 4356.25 | T29: 4356.25 | U29: 4356.25 | V29: 4356.25 | W29: 4356.25 | X29: 4356.25 | Y29: 4356.25 | Z29: 4356.25 | AA29: 52275 | AB29: =IF(N29="EUR",AA29,IF(N29="GBP",AA29/Rate!$C$3,AA29/Rate!$C$5)) -> 52275 | AC29: =IFERROR(VLOOKUP(K29,'4.2 Simplify Savings'!K:AB,18,0),0) -> 0 | AD29: =SUM(AB29:AC29) -> 52275
A30: =_xlfn.XLOOKUP(B30*1,'Reference '!I:I,'Reference '!K:K) -> Ben Gbeve | B30: =LEFT(C30,3) -> 601 | C30: 601_IS Service Delivery_EIL_GBP | D30: 601_IS Service Delivery_EIL_GBP | E30: 341001 - Global Wide Area Network (GWAN) | F30: 341001 - Global Wide Area Network (GWAN) | G30: 000000_Default | H30: 000000_Default | I30: 0000_Default | J30: 0000_Default | K30: EIL MPLS WAN & Internet Connections | L30: MASERGY COMMUNICATIONS INC | M30: Budget 2026 | N30: GBP | O30: 48085 | P30: 48085 | Q30: 48085 | R30: 48085 | S30: 48085 | T30: 48085 | U30: 48085 | V30: 48085 | W30: 48085 | X30: 48085 | Y30: 48085 | Z30: 48085 | AA30: 577020 | AB30: =IF(N30="EUR",AA30,IF(N30="GBP",AA30/Rate!$C$3,AA30/Rate!$C$5)) -> 663241.38 | AC30: =IFERROR(VLOOKUP(K30,'4.2 Simplify Savings'!K:AB,18,0),0) -> -289425 | AD30: =SUM(AB30:AC30) -> 373816.38
A31: =_xlfn.XLOOKUP(B31*1,'Reference '!I:I,'Reference '!K:K) -> Ben Gbeve | B31: =LEFT(C31,3) -> 601 | C31: 601_IS Service Delivery_EIL_USD | D31: 601_IS Service Delivery_EIL_USD | E31: 341001 - Global Wide Area Network (GWAN) | F31: 341001 - Global Wide Area Network (GWAN) | G31: 000000_Default | H31: 000000_Default | I31: 0000_Default | J31: 0000_Default | K31: SASE Replacement for Masergy MPLS and Security | L31: CATO NETWORKS (Or A N OTHER) | M31: Budget 2026 | N31: USD | R31: 35000 | S31: 35000 | T31: 35000 | U31: 35000 | V31: 35000 | W31: 35000 | X31: 35000 | Y31: 35000 | Z31: 35000 | AA31: 315000 | AB31: =IF(N31="EUR",AA31,IF(N31="GBP",AA31/Rate!$C$3,AA31/Rate!$C$5)) -> 269230.77 | AC31: =IFERROR(VLOOKUP(K31,'4.2 Simplify Savings'!K:AB,18,0),0) -> 0 | AD31: =SUM(AB31:AC31) -> 269230.77
A32: =_xlfn.XLOOKUP(B32*1,'Reference '!I:I,'Reference '!K:K) -> Ben Gbeve | B32: =LEFT(C32,3) -> 601 | C32: 601_IS Service Delivery_EIL_EUR | D32: 601_IS Service Delivery_EIL_EUR | E32: 341100 - Non Global Wide Area Network (GWAN) | F32: 341100 - Non Global Wide Area Network (GWAN) | G32: 000000_Default | H32: 000000_Default | I32: 0000_Default | J32: 0000_Default | K32: Internet in BMI BL Lounge | L32: EUROFIBER N.V. | M32: Budget 2026 | N32: EUR | O32: 385 | P32: 385 | Q32: 385 | R32: 385 | S32: 385 | T32: 385 | U32: 385 | V32: 385 | W32: 385 | X32: 385 | Y32: 385 | Z32: 385 | AA32: 4620 | AB32: =IF(N32="EUR",AA32,IF(N32="GBP",AA32/Rate!$C$3,AA32/Rate!$C$5)) -> 4620 | AC32: =IFERROR(VLOOKUP(K32,'4.2 Simplify Savings'!K:AB,18,0),0) -> -2310 | AD32: =SUM(AB32:AC32) -> 2310
A33: =_xlfn.XLOOKUP(B33*1,'Reference '!I:I,'Reference '!K:K) -> Ben Gbeve | B33: =LEFT(C33,3) -> 601 | C33: 601_IS Service Delivery_EIL_GBP | D33: 601_IS Service Delivery_EIL_GBP | E33: 341100 - Non Global Wide Area Network (GWAN) | F33: 341100 - Non Global Wide Area Network (GWAN) | G33: 000000_Default | H33: 000000_Default | I33: 0000_Default | J33: 0000_Default | K33: Amsterdam Station Internet Access (3yr contract from Dec 2023) | L33: BT BUSINESS COMMUNICATIONS | M33: Budget 2026 | N33: GBP | O33: 3470 | P33: 3470 | Q33: 3470 | R33: 3470 | S33: 3470 | T33: 3470 | U33: 3470 | V33: 3470 | W33: 3470 | X33: 3470 | Y33: 3470 | Z33: 3470 | AA33: 41640 | AB33: =IF(N33="EUR",AA33,IF(N33="GBP",AA33/Rate!$C$3,AA33/Rate!$C$5)) -> 47862.069 | AC33: =IFERROR(VLOOKUP(K33,'4.2 Simplify Savings'!K:AB,18,0),0) -> 0 | AD33: =SUM(AB33:AC33) -> 47862.069
A34: =_xlfn.XLOOKUP(B34*1,'Reference '!I:I,'Reference '!K:K) -> Ben Gbeve | B34: =LEFT(C34,3) -> 601 | C34: 601_IS Service Delivery_EIL_GBP | D34: 601_IS Service Delivery_EIL_GBP | E34: 341100 - Non Global Wide Area Network (GWAN) | F34: 341100 - Non Global Wide Area Network (GWAN) | G34: 000000_Default | H34: 000000_Default | I34: 0000_Default | J34: 0000_Default | K34: Rotterdam Station Internat Access (3yr contract from Oct 2020) | L34: BT BUSINESS COMMUNICATIONS | M34: Budget 2026 | N34: GBP | O34: 930 | P34: 930 | Q34: 930 | R34: 930 | S34: 930 | T34: 930 | U34: 930 | V34: 930 | W34: 930 | X34: 930 | Y34: 930 | Z34: 930 | AA34: 11160 | AB34: =IF(N34="EUR",AA34,IF(N34="GBP",AA34/Rate!$C$3,AA34/Rate!$C$5)) -> 12827.586 | AC34: =IFERROR(VLOOKUP(K34,'4.2 Simplify Savings'!K:AB,18,0),0) -> -9499.95 | AD34: =SUM(AB34:AC34) -> 3327.6362
A35: =_xlfn.XLOOKUP(B35*1,'Reference '!I:I,'Reference '!K:K) -> Ben Gbeve | B35: =LEFT(C35,3) -> 601 | C35: 601_IS Service Delivery_EIL_EUR | D35: 601_IS Service Delivery_EIL_EUR | E35: 341200 - Internet access | F35: 341200 - Internet access | G35: 000000_Default | H35: 000000_Default | I35: 1373_WiFi On Board | J35: 1373_WiFi On Board | K35: M2M Energy Monitoring | L35: ORANGE SA | M35: Budget 2026 | N35: EUR | O35: 617 | P35: 617 | Q35: 617 | R35: 617 | S35: 617 | T35: 617 | U35: 617 | V35: 617 | W35: 617 | X35: 617 | Y35: 617 | Z35: 617 | AA35: 7404 | AB35: =IF(N35="EUR",AA35,IF(N35="GBP",AA35/Rate!$C$3,AA35/Rate!$C$5)) -> 7404 | AC35: =IFERROR(VLOOKUP(K35,'4.2 Simplify Savings'!K:AB,18,0),0) -> 0 | AD35: =SUM(AB35:AC35) -> 7404
A36: =_xlfn.XLOOKUP(B36*1,'Reference '!I:I,'Reference '!K:K) -> Ben Gbeve | B36: =LEFT(C36,3) -> 601 | C36: 601_IS Service Delivery_EIL_EUR | D36: 601_IS Service Delivery_EIL_EUR | E36: 341200 - Internet access | F36: 341200 - Internet access | G36: 000000_Default | H36: 000000_Default | I36: 1373_WiFi On Board | J36: 1373_WiFi On Board | K36: Onboard passanger Wi-Fi (Channel EIL) | L36: ORANGE | M36: Budget 2026 | N36: EUR | O36: 145537 | P36: 145537 | Q36: 145537 | R36: 145537 | S36: 145537 | T36: 145537 | U36: 145537 | V36: 145537 | W36: 145537 | X36: 145537 | Y36: 145537 | Z36: 145537 | AA36: 1746444 | AB36: =IF(N36="EUR",AA36,IF(N36="GBP",AA36/Rate!$C$3,AA36/Rate!$C$5)) -> 1746444 | AC36: =IFERROR(VLOOKUP(K36,'4.2 Simplify Savings'!K:AB,18,0),0) -> -246444 | AD36: =SUM(AB36:AC36) -> 1500000
A37: =_xlfn.XLOOKUP(B37*1,'Reference '!I:I,'Reference '!K:K) -> Ben Gbeve | B37: =LEFT(C37,3) -> 601 | C37: 601_IS Service Delivery_EIL_GBP | D37: 601_IS Service Delivery_EIL_GBP | E37: 341200 - Internet access | F37: 341200 - Internet access | G37: 000000_Default | H37: 000000_Default | I37: 0000_Default | J37: 0000_Default | K37: Internet in PNO BL Lounge | L37: TELSTRA EUROPE LTD | M37: Budget 2026 | N37: GBP | O37: 2768 | P37: 2768 | Q37: 2768 | R37: 2768 | S37: 2768 | T37: 2768 | U37: 2768 | V37: 2768 | W37: 2768 | X37: 2768 | Y37: 2768 | Z37: 2768 | AA37: 33216 | AB37: =IF(N37="EUR",AA37,IF(N37="GBP",AA37/Rate!$C$3,AA37/Rate!$C$5)) -> 38179.31 | AC37: =IFERROR(VLOOKUP(K37,'4.2 Simplify Savings'!K:AB,18,0),0) -> -28275.12 | AD37: =SUM(AB37:AC37) -> 9904.1903
A38: =_xlfn.XLOOKUP(B38*1,'Reference '!I:I,'Reference '!K:K) -> Ben Gbeve | B38: =LEFT(C38,3) -> 601 | C38: 601_IS Service Delivery_EIL_GBP | D38: 601_IS Service Delivery_EIL_GBP | E38: 341200 - Internet access | F38: 341200 - Internet access | G38: 000000_Default | H38: 000000_Default | I38: 1373_WiFi On Board | J38: 1373_WiFi On Board | K38: M2M/CSD Jasper 2G train systems monitoring (No PIS contract) | L38: TELEFONICA UK LIMITED | M38: Budget 2026 | N38: GBP | O38: 5416.67 | P38: 5416.67 | Q38: 5416.67 | R38: 5416.67 | S38: 5416.67 | T38: 5416.67 | U38: 5416.67 | V38: 5416.67 | W38: 5416.67 | X38: 5416.67 | Y38: 5416.67 | Z38: 5416.67 | AA38: 65000.04 | AB38: =IF(N38="EUR",AA38,IF(N38="GBP",AA38/Rate!$C$3,AA38/Rate!$C$5)) -> 74712.69 | AC38: =IFERROR(VLOOKUP(K38,'4.2 Simplify Savings'!K:AB,18,0),0) -> 0 | AD38: =SUM(AB38:AC38) -> 74712.69
A39: =_xlfn.XLOOKUP(B39*1,'Reference '!I:I,'Reference '!K:K) -> Ben Gbeve | B39: =LEFT(C39,3) -> 601 | C39: 601_IS Service Delivery_EIL_GBP | D39: 601_IS Service Delivery_EIL_GBP | E39: 342001 - Systems support | F39: 342001 - Systems support | G39: 000000_Default | H39: 000000_Default | I39: 0000_Default | J39: 0000_Default | K39: WISI Mobile screens at stations | L39: Met Systems Limited | M39: Budget 2026 | N39: GBP | O39: 3750 | P39: 3750 | Q39: 3750 | R39: 3750 | S39: 3750 | T39: 3750 | U39: 3750 | V39: 3750 | W39: 3750 | X39: 3750 | Y39: 3750 | Z39: 3750 | AA39: 45000 | AB39: =IF(N39="EUR",AA39,IF(N39="GBP",AA39/Rate!$C$3,AA39/Rate!$C$5)) -> 51724.138 | AC39: =IFERROR(VLOOKUP(K39,'4.2 Simplify Savings'!K:AB,18,0),0) -> 0 | AD39: =SUM(AB39:AC39) -> 51724.138
A40: =_xlfn.XLOOKUP(B40*1,'Reference '!I:I,'Reference '!K:K) -> Ben Gbeve | B40: =LEFT(C40,3) -> 601 | C40: 601_IS Service Delivery_EIL_GBP | D40: 601_IS Service Delivery_EIL_GBP | E40: 342001 - Systems support | F40: 342001 - Systems support | G40: 000000_Default | H40: 000000_Default | I40: 0000_Default | J40: 0000_Default | K40: Support for station display screens | L40: MAINT-TEK ELECTRONICS SERVICES | M40: Budget 2026 | N40: GBP | O40: 7708.33 | P40: 7708.33 | Q40: 7708.33 | R40: 7708.33 | S40: 7708.33 | T40: 7708.33 | U40: 7708.33 | V40: 7708.33 | W40: 7708.33 | X40: 7708.33 | Y40: 7708.33 | Z40: 7708.33 | AA40: 92499.96 | AB40: =IF(N40="EUR",AA40,IF(N40="GBP",AA40/Rate!$C$3,AA40/Rate!$C$5)) -> 106321.79 | AC40: =IFERROR(VLOOKUP(K40,'4.2 Simplify Savings'!K:AB,18,0),0) -> 0 | AD40: =SUM(AB40:AC40) -> 106321.79
A41: =_xlfn.XLOOKUP(B41*1,'Reference '!I:I,'Reference '!K:K) -> Valerie Veyt | B41: =LEFT(C41,3) -> 602 | C41: 602_IS Operational_EIL_EUR | D41: 602_IS Operational_EIL_EUR | E41: 342001 - Systems support | F41: 342001 - Systems support | G41: 000000_Default | H41: 000000_Default | I41: 0000_Default | J41: 0000_Default | K41: Wifi Network Monitoring | L41: Xentrans / Netforecast | M41: Budget 2026 | N41: EUR | O41: 15000 | P41: 15000 | Q41: 15000 | R41: 15000 | S41: 15000 | T41: 15000 | U41: 15000 | V41: 15000 | W41: 15000 | X41: 15000 | Y41: 15000 | Z41: 15000 | AA41: 180000 | AB41: =IF(N41="EUR",AA41,IF(N41="GBP",AA41/Rate!$C$3,AA41/Rate!$C$5)) -> 180000 | AC41: =IFERROR(VLOOKUP(K41,'4.2 Simplify Savings'!K:AB,18,0),0) -> 0 | AD41: =SUM(AB41:AC41) -> 180000
A42: =_xlfn.XLOOKUP(B42*1,'Reference '!I:I,'Reference '!K:K) -> Valerie Veyt | B42: =LEFT(C42,3) -> 602 | C42: 602_IS Operational_EIL_EUR | D42: 602_IS Operational_EIL_EUR | E42: 342001 - Systems support | F42: 342001 - Systems support | G42: 000000_Default | H42: 000000_Default | I42: 0000_Default | J42: 0000_Default | K42: eRoster and Quintiq Maintenance and Planning TBC | L42: SOPRA STERIA BENELUX SA | M42: Budget 2026 | N42: EUR | O42: 10000 | P42: 10000 | Q42: 10000 | R42: 10000 | S42: 10000 | T42: 10000 | U42: 10000 | V42: 10000 | W42: 10000 | X42: 10000 | Y42: 10000 | Z42: 10000 | AA42: 120000 | AB42: =IF(N42="EUR",AA42,IF(N42="GBP",AA42/Rate!$C$3,AA42/Rate!$C$5)) -> 120000 | AC42: =IFERROR(VLOOKUP(K42,'4.2 Simplify Savings'!K:AB,18,0),0) -> 0 | AD42: =SUM(AB42:AC42) -> 120000
A43: =_xlfn.XLOOKUP(B43*1,'Reference '!I:I,'Reference '!K:K) -> Valerie Veyt | B43: =LEFT(C43,3) -> 602 | C43: 602_IS Operational_EIL_GBP | D43: 602_IS Operational_EIL_GBP | E43: 342001 - Systems support | F43: 342001 - Systems support | G43: 000000_Default | H43: 000000_Default | I43: 0000_Default | J43: 0000_Default | K43: e320 PIS App Support + PIS content update PIS content management | L43: WABTEC ANNAX | M43: Budget 2026 | N43: GBP | O43: 17916.37 | P43: 17916.37 | Q43: 17916.37 | R43: 17916.37 | S43: 17916.37 | T43: 17916.37 | U43: 17916.37 | V43: 17916.37 | W43: 17916.37 | X43: 17916.37 | Y43: 17916.37 | Z43: 17916.37 | AA43: 214996.44 | AB43: =IF(N43="EUR",AA43,IF(N43="GBP",AA43/Rate!$C$3,AA43/Rate!$C$5)) -> 247122.34 | AC43: =IFERROR(VLOOKUP(K43,'4.2 Simplify Savings'!K:AB,18,0),0) -> 0 | AD43: =SUM(AB43:AC43) -> 247122.34
... A55: =_xlfn.XLOOKUP(B55*1,'Reference '!I:I,'Reference '!K:K) -> Mael Delmas | B55: =LEFT(C55,3) -> 604 | C55: 604_IS Customer Systems_EIL_GBP | D55: 604_IS Customer Systems_EIL_GBP | E55: 342001 - Systems support | F55: 342001 - Systems support | G55: 000000_Default | H55: 000000_Default | I55: 0000_Default | J55: 0000_Default | K55: [Operations] - Disrution Management front-end - application Masintenance | L55: COFORGE U.K. LIMITED | M55: Budget 2026 | N55: GBP | O55: 4000 | P55: 4000 | Q55: 4000 | R55: 4000 | S55: 4000 | T55: 4000 | U55: 4000 | V55: 4000 | W55: 4000 | X55: 4000 | Y55: 4000 | Z55: 4000 | AA55: 48000 | AB55: =IF(N55="EUR",AA55,IF(N55="GBP",AA55/Rate!$C$3,AA55/Rate!$C$5)) -> 55172.414 | AC55: =IFERROR(VLOOKUP(K55,'4.2 Simplify Savings'!K:AB,18,0),0) -> -8372.28 | AD55: =SUM(AB55:AC55) -> 46800.134
A56: =_xlfn.XLOOKUP(B56*1,'Reference '!I:I,'Reference '!K:K) -> Mael Delmas | B56: =LEFT(C56,3) -> 604 | C56: 604_IS Customer Systems_EIL_GBP | D56: 604_IS Customer Systems_EIL_GBP | E56: 342001 - Systems support | F56: 342001 - Systems support | G56: 000000_Default | H56: 000000_Default | I56: 0000_Default | J56: 0000_Default | K56: [Stations] - New Station Data tool: application and maintenance - server, devOps, dev | M56: Budget 2026 | N56: GBP | O56: 5000 | P56: 5000 | Q56: 5000 | R56: 5000 | S56: 5000 | T56: 5000 | U56: 5000 | V56: 5000 | W56: 5000 | X56: 5000 | Y56: 5000 | Z56: 5000 | AA56: 60000 | AB56: =IF(N56="EUR",AA56,IF(N56="GBP",AA56/Rate!$C$3,AA56/Rate!$C$5)) -> 68965.517 | AC56: =IFERROR(VLOOKUP(K56,'4.2 Simplify Savings'!K:AB,18,0),0) -> -13953.72 | AD56: =SUM(AB56:AC56) -> 55011.797
A57: =_xlfn.XLOOKUP(B57*1,'Reference '!I:I,'Reference '!K:K) -> Olivier Lepret | B57: =LEFT(C57,3) -> 606 | C57: 606_Security & Architecture_EIL_EUR | D57: 606_Security & Architecture_EIL_EUR | E57: 342001 - Systems support | F57: 342001 - Systems support | G57: 000000_Default | H57: 000000_Default | I57: 0000_Default | J57: 0000_Default | K57: Continous Pentesting, Bug bounty | L57: YesWeHack | M57: Budget 2026 | N57: EUR | O57: 3833 | P57: 3833 | Q57: 3833 | R57: 3833 | S57: 3833 | T57: 3833 | U57: 3833 | V57: 3833 | W57: 3833 | X57: 3833 | Y57: 3833 | Z57: 3833 | AA57: 45996 | AB57: =IF(N57="EUR",AA57,IF(N57="GBP",AA57/Rate!$C$3,AA57/Rate!$C$5)) -> 45996 | AC57: =IFERROR(VLOOKUP(K57,'4.2 Simplify Savings'!K:AB,18,0),0) -> 0 | AD57: =SUM(AB57:AC57) -> 45996
A58: =_xlfn.XLOOKUP(B58*1,'Reference '!I:I,'Reference '!K:K) -> Olivier Lepret | B58: =LEFT(C58,3) -> 606 | C58: 606_Security & Architecture_EIL_EUR | D58: 606_Security & Architecture_EIL_EUR | E58: 342001 - Systems support | F58: 342001 - Systems support | G58: 000000_Default | H58: 000000_Default | I58: 0000_Default | J58: 0000_Default | K58: AlertLogic - Security Operating Center + Vulnerability Scans (THI Assets) | L58: Fortra | M58: Budget 2026 | N58: EUR | O58: 11667 | P58: 11667 | Q58: 11667 | R58: 11667 | S58: 11667 | T58: 11667 | U58: 11667 | V58: 11667 | W58: 11667 | X58: 11667 | Y58: 11667 | Z58: 11667 | AA58: 140004 | AB58: =IF(N58="EUR",AA58,IF(N58="GBP",AA58/Rate!$C$3,AA58/Rate!$C$5)) -> 140004 | AC58: =IFERROR(VLOOKUP(K58,'4.2 Simplify Savings'!K:AB,18,0),0) -> 0 | AD58: =SUM(AB58:AC58) -> 140004
A59: =_xlfn.XLOOKUP(B59*1,'Reference '!I:I,'Reference '!K:K) -> Olivier Lepret | B59: =LEFT(C59,3) -> 606 | C59: 606_Security & Architecture_EIL_EUR | D59: 606_Security & Architecture_EIL_EUR | E59: 342001 - Systems support | F59: 342001 - Systems support | G59: 000000_Default | H59: 000000_Default | I59: 0000_Default | J59: 0000_Default | K59: Small Software (AD audit+ …) | M59: Budget 2026 | N59: EUR | O59: 425 | P59: 425 | Q59: 425 | R59: 425 | S59: 425 | T59: 425 | U59: 425 | V59: 425 | W59: 425 | X59: 425 | Y59: 425 | Z59: 425 | AA59: 5100 | AB59: =IF(N59="EUR",AA59,IF(N59="GBP",AA59/Rate!$C$3,AA59/Rate!$C$5)) -> 5100 | AC59: =IFERROR(VLOOKUP(K59,'4.2 Simplify Savings'!K:AB,18,0),0) -> 0 | AD59: =SUM(AB59:AC59) -> 5100
A60: =_xlfn.XLOOKUP(B60*1,'Reference '!I:I,'Reference '!K:K) -> Roger Plummer | B60: =LEFT(C60,3) -> 607 | C60: 607_Corporate, Finance & HR Systems_EIL_GBP | D60: 607_Corporate, Finance & HR Systems_EIL_GBP | E60: 342001 - Systems support | F60: 342001 - Systems support | G60: 000000_Default | H60: 000000_Default | I60: 0000_Default | J60: 0000_Default | K60: Oracle EBS support (call off units) - Version 1 | L60: Version 1 | M60: Budget 2026 | N60: GBP | O60: 3333 | P60: 3333 | Q60: 3333 | R60: 3333 | S60: 3333 | T60: 3333 | U60: 3333 | V60: 3333 | W60: 3333 | X60: 3333 | Y60: 3333 | Z60: 3333 | AA60: 39996 | AB60: =IF(N60="EUR",AA60,IF(N60="GBP",AA60/Rate!$C$3,AA60/Rate!$C$5)) -> 45972.414 | AC60: =IFERROR(VLOOKUP(K60,'4.2 Simplify Savings'!K:AB,18,0),0) -> 0 | AD60: =SUM(AB60:AC60) -> 45972.414
A61: =_xlfn.XLOOKUP(B61*1,'Reference '!I:I,'Reference '!K:K) -> Roger Plummer | B61: =LEFT(C61,3) -> 607 | C61: 607_Corporate, Finance & HR Systems_EIL_GBP | D61: 607_Corporate, Finance & HR Systems_EIL_GBP | E61: 342001 - Systems support | F61: 342001 - Systems support | G61: 000000_Default | H61: 000000_Default | I61: 0000_Default | J61: 0000_Default | K61: Oracle technical and functional support - Version 1 | L61: Version 1 | M61: Budget 2026 | N61: GBP | O61: 10000 | P61: 10000 | Q61: 10000 | R61: 10000 | S61: 10000 | T61: 10000 | U61: 10000 | V61: 10000 | W61: 10000 | X61: 10000 | Y61: 10000 | Z61: 10000 | AA61: 120000 | AB61: =IF(N61="EUR",AA61,IF(N61="GBP",AA61/Rate!$C$3,AA61/Rate!$C$5)) -> 137931.03 | AC61: ='4.2 Simplify Savings'!$AB$16 -> -50004 | AD61: =SUM(AB61:AC61) -> 87927.034
A62: =_xlfn.XLOOKUP(B62*1,'Reference '!I:I,'Reference '!K:K) -> Roger Plummer | B62: =LEFT(C62,3) -> 607 | C62: 607_Corporate, Finance & HR Systems_EIL_GBP | D62: 607_Corporate, Finance & HR Systems_EIL_GBP | E62: 342001 - Systems support | F62: 342001 - Systems support | G62: 000000_Default | H62: 000000_Default | I62: 0000_Default | J62: 0000_Default | K62: Penetration Testing | L62: n/a | M62: Budget 2026 | N62: GBP | O62: 1750 | P62: 1750 | Q62: 1750 | R62: 1750 | S62: 1750 | T62: 1750 | U62: 1750 | V62: 1750 | W62: 1750 | X62: 1750 | Y62: 1750 | Z62: 1750 | AA62: 21000 | AB62: =IF(N62="EUR",AA62,IF(N62="GBP",AA62/Rate!$C$3,AA62/Rate!$C$5)) -> 24137.931 | AC62: =IFERROR(VLOOKUP(K62,'4.2 Simplify Savings'!K:AB,18,0),0) -> 0 | AD62: =SUM(AB62:AC62) -> 24137.931
A63: =_xlfn.XLOOKUP(B63*1,'Reference '!I:I,'Reference '!K:K) -> Roger Plummer | B63: =LEFT(C63,3) -> 607 | C63: 607_Corporate, Finance & HR Systems_EIL_GBP | D63: 607_Corporate, Finance & HR Systems_EIL_GBP | E63: 342001 - Systems support | F63: 342001 - Systems support | G63: 000000_Default | H63: 000000_Default | I63: 0000_Default | J63: 0000_Default | K63: Business Objects - Support | L63: infosol | M63: Budget 2026 | N63: GBP | O63: 1083 | P63: 1083 | Q63: 1083 | R63: 1083 | S63: 1083 | T63: 1083 | U63: 1083 | V63: 1083 | W63: 1083 | X63: 1083 | Y63: 1083 | Z63: 1083 | AA63: 12996 | AB63: =IF(N63="EUR",AA63,IF(N63="GBP",AA63/Rate!$C$3,AA63/Rate!$C$5)) -> 14937.931 | AC63: =IFERROR(VLOOKUP(K63,'4.2 Simplify Savings'!K:AB,18,0),0) -> 0 | AD63: =SUM(AB63:AC63) -> 14937.931
A64: =_xlfn.XLOOKUP(B64*1,'Reference '!I:I,'Reference '!K:K) -> Roger Plummer | B64: =LEFT(C64,3) -> 607 | C64: 607_Corporate, Finance & HR Systems_EIL_GBP | D64: 607_Corporate, Finance & HR Systems_EIL_GBP | E64: 342001 - Systems support | F64: 342001 - Systems support | G64: 000000_Default | H64: 000000_Default | I64: 0000_Default | J64: 0000_Default | K64: Access Control Solution Maintenance & Support | L64: Genetec | M64: Budget 2026 | N64: GBP | O64: 3333 | P64: 3333 | Q64: 3333 | R64: 3333 | S64: 3333 | T64: 3333 | U64: 3333 | V64: 3333 | W64: 3333 | X64: 3333 | Y64: 3333 | Z64: 3333 | AA64: 39996 | AB64: =IF(N64="EUR",AA64,IF(N64="GBP",AA64/Rate!$C$3,AA64/Rate!$C$5)) -> 45972.414 | AC64: =IFERROR(VLOOKUP(K64,'4.2 Simplify Savings'!K:AB,18,0),0) -> 0 | AD64: =SUM(AB64:AC64) -> 45972.414
A65: =_xlfn.XLOOKUP(B65*1,'Reference '!I:I,'Reference '!K:K) -> Roger Plummer | B65: =LEFT(C65,3) -> 607 | C65: 607_Corporate, Finance & HR Systems_EIL_GBP | D65: 607_Corporate, Finance & HR Systems_EIL_GBP | E65: 342001 - Systems support | F65: 342001 - Systems support | G65: 000000_Default | H65: 000000_Default | I65: 0000_Default | J65: 0000_Default | K65: Filemaker Door Access | L65: Filemaker | M65: Budget 2026 | N65: GBP | O65: 417 | P65: 417 | Q65: 417 | R65: 417 | S65: 417 | T65: 417 | U65: 417 | V65: 417 | W65: 417 | X65: 417 | Y65: 417 | Z65: 417 | AA65: 5004 | AB65: =IF(N65="EUR",AA65,IF(N65="GBP",AA65/Rate!$C$3,AA65/Rate!$C$5)) -> 5751.7241 | AC65: =IFERROR(VLOOKUP(K65,'4.2 Simplify Savings'!K:AB,18,0),0) -> 0 | AD65: =SUM(AB65:AC65) -> 5751.7241
A66: =_xlfn.XLOOKUP(B66*1,'Reference '!I:I,'Reference '!K:K) -> Roger Plummer | B66: =LEFT(C66,3) -> 607 | C66: 607_Corporate, Finance & HR Systems_EIL_GBP | D66: 607_Corporate, Finance & HR Systems_EIL_GBP | E66: 342001 - Systems support | F66: 342001 - Systems support | G66: 000000_Default | H66: 000000_Default | I66: 0000_Default | J66: 0000_Default | K66: EHS - ECO Online (Corporate Accident & Hazard Reporting) | L66: ECO Online | M66: Budget 2026 | N66: GBP | O66: 3333 | P66: 3333 | Q66: 3333 | R66: 3333 | S66: 3333 | T66: 3333 | U66: 3333 | V66: 3333 | W66: 3333 | X66: 3333 | Y66: 3333 | Z66: 3333 | AA66: 39996 | AB66: =IF(N66="EUR",AA66,IF(N66="GBP",AA66/Rate!$C$3,AA66/Rate!$C$5)) -> 45972.414 | AC66: =IFERROR(VLOOKUP(K66,'4.2 Simplify Savings'!K:AB,18,0),0) -> 0 | AD66: =SUM(AB66:AC66) -> 45972.414
A67: =_xlfn.XLOOKUP(B67*1,'Reference '!I:I,'Reference '!K:K) -> Roger Plummer | B67: =LEFT(C67,3) -> 607 | C67: 607_Corporate, Finance & HR Systems_EIL_GBP | D67: 607_Corporate, Finance & HR Systems_EIL_GBP | E67: 342001 - Systems support | F67: 342001 - Systems support | G67: 000000_Default | H67: 000000_Default | I67: 0000_Default | J67: 0000_Default | K67: Hotels Express | L67: Accommodation Plus International (API) | M67: Budget 2026 | N67: GBP | O67: 1667 | P67: 1667 | Q67: 1667 | R67: 1667 | S67: 1667 | T67: 1667 | U67: 1667 | V67: 1667 | W67: 1667 | X67: 1667 | Y67: 1667 | Z67: 1667 | AA67: 20004 | AB67: =IF(N67="EUR",AA67,IF(N67="GBP",AA67/Rate!$C$3,AA67/Rate!$C$5)) -> 22993.103 | AC67: =IFERROR(VLOOKUP(K67,'4.2 Simplify Savings'!K:AB,18,0),0) -> 0 | AD67: =SUM(AB67:AC67) -> 22993.103
A68: =_xlfn.XLOOKUP(B68*1,'Reference '!I:I,'Reference '!K:K) -> Roger Plummer | B68: =LEFT(C68,3) -> 607 | C68: 607_Corporate, Finance & HR Systems_EIL_USD | D68: 607_Corporate, Finance & HR Systems_EIL_USD | E68: 342001 - Systems support | F68: 342001 - Systems support | G68: 000000_Default | H68: 000000_Default | I68: 0000_Default | J68: 0000_Default | K68: ACES | L68: Accommodation Plus International (API) | M68: Budget 2026 | N68: USD | O68: 1667 | P68: 1667 | Q68: 1667 | R68: 1667 | S68: 1667 | T68: 1667 | U68: 1667 | V68: 1667 | W68: 1667 | X68: 1667 | Y68: 1667 | Z68: 1667 | AA68: 20004 | AB68: =IF(N68="EUR",AA68,IF(N68="GBP",AA68/Rate!$C$3,AA68/Rate!$C$5)) -> 17097.436 | AC68: =IFERROR(VLOOKUP(K68,'4.2 Simplify Savings'!K:AB,18,0),0) -> 0 | AD68: =SUM(AB68:AC68) -> 17097.436
A69: =_xlfn.XLOOKUP(B69*1,'Reference '!I:I,'Reference '!K:K) -> Ben Gbeve | B69: =LEFT(C69,3) -> 601 | C69: 601_IS Service Delivery_EIL_GBP | D69: 601_IS Service Delivery_EIL_GBP | E69: 342100 - Systems development | F69: 342100 - Systems development | G69: 000000_Default | H69: 000000_Default | I69: 0000_Default | J69: 0000_Default | K69: BTNet Internet service for KPL | L69: BT BUSINESS COMMUNICATIONS | M69: Budget 2026 | N69: GBP | O69: 500 | P69: 500 | Q69: 500 | R69: 500 | S69: 500 | T69: 500 | U69: 500 | V69: 500 | W69: 500 | X69: 500 | Y69: 500 | Z69: 500 | AA69: 6000 | AB69: =IF(N69="EUR",AA69,IF(N69="GBP",AA69/Rate!$C$3,AA69/Rate!$C$5)) -> 6896.5517 | AC69: =IFERROR(VLOOKUP(K69,'4.2 Simplify Savings'!K:AB,18,0),0) -> 0 | AD69: =SUM(AB69:AC69) -> 6896.5517
A70: =_xlfn.XLOOKUP(B70*1,'Reference '!I:I,'Reference '!K:K) -> Ben Gbeve | B70: =LEFT(C70,3) -> 601 | C70: 601_IS Service Delivery_EIL_GBP | D70: 601_IS Service Delivery_EIL_GBP | E70: 342100 - Systems development | F70: 342100 - Systems development | G70: 000000_Default | H70: 000000_Default | I70: 0000_Default | J70: 0000_Default | K70: BTNet Internet service for SPI Business Lounge | L70: BT BUSINESS COMMUNICATIONS | M70: Budget 2026 | N70: GBP | O70: 500 | P70: 500 | Q70: 500 | R70: 500 | S70: 500 | T70: 500 | U70: 500 | V70: 500 | W70: 500 | X70: 500 | Y70: 500 | Z70: 500 | AA70: 6000 | AB70: =IF(N70="EUR",AA70,IF(N70="GBP",AA70/Rate!$C$3,AA70/Rate!$C$5)) -> 6896.5517 | AC70: =IFERROR(VLOOKUP(K70,'4.2 Simplify Savings'!K:AB,18,0),0) -> 0 | AD70: =SUM(AB70:AC70) -> 6896.5517
A71: =_xlfn.XLOOKUP(B71*1,'Reference '!I:I,'Reference '!K:K) -> Valerie Veyt | B71: =LEFT(C71,3) -> 602 | C71: 602_IS Operational_EIL_GBP | D71: 602_IS Operational_EIL_GBP | E71: 342100 - Systems development | F71: 342100 - Systems development | G71: 000000_Default | H71: 000000_Default | I71: 0000_Default | J71: 0000_Default | K71: Contractor Onboard Tools Tech PO Adeolu Fagbire | L71: VENTULA CONSULTING | M71: Budget 2026 | N71: GBP | O71: 14333.1 | P71: 14333.1 | Q71: 14333.1 | R71: 14333.1 | S71: 14333.1 | T71: 14333.1 | U71: 14333.1 | V71: 14333.1 | W71: 14333.1 | X71: 14333.1 | Y71: 14333.1 | Z71: 14333.1 | AA71: 171997.2 | AB71: =IF(N71="EUR",AA71,IF(N71="GBP",AA71/Rate!$C$3,AA71/Rate!$C$5)) -> 197697.93 | AC71: =IFERROR(VLOOKUP(K71,'4.2 Simplify Savings'!K:AB,18,0),0) -> 0 | AD71: =SUM(AB71:AC71) -> 197697.93
A72: =_xlfn.XLOOKUP(B72*1,'Reference '!I:I,'Reference '!K:K) -> Mael Delmas | B72: =LEFT(C72,3) -> 604 | C72: 604_IS Customer Systems_EIL_GBP | D72: 604_IS Customer Systems_EIL_GBP | E72: 342100 - Systems development | F72: 342100 - Systems development | G72: 000000_Default | H72: 000000_Default | I72: 0000_Default | J72: 0000_Default | K72: [Salesforce] - SF development support - 125hrs/months for support and maintenance | L72: SALESFORCE | M72: Budget 2026 | N72: GBP | O72: 7900 | P72: 7900 | Q72: 7900 | R72: 7900 | S72: 7900 | T72: 7900 | U72: 7900 | V72: 7900 | W72: 7900 | X72: 7900 | Y72: 7900 | Z72: 7900 | AA72: 94800 | AB72: =IF(N72="EUR",AA72,IF(N72="GBP",AA72/Rate!$C$3,AA72/Rate!$C$5)) -> 108965.52 | AC72: =IFERROR(VLOOKUP(K72,'4.2 Simplify Savings'!K:AB,18,0),0) -> -11023.44 | AD72: =SUM(AB72:AC72) -> 97942.077
A73: =_xlfn.XLOOKUP(B73*1,'Reference '!I:I,'Reference '!K:K) -> Mael Delmas | B73: =LEFT(C73,3) -> 604 | C73: 604_IS Customer Systems_EIL_GBP | D73: 604_IS Customer Systems_EIL_GBP | E73: 342100 - Systems development | F73: 342100 - Systems development | G73: 000000_Default | H73: 000000_Default | I73: 0000_Default | J73: 0000_Default | K73: [Contact Centre] - projects with SF | M73: Budget 2026 | N73: GBP | O73: 19746 | P73: 19746 | Q73: 19746 | R73: 19746 | S73: 19746 | T73: 19746 | U73: 19746 | V73: 19746 | W73: 19746 | X73: 19746 | Y73: 19746 | Z73: 19746 | AA73: 236952 | AB73: =IF(N73="EUR",AA73,IF(N73="GBP",AA73/Rate!$C$3,AA73/Rate!$C$5)) -> 272358.62 | AC73: =IFERROR(VLOOKUP(K73,'4.2 Simplify Savings'!K:AB,18,0),0) -> 0 | AD73: =SUM(AB73:AC73) -> 272358.62
A74: =_xlfn.XLOOKUP(B74*1,'Reference '!I:I,'Reference '!K:K) -> Mael Delmas | B74: =LEFT(C74,3) -> 604 | C74: 604_IS Customer Systems_EIL_GBP | D74: 604_IS Customer Systems_EIL_GBP | E74: 342100 - Systems development | F74: 342100 - Systems development | G74: 000000_Default | H74: 000000_Default | I74: 0000_Default | J74: 0000_Default | K74: Other apps dev support: contingency (BA, POC, Dev, PM) | M74: Budget 2026 | N74: GBP | O74: 16000 | P74: 16000 | Q74: 16000 | R74: 16000 | S74: 16000 | T74: 16000 | U74: 16000 | V74: 16000 | W74: 16000 | X74: 16000 | Y74: 16000 | Z74: 16000 | AA74: 192000 | AB74: =IF(N74="EUR",AA74,IF(N74="GBP",AA74/Rate!$C$3,AA74/Rate!$C$5)) -> 220689.66 | AC74: =IFERROR(VLOOKUP(K74,'4.2 Simplify Savings'!K:AB,18,0),0) -> -78140.88 | AD74: =SUM(AB74:AC74) -> 142548.78
A75: =_xlfn.XLOOKUP(B75*1,'Reference '!I:I,'Reference '!K:K) -> Mael Delmas | B75: =LEFT(C75,3) -> 604 | C75: 604_IS Customer Systems_EIL_GBP | D75: 604_IS Customer Systems_EIL_GBP | E75: 342100 - Systems development | F75: 342100 - Systems development | G75: 000000_Default | H75: 000000_Default | I75: 0000_Default | J75: 0000_Default | K75: outsight AI in Amsterdam - removed | M75: Budget 2026 | N75: GBP | O75: 7000 | P75: 7000 | Q75: 7000 | R75: 7000 | S75: 7000 | T75: 7000 | U75: 7000 | V75: 7000 | W75: 7000 | X75: 7000 | Y75: 7000 | Z75: 7000 | AA75: 84000 | AB75: =IF(N75="EUR",AA75,IF(N75="GBP",AA75/Rate!$C$3,AA75/Rate!$C$5)) -> 96551.724 | AC75: =IFERROR(VLOOKUP(K75,'4.2 Simplify Savings'!K:AB,18,0),0) -> -97680 | AD75: =SUM(AB75:AC75) -> -1128.2759
A76: =_xlfn.XLOOKUP(B76*1,'Reference '!I:I,'Reference '!K:K) -> Mael Delmas | B76: =LEFT(C76,3) -> 604 | C76: 604_IS Customer Systems_EIL_GBP | D76: 604_IS Customer Systems_EIL_GBP | E76: 342100 - Systems development | F76: 342100 - Systems development | G76: 000000_Default | H76: 000000_Default | I76: 0000_Default | J76: 0000_Default | K76: project - data forecast removed | M76: Budget 2026 | N76: GBP | O76: 8333.33 | P76: 8333.33 | Q76: 8333.33 | R76: 8333.33 | S76: 8333.33 | T76: 8333.33 | U76: 8333.33 | V76: 8333.33 | W76: 8333.33 | X76: 8333.33 | Y76: 8333.33 | Z76: 8333.33 | AA76: 99999.96 | AB76: =IF(N76="EUR",AA76,IF(N76="GBP",AA76/Rate!$C$3,AA76/Rate!$C$5)) -> 114942.48 | AC76: =IFERROR(VLOOKUP(K76,'4.2 Simplify Savings'!K:AB,18,0),0) -> -116280 | AD76: =SUM(AB76:AC76) -> -1337.5172
A77: =_xlfn.XLOOKUP(B77*1,'Reference '!I:I,'Reference '!K:K) -> Mael Delmas | B77: =LEFT(C77,3) -> 604 | C77: 604_IS Customer Systems_EIL_GBP | D77: 604_IS Customer Systems_EIL_GBP | E77: 342100 - Systems development | F77: 342100 - Systems development | G77: 000000_Default | H77: 000000_Default | I77: 0000_Default | J77: 0000_Default | K77: Project - Email Marketing project | M77: Budget 2026 | N77: GBP | O77: 0 | P77: 0 | Q77: 0 | R77: 0 | S77: 10000 | T77: 20000 | U77: 20000 | V77: 20000 | W77: 30000 | X77: 10000 | Y77: 10000 | Z77: 0 | AA77: 120000 | AB77: =IF(N77="EUR",AA77,IF(N77="GBP",AA77/Rate!$C$3,AA77/Rate!$C$5)) -> 137931.03 | AC77: =IFERROR(VLOOKUP(K77,'4.2 Simplify Savings'!K:AB,18,0),0) -> -34884.3 | AD77: =SUM(AB77:AC77) -> 103046.73
A78: =_xlfn.XLOOKUP(B78*1,'Reference '!I:I,'Reference '!K:K) -> Mael Delmas | B78: =LEFT(C78,3) -> 604 | C78: 604_IS Customer Systems_EIL_GBP | D78: 604_IS Customer Systems_EIL_GBP | E78: 342100 - Systems development | F78: 342100 - Systems development | G78: 000000_Default | H78: 000000_Default | I78: 0000_Default | J78: 0000_Default | K78: Project - Loyalty - Projects | M78: Budget 2026 | N78: GBP | O78: 0 | P78: 0 | Q78: 0 | R78: 10000 | S78: 15000 | T78: 20000 | U78: 20000 | V78: 25000 | W78: 10000 | X78: 0 | Y78: 0 | Z78: 0 | AA78: 100000 | AB78: =IF(N78="EUR",AA78,IF(N78="GBP",AA78/Rate!$C$3,AA78/Rate!$C$5)) -> 114942.53 | AC78: =IFERROR(VLOOKUP(K78,'4.2 Simplify Savings'!K:AB,18,0),0) -> -29070.25 | AD78: =SUM(AB78:AC78) -> 85872.279
A79: =_xlfn.XLOOKUP(B79*1,'Reference '!I:I,'Reference '!K:K) -> Mael Delmas | B79: =LEFT(C79,3) -> 604 | C79: 604_IS Customer Systems_EIL_GBP | D79: 604_IS Customer Systems_EIL_GBP | E79: 342100 - Systems development | F79: 342100 - Systems development | G79: 000000_Default | H79: 000000_Default | I79: 0000_Default | J79: 0000_Default | K79: Project - Technical - AI | M79: Budget 2026 | N79: GBP | S79: 20000 | T79: 10000 | U79: 26000 | AA79: 56000 | AB79: =IF(N79="EUR",AA79,IF(N79="GBP",AA79/Rate!$C$3,AA79/Rate!$C$5)) -> 64367.816 | AC79: =IFERROR(VLOOKUP(K79,'4.2 Simplify Savings'!K:AB,18,0),0) -> 0 | AD79: =SUM(AB79:AC79) -> 64367.816
A80: =_xlfn.XLOOKUP(B80*1,'Reference '!I:I,'Reference '!K:K) -> Mael Delmas | B80: =LEFT(C80,3) -> 604 | C80: 604_IS Customer Systems_EIL_GBP | D80: 604_IS Customer Systems_EIL_GBP | E80: 342100 - Systems development | F80: 342100 - Systems development | G80: 000000_Default | H80: 000000_Default | I80: 0000_Default | J80: 0000_Default | K80: Project - Technical - Data Cloud | M80: Budget 2026 | N80: GBP | Q80: 30000 | R80: 20000 | S80: 17500 | AA80: 67500 | AB80: =IF(N80="EUR",AA80,IF(N80="GBP",AA80/Rate!$C$3,AA80/Rate!$C$5)) -> 77586.207 | AC80: =IFERROR(VLOOKUP(K80,'4.2 Simplify Savings'!K:AB,18,0),0) -> 0 | AD80: =SUM(AB80:AC80) -> 77586.207
A81: =_xlfn.XLOOKUP(B81*1,'Reference '!I:I,'Reference '!K:K) -> Mael Delmas | B81: =LEFT(C81,3) -> 604 | C81: 604_IS Customer Systems_EIL_GBP | D81: 604_IS Customer Systems_EIL_GBP | E81: 342100 - Systems development | F81: 342100 - Systems development | G81: 000000_Default | H81: 000000_Default | I81: 0000_Default | J81: 0000_Default | K81: Project - Technical - technical debt | M81: Budget 2026 | N81: GBP | U81: 10000 | V81: 10000 | W81: 25000 | AA81: 45000 | AB81: =IF(N81="EUR",AA81,IF(N81="GBP",AA81/Rate!$C$3,AA81/Rate!$C$5)) -> 51724.138 | AC81: =IFERROR(VLOOKUP(K81,'4.2 Simplify Savings'!K:AB,18,0),0) -> 0 | AD81: =SUM(AB81:AC81) -> 51724.138
A82: =_xlfn.XLOOKUP(B82*1,'Reference '!I:I,'Reference '!K:K) -> Mael Delmas | B82: =LEFT(C82,3) -> 604 | C82: 604_IS Customer Systems_EIL_GBP | D82: 604_IS Customer Systems_EIL_GBP | E82: 342100 - Systems development | F82: 342100 - Systems development | G82: 000000_Default | H82: 000000_Default | I82: 0000_Default | J82: 0000_Default | K82: RM - additional efforts | M82: Budget 2026 | N82: GBP | O82: 0 | P82: 0 | Q82: 0 | R82: 0 | S82: 0 | T82: 0 | U82: 0 | V82: 50000 | W82: 0 | X82: 0 | Y82: 0 | Z82: 0 | AA82: 50000 | AB82: =IF(N82="EUR",AA82,IF(N82="GBP",AA82/Rate!$C$3,AA82/Rate!$C$5)) -> 57471.264 | AC82: =IFERROR(VLOOKUP(K82,'4.2 Simplify Savings'!K:AB,18,0),0) -> -14535.13 | AD82: =SUM(AB82:AC82) -> 42936.134
A83: =_xlfn.XLOOKUP(B83*1,'Reference '!I:I,'Reference '!K:K) -> Roger Plummer | B83: =LEFT(C83,3) -> 607 | C83: 607_Corporate, Finance & HR Systems_EIL_EUR | D83: 607_Corporate, Finance & HR Systems_EIL_EUR | E83: 342100 - Systems development | F83: 342100 - Systems development | G83: 000000_Default | H83: 000000_Default | I83: 0000_Default | J83: 0000_Default | K83: Box to sharepoint | M83: Budget 2026 | N83: EUR | O83: 29167 | P83: 29167 | Q83: 29167 | R83: 29167 | S83: 29167 | T83: 29167 | U83: 29167 | V83: 29167 | W83: 29167 | X83: 29167 | Y83: 29167 | Z83: 29167 | AA83: 350004 | AB83: =IF(N83="EUR",AA83,IF(N83="GBP",AA83/Rate!$C$3,AA83/Rate!$C$5)) -> 350004 | AC83: =IFERROR(VLOOKUP(K83,'4.2 Simplify Savings'!K:AB,18,0),0) -> -350004 | AD83: =SUM(AB83:AC83) -> 0
A84: =_xlfn.XLOOKUP(B84*1,'Reference '!I:I,'Reference '!K:K) -> Xavier Romanet | B84: =LEFT(C84,3) -> 605 | C84: 605_IS Sales System_EIL_GBP | D84: 605_IS Sales System_EIL_GBP | E84: 342100 - Systems development | F84: 342100 - Systems development | G84: 000000_Default | H84: 000000_Default | I84: 0000_Default | J84: 0000_Default | K84: Innovation budget | L84: Various | M84: 3+9 2025 | N84: GBP | O84: 8333.3333 | P84: 8333.3333 | Q84: 8333.3333 | R84: 8333.3333 | S84: 8333.3333 | T84: 8333.3333 | U84: 8333.3333 | V84: 8333.3333 | W84: 8333.3333 | X84: 8333.3333 | Y84: 8333.3333 | Z84: 8333.3333 | AA84: 100000 | AB84: =IF(N84="EUR",AA84,IF(N84="GBP",AA84/Rate!$C$3,AA84/Rate!$C$5)) -> 114942.53 | AC84: =IFERROR(VLOOKUP(K84,'4.2 Simplify Savings'!K:AB,18,0),0) -> 0 | AD84: =SUM(AB84:AC84) -> 114942.53
A85: =_xlfn.XLOOKUP(B85*1,'Reference '!I:I,'Reference '!K:K) -> Ben Gbeve | B85: =LEFT(C85,3) -> 601 | C85: 601_IS Service Delivery_EIL_USD | D85: 601_IS Service Delivery_EIL_USD | E85: 342200 - Hosting | F85: 342200 - Hosting | G85: 000000_Default | H85: 000000_Default | I85: 0000_Default | J85: 0000_Default | K85: Hosting for IS Software/Business Systems Projects: Equinox dev/prod, Metastorm safety portal, Dark trace) | L85: AMAZON WEB SERVICES | M85: Budget 2026 | N85: USD | O85: 9200 | P85: 9200 | Q85: 9200 | R85: 9200 | S85: 9200 | T85: 9200 | U85: 9200 | V85: 9200 | W85: 9200 | X85: 9200 | Y85: 9200 | Z85: 9200 | AA85: 110400 | AB85: =IF(N85="EUR",AA85,IF(N85="GBP",AA85/Rate!$C$3,AA85/Rate!$C$5)) -> 94358.974 | AC85: =IFERROR(VLOOKUP(K85,'4.2 Simplify Savings'!K:AB,18,0),0) -> 0 | AD85: =SUM(AB85:AC85) -> 94358.974
A86: =_xlfn.XLOOKUP(B86*1,'Reference '!I:I,'Reference '!K:K) -> Ben Gbeve | B86: =LEFT(C86,3) -> 601 | C86: 601_IS Service Delivery_EIL_USD | D86: 601_IS Service Delivery_EIL_USD | E86: 342200 - Hosting | F86: 342200 - Hosting | G86: 000000_Default | H86: 000000_Default | I86: 0000_Default | J86: 0000_Default | K86: Projected AWS BAU consumption | L86: AMAZON WEB SERVICES | M86: Budget 2026 | N86: USD | O86: 89583.33 | P86: 89583.33 | Q86: 89583.33 | R86: 89583.33 | S86: 89583.33 | T86: 89583.33 | U86: 89583.33 | V86: 89583.33 | W86: 89583.33 | X86: 89583.33 | Y86: 89583.33 | Z86: 89583.33 | AA86: 1075000 | AB86: =IF(N86="EUR",AA86,IF(N86="GBP",AA86/Rate!$C$3,AA86/Rate!$C$5)) -> 918803.38 | AC86: =SUM('4.2 Simplify Savings'!$AB$25,'4.2 Simplify Savings'!$AB$26) -> -127968 | AD86: =SUM(AB86:AC86) -> 790835.38
A87: =_xlfn.XLOOKUP(B87*1,'Reference '!I:I,'Reference '!K:K) -> Valerie Veyt | B87: =LEFT(C87,3) -> 602 | C87: 602_IS Operational_EIL_GBP | D87: 602_IS Operational_EIL_GBP | E87: 342200 - Hosting | F87: 342200 - Hosting | G87: 000000_Default | H87: 000000_Default | I87: 0000_Default | J87: 0000_Default | K87: Equinox RDP Licenses | L87: EQUINOX | M87: Budget 2026 | N87: GBP | O87: 3153.28 | P87: 3153.28 | Q87: 3153.28 | R87: 3153.28 | S87: 3153.28 | T87: 3153.28 | U87: 3153.28 | V87: 3153.28 | W87: 3153.28 | X87: 3153.28 | Y87: 3153.28 | Z87: 3153.28 | AA87: 37839.36 | AB87: =IF(N87="EUR",AA87,IF(N87="GBP",AA87/Rate!$C$3,AA87/Rate!$C$5)) -> 43493.517 | AC87: =IFERROR(VLOOKUP(K87,'4.2 Simplify Savings'!K:AB,18,0),0) -> 0 | AD87: =SUM(AB87:AC87) -> 43493.517
A88: =_xlfn.XLOOKUP(B88*1,'Reference '!I:I,'Reference '!K:K) -> Valerie Veyt | B88: =LEFT(C88,3) -> 602 | C88: 602_IS Operational_EIL_GBP | D88: 602_IS Operational_EIL_GBP | E88: 342200 - Hosting | F88: 342200 - Hosting | G88: 000000_Default | H88: 000000_Default | I88: 0000_Default | J88: 0000_Default | K88: Quintiq hosting charges (eRoster and Quintic P&M) TBC | L88: DASSAULT SYSTEMES UK LIMITED | M88: Budget 2026 | N88: GBP | O88: 20782.99 | P88: 20782.99 | Q88: 20782.99 | R88: 20782.99 | S88: 20782.99 | T88: 20782.99 | U88: 20782.99 | V88: 20782.99 | W88: 20782.99 | X88: 20782.99 | Y88: 20782.99 | Z88: 20782.99 | AA88: 249395.88 | AB88: =IF(N88="EUR",AA88,IF(N88="GBP",AA88/Rate!$C$3,AA88/Rate!$C$5)) -> 286661.93 | AC88: =IFERROR(VLOOKUP(K88,'4.2 Simplify Savings'!K:AB,18,0),0) -> 0 | AD88: =SUM(AB88:AC88) -> 286661.93
A89: =_xlfn.XLOOKUP(B89*1,'Reference '!I:I,'Reference '!K:K) -> Ben Gbeve | B89: =LEFT(C89,3) -> 601 | C89: 601_IS Service Delivery_EIL_EUR | D89: 601_IS Service Delivery_EIL_EUR | E89: 342300 - Software Licences and support | F89: 342300 - Software Licences and support | G89: 000000_Default | H89: 000000_Default | I89: 0000_Default | J89: 0000_Default | K89: Microsoft Enterprise Agreement | L89: SCC France | M89: Budget 2026 | N89: EUR | O89: 58598.5 | P89: 58598.5 | Q89: 58598.5 | R89: 58598.5 | S89: 58598.5 | T89: 58598.5 | U89: 58598.5 | V89: 58598.5 | W89: 58598.5 | X89: 58598.5 | Y89: 58598.5 | Z89: 58598.5 | AA89: 703182 | AB89: =IF(N89="EUR",AA89,IF(N89="GBP",AA89/Rate!$C$3,AA89/Rate!$C$5)) -> 703182 | AC89: =IFERROR(VLOOKUP(K89,'4.2 Simplify Savings'!K:AB,18,0),0) -> 0 | AD89: =SUM(AB89:AC89) -> 703182
A90: =_xlfn.XLOOKUP(B90*1,'Reference '!I:I,'Reference '!K:K) -> Ben Gbeve | B90: =LEFT(C90,3) -> 601 | C90: 601_IS Service Delivery_EIL_GBP | D90: 601_IS Service Delivery_EIL_GBP | E90: 342300 - Software Licences and support | F90: 342300 - Software Licences and support | G90: 000000_Default | H90: 000000_Default | I90: 0000_Default | J90: 0000_Default | K90: Various Software ( (inc. Trados Studio Translation Software £992; ) | L90: Various (Trados Studio Translation Software £992; | M90: Budget 2026 | N90: GBP | O90: 8116 | P90: 8116 | Q90: 8116 | R90: 8116 | S90: 8117 | T90: 8117 | U90: 8117 | V90: 8117 | W90: 8117 | X90: 8117 | Y90: 8117 | Z90: 8117 | AA90: 97400 | AB90: =IF(N90="EUR",AA90,IF(N90="GBP",AA90/Rate!$C$3,AA90/Rate!$C$5)) -> 111954.02 | AC90: =IFERROR(VLOOKUP(K90,'4.2 Simplify Savings'!K:AB,18,0),0) -> 0 | AD90: =SUM(AB90:AC90) -> 111954.02
A91: =_xlfn.XLOOKUP(B91*1,'Reference '!I:I,'Reference '!K:K) -> Ben Gbeve | B91: =LEFT(C91,3) -> 601 | C91: 601_IS Service Delivery_EIL_GBP | D91: 601_IS Service Delivery_EIL_GBP | E91: 342300 - Software Licences and support | F91: 342300 - Software Licences and support | G91: 000000_Default | H91: 000000_Default | I91: 0000_Default | J91: 0000_Default | K91: Signage Live for SPI Horizon wall & BMI BP lounge | L91: SOLUTIONS AUDIO VISUAL LIMITED | M91: Budget 2026 | N91: GBP | O91: 880 | P91: 880 | Q91: 880 | R91: 880 | S91: 880 | T91: 880 | U91: 880 | V91: 880 | W91: 880 | X91: 880 | Y91: 880 | Z91: 880 | AA91: 10560 | AB91: =IF(N91="EUR",AA91,IF(N91="GBP",AA91/Rate!$C$3,AA91/Rate!$C$5)) -> 12137.931 | AC91: =IFERROR(VLOOKUP(K91,'4.2 Simplify Savings'!K:AB,18,0),0) -> 0 | AD91: =SUM(AB91:AC91) -> 12137.931
A92: =_xlfn.XLOOKUP(B92*1,'Reference '!I:I,'Reference '!K:K) -> Ben Gbeve | B92: =LEFT(C92,3) -> 601 | C92: 601_IS Service Delivery_EIL_GBP | D92: 601_IS Service Delivery_EIL_GBP | E92: 342300 - Software Licences and support | F92: 342300 - Software Licences and support | G92: 000000_Default | H92: 000000_Default | I92: 0000_Default | J92: 0000_Default | K92: Displays in EIL offices, LIL, Paris BP Lounge | L92: ScreenCloudSignage | M92: Budget 2026 | N92: GBP | O92: 667 | P92: 667 | Q92: 667 | R92: 667 | S92: 667 | T92: 667 | U92: 667 | V92: 667 | W92: 667 | X92: 667 | Y92: 667 | Z92: 667 | AA92: 8004 | AB92: =IF(N92="EUR",AA92,IF(N92="GBP",AA92/Rate!$C$3,AA92/Rate!$C$5)) -> 9200 | AC92: =IFERROR(VLOOKUP(K92,'4.2 Simplify Savings'!K:AB,18,0),0) -> 0 | AD92: =SUM(AB92:AC92) -> 9200
A93: =_xlfn.XLOOKUP(B93*1,'Reference '!I:I,'Reference '!K:K) -> Ben Gbeve | B93: =LEFT(C93,3) -> 601 | C93: 601_IS Service Delivery_EIL_GBP | D93: 601_IS Service Delivery_EIL_GBP | E93: 342300 - Software Licences and support | F93: 342300 - Software Licences and support | G93: 000000_Default | H93: 000000_Default | I93: 0000_Default | J93: 0000_Default | K93: Lucid Chart | L93: LUCID SOFTWARE INC | M93: Budget 2026 | N93: GBP | O93: 2666.67 | P93: 2666.67 | Q93: 2666.67 | R93: 2666.67 | S93: 2666.67 | T93: 2666.67 | U93: 2666.67 | V93: 2666.67 | W93: 2666.67 | X93: 2666.67 | Y93: 2666.67 | Z93: 2666.67 | AA93: 32000.04 | AB93: =IF(N93="EUR",AA93,IF(N93="GBP",AA93/Rate!$C$3,AA93/Rate!$C$5)) -> 36781.655 | AC93: =IFERROR(VLOOKUP(K93,'4.2 Simplify Savings'!K:AB,18,0),0) -> 0 | AD93: =SUM(AB93:AC93) -> 36781.655
A94: =_xlfn.XLOOKUP(B94*1,'Reference '!I:I,'Reference '!K:K) -> Ben Gbeve | B94: =LEFT(C94,3) -> 601 | C94: 601_IS Service Delivery_EIL_GBP | D94: 601_IS Service Delivery_EIL_GBP | E94: 342300 - Software Licences and support | F94: 342300 - Software Licences and support | G94: 000000_Default | H94: 000000_Default | I94: 0000_Default | J94: 0000_Default | L94: Linked to CAPEX Projects | M94: Budget 2026 | N94: GBP | O94: 10416.67 | P94: 10416.67 | Q94: 10416.67 | R94: 10416.67 | S94: 10416.67 | T94: 10416.67 | U94: 10416.67 | V94: 10416.67 | W94: 10416.67 | X94: 10416.67 | Y94: 10416.67 | Z94: 10416.67 | AA94: 125000.04 | AB94: =IF(N94="EUR",AA94,IF(N94="GBP",AA94/Rate!$C$3,AA94/Rate!$C$5)) -> 143678.21 | AC94: =IFERROR(VLOOKUP(K94,'4.2 Simplify Savings'!K:AB,18,0),0) -> 0 | AD94: =SUM(AB94:AC94) -> 143678.21
A95: =_xlfn.XLOOKUP(B95*1,'Reference '!I:I,'Reference '!K:K) -> Ben Gbeve | B95: =LEFT(C95,3) -> 601 | C95: 601_IS Service Delivery_EIL_GBP | D95: 601_IS Service Delivery_EIL_GBP | E95: 342300 - Software Licences and support | F95: 342300 - Software Licences and support | G95: 000000_Default | H95: 000000_Default | I95: 0000_Default | J95: 0000_Default | K95: Chomebits | L95: Google | M95: Budget 2026 | N95: GBP | O95: 250 | P95: 250 | Q95: 250 | R95: 250 | S95: 250 | T95: 250 | U95: 250 | V95: 250 | W95: 250 | X95: 250 | Y95: 250 | Z95: 250 | AA95: 3000 | AB95: =IF(N95="EUR",AA95,IF(N95="GBP",AA95/Rate!$C$3,AA95/Rate!$C$5)) -> 3448.2759 | AC95: ='4.2 Simplify Savings'!$AB$27 -> -3405 | AD95: =SUM(AB95:AC95) -> 43.275862
A96: =_xlfn.XLOOKUP(B96*1,'Reference '!I:I,'Reference '!K:K) -> Ben Gbeve | B96: =LEFT(C96,3) -> 601 | C96: 601_IS Service Delivery_EIL_GBP | D96: 601_IS Service Delivery_EIL_GBP | E96: 342300 - Software Licences and support | F96: 342300 - Software Licences and support | G96: 000000_Default | H96: 000000_Default | I96: 0000_Default | J96: 0000_Default | K96: Adobe Create Software | L96: Bytes Software Services Limited/Adobe | M96: Budget 2026 | N96: GBP | O96: 4384 | P96: 4384 | Q96: 4384 | R96: 4384 | S96: 4383 | T96: 4383 | U96: 4383 | V96: 4383 | W96: 4383 | X96: 4383 | Y96: 4383 | Z96: 4383 | AA96: 52600 | AB96: =IF(N96="EUR",AA96,IF(N96="GBP",AA96/Rate!$C$3,AA96/Rate!$C$5)) -> 60459.77 | AC96: =IFERROR(VLOOKUP(K96,'4.2 Simplify Savings'!K:AB,18,0),0) -> 0 | AD96: =SUM(AB96:AC96) -> 60459.77
A97: =_xlfn.XLOOKUP(B97*1,'Reference '!I:I,'Reference '!K:K) -> Ben Gbeve | B97: =LEFT(C97,3) -> 601 | C97: 601_IS Service Delivery_EIL_GBP | D97: 601_IS Service Delivery_EIL_GBP | E97: 342300 - Software Licences and support | F97: 342300 - Software Licences and support | G97: 000000_Default | H97: 000000_Default | I97: 0000_Default | J97: 0000_Default | K97: Druva Backup solution *Where is VEEEM?) | L97: BYTES SOFTWARE SERVICES LIMITED / DRUVA | M97: Budget 2026 | N97: GBP | O97: 3850 | P97: 3850 | Q97: 3850 | R97: 3850 | S97: 3850 | T97: 3850 | U97: 3850 | V97: 3850 | W97: 3850 | X97: 3850 | Y97: 3850 | Z97: 3850 | AA97: 46200 | AB97: =IF(N97="EUR",AA97,IF(N97="GBP",AA97/Rate!$C$3,AA97/Rate!$C$5)) -> 53103.448 | AC97: =IFERROR(VLOOKUP(K97,'4.2 Simplify Savings'!K:AB,18,0),0) -> 0 | AD97: =SUM(AB97:AC97) -> 53103.448
A98: =_xlfn.XLOOKUP(B98*1,'Reference '!I:I,'Reference '!K:K) -> Ben Gbeve | B98: =LEFT(C98,3) -> 601 | C98: 601_IS Service Delivery_EIL_GBP | D98: 601_IS Service Delivery_EIL_GBP | E98: 342300 - Software Licences and support | F98: 342300 - Software Licences and support | G98: 000000_Default | H98: 000000_Default | I98: 0000_Default | J98: 0000_Default | K98: Micosoft on premis/non-cloud software | L98: BYTES SOFTWARE SERVICES LIMITED | M98: Budget 2026 | N98: GBP | O98: 3083.33 | P98: 3083.33 | Q98: 3083.33 | R98: 3083.33 | S98: 3083.33 | T98: 3083.33 | U98: 3083.33 | V98: 3083.33 | W98: 3083.33 | X98: 3083.33 | Y98: 3083.33 | Z98: 3083.33 | AA98: 36999.96 | AB98: =IF(N98="EUR",AA98,IF(N98="GBP",AA98/Rate!$C$3,AA98/Rate!$C$5)) -> 42528.69 | AC98: =IFERROR(VLOOKUP(K98,'4.2 Simplify Savings'!K:AB,18,0),0) -> 0 | AD98: =SUM(AB98:AC98) -> 42528.69
A99: =_xlfn.XLOOKUP(B99*1,'Reference '!I:I,'Reference '!K:K) -> Ben Gbeve | B99: =LEFT(C99,3) -> 601 | C99: 601_IS Service Delivery_EIL_GBP | D99: 601_IS Service Delivery_EIL_GBP | E99: 342300 - Software Licences and support | F99: 342300 - Software Licences and support | G99: 000000_Default | H99: 000000_Default | I99: 0000_Default | J99: 0000_Default | K99: Mimecast email security - EIL | L99: BYTES SOFTWARE SERVICES LIMITED | M99: Budget 2026 | N99: GBP | O99: 7900 | P99: 7900 | Q99: 7900 | R99: 7900 | S99: 7900 | T99: 7900 | U99: 7900 | V99: 7900 | W99: 7900 | X99: 7900 | Y99: 7900 | Z99: 7900 | AA99: 94800 | AB99: =IF(N99="EUR",AA99,IF(N99="GBP",AA99/Rate!$C$3,AA99/Rate!$C$5)) -> 108965.52 | AC99: =IFERROR(VLOOKUP(K99,'4.2 Simplify Savings'!K:AB,18,0),0) -> 0 | AD99: =SUM(AB99:AC99) -> 108965.52
A100: =_xlfn.XLOOKUP(B100*1,'Reference '!I:I,'Reference '!K:K) -> Ben Gbeve | B100: =LEFT(C100,3) -> 601 | C100: 601_IS Service Delivery_EIL_USD | D100: 601_IS Service Delivery_EIL_USD | E100: 342300 - Software Licences and support | F100: 342300 - Software Licences and support | G100: 000000_Default | H100: 000000_Default | I100: 0000_Default | J100: 0000_Default | K100: Cost monitring service | L100: CLOUDCHECKR INC. | M100: Budget 2026 | N100: USD | O100: 2500 | P100: 2500 | Q100: 2500 | R100: 2500 | S100: 2500 | T100: 2500 | U100: 2500 | V100: 2500 | W100: 2500 | X100: 2500 | Y100: 2500 | Z100: 2500 | AA100: 30000 | AB100: =IF(N100="EUR",AA100,IF(N100="GBP",AA100/Rate!$C$3,AA100/Rate!$C$5)) -> 25641.026 | AC100: ='4.2 Simplify Savings'!$AB$28 -> -25800 | AD100: =SUM(AB100:AC100) -> -158.97436
A101: =_xlfn.XLOOKUP(B101*1,'Reference '!I:I,'Reference '!K:K) -> Ben Gbeve | B101: =LEFT(C101,3) -> 601 | C101: 601_IS Service Delivery_EIL_USD | D101: 601_IS Service Delivery_EIL_USD | E101: 342300 - Software Licences and support | F101: 342300 - Software Licences and support | G101: 000000_Default | H101: 000000_Default | I101: 0000_Default | J101: 0000_Default | K101: SentinelOne Endpoint protection | L101: BYTES SOFTWARE SERVICES LIMITED | M101: Budget 2026 | N101: USD | O101: 7613.67 | P101: 7613.67 | Q101: 7613.67 | R101: 7613.67 | S101: 7613.67 | T101: 7613.67 | U101: 7613.67 | V101: 7613.67 | W101: 7613.67 | X101: 7613.67 | Y101: 7613.67 | Z101: 7613.67 | AA101: 91364.04 | AB101: =IF(N101="EUR",AA101,IF(N101="GBP",AA101/Rate!$C$3,AA101/Rate!$C$5)) -> 78088.923 | AC101: =IFERROR(VLOOKUP(K101,'4.2 Simplify Savings'!K:AB,18,0),0) -> 0 | AD101: =SUM(AB101:AC101) -> 78088.923
A102: =_xlfn.XLOOKUP(B102*1,'Reference '!I:I,'Reference '!K:K) -> Valerie Veyt | B102: =LEFT(C102,3) -> 602 | C102: 602_IS Operational_EIL_EUR | D102: 602_IS Operational_EIL_EUR | E102: 342300 - Software Licences and support | F102: 342300 - Software Licences and support | G102: 000000_Default | H102: 000000_Default | I102: 0000_Default | J102: 0000_Default | K102: ATESS-FMS manages the data collected by ATESS: Support and License | L102: WABTEC FAIVELEY TRANSPORT Touraine | M102: Budget 2026 | N102: EUR | O102: 4666.67 | P102: 4666.67 | Q102: 4666.67 | R102: 4666.67 | S102: 4666.67 | T102: 4666.67 | U102: 4666.67 | V102: 4666.67 | W102: 4666.67 | X102: 4666.67 | Y102: 4666.67 | Z102: 4666.67 | AA102: 56000.04 | AB102: =IF(N102="EUR",AA102,IF(N102="GBP",AA102/Rate!$C$3,AA102/Rate!$C$5)) -> 56000.04 | AC102: =IFERROR(VLOOKUP(K102,'4.2 Simplify Savings'!K:AB,18,0),0) -> 0 | AD102: =SUM(AB102:AC102) -> 56000.04
A103: =_xlfn.XLOOKUP(B103*1,'Reference '!I:I,'Reference '!K:K) -> Valerie Veyt | B103: =LEFT(C103,3) -> 602 | C103: 602_IS Operational_EIL_EUR | D103: 602_IS Operational_EIL_EUR | E103: 342300 - Software Licences and support | F103: 342300 - Software Licences and support | G103: E14_SNCF VOYAGES GRANDES LIGNES | H103: E14_SNCF VOYAGES GRANDES LIGNES | I103: 1633_TIGRE Replacement | J103: 1633_TIGRE Replacement | K103: Tigre | L103: SNCF FC - Matériel | M103: Budget 2026 | N103: EUR | O103: 64583.33 | P103: 64583.33 | Q103: 64583.33 | R103: 64583.33 | S103: 64583.33 | T103: 64583.33 | U103: 64583.33 | V103: 64583.33 | W103: 64583.33 | X103: 64583.33 | Y103: 64583.33 | Z103: 64583.33 | AA103: 774999.96 | AB103: =IF(N103="EUR",AA103,IF(N103="GBP",AA103/Rate!$C$3,AA103/Rate!$C$5)) -> 774999.96 | AC103: =IFERROR(VLOOKUP(K103,'4.2 Simplify Savings'!K:AB,18,0),0) -> 0 | AD103: =SUM(AB103:AC103) -> 774999.96
A104: =_xlfn.XLOOKUP(B104*1,'Reference '!I:I,'Reference '!K:K) -> Valerie Veyt | B104: =LEFT(C104,3) -> 602 | C104: 602_IS Operational_EIL_EUR | D104: 602_IS Operational_EIL_EUR | E104: 342300 - Software Licences and support | F104: 342300 - Software Licences and support | G104: 000000_Default | H104: 000000_Default | I104: 0000_Default | J104: 0000_Default | K104: RNE Common Component System | L104: RAILNETEUROPE | M104: Budget 2026 | N104: EUR | O104: 641.67 | P104: 641.67 | Q104: 641.67 | R104: 641.67 | S104: 641.67 | T104: 641.67 | U104: 641.67 | V104: 641.67 | W104: 641.67 | X104: 641.67 | Y104: 641.67 | Z104: 641.67 | AA104: 7700.04 | AB104: =IF(N104="EUR",AA104,IF(N104="GBP",AA104/Rate!$C$3,AA104/Rate!$C$5)) -> 7700.04 | AC104: =IFERROR(VLOOKUP(K104,'4.2 Simplify Savings'!K:AB,18,0),0) -> 0 | AD104: =SUM(AB104:AC104) -> 7700.04
A105: =_xlfn.XLOOKUP(B105*1,'Reference '!I:I,'Reference '!K:K) -> Valerie Veyt | B105: =LEFT(C105,3) -> 602 | C105: 602_IS Operational_EIL_EUR | D105: 602_IS Operational_EIL_EUR | E105: 342300 - Software Licences and support | F105: 342300 - Software Licences and support | G105: 000000_Default | H105: 000000_Default | I105: 0000_Default | J105: 0000_Default | K105: Mantra CFT License | L105: Mantra CFT License | M105: Budget 2026 | N105: EUR | O105: 1666.67 | P105: 1666.67 | Q105: 1666.67 | R105: 1666.67 | S105: 1666.67 | T105: 1666.67 | U105: 1666.67 | V105: 1666.67 | W105: 1666.67 | X105: 1666.67 | Y105: 1666.67 | Z105: 1666.67 | AA105: 20000.04 | AB105: =IF(N105="EUR",AA105,IF(N105="GBP",AA105/Rate!$C$3,AA105/Rate!$C$5)) -> 20000.04 | AC105: =IFERROR(VLOOKUP(K105,'4.2 Simplify Savings'!K:AB,18,0),0) -> -20000.04 | AD105: =SUM(AB105:AC105) -> 0
A106: =_xlfn.XLOOKUP(B106*1,'Reference '!I:I,'Reference '!K:K) -> Valerie Veyt | B106: =LEFT(C106,3) -> 602 | C106: 602_IS Operational_EIL_EUR | D106: 602_IS Operational_EIL_EUR | E106: 342300 - Software Licences and support | F106: 342300 - Software Licences and support | G106: 000000_Default | H106: 000000_Default | I106: 1373_WiFi On Board | J106: 1373_WiFi On Board | K106: Quintic Software Licences and support (eRoster and Quintic P&M) TBC | L106: DASSAULT SYSTEMES UK LIMITED | M106: Budget 2026 | N106: EUR | O106: 20833.33 | P106: 20833.33 | Q106: 20833.33 | R106: 20833.33 | S106: 20833.33 | T106: 20833.33 | U106: 20833.33 | V106: 20833.33 | W106: 20833.33 | X106: 20833.33 | Y106: 20833.33 | Z106: 20833.33 | AA106: 249999.96 | AB106: =IF(N106="EUR",AA106,IF(N106="GBP",AA106/Rate!$C$3,AA106/Rate!$C$5)) -> 249999.96 | AC106: =IFERROR(VLOOKUP(K106,'4.2 Simplify Savings'!K:AB,18,0),0) -> 0 | AD106: =SUM(AB106:AC106) -> 249999.96
A107: =_xlfn.XLOOKUP(B107*1,'Reference '!I:I,'Reference '!K:K) -> Valerie Veyt | B107: =LEFT(C107,3) -> 602 | C107: 602_IS Operational_EIL_EUR | D107: 602_IS Operational_EIL_EUR | E107: 342300 - Software Licences and support | F107: 342300 - Software Licences and support | G107: 000000_Default | H107: 000000_Default | I107: 0000_Default | J107: 0000_Default | K107: star run | M107: Budget 2026 | N107: EUR | O107: 4166.67 | P107: 4166.67 | Q107: 4166.67 | R107: 4166.67 | S107: 4166.67 | T107: 4166.67 | U107: 4166.67 | V107: 4166.67 | W107: 4166.67 | X107: 4166.67 | Y107: 4166.67 | Z107: 4166.67 | AA107: 50000.04 | AB107: =IF(N107="EUR",AA107,IF(N107="GBP",AA107/Rate!$C$3,AA107/Rate!$C$5)) -> 50000.04 | AC107: =IFERROR(VLOOKUP(K107,'4.2 Simplify Savings'!K:AB,18,0),0) -> 0 | AD107: =SUM(AB107:AC107) -> 50000.04
A108: =_xlfn.XLOOKUP(B108*1,'Reference '!I:I,'Reference '!K:K) -> Valerie Veyt | B108: =LEFT(C108,3) -> 602 | C108: 602_IS Operational_EIL_GBP | D108: 602_IS Operational_EIL_GBP | E108: 342300 - Software Licences and support | F108: 342300 - Software Licences and support | G108: 000000_Default | H108: 000000_Default | I108: 0000_Default | J108: 0000_Default | K108: Siemens PIS & FMS Connectivity Support | L108: SIEMENS Mobility Limited | M108: Budget 2026 | N108: GBP | O108: 14333.1 | P108: 14333.1 | Q108: 14333.1 | R108: 14333.1 | S108: 14333.1 | T108: 14333.1 | U108: 14333.1 | V108: 14333.1 | W108: 14333.1 | X108: 14333.1 | Y108: 14333.1 | Z108: 14333.1 | AA108: 171997.2 | AB108: =IF(N108="EUR",AA108,IF(N108="GBP",AA108/Rate!$C$3,AA108/Rate!$C$5)) -> 197697.93 | AC108: =IFERROR(VLOOKUP(K108,'4.2 Simplify Savings'!K:AB,18,0),0) -> 0 | AD108: =SUM(AB108:AC108) -> 197697.93
A109: =_xlfn.XLOOKUP(B109*1,'Reference '!I:I,'Reference '!K:K) -> Valerie Veyt | B109: =LEFT(C109,3) -> 602 | C109: 602_IS Operational_EIL_GBP | D109: 602_IS Operational_EIL_GBP | E109: 342300 - Software Licences and support | F109: 342300 - Software Licences and support | G109: 000000_Default | H109: 000000_Default | I109: 0000_Default | J109: 0000_Default | K109: Escrow | L109: NCC SERVICES LIMITED | M109: Budget 2026 | N109: GBP | O109: 551.82 | P109: 551.82 | Q109: 551.82 | R109: 551.82 | S109: 551.82 | T109: 551.82 | U109: 551.82 | V109: 551.82 | W109: 551.82 | X109: 551.82 | Y109: 551.82 | Z109: 551.82 | AA109: 6621.84 | AB109: =IF(N109="EUR",AA109,IF(N109="GBP",AA109/Rate!$C$3,AA109/Rate!$C$5)) -> 7611.3103 | AC109: =IFERROR(VLOOKUP(K109,'4.2 Simplify Savings'!K:AB,18,0),0) -> 0 | AD109: =SUM(AB109:AC109) -> 7611.3103
A110: =_xlfn.XLOOKUP(B110*1,'Reference '!I:I,'Reference '!K:K) -> Valerie Veyt | B110: =LEFT(C110,3) -> 602 | C110: 602_IS Operational_EIL_GBP | D110: 602_IS Operational_EIL_GBP | E110: 342300 - Software Licences and support | F110: 342300 - Software Licences and support | G110: 000000_Default | H110: 000000_Default | I110: 0000_Default | J110: 0000_Default | K110: MRI Evolution | L110: MRI | M110: Budget 2026 | N110: GBP | O110: 5733.24 | P110: 5733.24 | Q110: 5733.24 | R110: 5733.24 | S110: 5733.24 | T110: 5733.24 | U110: 5733.24 | V110: 5733.24 | W110: 5733.24 | X110: 5733.24 | Y110: 5733.24 | Z110: 5733.24 | AA110: 68798.88 | AB110: =IF(N110="EUR",AA110,IF(N110="GBP",AA110/Rate!$C$3,AA110/Rate!$C$5)) -> 79079.172 | AC110: =IFERROR(VLOOKUP(K110,'4.2 Simplify Savings'!K:AB,18,0),0) -> 0 | AD110: =SUM(AB110:AC110) -> 79079.172
A111: =_xlfn.XLOOKUP(B111*1,'Reference '!I:I,'Reference '!K:K) -> Valerie Veyt | B111: =LEFT(C111,3) -> 602 | C111: 602_IS Operational_EIL_GBP | D111: 602_IS Operational_EIL_GBP | E111: 342300 - Software Licences and support | F111: 342300 - Software Licences and support | G111: 000000_Default | H111: 000000_Default | I111: 0000_Default | J111: 0000_Default | K111: Netcourier API - used by Eurodispatch | L111: METAFOUR UK LIMITED | M111: Budget 2026 | N111: GBP | O111: 3153.28 | P111: 3153.28 | Q111: 3153.28 | R111: 3153.28 | S111: 3153.28 | T111: 3153.28 | U111: 3153.28 | V111: 3153.28 | W111: 3153.28 | X111: 3153.28 | Y111: 3153.28 | Z111: 3153.28 | AA111: 37839.36 | AB111: =IF(N111="EUR",AA111,IF(N111="GBP",AA111/Rate!$C$3,AA111/Rate!$C$5)) -> 43493.517 | AC111: =IFERROR(VLOOKUP(K111,'4.2 Simplify Savings'!K:AB,18,0),0) -> 0 | AD111: =SUM(AB111:AC111) -> 43493.517
A112: =_xlfn.XLOOKUP(B112*1,'Reference '!I:I,'Reference '!K:K) -> Valerie Veyt | B112: =LEFT(C112,3) -> 602 | C112: 602_IS Operational_EIL_GBP | D112: 602_IS Operational_EIL_GBP | E112: 342300 - Software Licences and support | F112: 342300 - Software Licences and support | G112: 000000_Default | H112: 000000_Default | I112: 0000_Default | J112: 0000_Default | K112: License and support - Roster Stations and TMI | L112: KRONOS SYSTEMS LIMITED | M112: Budget 2026 | N112: GBP | O112: 6091.57 | P112: 6091.57 | Q112: 6091.57 | R112: 6091.57 | S112: 6091.57 | T112: 6091.57 | U112: 6091.57 | V112: 6091.57 | W112: 6091.57 | X112: 6091.57 | Y112: 6091.57 | Z112: 6091.57 | AA112: 73098.84 | AB112: =IF(N112="EUR",AA112,IF(N112="GBP",AA112/Rate!$C$3,AA112/Rate!$C$5)) -> 84021.655 | AC112: =IFERROR(VLOOKUP(K112,'4.2 Simplify Savings'!K:AB,18,0),0) -> 0 | AD112: =SUM(AB112:AC112) -> 84021.655
A113: =_xlfn.XLOOKUP(B113*1,'Reference '!I:I,'Reference '!K:K) -> Valerie Veyt | B113: =LEFT(C113,3) -> 602 | C113: 602_IS Operational_EIL_GBP | D113: 602_IS Operational_EIL_GBP | E113: 342300 - Software Licences and support | F113: 342300 - Software Licences and support | G113: 000000_Default | H113: 000000_Default | I113: 0000_Default | J113: 0000_Default | K113: ACMS Compentency Management Licenses and Support | L113: ASSESSTECH LIMITED | M113: Budget 2026 | N113: GBP | O113: 10835.82 | P113: 10835.82 | Q113: 10835.82 | R113: 10835.82 | S113: 10835.82 | T113: 10835.82 | U113: 10835.82 | V113: 10835.82 | W113: 10835.82 | X113: 10835.82 | Y113: 10835.82 | Z113: 10835.82 | AA113: 130029.84 | AB113: =IF(N113="EUR",AA113,IF(N113="GBP",AA113/Rate!$C$3,AA113/Rate!$C$5)) -> 149459.59 | AC113: =IFERROR(VLOOKUP(K113,'4.2 Simplify Savings'!K:AB,18,0),0) -> 0 | AD113: =SUM(AB113:AC113) -> 149459.59
...

Sheet 2.2 EIL COS
Y3: Total | Z3: =SUBTOTAL(9,Z5:Z22) -> 13274936
A4: Cost center manager | B4: Is Split Child Row | C4: Level Code | D4: Level Name | E4: Account Code Code | F4: Account Code Name | G4: Counterparty Code | H4: Counterparty Name | I4: Project Code | J4: Project Name | K4: Description | L4: Level Currency | M4: Jan-2026 | N4: Feb-2026 | O4: Mar-2026 | P4: Apr-2026 | Q4: May-2026 | R4: Jun-2026 | S4: Jul-2026 | T4: Aug-2026 | U4: Sep-2026 | V4: Oct-2026 | W4: Nov-2026 | X4: Dec-2026 | Y4: FY2026 | Z4: Cost in euros
A5: =_xlfn.XLOOKUP(B5*1,'Reference '!I:I,'Reference '!K:K) -> Xavier Romanet | B5: =LEFT(C5,3) -> 605 | C5: 605_IS Sales System_EIL_EUR | D5: 605_IS Sales System_EIL_EUR | E5: 230300 - GDS costs (CoS) | F5: 230300 - GDS costs (CoS) | G5: 000000_Default | H5: 000000_Default | I5: 0000_Default | J5: 0000_Default | K5: Amadeus CC Auth | L5: EUR | M5: 230 | N5: 230 | O5: 230 | P5: 230 | Q5: 230 | R5: 230 | S5: 230 | T5: 230 | U5: 230 | V5: 230 | W5: 230 | X5: 230 | Y5: 2760 | Z5: =IF(L5="EUR",Y5,IF(L5="GBP",Y5/[74]Rate!$C$3,Y5/[74]Rate!$C$5)) -> 2760
A6: =_xlfn.XLOOKUP(B6*1,'Reference '!I:I,'Reference '!K:K) -> Xavier Romanet | B6: =LEFT(C6,3) -> 605 | C6: 605_IS Sales System_EIL_USD | D6: 605_IS Sales System_EIL_USD | E6: 230300 - GDS costs (CoS) | F6: 230300 - GDS costs (CoS) | G6: 000000_Default | H6: 000000_Default | I6: 0000_Default | J6: 0000_Default | K6: ATPCO Fare filing services | L6: USD | M6: 594 | N6: 594 | O6: 594 | P6: 594 | Q6: 594 | R6: 594 | S6: 594 | T6: 594 | U6: 594 | V6: 594 | W6: 594 | X6: 594 | Y6: 7128 | Z6: =IF(L6="EUR",Y6,IF(L6="GBP",Y6/[74]Rate!$C$3,Y6/[74]Rate!$C$5)) -> 6092.3077
A7: =_xlfn.XLOOKUP(B7*1,'Reference '!I:I,'Reference '!K:K) -> Xavier Romanet | B7: =LEFT(C7,3) -> 605 | C7: 605_IS Sales System_EIL_USD | D7: 605_IS Sales System_EIL_USD | E7: 240200 - Hosting (CoS) | F7: 240200 - Hosting (CoS) | G7: 000000_Default | H7: 000000_Default | I7: 0000_Default | J7: 0000_Default | K7: AWS (USD) | L7: USD | M7: 96200 | N7: 96200 | O7: 96200 | P7: 96200 | Q7: 96200 | R7: 96200 | S7: 96200 | T7: 96200 | U7: 96200 | V7: 96200 | W7: 96200 | X7: 96200 | Y7: 1154400 | Z7: =IF(L7="EUR",Y7,IF(L7="GBP",Y7/[74]Rate!$C$3,Y7/[74]Rate!$C$5)) -> 986666.67
A8: =_xlfn.XLOOKUP(B8*1,'Reference '!I:I,'Reference '!K:K) -> Xavier Romanet | B8: =LEFT(C8,3) -> 605 | C8: 605_IS Sales System_EIL_EUR | D8: 605_IS Sales System_EIL_EUR | E8: 230300 - GDS costs (CoS) | F8: 230300 - GDS costs (CoS) | G8: 000000_Default | H8: 000000_Default | I8: 0000_Default | J8: 0000_Default | K8: BENErail | L8: EUR | M8: 60000 | N8: 60000 | O8: 60000 | P8: 60000 | Q8: 60000 | R8: 60000 | S8: 60000 | T8: 60000 | U8: 60000 | V8: 60000 | W8: 60000 | X8: 60000 | Y8: 720000 | Z8: =IF(L8="EUR",Y8,IF(L8="GBP",Y8/[74]Rate!$C$3,Y8/[74]Rate!$C$5)) -> 720000
A9: =_xlfn.XLOOKUP(B9*1,'Reference '!I:I,'Reference '!K:K) -> Mael Delmas | B9: =LEFT(C9,3) -> 604 | C9: 604_IS Customer Systems_EIL_GBP | D9: 604_IS Customer Systems_EIL_GBP | E9: 240200 - Hosting (CoS) | F9: 240200 - Hosting (CoS) | G9: 000000_Default | H9: 000000_Default | I9: 1052_RPO system | J9: 1052_RPO system | K9: Cazyn (Revenue Management Systems) | L9: GBP | M9: 82083.33 | N9: 82083.33 | O9: 82083.33 | P9: 82083.33 | Q9: 82083.33 | R9: 82083.33 | S9: 82083.33 | T9: 82083.33 | U9: 82083.33 | V9: 82083.33 | W9: 82083.33 | X9: 82083.33 | Y9: 984999.96 | Z9: =IF(L9="EUR",Y9,IF(L9="GBP",Y9/[74]Rate!$C$3,Y9/[74]Rate!$C$5)) -> 1132183.9
A10: =_xlfn.XLOOKUP(B10*1,'Reference '!I:I,'Reference '!K:K) -> Xavier Romanet | B10: =LEFT(C10,3) -> 605 | C10: 605_IS Sales System_EIL_EUR | D10: 605_IS Sales System_EIL_EUR | E10: 230300 - GDS costs (CoS) | F10: 230300 - GDS costs (CoS) | G10: 000000_Default | H10: 000000_Default | I10: 0000_Default | J10: 0000_Default | K10: EIL Amadeus Segment charges | L10: EUR | M10: 164988.46 | N10: 124206.88 | O10: 134532.67 | P10: 125092.51 | Q10: 118038.11 | R10: 111436.85 | S10: 105348.33 | T10: 104518.25 | U10: 130928.57 | V10: 124422.8 | W10: 114303.11 | X10: 90037.49 | Y10: 1447854 | Z10: =IF(L10="EUR",Y10,IF(L10="GBP",Y10/[74]Rate!$C$3,Y10/[74]Rate!$C$5)) -> 1447854
A11: =_xlfn.XLOOKUP(B11*1,'Reference '!I:I,'Reference '!K:K) -> Xavier Romanet | B11: =LEFT(C11,3) -> 605 | C11: 605_IS Sales System_EIL_EUR | D11: 605_IS Sales System_EIL_EUR | E11: 230100 - Distribution charges (CoS) | F11: 230100 - Distribution charges (CoS) | G11: E14_SNCF VOYAGES GRANDES LIGNES | H11: E14_SNCF VOYAGES GRANDES LIGNES | I11: 0000_Default | J11: 0000_Default | K11: EIL PAO Var fees (carrier agreement) | L11: EUR | M11: 18971.58 | N11: 14233.67 | O11: 15361.69 | P11: 14252.91 | Q11: 13447.31 | R11: 12719.11 | S11: 11972.06 | T11: 11724.41 | U11: 14919.74 | V11: 14280.46 | W11: 13143.71 | X11: 10396.31 | Y11: 165422.96 | Z11: =IF(L11="EUR",Y11,IF(L11="GBP",Y11/[74]Rate!$C$3,Y11/[74]Rate!$C$5)) -> 165422.96
A12: =_xlfn.XLOOKUP(B12*1,'Reference '!I:I,'Reference '!K:K) -> Xavier Romanet | B12: =LEFT(C12,3) -> 605 | C12: 605_IS Sales System_EIL_EUR | D12: 605_IS Sales System_EIL_EUR | E12: 230100 - Distribution charges (CoS) | F12: 230100 - Distribution charges (CoS) | G12: E14_SNCF VOYAGES GRANDES LIGNES | H12: E14_SNCF VOYAGES GRANDES LIGNES | I12: 0000_Default | J12: 0000_Default | K12: EIL PAO Var fees (distributor agreement) | L12: EUR | M12: 56132.5 | N12: 41928.5 | O12: 41280.02 | P12: 16457.04 | Q12: 16552.68 | R12: 24251.02 | S12: 53873.79 | T12: 44944.93 | U12: 68142.92 | V12: 54763.37 | W12: 44037.58 | X12: 29885.49 | Y12: 492249.84 | Z12: =IF(L12="EUR",Y12,IF(L12="GBP",Y12/[74]Rate!$C$3,Y12/[74]Rate!$C$5)) -> 492249.84
A13: =_xlfn.XLOOKUP(B13*1,'Reference '!I:I,'Reference '!K:K) -> Xavier Romanet | B13: =LEFT(C13,3) -> 605 | C13: 605_IS Sales System_EIL_USD | D13: 605_IS Sales System_EIL_USD | E13: 230300 - GDS costs (CoS) | F13: 230300 - GDS costs (CoS) | G13: 000000_Default | H13: 000000_Default | I13: 0000_Default | J13: 0000_Default | K13: EIL Sabre Segment charges | L13: USD | M13: 176132.32 | N13: 132596.22 | O13: 143619.45 | P13: 133541.66 | Q13: 126010.79 | R13: 118963.66 | S13: 112463.9 | T13: 111577.76 | U13: 139771.92 | V13: 132826.72 | W13: 122023.51 | X13: 96118.92 | Y13: 1545646.8 | Z13: =IF(L13="EUR",Y13,IF(L13="GBP",Y13/[74]Rate!$C$3,Y13/[74]Rate!$C$5)) -> 1321065.7
A14: =_xlfn.XLOOKUP(B14*1,'Reference '!I:I,'Reference '!K:K) -> Xavier Romanet | B14: =LEFT(C14,3) -> 605 | C14: 605_IS Sales System_EIL_EUR | D14: 605_IS Sales System_EIL_EUR | E14: 230100 - Distribution charges (CoS) | F14: 230100 - Distribution charges (CoS) | G14: 000000_Default | H14: 000000_Default | I14: 0000_Default | J14: 0000_Default | K14: EIL Sqills variable charge | L14: EUR | M14: 492229.77 | N14: 369301.58 | O14: 526680.15 | P14: 607529.78 | Q14: 573191.18 | R14: 542151.78 | S14: 510308.66 | T14: 499752.91 | U14: 440512.67 | V14: 370515.77 | W14: 341021.85 | X14: 269738.93 | Y14: 5542935 | Z14: =IF(L14="EUR",Y14,IF(L14="GBP",Y14/[74]Rate!$C$3,Y14/[74]Rate!$C$5)) -> 5542935
A15: =_xlfn.XLOOKUP(B15*1,'Reference '!I:I,'Reference '!K:K) -> Xavier Romanet | B15: =LEFT(C15,3) -> 605 | C15: 605_IS Sales System_EIL_GBP | D15: 605_IS Sales System_EIL_GBP | E15: 230300 - GDS costs (CoS) | F15: 230300 - GDS costs (CoS) | G15: 000000_Default | H15: 000000_Default | I15: 0000_Default | J15: 0000_Default | K15: EIL Travelport Segment charges | L15: GBP | M15: 94291.56 | N15: 70984.73 | O15: 76885.96 | P15: 71490.86 | Q15: 67459.25 | R15: 63686.6 | S15: 60206.99 | T15: 59732.6 | U15: 74826.2 | V15: 71108.12 | W15: 65324.68 | X15: 51456.78 | Y15: 827454.33 | Z15: =IF(L15="EUR",Y15,IF(L15="GBP",Y15/[74]Rate!$C$3,Y15/[74]Rate!$C$5)) -> 951096.93
A16: =_xlfn.XLOOKUP(B16*1,'Reference '!I:I,'Reference '!K:K) -> Xavier Romanet | B16: =LEFT(C16,3) -> 605 | C16: 605_IS Sales System_EIL_EUR | D16: 605_IS Sales System_EIL_EUR | E16: 230300 - GDS costs (CoS) | F16: 230300 - GDS costs (CoS) | G16: 000000_Default | H16: 000000_Default | I16: 0000_Default | J16: 0000_Default | K16: GDS Air Connection (Sqills fixed cost) | L16: EUR | M16: 8182.49 | N16: 8182.49 | O16: 8182.49 | P16: 8182.49 | Q16: 8182.49 | R16: 8182.49 | S16: 8182.49 | T16: 8182.49 | U16: 8182.49 | V16: 8182.49 | W16: 8182.49 | X16: 8182.49 | Y16: 98189.88 | Z16: =IF(L16="EUR",Y16,IF(L16="GBP",Y16/[74]Rate!$C$3,Y16/[74]Rate!$C$5)) -> 98189.88
... A22: =_xlfn.XLOOKUP(B22*1,'Reference '!I:I,'Reference '!K:K) -> Xavier Romanet | B22: =LEFT(C22,3) -> 605 | C22: 605_IS Sales System_EIL_GBP | D22: 605_IS Sales System_EIL_GBP | E22: 240001 - Software Licences and support (CoS) | F22: 240001 - Software Licences and support (CoS) | G22: 000000_Default | H22: 000000_Default | I22: 0000_Default | J22: 0000_Default | K22: Various Software & Tools | L22: GBP | M22: 18500 | N22: 18500 | O22: 18500 | P22: 18500 | Q22: 18500 | R22: 18500 | S22: 18500 | T22: 18500 | U22: 18500 | V22: 18500 | W22: 18500 | X22: 18500 | Y22: 222000 | Z22: =IF(L22="EUR",Y22,IF(L22="GBP",Y22/[74]Rate!$C$3,Y22/[74]Rate!$C$5)) -> 255172.41

Sheet 2.3 EIL Capex 
AP3: =SUBTOTAL(9,AP5:AP79) -> 26992811
A4: Is Split Child Row | B4: PARENT_ASSET_ID | C4: OWNED_LEASED | D4: Cost center manager | E4: Level (Cost Centre) Code | F4: Level (Cost Centre) Name | G4: Project Code | H4: Project Name | I4: Counterparty Code | J4: Counterparty Name | K4: Cost Centre Code | L4: Cost Centre Name | M4: Currency Level Code | N4: Currency Level Name | O4: Asset_Category_1 Code | P4: Asset_Category_1 Name | Q4: FP_Asset_Catergory_2 Code | R4: FP_Asset_Catergory_2 Name | S4: Asset Category 3 (20YP) Code | T4: Asset Category 3 (20YP) Name | U4: Description | V4: Detail | W4: Expected Asset Book cost (per Asset ID) | X4: REMAINING_LIFE_IN_MONTHS | Y4: Recongnition- Depn Start date | Z4: Asset Categorization at purchase Code | AA4: Asset Categorization at purchase Name | AB4: DEPRECIATE_FLAG | AC4: Jan-2026 | AD4: Feb-2026 | AE4: Mar-2026 | AF4: Apr-2026 | AG4: May-2026 | AH4: Jun-2026 | AI4: Jul-2026 | AJ4: Aug-2026 | AK4: Sep-2026 | AL4: Oct-2026 | AM4: Nov-2026 | AN4: Dec-2026 | AO4: FY2026 | AP4: Total in €
A5: No | C5: OWNED | D5: Blanche Derkenne | E5: 600_CIO_EIL_EUR | F5: 600_CIO_EIL_EUR | G5: 0000_Default | H5: 0000_Default | I5: 000000_Default | J5: 000000_Default | K5: 600 | L5: 600 | M5: EUR | N5: EUR | O5: SOFTWARE | P5: SOFTWARE | Q5: Software | R5: Software | S5: Software | T5: Software | U5: Cost savings Target | V5: Medium | W5: -5525316 | X5: 48 | Y5: 1/1/2027 | Z5: CIP | AA5: CIP | AB5: YES | AC5: -460443 | AD5: -460443 | AE5: -460443 | AF5: -460443 | AG5: -460443 | AH5: -460443 | AI5: -460443 | AJ5: -460443 | AK5: -460443 | AL5: -460443 | AM5: -460443 | AN5: -460443 | AO5: -5525316 | AP5: =IF(N5="EUR",AO5,IF(N5="GBP",AO5/Rate!$C$3,'2.3 EIL Capex '!AO34/Rate!$C$5)) -> -5525316 | AQ5: << Centralised IS cost saving target to come back in line with the business plan
A6: No | C6: OWNED | D6: Ben Gbeve | E6: 601_IS Service Delivery_EIL_EUR | F6: 601_IS Service Delivery_EIL_EUR | G6: 0000_Default | H6: 0000_Default | I6: 000000_Default | J6: 000000_Default | K6: 601 | L6: 601 | M6: EUR | N6: EUR | O6: SOFTWARE | P6: SOFTWARE | Q6: Software | R6: Software | S6: Software | T6: Software | U6: Android / IOS Consolidation | V6: Medium | W6: 125004 | X6: 48 | Y6: 1/1/2027 | Z6: CIP | AA6: CIP | AB6: YES | AC6: 10417 | AD6: 10417 | AE6: 10417 | AF6: 10417 | AG6: 10417 | AH6: 10417 | AI6: 10417 | AJ6: 10417 | AK6: 10417 | AL6: 10417 | AM6: 10417 | AN6: 10417 | AO6: 125004 | AP6: =IF(N6="EUR",AO6,IF(N6="GBP",AO6/Rate!$C$3,'2.3 EIL Capex '!AO25/Rate!$C$5)) -> 125004
A7: No | C7: OWNED | D7: Ben Gbeve | E7: 601_IS Service Delivery_EIL_EUR | F7: 601_IS Service Delivery_EIL_EUR | G7: 0000_Default | H7: 0000_Default | I7: 000000_Default | J7: 000000_Default | K7: 601 | L7: 601 | M7: EUR | N7: EUR | O7: SOFTWARE | P7: SOFTWARE | Q7: Software | R7: Software | S7: Software | T7: Software | U7: Cloud PKI | V7: Medium | W7: 50004 | X7: 48 | Y7: 1/1/2027 | Z7: CIP | AA7: CIP | AB7: YES | AC7: 4167 | AD7: 4167 | AE7: 4167 | AF7: 4167 | AG7: 4167 | AH7: 4167 | AI7: 4167 | AJ7: 4167 | AK7: 4167 | AL7: 4167 | AM7: 4167 | AN7: 4167 | AO7: 50004 | AP7: =IF(N7="EUR",AO7,IF(N7="GBP",AO7/Rate!$C$3,'2.3 EIL Capex '!AO28/Rate!$C$5)) -> 50004
A8: No | C8: OWNED | D8: Ben Gbeve | E8: 601_IS Service Delivery_EIL_EUR | F8: 601_IS Service Delivery_EIL_EUR | G8: 0000_Default | H8: 0000_Default | I8: 000000_Default | J8: 000000_Default | K8: 601 | L8: 601 | M8: EUR | N8: EUR | O8: SOFTWARE | P8: SOFTWARE | Q8: Software | R8: Software | S8: Software | T8: Software | U8: Consolidated solution for Cloud Back up & DR | V8: Medium | W8: 99996 | X8: 48 | Y8: 1/1/2027 | Z8: CIP | AA8: CIP | AB8: YES | AC8: 8333 | AD8: 8333 | AE8: 8333 | AF8: 8333 | AG8: 8333 | AH8: 8333 | AI8: 8333 | AJ8: 8333 | AK8: 8333 | AL8: 8333 | AM8: 8333 | AN8: 8333 | AO8: 99996 | AP8: =IF(N8="EUR",AO8,IF(N8="GBP",AO8/Rate!$C$3,'2.3 EIL Capex '!AO30/Rate!$C$5)) -> 99996
A9: No | C9: OWNED | D9: Ben Gbeve | E9: 601_IS Service Delivery_EIL_EUR | F9: 601_IS Service Delivery_EIL_EUR | G9: 0000_Default | H9: 0000_Default | I9: 000000_Default | J9: 000000_Default | K9: 601 | L9: 601 | M9: EUR | N9: EUR | O9: SOFTWARE | P9: SOFTWARE | Q9: Software | R9: Software | S9: Software | T9: Software | U9: Customer Information System refresh | V9: Medium | W9: 99996 | X9: 48 | Y9: 1/1/2027 | Z9: CIP | AA9: CIP | AB9: YES | AC9: 8333 | AD9: 8333 | AE9: 8333 | AF9: 8333 | AG9: 8333 | AH9: 8333 | AI9: 8333 | AJ9: 8333 | AK9: 8333 | AL9: 8333 | AM9: 8333 | AN9: 8333 | AO9: 99996 | AP9: =IF(N9="EUR",AO9,IF(N9="GBP",AO9/Rate!$C$3,'2.3 EIL Capex '!AO35/Rate!$C$5)) -> 99996
A10: No | C10: OWNED | D10: Ben Gbeve | E10: 601_IS Service Delivery_EIL_EUR | F10: 601_IS Service Delivery_EIL_EUR | G10: 0000_Default | H10: 0000_Default | I10: 000000_Default | J10: 000000_Default | K10: 601 | L10: 601 | M10: EUR | N10: EUR | O10: SOFTWARE | P10: SOFTWARE | Q10: Software | R10: Software | S10: Software | T10: Software | U10: DevOps pipeline and containers | V10: Medium | W10: 9996 | X10: 48 | Y10: 1/1/2027 | Z10: CIP | AA10: CIP | AB10: YES | AC10: 833 | AD10: 833 | AE10: 833 | AF10: 833 | AG10: 833 | AH10: 833 | AI10: 833 | AJ10: 833 | AK10: 833 | AL10: 833 | AM10: 833 | AN10: 833 | AO10: 9996 | AP10: =IF(N10="EUR",AO10,IF(N10="GBP",AO10/Rate!$C$3,'2.3 EIL Capex '!AO39/Rate!$C$5)) -> 9996
A11: No | C11: OWNED | D11: Ben Gbeve | E11: 601_IS Service Delivery_EIL_EUR | F11: 601_IS Service Delivery_EIL_EUR | G11: 0000_Default | H11: 0000_Default | I11: 000000_Default | J11: 000000_Default | K11: 601 | L11: 601 | M11: EUR | N11: EUR | O11: PLANT AND MACHINERY | P11: PLANT AND MACHINERY | Q11: It Equipments | R11: It Equipments | S11: Plant & Machinery - IT equipment | T11: Plant & Machinery - IT equipment | U11: Hardware BAU | V11: Medium | W11: 219996 | X11: 48 | Y11: 1/1/2027 | Z11: CIP | AA11: CIP | AB11: YES | AC11: 18333 | AD11: 18333 | AE11: 18333 | AF11: 18333 | AG11: 18333 | AH11: 18333 | AI11: 18333 | AJ11: 18333 | AK11: 18333 | AL11: 18333 | AM11: 18333 | AN11: 18333 | AO11: 219996 | AP11: =IF(N11="EUR",AO11,IF(N11="GBP",AO11/Rate!$C$3,'2.3 EIL Capex '!AO45/Rate!$C$5)) -> 219996
A12: No | C12: OWNED | D12: Ben Gbeve | E12: 601_IS Service Delivery_EIL_EUR | F12: 601_IS Service Delivery_EIL_EUR | G12: 0000_Default | H12: 0000_Default | I12: 000000_Default | J12: 000000_Default | K12: 601 | L12: 601 | M12: EUR | N12: EUR | O12: SOFTWARE | P12: SOFTWARE | Q12: Software | R12: Software | S12: Software | T12: Software | U12: Home drives (H) to OneDrive | V12: Medium | W12: 60000 | X12: 48 | Y12: 1/1/2027 | Z12: CIP | AA12: CIP | AB12: YES | AC12: 5000 | AD12: 5000 | AE12: 5000 | AF12: 5000 | AG12: 5000 | AH12: 5000 | AI12: 5000 | AJ12: 5000 | AK12: 5000 | AL12: 5000 | AM12: 5000 | AN12: 5000 | AO12: 60000 | AP12: =IF(N12="EUR",AO12,IF(N12="GBP",AO12/Rate!$C$3,'2.3 EIL Capex '!AO46/Rate!$C$5)) -> 60000
A13: No | C13: OWNED | D13: Ben Gbeve | E13: 601_IS Service Delivery_EIL_EUR | F13: 601_IS Service Delivery_EIL_EUR | G13: 0000_Default | H13: 0000_Default | I13: 000000_Default | J13: 000000_Default | K13: 601 | L13: 601 | M13: EUR | N13: EUR | O13: SOFTWARE | P13: SOFTWARE | Q13: Software | R13: Software | S13: Software | T13: Software | U13: ISLOG Replacement | V13: Medium | W13: 60000 | X13: 48 | Y13: 1/1/2027 | Z13: CIP | AA13: CIP | AB13: YES | AC13: 5000 | AD13: 5000 | AE13: 5000 | AF13: 5000 | AG13: 5000 | AH13: 5000 | AI13: 5000 | AJ13: 5000 | AK13: 5000 | AL13: 5000 | AM13: 5000 | AN13: 5000 | AO13: 60000 | AP13: =IF(N13="EUR",AO13,IF(N13="GBP",AO13/Rate!$C$3,'2.3 EIL Capex '!AO48/Rate!$C$5)) -> 60000
A14: No | C14: OWNED | D14: Ben Gbeve | E14: 601_IS Service Delivery_EIL_EUR | F14: 601_IS Service Delivery_EIL_EUR | G14: 0000_Default | H14: 0000_Default | I14: 000000_Default | J14: 000000_Default | K14: 601 | L14: 601 | M14: EUR | N14: EUR | O14: SOFTWARE | P14: SOFTWARE | Q14: Software | R14: Software | S14: Software | T14: Software | U14: Lounge Enhancements/Customer Exerience (Wi-Fi / IPTV / Portal) | V14: Medium | W14: 90000 | X14: 48 | Y14: 1/1/2027 | Z14: CIP | AA14: CIP | AB14: YES | AC14: 7500 | AD14: 7500 | AE14: 7500 | AF14: 7500 | AG14: 7500 | AH14: 7500 | AI14: 7500 | AJ14: 7500 | AK14: 7500 | AL14: 7500 | AM14: 7500 | AN14: 7500 | AO14: 90000 | AP14: =IF(N14="EUR",AO14,IF(N14="GBP",AO14/Rate!$C$3,'2.3 EIL Capex '!AO49/Rate!$C$5)) -> 90000
A15: No | C15: OWNED | D15: Ben Gbeve | E15: 601_IS Service Delivery_EIL_EUR | F15: 601_IS Service Delivery_EIL_EUR | G15: 0000_Default | H15: 0000_Default | I15: 000000_Default | J15: 000000_Default | K15: 601 | L15: 601 | M15: EUR | N15: EUR | O15: SOFTWARE | P15: SOFTWARE | Q15: Software | R15: Software | S15: Software | T15: Software | U15: OCC Disaster Recovery | V15: Medium | W15: 60000 | X15: 48 | Y15: 1/1/2027 | Z15: CIP | AA15: CIP | AB15: YES | AC15: 5000 | AD15: 5000 | AE15: 5000 | AF15: 5000 | AG15: 5000 | AH15: 5000 | AI15: 5000 | AJ15: 5000 | AK15: 5000 | AL15: 5000 | AM15: 5000 | AN15: 5000 | AO15: 60000 | AP15: =IF(N15="EUR",AO15,IF(N15="GBP",AO15/Rate!$C$3,'2.3 EIL Capex '!AO54/Rate!$C$5)) -> 60000
A16: No | C16: OWNED | D16: Ben Gbeve | E16: 601_IS Service Delivery_EIL_EUR | F16: 601_IS Service Delivery_EIL_EUR | G16: 0000_Default | H16: 0000_Default | I16: 000000_Default | J16: 000000_Default | K16: 601 | L16: 601 | M16: EUR | N16: EUR | O16: PLANT AND MACHINERY | P16: PLANT AND MACHINERY | Q16: It Equipments | R16: It Equipments | S16: Plant & Machinery - IT equipment | T16: Plant & Machinery - IT equipment | U16: Paris | V16: Medium | W16: 401268 | X16: 48 | Y16: 1/1/2027 | Z16: CIP | AA16: CIP | AB16: YES | AC16: 33439 | AD16: 33439 | AE16: 33439 | AF16: 33439 | AG16: 33439 | AH16: 33439 | AI16: 33439 | AJ16: 33439 | AK16: 33439 | AL16: 33439 | AM16: 33439 | AN16: 33439 | AO16: 401268 | AP16: =IF(N16="EUR",AO16,IF(N16="GBP",AO16/Rate!$C$3,'2.3 EIL Capex '!AO59/Rate!$C$5)) -> 401268
A17: No | C17: OWNED | D17: Ben Gbeve | E17: 601_IS Service Delivery_EIL_EUR | F17: 601_IS Service Delivery_EIL_EUR | G17: 0000_Default | H17: 0000_Default | I17: 000000_Default | J17: 000000_Default | K17: 601 | L17: 601 | M17: EUR | N17: EUR | O17: SOFTWARE | P17: SOFTWARE | Q17: Software | R17: Software | S17: Software | T17: Software | U17: Passwordless | V17: Medium | W17: 9996 | X17: 48 | Y17: 1/1/2027 | Z17: CIP | AA17: CIP | AB17: YES | AC17: 833 | AD17: 833 | AE17: 833 | AF17: 833 | AG17: 833 | AH17: 833 | AI17: 833 | AJ17: 833 | AK17: 833 | AL17: 833 | AM17: 833 | AN17: 833 | AO17: 9996 | AP17: =IF(N17="EUR",AO17,IF(N17="GBP",AO17/Rate!$C$3,'2.3 EIL Capex '!AO60/Rate!$C$5)) -> 9996
A18: No | C18: OWNED | D18: Ben Gbeve | E18: 601_IS Service Delivery_EIL_EUR | F18: 601_IS Service Delivery_EIL_EUR | G18: 0000_Default | H18: 0000_Default | I18: 000000_Default | J18: 000000_Default | K18: 601 | L18: 601 | M18: EUR | N18: EUR | O18: SOFTWARE | P18: SOFTWARE | Q18: Software | R18: Software | S18: Software | T18: Software | U18: Proactive laptop refresh & consolidation | V18: Medium | W18: 200004 | X18: 48 | Y18: 1/1/2027 | Z18: CIP | AA18: CIP | AB18: YES | AC18: 16667 | AD18: 16667 | AE18: 16667 | AF18: 16667 | AG18: 16667 | AH18: 16667 | AI18: 16667 | AJ18: 16667 | AK18: 16667 | AL18: 16667 | AM18: 16667 | AN18: 16667 | AO18: 200004 | AP18: =IF(N18="EUR",AO18,IF(N18="GBP",AO18/Rate!$C$3,'2.3 EIL Capex '!AO63/Rate!$C$5)) -> 200004
A19: No | C19: OWNED | D19: Ben Gbeve | E19: 601_IS Service Delivery_EIL_EUR | F19: 601_IS Service Delivery_EIL_EUR | G19: 0000_Default | H19: 0000_Default | I19: 000000_Default | J19: 000000_Default | K19: 601 | L19: 601 | M19: EUR | N19: EUR | O19: SOFTWARE | P19: SOFTWARE | Q19: Software | R19: Software | S19: Software | T19: Software | U19: SD-WAN / SASE / Consolidate VPN | V19: Medium | W19: 99996 | X19: 48 | Y19: 1/1/2027 | Z19: CIP | AA19: CIP | AB19: YES | AC19: 8333 | AD19: 8333 | AE19: 8333 | AF19: 8333 | AG19: 8333 | AH19: 8333 | AI19: 8333 | AJ19: 8333 | AK19: 8333 | AL19: 8333 | AM19: 8333 | AN19: 8333 | AO19: 99996 | AP19: =IF(N19="EUR",AO19,IF(N19="GBP",AO19/Rate!$C$3,'2.3 EIL Capex '!AO69/Rate!$C$5)) -> 99996
A20: No | C20: OWNED | D20: Ben Gbeve | E20: 601_IS Service Delivery_EIL_EUR | F20: 601_IS Service Delivery_EIL_EUR | G20: 0000_Default | H20: 0000_Default | I20: 000000_Default | J20: 000000_Default | K20: 601 | L20: 601 | M20: EUR | N20: EUR | O20: SOFTWARE | P20: SOFTWARE | Q20: Software | R20: Software | S20: Software | T20: Software | U20: SPI Phase 2 | V20: Medium | W20: 174996 | X20: 48 | Y20: 1/1/2027 | Z20: CIP | AA20: CIP | AB20: YES | AC20: 14583 | AD20: 14583 | AE20: 14583 | AF20: 14583 | AG20: 14583 | AH20: 14583 | AI20: 14583 | AJ20: 14583 | AK20: 14583 | AL20: 14583 | AM20: 14583 | AN20: 14583 | AO20: 174996 | AP20: =IF(N20="EUR",AO20,IF(N20="GBP",AO20/Rate!$C$3,'2.3 EIL Capex '!AO71/Rate!$C$5)) -> 174996
A21: No | C21: OWNED | D21: Ben Gbeve | E21: 601_IS Service Delivery_EIL_EUR | F21: 601_IS Service Delivery_EIL_EUR | G21: 0000_Default | H21: 0000_Default | I21: 000000_Default | J21: 000000_Default | K21: 601 | L21: 601 | M21: EUR | N21: EUR | O21: SOFTWARE | P21: SOFTWARE | Q21: Software | R21: Software | S21: Software | T21: Software | U21: Station Wi-Fi (for mobility) | V21: Medium | W21: 129996 | X21: 48 | Y21: 1/1/2027 | Z21: CIP | AA21: CIP | AB21: YES | AC21: 10833 | AD21: 10833 | AE21: 10833 | AF21: 10833 | AG21: 10833 | AH21: 10833 | AI21: 10833 | AJ21: 10833 | AK21: 10833 | AL21: 10833 | AM21: 10833 | AN21: 10833 | AO21: 129996 | AP21: =IF(N21="EUR",AO21,IF(N21="GBP",AO21/Rate!$C$3,'2.3 EIL Capex '!AO72/Rate!$C$5)) -> 129996
A22: No | C22: OWNED | D22: Ben Gbeve | E22: 601_IS Service Delivery_EIL_EUR | F22: 601_IS Service Delivery_EIL_EUR | G22: 0000_Default | H22: 0000_Default | I22: 000000_Default | J22: 000000_Default | K22: 601 | L22: 601 | M22: EUR | N22: EUR | O22: SOFTWARE | P22: SOFTWARE | Q22: Software | R22: Software | S22: Software | T22: Software | U22: Stations improvements | V22: Medium | W22: 150000 | X22: 48 | Y22: 1/1/2027 | Z22: CIP | AA22: CIP | AB22: YES | AC22: 12500 | AD22: 12500 | AE22: 12500 | AF22: 12500 | AG22: 12500 | AH22: 12500 | AI22: 12500 | AJ22: 12500 | AK22: 12500 | AL22: 12500 | AM22: 12500 | AN22: 12500 | AO22: 150000 | AP22: =IF(N22="EUR",AO22,IF(N22="GBP",AO22/Rate!$C$3,'2.3 EIL Capex '!AO74/Rate!$C$5)) -> 150000
A23: No | C23: OWNED | D23: Ben Gbeve | E23: 601_IS Service Delivery_EIL_EUR | F23: 601_IS Service Delivery_EIL_EUR | G23: 0000_Default | H23: 0000_Default | I23: 000000_Default | J23: 000000_Default | K23: 601 | L23: 601 | M23: EUR | N23: EUR | O23: SOFTWARE | P23: SOFTWARE | Q23: Software | R23: Software | S23: Software | T23: Software | U23: Teams Rooms Replacements | V23: Medium | W23: 99996 | X23: 48 | Y23: 1/1/2027 | Z23: CIP | AA23: CIP | AB23: YES | AC23: 8333 | AD23: 8333 | AE23: 8333 | AF23: 8333 | AG23: 8333 | AH23: 8333 | AI23: 8333 | AJ23: 8333 | AK23: 8333 | AL23: 8333 | AM23: 8333 | AN23: 8333 | AO23: 99996 | AP23: =IF(N23="EUR",AO23,IF(N23="GBP",AO23/Rate!$C$3,'2.3 EIL Capex '!AO75/Rate!$C$5)) -> 99996
A24: No | C24: OWNED | D24: Ben Gbeve | E24: 601_IS Service Delivery_EIL_EUR | F24: 601_IS Service Delivery_EIL_EUR | G24: 0000_Default | H24: 0000_Default | I24: 000000_Default | J24: 000000_Default | K24: 601 | L24: 601 | M24: EUR | N24: EUR | O24: PLANT AND MACHINERY | P24: PLANT AND MACHINERY | Q24: It Equipments | R24: It Equipments | S24: Plant & Machinery - IT equipment | T24: Plant & Machinery - IT equipment | U24: Terminal Control Refurb | V24: Medium | W24: 211188 | X24: 48 | Y24: 1/1/2027 | Z24: CIP | AA24: CIP | AB24: YES | AC24: 17599 | AD24: 17599 | AE24: 17599 | AF24: 17599 | AG24: 17599 | AH24: 17599 | AI24: 17599 | AJ24: 17599 | AK24: 17599 | AL24: 17599 | AM24: 17599 | AN24: 17599 | AO24: 211188 | AP24: =IF(N24="EUR",AO24,IF(N24="GBP",AO24/Rate!$C$3,'2.3 EIL Capex '!AO76/Rate!$C$5)) -> 211188
A25: No | C25: OWNED | D25: Ben Gbeve | E25: 601_IS Service Delivery_EIL_EUR | F25: 601_IS Service Delivery_EIL_EUR | G25: 0000_Default | H25: 0000_Default | I25: 000000_Default | J25: 000000_Default | K25: 601 | L25: 601 | M25: EUR | N25: EUR | O25: SOFTWARE | P25: SOFTWARE | Q25: Software | R25: Software | S25: Software | T25: Software | U25: UPS Upgrades + Power | V25: Medium | W25: 99996 | X25: 48 | Y25: 1/1/2027 | Z25: CIP | AA25: CIP | AB25: YES | AC25: 8333 | AD25: 8333 | AE25: 8333 | AF25: 8333 | AG25: 8333 | AH25: 8333 | AI25: 8333 | AJ25: 8333 | AK25: 8333 | AL25: 8333 | AM25: 8333 | AN25: 8333 | AO25: 99996 | AP25: =IF(N25="EUR",AO25,IF(N25="GBP",AO25/Rate!$C$3,'2.3 EIL Capex '!AO78/Rate!$C$5)) -> 99996
A26: No | C26: OWNED | D26: Ben Gbeve | E26: 601_IS Service Delivery_EIL_EUR | F26: 601_IS Service Delivery_EIL_EUR | G26: 0000_Default | H26: 0000_Default | I26: 000000_Default | J26: 000000_Default | K26: 601 | L26: 601 | M26: EUR | N26: EUR | O26: SOFTWARE | P26: SOFTWARE | Q26: Software | R26: Software | S26: Software | T26: Software | U26: Windows 2016 Sever replacement | V26: Medium | W26: 80004 | X26: 48 | Y26: 1/1/2027 | Z26: CIP | AA26: CIP | AB26: YES | AC26: 6667 | AD26: 6667 | AE26: 6667 | AF26: 6667 | AG26: 6667 | AH26: 6667 | AI26: 6667 | AJ26: 6667 | AK26: 6667 | AL26: 6667 | AM26: 6667 | AN26: 6667 | AO26: 80004 | AP26: =IF(N26="EUR",AO26,IF(N26="GBP",AO26/Rate!$C$3,'2.3 EIL Capex '!AO79/Rate!$C$5)) -> 80004
A27: No | C27: OWNED | D27: Valerie Veyt | E27: 602_IS Operational_EIL_EUR | F27: 602_IS Operational_EIL_EUR | G27: 0000_Default | H27: 0000_Default | I27: 000000_Default | J27: 000000_Default | K27: 602 | L27: 602 | M27: EUR | N27: EUR | O27: SOFTWARE | P27: SOFTWARE | Q27: Software | R27: Software | S27: Software | T27: Software | U27: [RTSP] Developments/Enhancements | V27: Medium | W27: 17004 | X27: 48 | Y27: 1/1/2027 | Z27: CIP | AA27: CIP | AB27: YES | AC27: 1417 | AD27: 1417 | AE27: 1417 | AF27: 1417 | AG27: 1417 | AH27: 1417 | AI27: 1417 | AJ27: 1417 | AK27: 1417 | AL27: 1417 | AM27: 1417 | AN27: 1417 | AO27: 17004 | AP27: =IF(N27="EUR",AO27,IF(N27="GBP",AO27/Rate!$C$3,'2.3 EIL Capex '!AO11/Rate!$C$5)) -> 17004
A28: No | C28: OWNED | D28: Valerie Veyt | E28: 602_IS Operational_EIL_EUR | F28: 602_IS Operational_EIL_EUR | G28: 0000_Default | H28: 0000_Default | I28: 000000_Default | J28: 000000_Default | K28: 602 | L28: 602 | M28: EUR | N28: EUR | O28: SOFTWARE | P28: SOFTWARE | Q28: Software | R28: Software | S28: Software | T28: Software | U28: [SIMPLIFY] Quintic Planning and maintenance version upgrade | V28: Medium | W28: 99996 | X28: 48 | Y28: 1/1/2027 | Z28: CIP | AA28: CIP | AB28: YES | AC28: 8333 | AD28: 8333 | AE28: 8333 | AF28: 8333 | AG28: 8333 | AH28: 8333 | AI28: 8333 | AJ28: 8333 | AK28: 8333 | AL28: 8333 | AM28: 8333 | AN28: 8333 | AO28: 99996 | AP28: =IF(N28="EUR",AO28,IF(N28="GBP",AO28/Rate!$C$3,'2.3 EIL Capex '!AO12/Rate!$C$5)) -> 99996
A29: No | C29: OWNED | D29: Valerie Veyt | E29: 602_IS Operational_EIL_EUR | F29: 602_IS Operational_EIL_EUR | G29: 0000_Default | H29: 0000_Default | I29: 000000_Default | J29: 000000_Default | K29: 602 | L29: 602 | M29: EUR | N29: EUR | O29: SOFTWARE | P29: SOFTWARE | Q29: Software | R29: Software | S29: Software | T29: Software | U29: API into MRI Evolution | V29: Medium | W29: 50004 | X29: 48 | Y29: 1/1/2027 | Z29: CIP | AA29: CIP | AB29: YES | AC29: 4167 | AD29: 4167 | AE29: 4167 | AF29: 4167 | AG29: 4167 | AH29: 4167 | AI29: 4167 | AJ29: 4167 | AK29: 4167 | AL29: 4167 | AM29: 4167 | AN29: 4167 | AO29: 50004 | AP29: =IF(N29="EUR",AO29,IF(N29="GBP",AO29/Rate!$C$3,'2.3 EIL Capex '!AO26/Rate!$C$5)) -> 50004
A30: No | C30: OWNED | D30: Valerie Veyt | E30: 602_IS Operational_EIL_EUR | F30: 602_IS Operational_EIL_EUR | G30: 0000_Default | H30: 0000_Default | I30: 000000_Default | J30: 000000_Default | K30: 602 | L30: 602 | M30: EUR | N30: EUR | O30: SOFTWARE | P30: SOFTWARE | Q30: Software | R30: Software | S30: Software | T30: Software | U30: AssessTech - Onboarding Ops continental teams proj (Phase 2) | V30: Medium | W30: 57996 | X30: 48 | Y30: 1/1/2027 | Z30: CIP | AA30: CIP | AB30: YES | AC30: 4833 | AD30: 4833 | AE30: 4833 | AF30: 4833 | AG30: 4833 | AH30: 4833 | AI30: 4833 | AJ30: 4833 | AK30: 4833 | AL30: 4833 | AM30: 4833 | AN30: 4833 | AO30: 57996 | AP30: =IF(N30="EUR",AO30,IF(N30="GBP",AO30/Rate!$C$3,'2.3 EIL Capex '!AO27/Rate!$C$5)) -> 57996
A31: No | C31: OWNED | D31: Valerie Veyt | E31: 602_IS Operational_EIL_EUR | F31: 602_IS Operational_EIL_EUR | G31: 0000_Default | H31: 0000_Default | I31: 000000_Default | J31: 000000_Default | K31: 602 | L31: 602 | M31: EUR | N31: EUR | O31: PLANT AND MACHINERY | P31: PLANT AND MACHINERY | Q31: It Equipments | R31: It Equipments | S31: Plant & Machinery - IT equipment | T31: Plant & Machinery - IT equipment | U31: Continental Fleet PIS Enhancements | V31: Medium | W31: 99996 | X31: 48 | Y31: 1/1/2027 | Z31: CIP | AA31: CIP | AB31: YES | AC31: 8333 | AD31: 8333 | AE31: 8333 | AF31: 8333 | AG31: 8333 | AH31: 8333 | AI31: 8333 | AJ31: 8333 | AK31: 8333 | AL31: 8333 | AM31: 8333 | AN31: 8333 | AO31: 99996 | AP31: =IF(N31="EUR",AO31,IF(N31="GBP",AO31/Rate!$C$3,'2.3 EIL Capex '!AO31/Rate!$C$5)) -> 99996
A32: No | C32: OWNED | D32: Valerie Veyt | E32: 602_IS Operational_EIL_EUR | F32: 602_IS Operational_EIL_EUR | G32: 0000_Default | H32: 0000_Default | I32: 000000_Default | J32: 000000_Default | K32: 602 | L32: 602 | M32: EUR | N32: EUR | O32: SOFTWARE | P32: SOFTWARE | Q32: Software | R32: Software | S32: Software | T32: Software | U32: Contractor E2M Project - BA / PM | V32: Medium | W32: 200004 | X32: 48 | Y32: 1/1/2027 | Z32: CIP | AA32: CIP | AB32: YES | AC32: 16667 | AD32: 16667 | AE32: 16667 | AF32: 16667 | AG32: 16667 | AH32: 16667 | AI32: 16667 | AJ32: 16667 | AK32: 16667 | AL32: 16667 | AM32: 16667 | AN32: 16667 | AO32: 200004 | AP32: =IF(N32="EUR",AO32,IF(N32="GBP",AO32/Rate!$C$3,'2.3 EIL Capex '!AO32/Rate!$C$5)) -> 200004
A33: No | C33: OWNED | D33: Valerie Veyt | E33: 602_IS Operational_EIL_EUR | F33: 602_IS Operational_EIL_EUR | G33: 0000_Default | H33: 0000_Default | I33: 000000_Default | J33: 000000_Default | K33: 602 | L33: 602 | M33: EUR | N33: EUR | O33: SOFTWARE | P33: SOFTWARE | Q33: Software | R33: Software | S33: Software | T33: Software | U33: Contractor Wifi PoC Project TECH PM Vrushik Patel | V33: Medium | W33: 200004 | X33: 48 | Y33: 1/1/2027 | Z33: CIP | AA33: CIP | AB33: YES | AC33: 16667 | AD33: 16667 | AE33: 16667 | AF33: 16667 | AG33: 16667 | AH33: 16667 | AI33: 16667 | AJ33: 16667 | AK33: 16667 | AL33: 16667 | AM33: 16667 | AN33: 16667 | AO33: 200004 | AP33: =IF(N33="EUR",AO33,IF(N33="GBP",AO33/Rate!$C$3,'2.3 EIL Capex '!AO33/Rate!$C$5)) -> 200004
A34: No | C34: OWNED | D34: Valerie Veyt | E34: 602_IS Operational_EIL_EUR | F34: 602_IS Operational_EIL_EUR | G34: 0000_Default | H34: 0000_Default | I34: 000000_Default | J34: 000000_Default | K34: 602 | L34: 602 | M34: EUR | N34: EUR | O34: SOFTWARE | P34: SOFTWARE | Q34: Software | R34: Software | S34: Software | T34: Software | U34: Demand mgt, reporting and roadmap tool for IS OPS | V34: Medium | W34: 99996 | X34: 48 | Y34: 1/1/2027 | Z34: CIP | AA34: CIP | AB34: YES | AC34: 8333 | AD34: 8333 | AE34: 8333 | AF34: 8333 | AG34: 8333 | AH34: 8333 | AI34: 8333 | AJ34: 8333 | AK34: 8333 | AL34: 8333 | AM34: 8333 | AN34: 8333 | AO34: 99996 | AP34: =IF(N34="EUR",AO34,IF(N34="GBP",AO34/Rate!$C$3,'2.3 EIL Capex '!AO38/Rate!$C$5)) -> 99996
A35: No | C35: OWNED | D35: Valerie Veyt | E35: 602_IS Operational_EIL_EUR | F35: 602_IS Operational_EIL_EUR | G35: 0000_Default | H35: 0000_Default | I35: 000000_Default | J35: 000000_Default | K35: 602 | L35: 602 | M35: EUR | N35: EUR | O35: SOFTWARE | P35: SOFTWARE | Q35: Software | R35: Software | S35: Software | T35: Software | U35: Disaster recovery improvements | V35: Medium | W35: 99996 | X35: 48 | Y35: 1/1/2027 | Z35: CIP | AA35: CIP | AB35: YES | AC35: 8333 | AD35: 8333 | AE35: 8333 | AF35: 8333 | AG35: 8333 | AH35: 8333 | AI35: 8333 | AJ35: 8333 | AK35: 8333 | AL35: 8333 | AM35: 8333 | AN35: 8333 | AO35: 99996 | AP35: =IF(N35="EUR",AO35,IF(N35="GBP",AO35/Rate!$C$3,'2.3 EIL Capex '!AO41/Rate!$C$5)) -> 99996
A36: No | C36: OWNED | D36: Valerie Veyt | E36: 602_IS Operational_EIL_EUR | F36: 602_IS Operational_EIL_EUR | G36: 0000_Default | H36: 0000_Default | I36: 000000_Default | J36: 000000_Default | K36: 602 | L36: 602 | M36: EUR | N36: EUR | O36: PLANT AND MACHINERY | P36: PLANT AND MACHINERY | Q36: It Equipments | R36: It Equipments | S36: Plant & Machinery - IT equipment | T36: Plant & Machinery - IT equipment | U36: E320 Onboard 5G WIFI Deployment Project - Full Fleet | V36: Medium | W36: 5799996 | X36: 48 | Y36: 1/1/2027 | Z36: CIP | AA36: CIP | AB36: YES | AC36: 483333 | AD36: 483333 | AE36: 483333 | AF36: 483333 | AG36: 483333 | AH36: 483333 | AI36: 483333 | AJ36: 483333 | AK36: 483333 | AL36: 483333 | AM36: 483333 | AN36: 483333 | AO36: 5799996 | AP36: =IF(N36="EUR",AO36,IF(N36="GBP",AO36/Rate!$C$3,'2.3 EIL Capex '!AO42/Rate!$C$5)) -> 5799996
A37: No | C37: OWNED | D37: Valerie Veyt | E37: 602_IS Operational_EIL_EUR | F37: 602_IS Operational_EIL_EUR | G37: 0000_Default | H37: 0000_Default | I37: 000000_Default | J37: 000000_Default | K37: 602 | L37: 602 | M37: EUR | N37: EUR | O37: SOFTWARE | P37: SOFTWARE | Q37: Software | R37: Software | S37: Software | T37: Software | U37: Migration of Performance Applications from SalesForce | V37: Medium | W37: 174000 | X37: 48 | Y37: 1/1/2027 | Z37: CIP | AA37: CIP | AB37: YES | AC37: 14500 | AD37: 14500 | AE37: 14500 | AF37: 14500 | AG37: 14500 | AH37: 14500 | AI37: 14500 | AJ37: 14500 | AK37: 14500 | AL37: 14500 | AM37: 14500 | AN37: 14500 | AO37: 174000 | AP37: =IF(N37="EUR",AO37,IF(N37="GBP",AO37/Rate!$C$3,'2.3 EIL Capex '!AO51/Rate!$C$5)) -> 174000
A38: No | C38: OWNED | D38: Valerie Veyt | E38: 602_IS Operational_EIL_EUR | F38: 602_IS Operational_EIL_EUR | G38: 0000_Default | H38: 0000_Default | I38: 000000_Default | J38: 000000_Default | K38: 602 | L38: 602 | M38: EUR | N38: EUR | O38: SOFTWARE | P38: SOFTWARE | Q38: Software | R38: Software | S38: Software | T38: Software | U38: NEW TMI App - Security & move into Eil Enterprise | V38: Medium | W38: 1449996 | X38: 48 | Y38: 1/1/2027 | Z38: CIP | AA38: CIP | AB38: YES | AC38: 120833 | AD38: 120833 | AE38: 120833 | AF38: 120833 | AG38: 120833 | AH38: 120833 | AI38: 120833 | AJ38: 120833 | AK38: 120833 | AL38: 120833 | AM38: 120833 | AN38: 120833 | AO38: 1449996 | AP38: =IF(N38="EUR",AO38,IF(N38="GBP",AO38/Rate!$C$3,'2.3 EIL Capex '!AO52/Rate!$C$5)) -> 1449996
A39: No | C39: OWNED | D39: Valerie Veyt | E39: 602_IS Operational_EIL_EUR | F39: 602_IS Operational_EIL_EUR | G39: 1845_Ops Masterplan | H39: 1845_Ops Masterplan | I39: 000000_Default | J39: 000000_Default | K39: 602 | L39: 602 | M39: EUR | N39: EUR | O39: SOFTWARE | P39: SOFTWARE | Q39: Software | R39: Software | S39: Software | T39: Software | U39: OMP 2026 (per gateway review) | W39: 1120377 | X39: 48 | Y39: 12/31/2026 | Z39: CIP | AA39: CIP | AB39: YES | AC39: 100000 | AD39: 100000 | AE39: 100000 | AF39: 100000 | AG39: 100000 | AH39: 100000 | AI39: 100000 | AJ39: 100000 | AK39: 100000 | AL39: 100000 | AM39: 100000 | AN39: 20377 | AO39: 1120377 | AP39: =IF(N39="EUR",AO39,IF(N39="GBP",AO39/Rate!$C$3,'2.3 EIL Capex '!AO55/Rate!$C$5)) -> 1120377
A40: No | C40: OWNED | D40: Valerie Veyt | E40: 602_IS Operational_EIL_EUR | F40: 602_IS Operational_EIL_EUR | G40: 0000_Default | H40: 0000_Default | I40: 000000_Default | J40: 000000_Default | K40: 602 | L40: 602 | M40: EUR | N40: EUR | O40: SOFTWARE | P40: SOFTWARE | Q40: Software | R40: Software | S40: Software | T40: Software | U40: RAC Digitalisation du process de mise à jour | V40: Medium | W40: 99996 | X40: 48 | Y40: 1/1/2027 | Z40: CIP | AA40: CIP | AB40: YES | AC40: 8333 | AD40: 8333 | AE40: 8333 | AF40: 8333 | AG40: 8333 | AH40: 8333 | AI40: 8333 | AJ40: 8333 | AK40: 8333 | AL40: 8333 | AM40: 8333 | AN40: 8333 | AO40: 99996 | AP40: =IF(N40="EUR",AO40,IF(N40="GBP",AO40/Rate!$C$3,'2.3 EIL Capex '!AO64/Rate!$C$5)) -> 99996
A41: No | C41: OWNED | D41: Valerie Veyt | E41: 602_IS Operational_EIL_EUR | F41: 602_IS Operational_EIL_EUR | G41: 0000_Default | H41: 0000_Default | I41: 000000_Default | J41: 000000_Default | K41: 602 | L41: 602 | M41: EUR | N41: EUR | O41: SOFTWARE | P41: SOFTWARE | Q41: Software | R41: Software | S41: Software | T41: Software | U41: RTSP Developments/Enhancements | V41: Medium | W41: 60000 | X41: 48 | Y41: 1/1/2027 | Z41: CIP | AA41: CIP | AB41: YES | AC41: 5000 | AD41: 5000 | AE41: 5000 | AF41: 5000 | AG41: 5000 | AH41: 5000 | AI41: 5000 | AJ41: 5000 | AK41: 5000 | AL41: 5000 | AM41: 5000 | AN41: 5000 | AO41: 60000 | AP41: =IF(N41="EUR",AO41,IF(N41="GBP",AO41/Rate!$C$3,'2.3 EIL Capex '!AO68/Rate!$C$5)) -> 60000
A42: No | C42: OWNED | D42: Valerie Veyt | E42: 602_IS Operational_EIL_EUR | F42: 602_IS Operational_EIL_EUR | G42: 0000_Default | H42: 0000_Default | I42: 000000_Default | J42: 000000_Default | K42: 602 | L42: 602 | M42: EUR | N42: EUR | O42: SOFTWARE | P42: SOFTWARE | Q42: Software | R42: Software | S42: Software | T42: Software | U42: SMART Replatforming | V42: Medium | W42: 50004 | X42: 48 | Y42: 1/1/2027 | Z42: CIP | AA42: CIP | AB42: YES | AC42: 4167 | AD42: 4167 | AE42: 4167 | AF42: 4167 | AG42: 4167 | AH42: 4167 | AI42: 4167 | AJ42: 4167 | AK42: 4167 | AL42: 4167 | AM42: 4167 | AN42: 4167 | AO42: 50004 | AP42: =IF(N42="EUR",AO42,IF(N42="GBP",AO42/Rate!$C$3,'2.3 EIL Capex '!AO70/Rate!$C$5)) -> 50004
A43: No | C43: OWNED | D43: Mael Delmas | E43: 604_IS Customer Systems_EIL_GBP | F43: 604_IS Customer Systems_EIL_GBP | G43: 0000_Default | H43: 0000_Default | I43: 000000_Default | J43: 000000_Default | K43: 604 | L43: 604 | M43: GBP | N43: GBP | O43: SOFTWARE | P43: SOFTWARE | Q43: Software | R43: Software | S43: Software | T43: Software | U43: [On-Board] - [iTM] - small maintenance projects | V43: Medium | W43: 50004 | X43: 48 | Y43: 1/1/2027 | Z43: CIP | AA43: CIP | AB43: YES | AC43: 4167 | AD43: 4167 | AE43: 4167 | AF43: 4167 | AG43: 4167 | AH43: 4167 | AI43: 4167 | AJ43: 4167 | AK43: 4167 | AL43: 4167 | AM43: 4167 | AN43: 4167 | AO43: 50004 | AP43: =IF(N43="EUR",AO43,IF(N43="GBP",AO43/Rate!$C$3,'2.3 EIL Capex '!AO6/Rate!$C$5)) -> 57475.862
A44: No | C44: OWNED | D44: Mael Delmas | E44: 604_IS Customer Systems_EIL_GBP | F44: 604_IS Customer Systems_EIL_GBP | G44: 0000_Default | H44: 0000_Default | I44: 000000_Default | J44: 000000_Default | K44: 604 | L44: 604 | M44: GBP | N44: GBP | O44: SOFTWARE | P44: SOFTWARE | Q44: Software | R44: Software | S44: Software | T44: Software | U44: [On-board] - Unification of TACT and iTM (hardware + software) TBC | V44: Medium | W44: 849996 | X44: 48 | Y44: 1/1/2027 | Z44: CIP | AA44: CIP | AB44: YES | AC44: 70833 | AD44: 70833 | AE44: 70833 | AF44: 70833 | AG44: 70833 | AH44: 70833 | AI44: 70833 | AJ44: 70833 | AK44: 70833 | AL44: 70833 | AM44: 70833 | AN44: 70833 | AO44: 849996 | AP44: =IF(N44="EUR",AO44,IF(N44="GBP",AO44/Rate!$C$3,'2.3 EIL Capex '!AO7/Rate!$C$5)) -> 977006.9
A45: No | C45: OWNED | D45: Mael Delmas | E45: 604_IS Customer Systems_EIL_GBP | F45: 604_IS Customer Systems_EIL_GBP | G45: 0000_Default | H45: 0000_Default | I45: 000000_Default | J45: 000000_Default | K45: 604 | L45: 604 | M45: GBP | N45: GBP | O45: SOFTWARE | P45: SOFTWARE | Q45: Software | R45: Software | S45: Software | T45: Software | U45: [Operations/Stations] - Customer Information - CIS data consolidations (train, delay, queuing time...) | V45: Medium | W45: 300000 | X45: 48 | Y45: 1/1/2027 | Z45: CIP | AA45: CIP | AB45: YES | AC45: 25000 | AD45: 25000 | AE45: 25000 | AF45: 25000 | AG45: 25000 | AH45: 25000 | AI45: 25000 | AJ45: 25000 | AK45: 25000 | AL45: 25000 | AM45: 25000 | AN45: 25000 | AO45: 300000 | AP45: =IF(N45="EUR",AO45,IF(N45="GBP",AO45/Rate!$C$3,'2.3 EIL Capex '!AO8/Rate!$C$5)) -> 344827.59
A46: No | C46: OWNED | D46: Mael Delmas | E46: 604_IS Customer Systems_EIL_GBP | F46: 604_IS Customer Systems_EIL_GBP | G46: 0000_Default | H46: 0000_Default | I46: 000000_Default | J46: 000000_Default | K46: 604 | L46: 604 | M46: GBP | N46: GBP | O46: SOFTWARE | P46: SOFTWARE | Q46: Software | R46: Software | S46: Software | T46: Software | U46: [Operations/Stations] - unification of Self Service within DPAX | V46: Medium | W46: 290004 | X46: 48 | Y46: 1/1/2027 | Z46: CIP | AA46: CIP | AB46: YES | AC46: 24167 | AD46: 24167 | AE46: 24167 | AF46: 24167 | AG46: 24167 | AH46: 24167 | AI46: 24167 | AJ46: 24167 | AK46: 24167 | AL46: 24167 | AM46: 24167 | AN46: 24167 | AO46: 290004 | AP46: =IF(N46="EUR",AO46,IF(N46="GBP",AO46/Rate!$C$3,'2.3 EIL Capex '!AO9/Rate!$C$5)) -> 333337.93
A47: No | C47: OWNED | D47: Mael Delmas | E47: 604_IS Customer Systems_EIL_GBP | F47: 604_IS Customer Systems_EIL_GBP | G47: 0000_Default | H47: 0000_Default | I47: 000000_Default | J47: 000000_Default | K47: 604 | L47: 604 | M47: GBP | N47: GBP | O47: SOFTWARE | P47: SOFTWARE | Q47: Software | R47: Software | S47: Software | T47: Software | U47: [Operations] - Equipment Change - automation of equipment changes (BA time + dev) - PRJ: 1853 | V47: Medium | W47: 489996 | X47: 48 | Y47: 1/1/2027 | Z47: CIP | AA47: CIP | AB47: YES | AC47: 40833 | AD47: 40833 | AE47: 40833 | AF47: 40833 | AG47: 40833 | AH47: 40833 | AI47: 40833 | AJ47: 40833 | AK47: 40833 | AL47: 40833 | AM47: 40833 | AN47: 40833 | AO47: 489996 | AP47: =IF(N47="EUR",AO47,IF(N47="GBP",AO47/Rate!$C$3,'2.3 EIL Capex '!AO10/Rate!$C$5)) -> 563213.79
A48: No | C48: OWNED | D48: Mael Delmas | E48: 604_IS Customer Systems_EIL_GBP | F48: 604_IS Customer Systems_EIL_GBP | G48: 0000_Default | H48: 0000_Default | I48: 000000_Default | J48: 000000_Default | K48: 604 | L48: 604 | M48: GBP | N48: GBP | O48: SOFTWARE | P48: SOFTWARE | Q48: Software | R48: Software | S48: Software | T48: Software | U48: [Stations/Operations] - DATA - Station data in Data hub + ML based forecast reports for all stations | V48: Medium | W48: 300000 | X48: 48 | Y48: 1/1/2027 | Z48: CIP | AA48: CIP | AB48: YES | AC48: 25000 | AD48: 25000 | AE48: 25000 | AF48: 25000 | AG48: 25000 | AH48: 25000 | AI48: 25000 | AJ48: 25000 | AK48: 25000 | AL48: 25000 | AM48: 25000 | AN48: 25000 | AO48: 300000 | AP48: =IF(N48="EUR",AO48,IF(N48="GBP",AO48/Rate!$C$3,'2.3 EIL Capex '!AO13/Rate!$C$5)) -> 344827.59
A49: No | C49: OWNED | D49: Mael Delmas | E49: 604_IS Customer Systems_EIL_GBP | F49: 604_IS Customer Systems_EIL_GBP | G49: 0000_Default | H49: 0000_Default | I49: 000000_Default | J49: 000000_Default | K49: 604 | L49: 604 | M49: GBP | N49: GBP | O49: SOFTWARE | P49: SOFTWARE | Q49: Software | R49: Software | S49: Software | T49: Software | U49: [Stations/Operations] - New Start On Time (TBC) - replacement with further integration for stations for x-channel | V49: Medium | W49: 200004 | X49: 48 | Y49: 1/1/2027 | Z49: CIP | AA49: CIP | AB49: YES | AC49: 16667 | AD49: 16667 | AE49: 16667 | AF49: 16667 | AG49: 16667 | AH49: 16667 | AI49: 16667 | AJ49: 16667 | AK49: 16667 | AL49: 16667 | AM49: 16667 | AN49: 16667 | AO49: 200004 | AP49: =IF(N49="EUR",AO49,IF(N49="GBP",AO49/Rate!$C$3,'2.3 EIL Capex '!AO14/Rate!$C$5)) -> 229889.66
A50: No | C50: OWNED | D50: Mael Delmas | E50: 604_IS Customer Systems_EIL_GBP | F50: 604_IS Customer Systems_EIL_GBP | G50: 0000_Default | H50: 0000_Default | I50: 000000_Default | J50: 000000_Default | K50: 604 | L50: 604 | M50: GBP | N50: GBP | O50: SOFTWARE | P50: SOFTWARE | Q50: Software | R50: Software | S50: Software | T50: Software | U50: [Stations] - CAPACITY - Check-in position replaced by Mobile Check-in | V50: Medium | W50: 120000 | X50: 48 | Y50: 1/1/2027 | Z50: CIP | AA50: CIP | AB50: YES | AC50: 10000 | AD50: 10000 | AE50: 10000 | AF50: 10000 | AG50: 10000 | AH50: 10000 | AI50: 10000 | AJ50: 10000 | AK50: 10000 | AL50: 10000 | AM50: 10000 | AN50: 10000 | AO50: 120000 | AP50: =IF(N50="EUR",AO50,IF(N50="GBP",AO50/Rate!$C$3,'2.3 EIL Capex '!AO15/Rate!$C$5)) -> 137931.03
A51: No | C51: OWNED | D51: Mael Delmas | E51: 604_IS Customer Systems_EIL_GBP | F51: 604_IS Customer Systems_EIL_GBP | G51: 0000_Default | H51: 0000_Default | I51: 000000_Default | J51: 000000_Default | K51: 604 | L51: 604 | M51: GBP | N51: GBP | O51: SOFTWARE | P51: SOFTWARE | Q51: Software | R51: Software | S51: Software | T51: Software | U51: [Stations] - CAPACITY - SPARK - improvements | V51: Medium | W51: 350004 | X51: 48 | Y51: 1/1/2027 | Z51: CIP | AA51: CIP | AB51: YES | AC51: 29167 | AD51: 29167 | AE51: 29167 | AF51: 29167 | AG51: 29167 | AH51: 29167 | AI51: 29167 | AJ51: 29167 | AK51: 29167 | AL51: 29167 | AM51: 29167 | AN51: 29167 | AO51: 350004 | AP51: =IF(N51="EUR",AO51,IF(N51="GBP",AO51/Rate!$C$3,'2.3 EIL Capex '!AO16/Rate!$C$5)) -> 402303.45
A52: No | C52: OWNED | D52: Mael Delmas | E52: 604_IS Customer Systems_EIL_GBP | F52: 604_IS Customer Systems_EIL_GBP | G52: 0000_Default | H52: 0000_Default | I52: 000000_Default | J52: 000000_Default | K52: 604 | L52: 604 | M52: GBP | N52: GBP | O52: SOFTWARE | P52: SOFTWARE | Q52: Software | R52: Software | S52: Software | T52: Software | U52: [Stations] - CAPACITY - SST refit POC | V52: Medium | W52: 60000 | X52: 48 | Y52: 1/1/2027 | Z52: CIP | AA52: CIP | AB52: YES | AC52: 5000 | AD52: 5000 | AE52: 5000 | AF52: 5000 | AG52: 5000 | AH52: 5000 | AI52: 5000 | AJ52: 5000 | AK52: 5000 | AL52: 5000 | AM52: 5000 | AN52: 5000 | AO52: 60000 | AP52: =IF(N52="EUR",AO52,IF(N52="GBP",AO52/Rate!$C$3,'2.3 EIL Capex '!AO17/Rate!$C$5)) -> 68965.517
A53: No | C53: OWNED | D53: Mael Delmas | E53: 604_IS Customer Systems_EIL_GBP | F53: 604_IS Customer Systems_EIL_GBP | G53: 0000_Default | H53: 0000_Default | I53: 000000_Default | J53: 000000_Default | K53: 604 | L53: 604 | M53: GBP | N53: GBP | O53: SOFTWARE | P53: SOFTWARE | Q53: Software | R53: Software | S53: Software | T53: Software | U53: [Stations] - CAPACITY Voyager on Mobile (inc 20% of contingency for PM) - TBC with David | V53: Medium | W53: 360000 | X53: 48 | Y53: 1/1/2027 | Z53: CIP | AA53: CIP | AB53: YES | AC53: 30000 | AD53: 30000 | AE53: 30000 | AF53: 30000 | AG53: 30000 | AH53: 30000 | AI53: 30000 | AJ53: 30000 | AK53: 30000 | AL53: 30000 | AM53: 30000 | AN53: 30000 | AO53: 360000 | AP53: =IF(N53="EUR",AO53,IF(N53="GBP",AO53/Rate!$C$3,'2.3 EIL Capex '!AO18/Rate!$C$5)) -> 413793.1
A54: No | C54: OWNED | D54: Mael Delmas | E54: 604_IS Customer Systems_EIL_GBP | F54: 604_IS Customer Systems_EIL_GBP | G54: 0000_Default | H54: 0000_Default | I54: 000000_Default | J54: 000000_Default | K54: 604 | L54: 604 | M54: GBP | N54: GBP | O54: SOFTWARE | P54: SOFTWARE | Q54: Software | R54: Software | S54: Software | T54: Software | U54: [Stations] - CIS - Integration with SNCF G&C systems (connection to LIVE) | V54: Medium | W54: 210000 | X54: 48 | Y54: 1/1/2027 | Z54: CIP | AA54: CIP | AB54: YES | AC54: 17500 | AD54: 17500 | AE54: 17500 | AF54: 17500 | AG54: 17500 | AH54: 17500 | AI54: 17500 | AJ54: 17500 | AK54: 17500 | AL54: 17500 | AM54: 17500 | AN54: 17500 | AO54: 210000 | AP54: =IF(N54="EUR",AO54,IF(N54="GBP",AO54/Rate!$C$3,'2.3 EIL Capex '!AO19/Rate!$C$5)) -> 241379.31
A55: No | C55: OWNED | D55: Mael Delmas | E55: 604_IS Customer Systems_EIL_GBP | F55: 604_IS Customer Systems_EIL_GBP | G55: 0000_Default | H55: 0000_Default | I55: 000000_Default | J55: 000000_Default | K55: 604 | L55: 604 | M55: GBP | N55: GBP | O55: SOFTWARE | P55: SOFTWARE | Q55: Software | R55: Software | S55: Software | T55: Software | U55: [Stations] - CX - BORDERS - station way finder for border control | V55: Medium | W55: 129996 | X55: 48 | Y55: 1/1/2027 | Z55: CIP | AA55: CIP | AB55: YES | AC55: 10833 | AD55: 10833 | AE55: 10833 | AF55: 10833 | AG55: 10833 | AH55: 10833 | AI55: 10833 | AJ55: 10833 | AK55: 10833 | AL55: 10833 | AM55: 10833 | AN55: 10833 | AO55: 129996 | AP55: =IF(N55="EUR",AO55,IF(N55="GBP",AO55/Rate!$C$3,'2.3 EIL Capex '!AO20/Rate!$C$5)) -> 149420.69
A56: No | C56: OWNED | D56: Mael Delmas | E56: 604_IS Customer Systems_EIL_GBP | F56: 604_IS Customer Systems_EIL_GBP | G56: 0000_Default | H56: 0000_Default | I56: 000000_Default | J56: 000000_Default | K56: 604 | L56: 604 | M56: GBP | N56: GBP | O56: SOFTWARE | P56: SOFTWARE | Q56: Software | R56: Software | S56: Software | T56: Software | U56: [Stations] - CX - CIS - CIS refit for SPI (Start) - hardware + software | V56: Medium | W56: 240000 | X56: 48 | Y56: 1/1/2027 | Z56: CIP | AA56: CIP | AB56: YES | AC56: 20000 | AD56: 20000 | AE56: 20000 | AF56: 20000 | AG56: 20000 | AH56: 20000 | AI56: 20000 | AJ56: 20000 | AK56: 20000 | AL56: 20000 | AM56: 20000 | AN56: 20000 | AO56: 240000 | AP56: =IF(N56="EUR",AO56,IF(N56="GBP",AO56/Rate!$C$3,'2.3 EIL Capex '!AO21/Rate!$C$5)) -> 275862.07
A57: No | C57: OWNED | D57: Mael Delmas | E57: 604_IS Customer Systems_EIL_GBP | F57: 604_IS Customer Systems_EIL_GBP | G57: 0000_Default | H57: 0000_Default | I57: 000000_Default | J57: 000000_Default | K57: 604 | L57: 604 | M57: GBP | N57: GBP | O57: SOFTWARE | P57: SOFTWARE | Q57: Software | R57: Software | S57: Software | T57: Software | U57: [Stations] - CX - CIS - Mobile Screen refit | V57: Medium | W57: 120000 | X57: 48 | Y57: 1/1/2027 | Z57: CIP | AA57: CIP | AB57: YES | AC57: 10000 | AD57: 10000 | AE57: 10000 | AF57: 10000 | AG57: 10000 | AH57: 10000 | AI57: 10000 | AJ57: 10000 | AK57: 10000 | AL57: 10000 | AM57: 10000 | AN57: 10000 | AO57: 120000 | AP57: =IF(N57="EUR",AO57,IF(N57="GBP",AO57/Rate!$C$3,'2.3 EIL Capex '!AO22/Rate!$C$5)) -> 137931.03
A58: No | C58: OWNED | D58: Mael Delmas | E58: 604_IS Customer Systems_EIL_GBP | F58: 604_IS Customer Systems_EIL_GBP | G58: 0000_Default | H58: 0000_Default | I58: 000000_Default | J58: 000000_Default | K58: 604 | L58: 604 | M58: GBP | N58: GBP | O58: SOFTWARE | P58: SOFTWARE | Q58: Software | R58: Software | S58: Software | T58: Software | U58: [Stations] - CX - COMMS - auto-communication to for customer Station journey preparations (pre-travel, auto-reaccommodations, smart queuing, ...) | V58: Medium | W58: 240000 | X58: 48 | Y58: 1/1/2027 | Z58: CIP | AA58: CIP | AB58: YES | AC58: 20000 | AD58: 20000 | AE58: 20000 | AF58: 20000 | AG58: 20000 | AH58: 20000 | AI58: 20000 | AJ58: 20000 | AK58: 20000 | AL58: 20000 | AM58: 20000 | AN58: 20000 | AO58: 240000 | AP58: =IF(N58="EUR",AO58,IF(N58="GBP",AO58/Rate!$C$3,'2.3 EIL Capex '!AO23/Rate!$C$5)) -> 275862.07
A59: No | C59: OWNED | D59: Mael Delmas | E59: 604_IS Customer Systems_EIL_GBP | F59: 604_IS Customer Systems_EIL_GBP | G59: 0000_Default | H59: 0000_Default | I59: 000000_Default | J59: 000000_Default | K59: 604 | L59: 604 | M59: GBP | N59: GBP | O59: PLANT AND MACHINERY | P59: PLANT AND MACHINERY | Q59: It Equipments | R59: It Equipments | S59: Plant & Machinery - IT equipment | T59: Plant & Machinery - IT equipment | U59: [Stations] - CX - Display - queuing time display on mobile screen or Mobile app | V59: Medium | W59: 60000 | X59: 48 | Y59: 1/1/2027 | Z59: CIP | AA59: CIP | AB59: YES | AC59: 5000 | AD59: 5000 | AE59: 5000 | AF59: 5000 | AG59: 5000 | AH59: 5000 | AI59: 5000 | AJ59: 5000 | AK59: 5000 | AL59: 5000 | AM59: 5000 | AN59: 5000 | AO59: 60000 | AP59: =IF(N59="EUR",AO59,IF(N59="GBP",AO59/Rate!$C$3,'2.3 EIL Capex '!AO24/Rate!$C$5)) -> 68965.517
A60: No | C60: OWNED | D60: Mael Delmas | E60: 604_IS Customer Systems_EIL_GBP | F60: 604_IS Customer Systems_EIL_GBP | G60: 0000_Default | H60: 0000_Default | I60: 000000_Default | J60: 000000_Default | K60: 604 | L60: 604 | M60: GBP | N60: GBP | O60: SOFTWARE | P60: SOFTWARE | Q60: Software | R60: Software | S60: Software | T60: Software | U60: Loyalty/Stations - lounge entry solution POC (based some recognition technical solution) | V60: Medium | W60: 50004 | X60: 48 | Y60: 1/1/2027 | Z60: CIP | AA60: CIP | AB60: YES | AC60: 4167 | AD60: 4167 | AE60: 4167 | AF60: 4167 | AG60: 4167 | AH60: 4167 | AI60: 4167 | AJ60: 4167 | AK60: 4167 | AL60: 4167 | AM60: 4167 | AN60: 4167 | AO60: 50004 | AP60: =IF(N60="EUR",AO60,IF(N60="GBP",AO60/Rate!$C$3,'2.3 EIL Capex '!AO50/Rate!$C$5)) -> 57475.862
A61: No | C61: OWNED | D61: Mael Delmas | E61: 604_IS Customer Systems_EIL_GBP | F61: 604_IS Customer Systems_EIL_GBP | G61: 0000_Default | H61: 0000_Default | I61: 000000_Default | J61: 000000_Default | K61: 604 | L61: 604 | M61: GBP | N61: GBP | O61: SOFTWARE | P61: SOFTWARE | Q61: Software | R61: Software | S61: Software | T61: Software | U61: Operation Project Manager - Paul broomhead | V61: Medium | W61: 144000 | X61: 48 | Y61: 1/1/2027 | Z61: CIP | AA61: CIP | AB61: YES | AC61: 12000 | AD61: 12000 | AE61: 12000 | AF61: 12000 | AG61: 12000 | AH61: 12000 | AI61: 12000 | AJ61: 12000 | AK61: 12000 | AL61: 12000 | AM61: 12000 | AN61: 12000 | AO61: 144000 | AP61: =IF(N61="EUR",AO61,IF(N61="GBP",AO61/Rate!$C$3,'2.3 EIL Capex '!AO56/Rate!$C$5)) -> 165517.24
A62: No | C62: OWNED | D62: Mael Delmas | E62: 604_IS Customer Systems_EIL_GBP | F62: 604_IS Customer Systems_EIL_GBP | G62: 0000_Default | H62: 0000_Default | I62: 000000_Default | J62: 000000_Default | K62: 604 | L62: 604 | M62: GBP | N62: GBP | O62: PLANT AND MACHINERY | P62: PLANT AND MACHINERY | Q62: It Equipments | R62: It Equipments | S62: Plant & Machinery - IT equipment | T62: Plant & Machinery - IT equipment | U62: Other Projects | V62: Medium | W62: 156000 | X62: 48 | Y62: 1/1/2027 | Z62: CIP | AA62: CIP | AB62: YES | AC62: 13000 | AD62: 13000 | AE62: 13000 | AF62: 13000 | AG62: 13000 | AH62: 13000 | AI62: 13000 | AJ62: 13000 | AK62: 13000 | AL62: 13000 | AM62: 13000 | AN62: 13000 | AO62: 156000 | AP62: =IF(N62="EUR",AO62,IF(N62="GBP",AO62/Rate!$C$3,'2.3 EIL Capex '!AO58/Rate!$C$5)) -> 179310.34
A63: No | C63: OWNED | D63: Mael Delmas | E63: 604_IS Customer Systems_EIL_GBP | F63: 604_IS Customer Systems_EIL_GBP | G63: 0000_Default | H63: 0000_Default | I63: 000000_Default | J63: 000000_Default | K63: 604 | L63: 604 | M63: GBP | N63: GBP | O63: SOFTWARE | P63: SOFTWARE | Q63: Software | R63: Software | S63: Software | T63: Software | U63: RM360 - general improvement to match new need followng migration to new RM tool | V63: Medium | W63: 39996 | X63: 48 | Y63: 1/1/2027 | Z63: CIP | AA63: CIP | AB63: YES | AC63: 3333 | AD63: 3333 | AE63: 3333 | AF63: 3333 | AG63: 3333 | AH63: 3333 | AI63: 3333 | AJ63: 3333 | AK63: 3333 | AL63: 3333 | AM63: 3333 | AN63: 3333 | AO63: 39996 | AP63: =IF(N63="EUR",AO63,IF(N63="GBP",AO63/Rate!$C$3,'2.3 EIL Capex '!AO65/Rate!$C$5)) -> 45972.414
A64: No | C64: OWNED | D64: Xavier Romanet | E64: 605_IS Sales System_EIL_GBP | F64: 605_IS Sales System_EIL_GBP | G64: 1780_Digital Roadmap 2024 - Digital Product | H64: 1780_Digital Roadmap 2024 - Digital Product | I64: 000000_Default | J64: 000000_Default | K64: 605 | L64: 605 | M64: GBP | N64: GBP | O64: SOFTWARE | P64: SOFTWARE | Q64: Software | R64: Software | S64: Software | T64: Software | U64: Digital dev road map 2026 | V64: Medium | W64: 9500004 | X64: 48 | Y64: 1/1/2027 | Z64: CIP | AA64: CIP | AB64: YES | AC64: 791667 | AD64: 791667 | AE64: 791667 | AF64: 791667 | AG64: 791667 | AH64: 791667 | AI64: 791667 | AJ64: 791667 | AK64: 791667 | AL64: 791667 | AM64: 791667 | AN64: 791667 | AO64: 9500004 | AP64: =IF(N64="EUR",AO64,IF(N64="GBP",AO64/Rate!$C$3,'2.3 EIL Capex '!AO40/Rate!$C$5)) -> 10919545
A65: No | C65: OWNED | D65: Paolo Rodeghiero | E65: 608_Data & Middleware_EIL_EUR | F65: 608_Data & Middleware_EIL_EUR | G65: 0000_Default | H65: 0000_Default | I65: 000000_Default | J65: 000000_Default | K65: 608 | L65: 608 | M65: EUR | N65: EUR | O65: SOFTWARE | P65: SOFTWARE | Q65: Software | R65: Software | S65: Software | T65: Software | U65: 2025 Leftover - New Customer Segmentation / C360 Evolutions | V65: Medium | W65: 207996 | X65: 48 | Y65: 1/1/2027 | Z65: CIP | AA65: CIP | AB65: YES | AC65: 17333 | AD65: 17333 | AE65: 17333 | AF65: 17333 | AG65: 17333 | AH65: 17333 | AI65: 17333 | AJ65: 17333 | AK65: 17333 | AL65: 17333 | AM65: 17333 | AN65: 17333 | AO65: 207996 | AP65: =IF(N65="EUR",AO65,IF(N65="GBP",AO65/Rate!$C$3,'2.3 EIL Capex '!AO5/Rate!$C$5)) -> 207996
A66: No | C66: OWNED | D66: Paolo Rodeghiero | E66: 608_Data & Middleware_EIL_EUR | F66: 608_Data & Middleware_EIL_EUR | G66: 0000_Default | H66: 0000_Default | I66: 000000_Default | J66: 000000_Default | K66: 608 | L66: 608 | M66: EUR | N66: EUR | O66: SOFTWARE | P66: SOFTWARE | Q66: Software | R66: Software | S66: Software | T66: Software | U66: Commercial - Joint Customer Database | V66: High | W66: 180000 | X66: 48 | Y66: 1/1/2027 | Z66: CIP | AA66: CIP | AB66: YES | AC66: 15000 | AD66: 15000 | AE66: 15000 | AF66: 15000 | AG66: 15000 | AH66: 15000 | AI66: 15000 | AJ66: 15000 | AK66: 15000 | AL66: 15000 | AM66: 15000 | AN66: 15000 | AO66: 180000 | AP66: =IF(N66="EUR",AO66,IF(N66="GBP",AO66/Rate!$C$3,'2.3 EIL Capex '!AO29/Rate!$C$5)) -> 180000
A67: No | C67: OWNED | D67: Paolo Rodeghiero | E67: 608_Data & Middleware_EIL_EUR | F67: 608_Data & Middleware_EIL_EUR | G67: 0000_Default | H67: 0000_Default | I67: 000000_Default | J67: 000000_Default | K67: 608 | L67: 608 | M67: EUR | N67: EUR | O67: SOFTWARE | P67: SOFTWARE | Q67: Software | R67: Software | S67: Software | T67: Software | U67: DataHub Platform Roadmap | V67: High | W67: 450000 | X67: 48 | Y67: 1/1/2027 | Z67: CIP | AA67: CIP | AB67: YES | AC67: 37500 | AD67: 37500 | AE67: 37500 | AF67: 37500 | AG67: 37500 | AH67: 37500 | AI67: 37500 | AJ67: 37500 | AK67: 37500 | AL67: 37500 | AM67: 37500 | AN67: 37500 | AO67: 450000 | AP67: =IF(N67="EUR",AO67,IF(N67="GBP",AO67/Rate!$C$3,'2.3 EIL Capex '!AO36/Rate!$C$5)) -> 450000
A68: No | C68: OWNED | D68: Paolo Rodeghiero | E68: 608_Data & Middleware_EIL_EUR | F68: 608_Data & Middleware_EIL_EUR | G68: 0000_Default | H68: 0000_Default | I68: 000000_Default | J68: 000000_Default | K68: 608 | L68: 608 | M68: EUR | N68: EUR | O68: SOFTWARE | P68: SOFTWARE | Q68: Software | R68: Software | S68: Software | T68: Software | U68: Datalakehouse Platform Roadmap | V68: High | W68: 195000 | X68: 48 | Y68: 1/1/2027 | Z68: CIP | AA68: CIP | AB68: YES | AC68: 16250 | AD68: 16250 | AE68: 16250 | AF68: 16250 | AG68: 16250 | AH68: 16250 | AI68: 16250 | AJ68: 16250 | AK68: 16250 | AL68: 16250 | AM68: 16250 | AN68: 16250 | AO68: 195000 | AP68: =IF(N68="EUR",AO68,IF(N68="GBP",AO68/Rate!$C$3,'2.3 EIL Capex '!AO37/Rate!$C$5)) -> 195000
A69: No | C69: OWNED | D69: Paolo Rodeghiero | E69: 608_Data & Middleware_EIL_EUR | F69: 608_Data & Middleware_EIL_EUR | G69: 0000_Default | H69: 0000_Default | I69: 000000_Default | J69: 000000_Default | K69: 608 | L69: 608 | M69: EUR | N69: EUR | O69: SOFTWARE | P69: SOFTWARE | Q69: Software | R69: Software | S69: Software | T69: Software | U69: Enablers Evolutions | V69: High | W69: 320004 | X69: 48 | Y69: 1/1/2027 | Z69: CIP | AA69: CIP | AB69: YES | AC69: 26667 | AD69: 26667 | AE69: 26667 | AF69: 26667 | AG69: 26667 | AH69: 26667 | AI69: 26667 | AJ69: 26667 | AK69: 26667 | AL69: 26667 | AM69: 26667 | AN69: 26667 | AO69: 320004 | AP69: =IF(N69="EUR",AO69,IF(N69="GBP",AO69/Rate!$C$3,'2.3 EIL Capex '!AO43/Rate!$C$5)) -> 320004
A70: No | C70: OWNED | D70: Paolo Rodeghiero | E70: 608_Data & Middleware_EIL_EUR | F70: 608_Data & Middleware_EIL_EUR | G70: 0000_Default | H70: 0000_Default | I70: 000000_Default | J70: 000000_Default | K70: 608 | L70: 608 | M70: EUR | N70: EUR | O70: SOFTWARE | P70: SOFTWARE | Q70: Software | R70: Software | S70: Software | T70: Software | U70: Finance & HR - ERP Compatibility Layer | V70: Medium | W70: 189996 | X70: 48 | Y70: 1/1/2027 | Z70: CIP | AA70: CIP | AB70: YES | AC70: 15833 | AD70: 15833 | AE70: 15833 | AF70: 15833 | AG70: 15833 | AH70: 15833 | AI70: 15833 | AJ70: 15833 | AK70: 15833 | AL70: 15833 | AM70: 15833 | AN70: 15833 | AO70: 189996 | AP70: =IF(N70="EUR",AO70,IF(N70="GBP",AO70/Rate!$C$3,'2.3 EIL Capex '!AO44/Rate!$C$5)) -> 189996
A71: No | C71: OWNED | D71: Paolo Rodeghiero | E71: 608_Data & Middleware_EIL_EUR | F71: 608_Data & Middleware_EIL_EUR | G71: 0000_Default | H71: 0000_Default | I71: 000000_Default | J71: 000000_Default | K71: 608 | L71: 608 | M71: EUR | N71: EUR | O71: SOFTWARE | P71: SOFTWARE | Q71: Software | R71: Software | S71: Software | T71: Software | U71: Innovation Budget | V71: High | W71: 225000 | X71: 48 | Y71: 1/1/2027 | Z71: CIP | AA71: CIP | AB71: YES | AC71: 18750 | AD71: 18750 | AE71: 18750 | AF71: 18750 | AG71: 18750 | AH71: 18750 | AI71: 18750 | AJ71: 18750 | AK71: 18750 | AL71: 18750 | AM71: 18750 | AN71: 18750 | AO71: 225000 | AP71: =IF(N71="EUR",AO71,IF(N71="GBP",AO71/Rate!$C$3,'2.3 EIL Capex '!AO47/Rate!$C$5)) -> 225000
A72: No | C72: OWNED | D72: Paolo Rodeghiero | E72: 608_Data & Middleware_EIL_EUR | F72: 608_Data & Middleware_EIL_EUR | G72: 0000_Default | H72: 0000_Default | I72: 000000_Default | J72: 000000_Default | K72: 608 | L72: 608 | M72: EUR | N72: EUR | O72: SOFTWARE | P72: SOFTWARE | Q72: Software | R72: Software | S72: Software | T72: Software | U72: OASSIS PowerBI Reporting Layer | V72: Medium | W72: 95004 | X72: 48 | Y72: 1/1/2027 | Z72: CIP | AA72: CIP | AB72: YES | AC72: 7917 | AD72: 7917 | AE72: 7917 | AF72: 7917 | AG72: 7917 | AH72: 7917 | AI72: 7917 | AJ72: 7917 | AK72: 7917 | AL72: 7917 | AM72: 7917 | AN72: 7917 | AO72: 95004 | AP72: =IF(N72="EUR",AO72,IF(N72="GBP",AO72/Rate!$C$3,'2.3 EIL Capex '!AO53/Rate!$C$5)) -> 95004
A73: No | C73: OWNED | D73: Paolo Rodeghiero | E73: 608_Data & Middleware_EIL_EUR | F73: 608_Data & Middleware_EIL_EUR | G73: 0000_Default | H73: 0000_Default | I73: 000000_Default | J73: 000000_Default | K73: 608 | L73: 608 | M73: EUR | N73: EUR | O73: SOFTWARE | P73: SOFTWARE | Q73: Software | R73: Software | S73: Software | T73: Software | U73: Operations - Analytics Continous Improvement Projects (non-OMP) | V73: High | W73: 560004 | X73: 48 | Y73: 1/1/2027 | Z73: CIP | AA73: CIP | AB73: YES | AC73: 46667 | AD73: 46667 | AE73: 46667 | AF73: 46667 | AG73: 46667 | AH73: 46667 | AI73: 46667 | AJ73: 46667 | AK73: 46667 | AL73: 46667 | AM73: 46667 | AN73: 46667 | AO73: 560004 | AP73: =IF(N73="EUR",AO73,IF(N73="GBP",AO73/Rate!$C$3,'2.3 EIL Capex '!AO57/Rate!$C$5)) -> 560004
A74: No | C74: OWNED | D74: Paolo Rodeghiero | E74: 608_Data & Middleware_EIL_EUR | F74: 608_Data & Middleware_EIL_EUR | G74: 0000_Default | H74: 0000_Default | I74: 000000_Default | J74: 000000_Default | K74: 608 | L74: 608 | M74: EUR | N74: EUR | O74: SOFTWARE | P74: SOFTWARE | Q74: Software | R74: Software | S74: Software | T74: Software | U74: Polaris Middleware Decoupling | V74: High | W74: 157500 | X74: 48 | Y74: 1/1/2027 | Z74: CIP | AA74: CIP | AB74: YES | AC74: 13125 | AD74: 13125 | AE74: 13125 | AF74: 13125 | AG74: 13125 | AH74: 13125 | AI74: 13125 | AJ74: 13125 | AK74: 13125 | AL74: 13125 | AM74: 13125 | AN74: 13125 | AO74: 157500 | AP74: =IF(N74="EUR",AO74,IF(N74="GBP",AO74/Rate!$C$3,'2.3 EIL Capex '!AO61/Rate!$C$5)) -> 157500
A75: No | C75: OWNED | D75: Paolo Rodeghiero | E75: 608_Data & Middleware_EIL_EUR | F75: 608_Data & Middleware_EIL_EUR | G75: 0000_Default | H75: 0000_Default | I75: 000000_Default | J75: 000000_Default | K75: 608 | L75: 608 | M75: EUR | N75: EUR | O75: SOFTWARE | P75: SOFTWARE | Q75: Software | R75: Software | S75: Software | T75: Software | U75: Polaris Roadmap | V75: High | W75: 135000 | X75: 48 | Y75: 1/1/2027 | Z75: CIP | AA75: CIP | AB75: YES | AC75: 11250 | AD75: 11250 | AE75: 11250 | AF75: 11250 | AG75: 11250 | AH75: 11250 | AI75: 11250 | AJ75: 11250 | AK75: 11250 | AL75: 11250 | AM75: 11250 | AN75: 11250 | AO75: 135000 | AP75: =IF(N75="EUR",AO75,IF(N75="GBP",AO75/Rate!$C$3,'2.3 EIL Capex '!AO62/Rate!$C$5)) -> 135000
A76: No | C76: OWNED | D76: Paolo Rodeghiero | E76: 608_Data & Middleware_EIL_EUR | F76: 608_Data & Middleware_EIL_EUR | G76: 0000_Default | H76: 0000_Default | I76: 000000_Default | J76: 000000_Default | K76: 608 | L76: 608 | M76: EUR | N76: EUR | O76: SOFTWARE | P76: SOFTWARE | Q76: Software | R76: Software | S76: Software | T76: Software | U76: Rolling Stock - Analytics Projects | V76: High | W76: 350004 | X76: 48 | Y76: 1/1/2027 | Z76: CIP | AA76: CIP | AB76: YES | AC76: 29167 | AD76: 29167 | AE76: 29167 | AF76: 29167 | AG76: 29167 | AH76: 29167 | AI76: 29167 | AJ76: 29167 | AK76: 29167 | AL76: 29167 | AM76: 29167 | AN76: 29167 | AO76: 350004 | AP76: =IF(N76="EUR",AO76,IF(N76="GBP",AO76/Rate!$C$3,'2.3 EIL Capex '!AO66/Rate!$C$5)) -> 350004
A77: No | C77: OWNED | D77: Paolo Rodeghiero | E77: 608_Data & Middleware_EIL_EUR | F77: 608_Data & Middleware_EIL_EUR | G77: 0000_Default | H77: 0000_Default | I77: 000000_Default | J77: 000000_Default | K77: 608 | L77: 608 | M77: EUR | N77: EUR | O77: SOFTWARE | P77: SOFTWARE | Q77: Software | R77: Software | S77: Software | T77: Software | U77: Rolling Stock - OpsAPI Refactoring & DataHub Integration (Including NIS2 Activity) | V77: High | W77: 240000 | X77: 48 | Y77: 1/1/2027 | Z77: CIP | AA77: CIP | AB77: YES | AC77: 20000 | AD77: 20000 | AE77: 20000 | AF77: 20000 | AG77: 20000 | AH77: 20000 | AI77: 20000 | AJ77: 20000 | AK77: 20000 | AL77: 20000 | AM77: 20000 | AN77: 20000 | AO77: 240000 | AP77: =IF(N77="EUR",AO77,IF(N77="GBP",AO77/Rate!$C$3,'2.3 EIL Capex '!AO67/Rate!$C$5)) -> 240000
A78: No | C78: OWNED | D78: Paolo Rodeghiero | E78: 608_Data & Middleware_EIL_EUR | F78: 608_Data & Middleware_EIL_EUR | G78: 0000_Default | H78: 0000_Default | I78: 000000_Default | J78: 000000_Default | K78: 608 | L78: 608 | M78: EUR | N78: EUR | O78: SOFTWARE | P78: SOFTWARE | Q78: Software | R78: Software | S78: Software | T78: Software | U78: Stations - Analytics Projects | V78: High | W78: 290004 | X78: 48 | Y78: 1/1/2027 | Z78: CIP | AA78: CIP | AB78: YES | AC78: 24167 | AD78: 24167 | AE78: 24167 | AF78: 24167 | AG78: 24167 | AH78: 24167 | AI78: 24167 | AJ78: 24167 | AK78: 24167 | AL78: 24167 | AM78: 24167 | AN78: 24167 | AO78: 290004 | AP78: =IF(N78="EUR",AO78,IF(N78="GBP",AO78/Rate!$C$3,'2.3 EIL Capex '!AO73/Rate!$C$5)) -> 290004
A79: No | C79: OWNED | D79: Paolo Rodeghiero | E79: 608_Data & Middleware_EIL_EUR | F79: 608_Data & Middleware_EIL_EUR | G79: 0000_Default | H79: 0000_Default | I79: 000000_Default | J79: 000000_Default | K79: 608 | L79: 608 | M79: EUR | N79: EUR | O79: SOFTWARE | P79: SOFTWARE | Q79: Software | R79: Software | S79: Software | T79: Software | U79: Thapaas Evolutions | V79: High | W79: 320004 | X79: 48 | Y79: 1/1/2027 | Z79: CIP | AA79: CIP | AB79: YES | AC79: 26667 | AD79: 26667 | AE79: 26667 | AF79: 26667 | AG79: 26667 | AH79: 26667 | AI79: 26667 | AJ79: 26667 | AK79: 26667 | AL79: 26667 | AM79: 26667 | AN79: 26667 | AO79: 320004 | AP79: =IF(N79="EUR",AO79,IF(N79="GBP",AO79/Rate!$C$3,'2.3 EIL Capex '!AO77/Rate!$C$5)) -> 320004
A83: Notes:
A87: Nov 20, 2025 9:07:58 AM GMT
A88: Confidential Information. Do not distribute without permission.

Sheet 3.1 THIF Opex
S1: =SUBTOTAL(9,S3:S138) -> 20560853 | T1: =SUBTOTAL(9,T3:T138) -> -1823264 | U1: =SUBTOTAL(9,U3:U138) -> 18737589
A2: Cost center manager | B2: Level Code | C2: Compte_Général Code | D2: Type de tiers Code | E2: Type de tiers Name | F2: Projet Code | G2: 46023 | H2: 46054 | I2: 46082 | J2: 46113 | K2: 46143 | L2: 46174 | M2: 46204 | N2: 46235 | O2: 46266 | P2: 46296 | Q2: 46327 | R2: 46357 | S2: Total | T2: Simplify savings | U2: Total after Simplify
A3: =_xlfn.XLOOKUP(B3,'Reference '!J:J,'Reference '!K:K) -> Blanche Derkenne | B3: 0560_DSI PM | C3: 613020 | D3: GENERAL | E3: Gartner membership | F3: GENERAL | G3: 10655.067 | H3: 10655.067 | I3: 10655.067 | J3: 10655.067 | K3: 10655.067 | L3: 10655.067 | M3: 10655.067 | N3: 10655.067 | O3: 10655.067 | P3: 10655.067 | Q3: 10655.067 | R3: 10655.067 | S3: =SUM(G3:R3) -> 127860.8 | T3: ='4.2 Simplify Savings'!AB49 -> -14000 | U3: =SUM(S3:T3) -> 113860.8
A4: =_xlfn.XLOOKUP(B4,'Reference '!J:J,'Reference '!K:K) -> Blanche Derkenne | B4: 0560_DSI PM | C4: 613020 | D4: GENERAL | E4: Global Learning | F4: GENERAL | G4: 3333.3333 | H4: 3333.3333 | I4: 3333.3333 | J4: 3333.3333 | K4: 3333.3333 | L4: 3333.3333 | M4: 3333.3333 | N4: 3333.3333 | O4: 3333.3333 | P4: 3333.3333 | Q4: 3333.3333 | R4: 3333.3333 | S4: =SUM(G4:R4) -> 40000 | U4: =SUM(S4:T4) -> 40000
A5: =_xlfn.XLOOKUP(B5,'Reference '!J:J,'Reference '!K:K) -> Blanche Derkenne | B5: 0560_DSI PM | C5: 616800 | D5: GENERAL | E5: Teambuildings | F5: GENERAL | G5: 5589.6222 | H5: 5589.6222 | I5: 5589.6222 | J5: 5589.6222 | K5: 5589.6222 | L5: 5589.6222 | M5: 5589.6222 | N5: 5589.6222 | O5: 5589.6222 | P5: 5589.6222 | Q5: 5589.6222 | R5: 5589.6222 | S5: =SUM(G5:R5) -> 67075.466 | U5: =SUM(S5:T5) -> 67075.466
A6: =_xlfn.XLOOKUP(B6,'Reference '!J:J,'Reference '!K:K) -> Blanche Derkenne | B6: 0560_DSI PM | C6: 615100 | D6: GENERAL | E6: Travel costs (train, bus…) | F6: GENERAL | G6: 1018 | H6: 1018 | I6: 1018 | J6: 1018 | K6: 1018 | L6: 1018 | M6: 1018 | N6: 1018 | O6: 1018 | P6: 1018 | Q6: 1018 | R6: 1018 | S6: =SUM(G6:R6) -> 12216 | U6: =SUM(S6:T6) -> 12216
A7: =_xlfn.XLOOKUP(B7,'Reference '!J:J,'Reference '!K:K) -> Blanche Derkenne | B7: 0560_DSI PM | C7: 615105 | D7: GENERAL | E7: Travel costs (taxis) | F7: GENERAL | G7: 848.33333 | H7: 848.33333 | I7: 848.33333 | J7: 848.33333 | K7: 848.33333 | L7: 848.33333 | M7: 848.33333 | N7: 848.33333 | O7: 848.33333 | P7: 848.33333 | Q7: 848.33333 | R7: 848.33333 | S7: =SUM(G7:R7) -> 10180 | U7: =SUM(S7:T7) -> 10180
A8: =_xlfn.XLOOKUP(B8,'Reference '!J:J,'Reference '!K:K) -> Blanche Derkenne | B8: 0560_DSI PM | C8: 615120 | D8: GENERAL | E8: Travel costs (restaurants) | F8: GENERAL | G8: 1946.9167 | H8: 1946.9167 | I8: 1946.9167 | J8: 1946.9167 | K8: 1946.9167 | L8: 1946.9167 | M8: 1946.9167 | N8: 1946.9167 | O8: 1946.9167 | P8: 1946.9167 | Q8: 1946.9167 | R8: 1946.9167 | S8: =SUM(G8:R8) -> 23363 | U8: =SUM(S8:T8) -> 23363
A9: =_xlfn.XLOOKUP(B9,'Reference '!J:J,'Reference '!K:K) -> Ben Gbeve | B9: 0530_DSI OAIN | C9: 612503 | D9: GENERAL | E9: COLT (TBC - customer service numbers?) | F9: GENERAL | G9: 1250 | H9: 1250 | I9: 1250 | J9: 1250 | K9: 1250 | L9: 1250 | M9: 1250 | N9: 1250 | O9: 1250 | P9: 1250 | Q9: 1250 | R9: 1250 | S9: =SUM(G9:R9) -> 15000 | U9: =SUM(S9:T9) -> 15000
A10: =_xlfn.XLOOKUP(B10,'Reference '!J:J,'Reference '!K:K) -> Ben Gbeve | B10: 0530_DSI OAIN | C10: 613003 | D10: GENERAL | E10: Eurofiber Dark fibre between HQ and OCC | F10: GENERAL | G10: 250 | H10: 250 | I10: 250 | J10: 250 | K10: 250 | L10: 250 | M10: 250 | N10: 250 | O10: 250 | P10: 250 | Q10: 250 | R10: 250 | S10: =SUM(G10:R10) -> 3000 | U10: =SUM(S10:T10) -> 3000
A11: =_xlfn.XLOOKUP(B11,'Reference '!J:J,'Reference '!K:K) -> Ben Gbeve | B11: 0530_DSI OAIN | C11: 613020 | D11: GENERAL | E11: HitRail, Hetmes/Tigre connection | F11: GENERAL | G11: 4333.3333 | H11: 4333.3333 | I11: 4333.3333 | J11: 4333.3333 | K11: 4333.3333 | L11: 4333.3333 | M11: 4333.3333 | N11: 4333.3333 | O11: 4333.3333 | P11: 4333.3333 | Q11: 4333.3333 | R11: 4333.3333 | S11: =SUM(G11:R11) -> 52000 | U11: =SUM(S11:T11) -> 52000
A12: =_xlfn.XLOOKUP(B12,'Reference '!J:J,'Reference '!K:K) -> Ben Gbeve | B12: 0530_DSI OAIN | C12: 612503 | D12: GENERAL | E12: Telekom Deutschland German Customer Service Freecall number | F12: GENERAL | G12: 250 | H12: 250 | I12: 250 | J12: 250 | K12: 250 | L12: 250 | M12: 250 | N12: 250 | O12: 250 | P12: 250 | Q12: 250 | R12: 250 | S12: =SUM(G12:R12) -> 3000 | U12: =SUM(S12:T12) -> 3000
A13: =_xlfn.XLOOKUP(B13,'Reference '!J:J,'Reference '!K:K) -> Ben Gbeve | B13: 0530_DSI OAIN | C13: 612503 | D13: GENERAL | E13: New Internet Service For SDWAN | F13: GENERAL | G13: 5300 | H13: 5300 | I13: 5300 | J13: 5300 | K13: 5300 | L13: 5300 | M13: 5300 | N13: 5300 | O13: 5300 | P13: 5300 | Q13: 5300 | R13: 5300 | S13: =SUM(G13:R13) -> 63600 | U13: =SUM(S13:T13) -> 63600
A14: =_xlfn.XLOOKUP(B14,'Reference '!J:J,'Reference '!K:K) -> Ben Gbeve | B14: 0530_DSI OAIN | C14: 612503 | D14: GENERAL | E14: SASE Replacement for Proximus MPLS | F14: GENERAL | G14: 0 | H14: 0 | I14: 0 | J14: 15000 | K14: 15000 | L14: 15000 | M14: 15000 | N14: 15000 | O14: 15000 | P14: 15000 | Q14: 15000 | R14: 15000 | S14: =SUM(G14:R14) -> 135000 | T14: ='4.2 Simplify Savings'!AB51 -> -120000 | U14: =SUM(S14:T14) -> 15000
A15: =_xlfn.XLOOKUP(B15,'Reference '!J:J,'Reference '!K:K) -> Ben Gbeve | B15: 0530_DSI OAIN | C15: 612503 | D15: GENERAL | E15: French crew mobile (SNCF contract) | F15: GENERAL | G15: 1666.6667 | H15: 1666.6667 | I15: 1666.6667 | J15: 1666.6667 | K15: 1666.6667 | L15: 1666.6667 | M15: 1666.6667 | N15: 1666.6667 | O15: 1666.6667 | P15: 1666.6667 | Q15: 1666.6667 | R15: 1666.6667 | S15: =SUM(G15:R15) -> 20000 | U15: =SUM(S15:T15) -> 20000
A16: =_xlfn.XLOOKUP(B16,'Reference '!J:J,'Reference '!K:K) -> Ben Gbeve | B16: 0530_DSI OAIN | C16: 612503 | D16: GENERAL | E16: ORANGE (TM, TD & Office mobiles) | F16: GENERAL | G16: 20416.667 | H16: 20416.667 | I16: 20416.667 | J16: 20416.667 | K16: 20416.667 | L16: 20416.667 | M16: 20416.667 | N16: 20416.667 | O16: 20416.667 | P16: 20416.667 | Q16: 20416.667 | R16: 20416.667 | S16: =SUM(G16:R16) -> 245000 | U16: =SUM(S16:T16) -> 245000
A17: =_xlfn.XLOOKUP(B17,'Reference '!J:J,'Reference '!K:K) -> Ben Gbeve | B17: 0530_DSI OAIN | C17: 612503 | D17: GENERAL | E17: SFR Mobile France leagcy connections for SNCF transferees | F17: GENERAL | G17: 666.66667 | H17: 666.66667 | I17: 666.66667 | J17: 666.66667 | K17: 666.66667 | L17: 666.66667 | M17: 666.66667 | N17: 666.66667 | O17: 666.66667 | P17: 666.66667 | Q17: 666.66667 | R17: 666.66667 | S17: =SUM(G17:R17) -> 8000 | U17: =SUM(S17:T17) -> 8000
A18: =_xlfn.XLOOKUP(B18,'Reference '!J:J,'Reference '!K:K) -> Ben Gbeve | B18: 0530_DSI OAIN | C18: 612520 | D18: GENERAL | E18: Licences F5, firewall services | F18: GENERAL | G18: 4500 | H18: 4500 | I18: 4500 | J18: 4500 | K18: 4500 | L18: 4500 | M18: 4500 | N18: 4500 | O18: 4500 | P18: 4500 | Q18: 4500 | R18: 4500 | S18: =SUM(G18:R18) -> 54000 | U18: =SUM(S18:T18) -> 54000
A19: =_xlfn.XLOOKUP(B19,'Reference '!J:J,'Reference '!K:K) -> Ben Gbeve | B19: 0530_DSI OAIN | C19: 612520 | D19: GENERAL | E19: Checkpoint firewall maintenance | F19: GENERAL | G19: 8333.3333 | H19: 8333.3333 | I19: 8333.3333 | J19: 8333.3333 | K19: 8333.3333 | L19: 8333.3333 | M19: 8333.3333 | N19: 8333.3333 | O19: 8333.3333 | P19: 8333.3333 | Q19: 8333.3333 | R19: 8333.3333 | S19: =SUM(G19:R19) -> 100000 | U19: =SUM(S19:T19) -> 100000
A20: =_xlfn.XLOOKUP(B20,'Reference '!J:J,'Reference '!K:K) -> Ben Gbeve | B20: 0530_DSI OAIN | C20: 612503 | D20: GENERAL | E20: OCC telephone support | F20: GENERAL | G20: 2083.3333 | H20: 2083.3333 | I20: 2083.3333 | J20: 2083.3333 | K20: 2083.3333 | L20: 2083.3333 | M20: 2083.3333 | N20: 2083.3333 | O20: 2083.3333 | P20: 2083.3333 | Q20: 2083.3333 | R20: 2083.3333 | S20: =SUM(G20:R20) -> 25000 | U20: =SUM(S20:T20) -> 25000
A21: =_xlfn.XLOOKUP(B21,'Reference '!J:J,'Reference '!K:K) -> Ben Gbeve | B21: 0530_DSI OAIN | C21: 612503 | D21: GENERAL | E21: Paris Internet connecting (COLT reseller) | F21: GENERAL | G21: 2083.3333 | H21: 2083.3333 | I21: 2083.3333 | J21: 2083.3333 | K21: 2083.3333 | L21: 2083.3333 | M21: 2083.3333 | N21: 2083.3333 | O21: 2083.3333 | P21: 2083.3333 | Q21: 2083.3333 | R21: 2083.3333 | S21: =SUM(G21:R21) -> 25000 | T21: ='4.2 Simplify Savings'!AB50 -> -12500 | U21: =SUM(S21:T21) -> 12500
A22: =_xlfn.XLOOKUP(B22,'Reference '!J:J,'Reference '!K:K) -> Ben Gbeve | B22: 0530_DSI OAIN | C22: 612503 | D22: GENERAL | E22: PROXIMUS (MPLS and Internet) | F22: GENERAL | G22: 20000 | H22: 20000 | I22: 20000 | J22: 20000 | K22: 20000 | L22: 20000 | M22: 20000 | N22: 20000 | O22: 20000 | P22: 20000 | Q22: 20000 | R22: 20000 | S22: =SUM(G22:R22) -> 240000 | U22: =SUM(S22:T22) -> 240000
A23: =_xlfn.XLOOKUP(B23,'Reference '!J:J,'Reference '!K:K) -> Ben Gbeve | B23: 0530_DSI OAIN | C23: 612520 | D23: GENERAL | E23: Visual Audio | F23: GENERAL | G23: 1250 | H23: 1250 | I23: 1250 | J23: 1250 | K23: 1250 | L23: 1250 | M23: 1250 | N23: 1250 | O23: 1250 | P23: 1250 | Q23: 1250 | R23: 1250 | S23: =SUM(G23:R23) -> 15000 | U23: =SUM(S23:T23) -> 15000
A24: =_xlfn.XLOOKUP(B24,'Reference '!J:J,'Reference '!K:K) -> Ben Gbeve | B24: 0530_DSI OAIN | C24: 611200 | D24: GENERAL | E24: Stations | F24: GENERAL | G24: 801.33333 | H24: 801.33333 | I24: 801.33333 | J24: 801.33333 | K24: 801.33333 | L24: 801.33333 | M24: 801.33333 | N24: 801.33333 | O24: 801.33333 | P24: 801.33333 | Q24: 801.33333 | R24: 801.33333 | S24: =SUM(G24:R24) -> 9616 | U24: =SUM(S24:T24) -> 9616
A25: =_xlfn.XLOOKUP(B25,'Reference '!J:J,'Reference '!K:K) -> Ben Gbeve | B25: 0530_DSI OAIN | C25: 612520 | D25: GENERAL | E25: ZEBRIX Digital Signage Screens | F25: GENERAL | G25: 291.66667 | H25: 291.66667 | I25: 291.66667 | J25: 291.66667 | K25: 291.66667 | L25: 291.66667 | M25: 291.66667 | N25: 291.66667 | O25: 291.66667 | P25: 291.66667 | Q25: 291.66667 | R25: 291.66667 | S25: =SUM(G25:R25) -> 3500 | U25: =SUM(S25:T25) -> 3500
A26: =_xlfn.XLOOKUP(B26,'Reference '!J:J,'Reference '!K:K) -> Ben Gbeve | B26: 0530_DSI OAIN | C26: 612900 | D26: GENERAL | E26: Hardware and consumables | F26: GENERAL | G26: 14583.333 | H26: 14583.333 | I26: 14583.333 | J26: 14583.333 | K26: 14583.333 | L26: 14583.333 | M26: 14583.333 | N26: 14583.333 | O26: 14583.333 | P26: 14583.333 | Q26: 14583.333 | R26: 14583.333 | S26: =SUM(G26:R26) -> 175000 | U26: =SUM(S26:T26) -> 175000
A27: =_xlfn.XLOOKUP(B27,'Reference '!J:J,'Reference '!K:K) -> Ben Gbeve | B27: 0530_DSI OAIN | C27: 612520 | D27: GENERAL | E27: CreativeOne (Door access video phone Brussels) | F27: GENERAL | G27: 81 | H27: 81 | I27: 81 | J27: 81 | K27: 81 | L27: 81 | M27: 81 | N27: 81 | O27: 81 | P27: 81 | Q27: 81 | R27: 81 | S27: =SUM(G27:R27) -> 972 | U27: =SUM(S27:T27) -> 972
A28: =_xlfn.XLOOKUP(B28,'Reference '!J:J,'Reference '!K:K) -> Ben Gbeve | B28: 0530_DSI OAIN | C28: 612900 | D28: GENERAL | E28: Smart phones | F28: GENERAL | G28: 8333.3333 | H28: 8333.3333 | I28: 8333.3333 | J28: 8333.3333 | K28: 8333.3333 | L28: 8333.3333 | M28: 8333.3333 | N28: 8333.3333 | O28: 8333.3333 | P28: 8333.3333 | Q28: 8333.3333 | R28: 8333.3333 | S28: =SUM(G28:R28) -> 100000 | U28: =SUM(S28:T28) -> 100000
A29: =_xlfn.XLOOKUP(B29,'Reference '!J:J,'Reference '!K:K) -> Ben Gbeve | B29: 0530_DSI OAIN | C29: 612520 | D29: GENERAL | E29: E-FOTA, Samsung sw/fw deployment | F29: GENERAL | G29: 1583.3333 | H29: 1583.3333 | I29: 1583.3333 | J29: 1583.3333 | K29: 1583.3333 | L29: 1583.3333 | M29: 1583.3333 | N29: 1583.3333 | O29: 1583.3333 | P29: 1583.3333 | Q29: 1583.3333 | R29: 1583.3333 | S29: =SUM(G29:R29) -> 19000 | U29: =SUM(S29:T29) -> 19000
A30: =_xlfn.XLOOKUP(B30,'Reference '!J:J,'Reference '!K:K) -> Ben Gbeve | B30: 0530_DSI OAIN | C30: 612520 | D30: GENERAL | E30: AirWatch Mobile device management | F30: GENERAL | G30: 4750 | H30: 4750 | I30: 4750 | J30: 4750 | K30: 4750 | L30: 4750 | M30: 4750 | N30: 4750 | O30: 4750 | P30: 4750 | Q30: 4750 | R30: 4750 | S30: =SUM(G30:R30) -> 57000 | U30: =SUM(S30:T30) -> 57000
A31: =_xlfn.XLOOKUP(B31,'Reference '!J:J,'Reference '!K:K) -> Ben Gbeve | B31: 0530_DSI OAIN | C31: 612520 | D31: GENERAL | E31: ITMS / Alteris | F31: GENERAL | G31: 5500 | H31: 5500 | I31: 5500 | J31: 5500 | K31: 5500 | L31: 5500 | M31: 5500 | N31: 5500 | O31: 5500 | P31: 5500 | Q31: 5500 | R31: 5500 | S31: =SUM(G31:R31) -> 66000 | T31: ='4.2 Simplify Savings'!AB52 -> -66000 | U31: =SUM(S31:T31) -> 0
A32: =_xlfn.XLOOKUP(B32,'Reference '!J:J,'Reference '!K:K) -> Ben Gbeve | B32: 0530_DSI OAIN | C32: 612520 | D32: GENERAL | E32: Licences additionnelles | F32: GENERAL | G32: 5833.3333 | H32: 5833.3333 | I32: 5833.3333 | J32: 5833.3333 | K32: 5833.3333 | L32: 5833.3333 | M32: 5833.3333 | N32: 5833.3333 | O32: 5833.3333 | P32: 5833.3333 | Q32: 5833.3333 | R32: 5833.3333 | S32: =SUM(G32:R32) -> 70000 | U32: =SUM(S32:T32) -> 70000
A33: =_xlfn.XLOOKUP(B33,'Reference '!J:J,'Reference '!K:K) -> Ben Gbeve | B33: 0530_DSI OAIN | C33: 611100 | D33: GENERAL | E33: GCS avance copie | F33: GENERAL | G33: 833.33333 | H33: 833.33333 | I33: 833.33333 | J33: 833.33333 | K33: 833.33333 | L33: 833.33333 | M33: 833.33333 | N33: 833.33333 | O33: 833.33333 | P33: 833.33333 | Q33: 833.33333 | R33: 833.33333 | S33: =SUM(G33:R33) -> 10000 | U33: =SUM(S33:T33) -> 10000
A34: =_xlfn.XLOOKUP(B34,'Reference '!J:J,'Reference '!K:K) -> Ben Gbeve | B34: 0530_DSI OAIN | C34: 612520 | D34: GENERAL | E34: Office365, end user licences | F34: GENERAL | G34: 25250 | H34: 25250 | I34: 25250 | J34: 25250 | K34: 25250 | L34: 25250 | M34: 25250 | N34: 25250 | O34: 25250 | P34: 25250 | Q34: 25250 | R34: 25250 | S34: =SUM(G34:R34) -> 303000 | U34: =SUM(S34:T34) -> 303000
A35: =_xlfn.XLOOKUP(B35,'Reference '!J:J,'Reference '!K:K) -> Ben Gbeve | B35: 0530_DSI OAIN | C35: 612520 | D35: GENERAL | E35: Mimecast email security - THIF | F35: GENERAL | G35: 6250 | H35: 6250 | I35: 6250 | J35: 6250 | K35: 6250 | L35: 6250 | M35: 6250 | N35: 6250 | O35: 6250 | P35: 6250 | Q35: 6250 | R35: 6250 | S35: =SUM(G35:R35) -> 75000 | U35: =SUM(S35:T35) -> 75000
A36: =_xlfn.XLOOKUP(B36,'Reference '!J:J,'Reference '!K:K) -> Ben Gbeve | B36: 0530_DSI OAIN | C36: 612520 | D36: GENERAL | E36: Symantec Endpoint | F36: GENERAL | G36: 1666.6667 | H36: 1666.6667 | I36: 1666.6667 | J36: 1666.6667 | K36: 1666.6667 | L36: 1666.6667 | M36: 1666.6667 | N36: 1666.6667 | O36: 1666.6667 | P36: 1666.6667 | Q36: 1666.6667 | R36: 1666.6667 | S36: =SUM(G36:R36) -> 20000 | T36: ='4.2 Simplify Savings'!AB53 -> -20000.04 | U36: =SUM(S36:T36) -> -0.04
A37: =_xlfn.XLOOKUP(B37,'Reference '!J:J,'Reference '!K:K) -> Ben Gbeve | B37: 0530_DSI OAIN | C37: 612520 | D37: GENERAL | E37: Sentinell ONE | F37: GENERAL | G37: 4166.6667 | H37: 4166.6667 | I37: 4166.6667 | J37: 4166.6667 | K37: 4166.6667 | L37: 4166.6667 | M37: 4166.6667 | N37: 4166.6667 | O37: 4166.6667 | P37: 4166.6667 | Q37: 4166.6667 | R37: 4166.6667 | S37: =SUM(G37:R37) -> 50000 | U37: =SUM(S37:T37) -> 50000
A38: =_xlfn.XLOOKUP(B38,'Reference '!J:J,'Reference '!K:K) -> Ben Gbeve | B38: 0530_DSI OAIN | C38: 612620 | D38: GENERAL | E38: Azure, Microsoft cloud hosting | F38: GENERAL | G38: 120833.33 | H38: 120833.33 | I38: 120833.33 | J38: 120833.33 | K38: 120833.33 | L38: 120833.33 | M38: 120833.33 | N38: 120833.33 | O38: 120833.33 | P38: 120833.33 | Q38: 120833.33 | R38: 120833.33 | S38: =SUM(G38:R38) -> 1450000 | T38: ='4.2 Simplify Savings'!AB54 -> -66000 | U38: =SUM(S38:T38) -> 1384000
A39: =_xlfn.XLOOKUP(B39,'Reference '!J:J,'Reference '!K:K) -> Ben Gbeve | B39: 0530_DSI OAIN | C39: 612620 | D39: GENERAL | E39: Projected Azure BAU reductions (250K SVOT/SVOC decom shown in D&M budget) | F39: GENERAL | G39: 0 | H39: 0 | I39: 0 | J39: 0 | K39: 0 | L39: 0 | M39: 0 | N39: 0 | O39: 0 | P39: 0 | Q39: 0 | R39: 0 | S39: =SUM(G39:R39) -> 0 | U39: =SUM(S39:T39) -> 0
A40: =_xlfn.XLOOKUP(B40,'Reference '!J:J,'Reference '!K:K) -> Ben Gbeve | B40: 0530_DSI OAIN | C40: 612620 | D40: GENERAL | E40: Azure, Microsoft cloud hosting (New Projects: Eroster 100K, Exit checks 40K, JoinDas 40K, ARC patching 25K: ) | F40: GENERAL | G40: 16667 | H40: 16667 | I40: 16667 | J40: 16667 | K40: 16667 | L40: 16667 | M40: 16667 | N40: 16667 | O40: 16667 | P40: 16667 | Q40: 16667 | R40: 16667 | S40: =SUM(G40:R40) -> 200004 | U40: =SUM(S40:T40) -> 200004
A41: =_xlfn.XLOOKUP(B41,'Reference '!J:J,'Reference '!K:K) -> Ben Gbeve | B41: 0530_DSI OAIN | C41: 612520 | D41: GENERAL | E41: Terraform - Hashicorp | F41: GENERAL | G41: 833.33333 | H41: 833.33333 | I41: 833.33333 | J41: 833.33333 | K41: 833.33333 | L41: 833.33333 | M41: 833.33333 | N41: 833.33333 | O41: 833.33333 | P41: 833.33333 | Q41: 833.33333 | R41: 833.33333 | S41: =SUM(G41:R41) -> 10000 | U41: =SUM(S41:T41) -> 10000
A42: =_xlfn.XLOOKUP(B42,'Reference '!J:J,'Reference '!K:K) -> Ben Gbeve | B42: 0530_DSI OAIN | C42: 612520 | D42: GENERAL | E42: Digital Certificates | F42: GENERAL | G42: 833.33333 | H42: 833.33333 | I42: 833.33333 | J42: 833.33333 | K42: 833.33333 | L42: 833.33333 | M42: 833.33333 | N42: 833.33333 | O42: 833.33333 | P42: 833.33333 | Q42: 833.33333 | R42: 833.33333 | S42: =SUM(G42:R42) -> 10000 | U42: =SUM(S42:T42) -> 10000
A43: =_xlfn.XLOOKUP(B43,'Reference '!J:J,'Reference '!K:K) -> Ben Gbeve | B43: 0530_DSI OAIN | C43: 612520 | D43: GENERAL | E43: Github - CCOE, code repository | F43: GENERAL | G43: 833.33333 | H43: 833.33333 | I43: 833.33333 | J43: 833.33333 | K43: 833.33333 | L43: 833.33333 | M43: 833.33333 | N43: 833.33333 | O43: 833.33333 | P43: 833.33333 | Q43: 833.33333 | R43: 833.33333 | S43: =SUM(G43:R43) -> 10000 | U43: =SUM(S43:T43) -> 10000
A44: =_xlfn.XLOOKUP(B44,'Reference '!J:J,'Reference '!K:K) -> Ben Gbeve | B44: 0530_DSI OAIN | C44: 612520 | D44: GENERAL | E44: Oracle DB for Totem+ | F44: GENERAL | G44: 1666.6667 | H44: 1666.6667 | I44: 1666.6667 | J44: 1666.6667 | K44: 1666.6667 | L44: 1666.6667 | M44: 1666.6667 | N44: 1666.6667 | O44: 1666.6667 | P44: 1666.6667 | Q44: 1666.6667 | R44: 1666.6667 | S44: =SUM(G44:R44) -> 20000 | U44: =SUM(S44:T44) -> 20000
A45: =_xlfn.XLOOKUP(B45,'Reference '!J:J,'Reference '!K:K) -> Ben Gbeve | B45: 0530_DSI OAIN | C45: 612620 | D45: GENERAL | E45: NetApp Storage | F45: GENERAL | G45: 1916.6667 | H45: 1916.6667 | I45: 1916.6667 | J45: 1916.6667 | K45: 1916.6667 | L45: 1916.6667 | M45: 1916.6667 | N45: 1916.6667 | O45: 1916.6667 | P45: 1916.6667 | Q45: 1916.6667 | R45: 1916.6667 | S45: =SUM(G45:R45) -> 23000 | U45: =SUM(S45:T45) -> 23000
A46: =_xlfn.XLOOKUP(B46,'Reference '!J:J,'Reference '!K:K) -> Ben Gbeve | B46: 0530_DSI OAIN | C46: 612620 | D46: GENERAL | E46: Managed Service Provider - Core Service Charge (BAU & Tx) | F46: GENERAL | G46: 98333 | H46: 98333 | I46: 98333 | J46: 98333 | K46: 98333 | L46: 98333 | M46: 98333 | N46: 98333 | O46: 98333 | P46: 98333 | Q46: 98333 | R46: 98333 | S46: =SUM(G46:R46) -> 1179996 | T46: ='4.2 Simplify Savings'!AB55 -> -151524 | U46: =SUM(S46:T46) -> 1028472
A47: =_xlfn.XLOOKUP(B47,'Reference '!J:J,'Reference '!K:K) -> Ben Gbeve | B47: 0530_DSI OAIN | C47: 612520 | D47: GENERAL | E47: Managed Service Provider - Arc/Rcs | F47: GENERAL | G47: 2084 | H47: 2084 | I47: 2084 | J47: 2084 | K47: 2084 | L47: 2084 | M47: 2084 | N47: 2084 | O47: 2084 | P47: 2084 | Q47: 2084 | R47: 2084 | S47: =SUM(G47:R47) -> 25008 | U47: =SUM(S47:T47) -> 25008
A48: =_xlfn.XLOOKUP(B48,'Reference '!J:J,'Reference '!K:K) -> Ben Gbeve | B48: 0530_DSI OAIN | C48: 612620 | D48: GENERAL | E48: Managed Service Provider - Non BAU | F48: GENERAL | G48: 5333 | H48: 5333 | I48: 5333 | J48: 5333 | K48: 5333 | L48: 5333 | M48: 5333 | N48: 5333 | O48: 5333 | P48: 5333 | Q48: 5333 | R48: 5333 | S48: =SUM(G48:R48) -> 63996 | U48: =SUM(S48:T48) -> 63996
A49: =_xlfn.XLOOKUP(B49,'Reference '!J:J,'Reference '!K:K) -> Ben Gbeve | B49: 0530_DSI OAIN | C49: 612620 | D49: GENERAL | E49: Managed Service Provider - TUPE Provision | F49: GENERAL | G49: 1083.3 | H49: 1083.3 | I49: 1083.3 | J49: 1083.3 | K49: 1083.3 | L49: 1083.3 | M49: 1083.3 | N49: 1083.3 | O49: 1083.3 | P49: 1083.3 | Q49: 1083.3 | R49: 1083.3 | S49: =SUM(G49:R49) -> 12999.6 | U49: =SUM(S49:T49) -> 12999.6
A50: =_xlfn.XLOOKUP(B50,'Reference '!J:J,'Reference '!K:K) -> Ben Gbeve | B50: 0530_DSI OAIN | C50: 613025 | D50: GENERAL | E50: Renfort Infra - Jonathan Jamart | F50: GENERAL | G50: 11646 | H50: 11646 | I50: 11646 | J50: 11646 | K50: 11646 | L50: 11646 | M50: 11646 | N50: 11646 | O50: 11646 | P50: 11646 | Q50: 11646 | R50: 11646 | S50: =SUM(G50:R50) -> 139752 | U50: =SUM(S50:T50) -> 139752 | V50: << staff cost (non FTE)
A51: =_xlfn.XLOOKUP(B51,'Reference '!J:J,'Reference '!K:K) -> Ben Gbeve | B51: 0530_DSI OAIN | C51: 613025 | D51: GENERAL | E51: Renfort infra - Thomas Vitali | F51: GENERAL | G51: 8820 | H51: 8820 | I51: 8820 | J51: 8820 | K51: 8820 | L51: 8820 | M51: 8820 | N51: 8820 | O51: 8820 | P51: 8820 | Q51: 8820 | R51: 8820 | S51: =SUM(G51:R51) -> 105840 | T51: ='4.2 Simplify Savings'!AB56 -> -105840 | U51: =SUM(S51:T51) -> 0 | V51: << staff cost (non FTE)
A52: =_xlfn.XLOOKUP(B52,'Reference '!J:J,'Reference '!K:K) -> Valerie Veyt | B52: 0520_DSI OSS | C52: 603300 | D52: GENERAL | E52: [ICOMERA] Wifi Licenses & Services (2026) | F52: GENERAL | G52: 79166.667 | H52: 79166.667 | I52: 79166.667 | J52: 79166.667 | K52: 79166.667 | L52: 79166.667 | M52: 79166.667 | N52: 79166.667 | O52: 79166.667 | P52: 79166.667 | Q52: 79166.667 | R52: 79166.667 | S52: =SUM(G52:R52) -> 950000 | T52: ='4.2 Simplify Savings'!AB57 -> -300000 | U52: =SUM(S52:T52) -> 650000
A53: =_xlfn.XLOOKUP(B53,'Reference '!J:J,'Reference '!K:K) -> Valerie Veyt | B53: 0520_DSI OSS | C53: 603300 | D53: GENERAL | E53: [ICOMERA] Wifi Mobile data (2026) | F53: GENERAL | G53: 100000 | H53: 100000 | I53: 100000 | J53: 100000 | K53: 100000 | L53: 100000 | M53: 100000 | N53: 100000 | O53: 100000 | P53: 100000 | Q53: 100000 | R53: 100000 | S53: =SUM(G53:R53) -> 1200000 | U53: =SUM(S53:T53) -> 1200000
A54: =_xlfn.XLOOKUP(B54,'Reference '!J:J,'Reference '!K:K) -> Valerie Veyt | B54: 0520_DSI OSS | C54: 603300 | D54: GENERAL | E54: [ICOMERA] Icoshape Traffic Shaping Activation | F54: GENERAL | G54: 4166.6667 | H54: 4166.6667 | I54: 4166.6667 | J54: 4166.6667 | K54: 4166.6667 | L54: 4166.6667 | M54: 4166.6667 | N54: 4166.6667 | O54: 4166.6667 | P54: 4166.6667 | Q54: 4166.6667 | R54: 4166.6667 | S54: =SUM(G54:R54) -> 50000 | U54: =SUM(S54:T54) -> 50000
A55: =_xlfn.XLOOKUP(B55,'Reference '!J:J,'Reference '!K:K) -> Valerie Veyt | B55: 0520_DSI OSS | C55: 612502 | D55: GENERAL | E55: SEMES (SNCB) - description à finaliser | F55: GENERAL | G55: 3333.3333 | H55: 3333.3333 | I55: 3333.3333 | J55: 3333.3333 | K55: 3333.3333 | L55: 3333.3333 | M55: 3333.3333 | N55: 3333.3333 | O55: 3333.3333 | P55: 3333.3333 | Q55: 3333.3333 | R55: 3333.3333 | S55: =SUM(G55:R55) -> 40000 | U55: =SUM(S55:T55) -> 40000
A56: =_xlfn.XLOOKUP(B56,'Reference '!J:J,'Reference '!K:K) -> Valerie Veyt | B56: 0520_DSI OSS | C56: 612520 | D56: GENERAL | E56: ATESS - sécurité embarquée - à bord des rames | F56: GENERAL | G56: 1666.6667 | H56: 1666.6667 | I56: 1666.6667 | J56: 1666.6667 | K56: 1666.6667 | L56: 1666.6667 | M56: 1666.6667 | N56: 1666.6667 | O56: 1666.6667 | P56: 1666.6667 | Q56: 1666.6667 | R56: 1666.6667 | S56: =SUM(G56:R56) -> 20000 | U56: =SUM(S56:T56) -> 20000
A57: =_xlfn.XLOOKUP(B57,'Reference '!J:J,'Reference '!K:K) -> Valerie Veyt | B57: 0520_DSI OSS | C57: 612520 | D57: GENERAL | E57: Qualishare | F57: GENERAL | G57: 1333.3333 | H57: 1333.3333 | I57: 1333.3333 | J57: 1333.3333 | K57: 1333.3333 | L57: 1333.3333 | M57: 1333.3333 | N57: 1333.3333 | O57: 1333.3333 | P57: 1333.3333 | Q57: 1333.3333 | R57: 1333.3333 | S57: =SUM(G57:R57) -> 16000 | U57: =SUM(S57:T57) -> 16000
A58: =_xlfn.XLOOKUP(B58,'Reference '!J:J,'Reference '!K:K) -> Valerie Veyt | B58: 0520_DSI OSS | C58: 612520 | D58: GENERAL | E58: RNE | F58: GENERAL | G58: 416.66667 | H58: 416.66667 | I58: 416.66667 | J58: 416.66667 | K58: 416.66667 | L58: 416.66667 | M58: 416.66667 | N58: 416.66667 | O58: 416.66667 | P58: 416.66667 | Q58: 416.66667 | R58: 416.66667 | S58: =SUM(G58:R58) -> 5000 | U58: =SUM(S58:T58) -> 5000
A59: =_xlfn.XLOOKUP(B59,'Reference '!J:J,'Reference '!K:K) -> Valerie Veyt | B59: 0520_DSI OSS | C59: 613003 | D59: GENERAL | E59: [MASTERIS] TIGRE, Base Sillon, … | F59: GMAO | G59: 193750 | H59: 193750 | I59: 193750 | J59: 193750 | K59: 193750 | L59: 193750 | M59: 193750 | N59: 193750 | O59: 193750 | P59: 193750 | Q59: 193750 | R59: 193750 | S59: =SUM(G59:R59) -> 2325000 | U59: =SUM(S59:T59) -> 2325000
A60: =_xlfn.XLOOKUP(B60,'Reference '!J:J,'Reference '!K:K) -> Valerie Veyt | B60: 0520_DSI OSS | C60: 613003 | D60: GENERAL | E60: [JLL] - Support annuel 2026 | F60: GENERAL | G60: 4166.6667 | H60: 4166.6667 | I60: 4166.6667 | J60: 4166.6667 | K60: 4166.6667 | L60: 4166.6667 | M60: 4166.6667 | N60: 4166.6667 | O60: 4166.6667 | P60: 4166.6667 | Q60: 4166.6667 | R60: 4166.6667 | S60: =SUM(G60:R60) -> 50000 | U60: =SUM(S60:T60) -> 50000
A61: =_xlfn.XLOOKUP(B61,'Reference '!J:J,'Reference '!K:K) -> Valerie Veyt | B61: 0520_DSI OSS | C61: 613003 | D61: GENERAL | E61: [Totem+ Mantra] Support et maintenance 2026 | F61: GENERAL | G61: 16666.667 | H61: 16666.667 | I61: 16666.667 | J61: 16666.667 | K61: 16666.667 | L61: 16666.667 | M61: 16666.667 | N61: 16666.667 | O61: 16666.667 | P61: 16666.667 | Q61: 16666.667 | R61: 16666.667 | S61: =SUM(G61:R61) -> 200000 | T61: ='4.2 Simplify Savings'!AB58 -> -10000 | U61: =SUM(S61:T61) -> 190000
A62: =_xlfn.XLOOKUP(B62,'Reference '!J:J,'Reference '!K:K) -> Valerie Veyt | B62: 0520_DSI OSS | C62: 613003 | D62: GENERAL | E62: [Totem+ Mantra] Astreintes 2026 | F62: GENERAL | G62: 4166.6667 | H62: 4166.6667 | I62: 4166.6667 | J62: 4166.6667 | K62: 4166.6667 | L62: 4166.6667 | M62: 4166.6667 | N62: 4166.6667 | O62: 4166.6667 | P62: 4166.6667 | Q62: 4166.6667 | R62: 4166.6667 | S62: =SUM(G62:R62) -> 50000 | U62: =SUM(S62:T62) -> 50000
A63: =_xlfn.XLOOKUP(B63,'Reference '!J:J,'Reference '!K:K) -> Valerie Veyt | B63: 0520_DSI OSS | C63: 613003 | D63: GENERAL | E63: [SSG] Support TAM TAM 2026 (fixed) | F63: GENERAL | G63: 2500 | H63: 2500 | I63: 2500 | J63: 2500 | K63: 2500 | L63: 2500 | M63: 2500 | N63: 2500 | O63: 2500 | P63: 2500 | Q63: 2500 | R63: 2500 | S63: =SUM(G63:R63) -> 30000 | U63: =SUM(S63:T63) -> 30000
A64: =_xlfn.XLOOKUP(B64,'Reference '!J:J,'Reference '!K:K) -> Valerie Veyt | B64: 0520_DSI OSS | C64: 613003 | D64: GENERAL | E64: [SSG] Support TAM TAM 2026 (variable part) | F64: GENERAL | G64: 10000 | H64: 10000 | I64: 10000 | J64: 10000 | K64: 10000 | L64: 10000 | M64: 10000 | N64: 10000 | O64: 10000 | P64: 10000 | Q64: 10000 | R64: 10000 | S64: =SUM(G64:R64) -> 120000 | U64: =SUM(S64:T64) -> 120000
A65: =_xlfn.XLOOKUP(B65,'Reference '!J:J,'Reference '!K:K) -> Valerie Veyt | B65: 0520_DSI OSS | C65: 613003 | D65: GENERAL | E65: [TAM TAM] - Support and maintenance 2026 | F65: GENERAL | G65: 4583.3333 | H65: 4583.3333 | I65: 4583.3333 | J65: 4583.3333 | K65: 4583.3333 | L65: 4583.3333 | M65: 4583.3333 | N65: 4583.3333 | O65: 4583.3333 | P65: 4583.3333 | Q65: 4583.3333 | R65: 4583.3333 | S65: =SUM(G65:R65) -> 55000 | U65: =SUM(S65:T65) -> 55000
A66: =_xlfn.XLOOKUP(B66,'Reference '!J:J,'Reference '!K:K) -> Valerie Veyt | B66: 0520_DSI OSS | C66: 613003 | D66: GENERAL | E66: [SIMPLIFY] E ROSTER / TAM TAM - Technical evolutions (archive, hosting…) | F66: GENERAL | G66: 12500 | H66: 12500 | I66: 12500 | J66: 12500 | K66: 12500 | L66: 12500 | M66: 12500 | N66: 12500 | O66: 12500 | P66: 12500 | Q66: 12500 | R66: 12500 | S66: =SUM(G66:R66) -> 150000 | U66: =SUM(S66:T66) -> 150000
A67: =_xlfn.XLOOKUP(B67,'Reference '!J:J,'Reference '!K:K) -> Valerie Veyt | B67: 0520_DSI OSS | C67: 613003 | D67: GENERAL | E67: [DocThalys\ValidMe + TCS] - Support 2026 | F67: GENERAL | G67: 1666.6667 | H67: 1666.6667 | I67: 1666.6667 | J67: 1666.6667 | K67: 1666.6667 | L67: 1666.6667 | M67: 1666.6667 | N67: 1666.6667 | O67: 1666.6667 | P67: 1666.6667 | Q67: 1666.6667 | R67: 1666.6667 | S67: =SUM(G67:R67) -> 20000 | U67: =SUM(S67:T67) -> 20000
A68: =_xlfn.XLOOKUP(B68,'Reference '!J:J,'Reference '!K:K) -> Valerie Veyt | B68: 0520_DSI OSS | C68: 613003 | D68: GENERAL | E68: [Itersys] - Evolution SI PROD 2026 | F68: GENERAL | G68: 41666.667 | H68: 41666.667 | I68: 41666.667 | J68: 41666.667 | K68: 41666.667 | L68: 41666.667 | M68: 41666.667 | N68: 41666.667 | O68: 41666.667 | P68: 41666.667 | Q68: 41666.667 | R68: 41666.667 | S68: =SUM(G68:R68) -> 500000 | U68: =SUM(S68:T68) -> 500000
A69: =_xlfn.XLOOKUP(B69,'Reference '!J:J,'Reference '!K:K) -> Valerie Veyt | B69: 0520_DSI OSS | C69: 613003 | D69: GENERAL | E69: [Itersys] - Support SI PROD 2026 | F69: GENERAL | G69: 25000 | H69: 25000 | I69: 25000 | J69: 25000 | K69: 25000 | L69: 25000 | M69: 25000 | N69: 25000 | O69: 25000 | P69: 25000 | Q69: 25000 | R69: 25000 | S69: =SUM(G69:R69) -> 300000 | U69: =SUM(S69:T69) -> 300000
A70: =_xlfn.XLOOKUP(B70,'Reference '!J:J,'Reference '!K:K) -> Valerie Veyt | B70: 0520_DSI OSS | C70: 613003 | D70: GENERAL | E70: [Teams+] Corrective Maintenance / Release Management 2026 | F70: GENERAL | G70: 5750 | H70: 5750 | I70: 5750 | J70: 5750 | K70: 5750 | L70: 5750 | M70: 5750 | N70: 5750 | O70: 5750 | P70: 5750 | Q70: 5750 | R70: 5750 | S70: =SUM(G70:R70) -> 69000 | U70: =SUM(S70:T70) -> 69000
A71: =_xlfn.XLOOKUP(B71,'Reference '!J:J,'Reference '!K:K) -> Valerie Veyt | B71: 0520_DSI OSS | C71: 613025 | D71: GENERAL | E71: [Abdelilah Skouri] Pdct Ownr & PM - 2026 | F71: GENERAL | G71: 13666.667 | H71: 13666.667 | I71: 13666.667 | J71: 13666.667 | K71: 13666.667 | L71: 13666.667 | M71: 13666.667 | N71: 13666.667 | O71: 13666.667 | P71: 13666.667 | Q71: 13666.667 | R71: 13666.667 | S71: =SUM(G71:R71) -> 164000 | U71: =SUM(S71:T71) -> 164000 | V71: << staff cost (non FTE)
A72: =_xlfn.XLOOKUP(B72,'Reference '!J:J,'Reference '!K:K) -> Valerie Veyt | B72: 0520_DSI OSS | C72: 613025 | D72: GENERAL | E72: [SIMPLIFY] [IS OPS] - DECOMISSIONNING PM (1 ETP) - 2026 | F72: GENERAL | G72: 15000 | H72: 15000 | I72: 15000 | J72: 15000 | K72: 15000 | L72: 15000 | M72: 15000 | N72: 15000 | O72: 15000 | P72: 15000 | Q72: 15000 | R72: 15000 | S72: =SUM(G72:R72) -> 180000 | U72: =SUM(S72:T72) -> 180000 | V72: << staff cost (non FTE)
A73: =_xlfn.XLOOKUP(B73,'Reference '!J:J,'Reference '!K:K) -> Valerie Veyt | B73: 0520_DSI OSS | C73: 613003 | D73: GENERAL | E73: NIS2 | F73: GENERAL | G73: 15000 | H73: 15000 | I73: 15000 | J73: 15000 | K73: 15000 | L73: 15000 | M73: 15000 | N73: 15000 | O73: 15000 | P73: 15000 | Q73: 15000 | R73: 15000 | S73: =SUM(G73:R73) -> 180000 | U73: =SUM(S73:T73) -> 180000
A74: =_xlfn.XLOOKUP(B74,'Reference '!J:J,'Reference '!K:K) -> Valerie Veyt | B74: 0520_DSI OSS | C74: 603300 | D74: GENERAL | E74: [ICOMERA] Wifi Licenses & Services (2026) | F74: GENERAL | G74: 25000 | H74: 25000 | I74: 25000 | J74: 25000 | K74: 25000 | L74: 25000 | M74: 25000 | N74: 25000 | O74: 25000 | P74: 25000 | Q74: 25000 | R74: 25000 | S74: =SUM(G74:R74) -> 300000 | U74: =SUM(S74:T74) -> 300000
A75: =_xlfn.XLOOKUP(B75,'Reference '!J:J,'Reference '!K:K) -> Valerie Veyt | B75: 0520_DSI OSS | C75: 613003 | D75: GENERAL | E75: [Totem+Mantra] Support et maintenance 2025 | F75: GENERAL | G75: 833.33333 | H75: 833.33333 | I75: 833.33333 | J75: 833.33333 | K75: 833.33333 | L75: 833.33333 | M75: 833.33333 | N75: 833.33333 | O75: 833.33333 | P75: 833.33333 | Q75: 833.33333 | R75: 833.33333 | S75: =SUM(G75:R75) -> 10000 | U75: =SUM(S75:T75) -> 10000
A76: =_xlfn.XLOOKUP(B76,'Reference '!J:J,'Reference '!K:K) -> Valerie Veyt | B76: 0520_DSI OSS | C76: 612502 | D76: GENERAL | E76: Netsize | F76: GENERAL | G76: 8333.3333 | H76: 8333.3333 | I76: 8333.3333 | J76: 8333.3333 | K76: 8333.3333 | L76: 8333.3333 | M76: 8333.3333 | N76: 8333.3333 | O76: 8333.3333 | P76: 8333.3333 | Q76: 8333.3333 | R76: 8333.3333 | S76: =SUM(G76:R76) -> 100000 | T76: ='4.2 Simplify Savings'!AB59 -> -100000 | U76: =SUM(S76:T76) -> 0
A77: =_xlfn.XLOOKUP(B77,'Reference '!J:J,'Reference '!K:K) -> Valerie Veyt | B77: 0520_DSI OSS | C77: 613003 | D77: GENERAL | E77: [GoRail] Licence 2025 | F77: GENERAL | G77: 4583.3333 | H77: 4583.3333 | I77: 4583.3333 | J77: 4583.3333 | K77: 4583.3333 | L77: 4583.3333 | M77: 4583.3333 | N77: 4583.3333 | O77: 4583.3333 | P77: 4583.3333 | Q77: 4583.3333 | R77: 4583.3333 | S77: =SUM(G77:R77) -> 55000 | T77: ='4.2 Simplify Savings'!AB60 -> -55000 | U77: =SUM(S77:T77) -> 0
A78: =_xlfn.XLOOKUP(B78,'Reference '!J:J,'Reference '!K:K) -> Mael Delmas | B78: 0540_DSI ECOM | C78: 612520 | D78: SNCF-GLI76 | E78: [Salesforce] - SALESFORCE - Service/SalesClould licence | F78: GENERAL | G78: 41535.573 | H78: 41535.573 | I78: 41535.573 | J78: 41535.573 | K78: 41535.573 | L78: 41535.573 | M78: 41535.573 | N78: 41535.573 | O78: 41535.573 | P78: 41535.573 | Q78: 41535.573 | R78: 41535.573 | S78: =SUM(G78:R78) -> 498426.88 | U78: =SUM(S78:T78) -> 498426.88
A79: =_xlfn.XLOOKUP(B79,'Reference '!J:J,'Reference '!K:K) -> Mael Delmas | B79: 0540_DSI ECOM | C79: 612520 | D79: SNCF-GLI76 | E79: [Salesforce] - Salesforce Marketing Cloud licence | F79: GENERAL | G79: 19128.224 | H79: 19128.224 | I79: 19128.224 | J79: 19128.224 | K79: 19128.224 | L79: 19128.224 | M79: 19128.224 | N79: 19128.224 | O79: 19128.224 | P79: 19128.224 | Q79: 19128.224 | R79: 19128.224 | S79: =SUM(G79:R79) -> 229538.69 | U79: =SUM(S79:T79) -> 229538.69
A80: =_xlfn.XLOOKUP(B80,'Reference '!J:J,'Reference '!K:K) -> Mael Delmas | B80: 0540_DSI ECOM | C80: 612520 | D80: SNCF-GLI76 | E80: [Salesforce] Loyalty Cloud licence | F80: GENERAL | G80: 12979.867 | H80: 12979.867 | I80: 12979.867 | J80: 12979.867 | K80: 12979.867 | L80: 12979.867 | M80: 12979.867 | N80: 12979.32 | O80: 12979.867 | P80: 12979.867 | Q80: 12979.867 | R80: 12979.867 | S80: =SUM(G80:R80) -> 155757.85 | U80: =SUM(S80:T80) -> 155757.85
A81: =_xlfn.XLOOKUP(B81,'Reference '!J:J,'Reference '!K:K) -> Mael Delmas | B81: 0540_DSI ECOM | C81: 612520 | D81: SNCF-GLI76 | E81: [Loyalty] - ICLP PLC/Collinsons: Application maintenance for Loyalty | F81: GENERAL | G81: 17800.179 | H81: 17800.179 | I81: 17800.179 | J81: 17800.179 | K81: 17800.179 | L81: 17800.179 | M81: 17800.179 | N81: 17800.179 | O81: 17800.726 | P81: 17801.272 | Q81: 17801.819 | R81: 17802.365 | S81: =SUM(G81:R81) -> 213607.62 | U81: =SUM(S81:T81) -> 213607.62
A82: =_xlfn.XLOOKUP(B82,'Reference '!J:J,'Reference '!K:K) -> Mael Delmas | B82: 0540_DSI ECOM | C82: 613004 | D82: GENERAL | E82: [On-board] - TACT hosting and application maintenance | F82: GENERAL | G82: 30000 | H82: 30000 | I82: 30000 | J82: 30000 | K82: 30000 | L82: 30000 | M82: 30000 | N82: 30000 | O82: 30000 | P82: 30000 | Q82: 30000 | R82: 30000 | S82: =SUM(G82:R82) -> 360000 | T82: ='4.2 Simplify Savings'!AB61 -> -8400 | U82: =SUM(S82:T82) -> 351600
A83: =_xlfn.XLOOKUP(B83,'Reference '!J:J,'Reference '!K:K) -> Mael Delmas | B83: 0540_DSI ECOM | C83: 613003 | D83: GENERAL | E83: [On-board] - TACT additional 150 MPOS (added in June 2024) | F83: GENERAL | G83: 922 | H83: 922 | I83: 922 | J83: 922 | K83: 922 | L83: 922 | M83: 922 | N83: 922 | O83: 922 | P83: 922 | Q83: 922 | R83: 922 | S83: =SUM(G83:R83) -> 11064 | U83: =SUM(S83:T83) -> 11064
A84: =_xlfn.XLOOKUP(B84,'Reference '!J:J,'Reference '!K:K) -> Mael Delmas | B84: 0540_DSI ECOM | C84: 613003 | D84: GENERAL | E84: [On-Board] - SoftPOS solution (for 400 TMs and 6k transaction) | F84: GENERAL | G84: 3513.5 | H84: 3513.5 | I84: 3513.5 | J84: 3513.5 | K84: 3513.5 | L84: 3513.5 | M84: 3513.5 | N84: 3513.5 | O84: 3513.5 | P84: 3513.5 | Q84: 3513.5 | R84: 3513.5 | S84: =SUM(G84:R84) -> 42162 | U84: =SUM(S84:T84) -> 42162
A85: =_xlfn.XLOOKUP(B85,'Reference '!J:J,'Reference '!K:K) -> Olivier Lepret | B85: 0535_DSI PERFSEC&ARC | C85: 612520 | D85: GENERAL | E85: BizzDesign - Enterprise Architecture modeling software | F85: GENERAL | G85: 5833.3333 | H85: 5833.3333 | I85: 5833.3333 | J85: 5833.3333 | K85: 5833.3333 | L85: 5833.3333 | M85: 5833.3333 | N85: 5833.3333 | O85: 5833.3333 | P85: 5833.3333 | Q85: 5833.3333 | R85: 5833.3333 | S85: =SUM(G85:R85) -> 70000 | T85: ='4.2 Simplify Savings'!AB62 -> -100000 | U85: =SUM(S85:T85) -> -30000
A86: =_xlfn.XLOOKUP(B86,'Reference '!J:J,'Reference '!K:K) -> Olivier Lepret | B86: 0535_DSI PERFSEC&ARC | C86: 612520 | D86: GENERAL | E86: Darktrace - Network Behaviour Monitoring tool (Year 3 of 3) | F86: GENERAL | G86: 12725 | H86: 12725 | I86: 12725 | J86: 12725 | K86: 12725 | L86: 12725 | M86: 12725 | N86: 12725 | O86: 12725 | P86: 12725 | Q86: 12725 | R86: 12725 | S86: =SUM(G86:R86) -> 152700 | U86: =SUM(S86:T86) -> 152700
A87: =_xlfn.XLOOKUP(B87,'Reference '!J:J,'Reference '!K:K) -> Olivier Lepret | B87: 0535_DSI PERFSEC&ARC | C87: 613020 | D87: GENERAL | E87: AlertLogic - Security Operating Center + Vulnerability Scans (THI Assets) | F87: GENERAL | G87: 7500 | H87: 7500 | I87: 7500 | J87: 7500 | K87: 7500 | L87: 7500 | M87: 7500 | N87: 7500 | O87: 7500 | P87: 7500 | Q87: 7500 | R87: 7500 | S87: =SUM(G87:R87) -> 90000 | U87: =SUM(S87:T87) -> 90000
A88: =_xlfn.XLOOKUP(B88,'Reference '!J:J,'Reference '!K:K) -> Olivier Lepret | B88: 0535_DSI PERFSEC&ARC | C88: 613025 | D88: GENERAL | E88: Cybersecurity system expertise | F88: GENERAL | G88: 1696.6667 | H88: 1696.6667 | I88: 1696.6667 | J88: 1696.6667 | K88: 1696.6667 | L88: 1696.6667 | M88: 1696.6667 | N88: 1696.6667 | O88: 1696.6667 | P88: 1696.6667 | Q88: 1696.6667 | R88: 1696.6667 | S88: =SUM(G88:R88) -> 20360 | U88: =SUM(S88:T88) -> 20360 | V88: << staff cost (non FTE)
A89: =_xlfn.XLOOKUP(B89,'Reference '!J:J,'Reference '!K:K) -> Olivier Lepret | B89: 0535_DSI PERFSEC&ARC | C89: 613025 | D89: GENERAL | E89: Computer Emergency Response Team: Assistance, Red team exercises | F89: GENERAL | G89: 1250 | H89: 1250 | I89: 1250 | J89: 1250 | K89: 1250 | L89: 1250 | M89: 1250 | N89: 1250 | O89: 1250 | P89: 1250 | Q89: 1250 | R89: 1250 | S89: =SUM(G89:R89) -> 15000 | U89: =SUM(S89:T89) -> 15000 | V89: << staff cost (non FTE)
A90: =_xlfn.XLOOKUP(B90,'Reference '!J:J,'Reference '!K:K) -> Olivier Lepret | B90: 0535_DSI PERFSEC&ARC | C90: 612520 | D90: GENERAL | E90: Security operations orchestration/automation | F90: GENERAL | G90: 12500 | H90: 12500 | I90: 12500 | J90: 12500 | K90: 12500 | L90: 12500 | M90: 12500 | N90: 12500 | O90: 12500 | P90: 12500 | Q90: 12500 | R90: 12500 | S90: =SUM(G90:R90) -> 150000 | U90: =SUM(S90:T90) -> 150000
A91: =_xlfn.XLOOKUP(B91,'Reference '!J:J,'Reference '!K:K) -> Olivier Lepret | B91: 0535_DSI PERFSEC&ARC | C91: 613025 | D91: GENERAL | E91: Cybersecurity operation specialist #2 | F91: GENERAL | G91: 22666.667 | H91: 22666.667 | I91: 22666.667 | J91: 22666.667 | K91: 22666.667 | L91: 22666.667 | M91: 22666.667 | N91: 22666.667 | O91: 22666.667 | P91: 22666.667 | Q91: 22666.667 | R91: 22666.667 | S91: =SUM(G91:R91) -> 272000 | U91: =SUM(S91:T91) -> 272000 | V91: << staff cost (non FTE)
A92: =_xlfn.XLOOKUP(B92,'Reference '!J:J,'Reference '!K:K) -> Olivier Lepret | B92: 0535_DSI PERFSEC&ARC | C92: 612520 | D92: GENERAL | E92: Small Software (AD audit+ …) | F92: GENERAL | G92: 424.16667 | H92: 424.16667 | I92: 424.16667 | J92: 424.16667 | K92: 424.16667 | L92: 424.16667 | M92: 424.16667 | N92: 424.16667 | O92: 424.16667 | P92: 424.16667 | Q92: 424.16667 | R92: 424.16667 | S92: =SUM(G92:R92) -> 5090 | U92: =SUM(S92:T92) -> 5090
A93: =_xlfn.XLOOKUP(B93,'Reference '!J:J,'Reference '!K:K) -> Olivier Lepret | B93: 0535_DSI PERFSEC&ARC | C93: 613020 | D93: GENERAL | E93: Cybersecurity Awareness | F93: GENERAL | G93: 633.33333 | H93: 633.33333 | I93: 633.33333 | J93: 633.33333 | K93: 633.33333 | L93: 633.33333 | M93: 633.33333 | N93: 633.33333 | O93: 633.33333 | P93: 633.33333 | Q93: 633.33333 | R93: 633.33333 | S93: =SUM(G93:R93) -> 7600 | U93: =SUM(S93:T93) -> 7600
A94: =_xlfn.XLOOKUP(B94,'Reference '!J:J,'Reference '!K:K) -> Olivier Lepret | B94: 0535_DSI PERFSEC&ARC | C94: 613020 | D94: GENERAL | E94: NIS2 Compliance project | F94: GENERAL | G94: 32250 | H94: 32250 | I94: 32250 | J94: 32250 | K94: 32250 | L94: 32250 | M94: 32250 | N94: 32250 | O94: 32250 | P94: 32250 | Q94: 32250 | R94: 32250 | S94: =SUM(G94:R94) -> 387000 | U94: =SUM(S94:T94) -> 387000
A95: =_xlfn.XLOOKUP(B95,'Reference '!J:J,'Reference '!K:K) -> Olivier Lepret | B95: 0535_DSI PERFSEC&ARC | C95: 615130 | D95: GENERAL | E95: Travel Costs | F95: GENERAL | G95: 833.33333 | H95: 833.33333 | I95: 833.33333 | J95: 833.33333 | K95: 833.33333 | L95: 833.33333 | M95: 833.33333 | N95: 833.33333 | O95: 833.33333 | P95: 833.33333 | Q95: 833.33333 | R95: 833.33333 | S95: =SUM(G95:R95) -> 10000 | U95: =SUM(S95:T95) -> 10000
A96: =_xlfn.XLOOKUP(B96,'Reference '!J:J,'Reference '!K:K) -> Olivier Lepret | B96: 0535_DSI PERFSEC&ARC | C96: 612620 | D96: GENERAL | E96: Internship 3 months | F96: GENERAL | G96: 666.66667 | H96: 666.66667 | I96: 666.66667 | J96: 666.66667 | K96: 666.66667 | L96: 666.66667 | M96: 666.66667 | N96: 666.66667 | O96: 666.66667 | P96: 666.66667 | Q96: 666.66667 | R96: 666.66667 | S96: =SUM(G96:R96) -> 8000 | U96: =SUM(S96:T96) -> 8000
A97: =_xlfn.XLOOKUP(B97,'Reference '!J:J,'Reference '!K:K) -> Olivier Lepret | B97: 0535_DSI PERFSEC&ARC | C97: 612620 | D97: GENERAL | E97: Training THIF resources (3 pers*5days) | F97: GENERAL | G97: 1250 | H97: 1250 | I97: 1250 | J97: 1250 | K97: 1250 | L97: 1250 | M97: 1250 | N97: 1250 | O97: 1250 | P97: 1250 | Q97: 1250 | R97: 1250 | S97: =SUM(G97:R97) -> 15000 | U97: =SUM(S97:T97) -> 15000
A98: =_xlfn.XLOOKUP(B98,'Reference '!J:J,'Reference '!K:K) -> Olivier Lepret | B98: 0535_DSI PERFSEC&ARC | C98: 616800 | D98: GENERAL | E98: Teambuilding (combined THIF/EIL) | F98: GENERAL | G98: 66.666667 | H98: 66.666667 | I98: 66.666667 | J98: 66.666667 | K98: 66.666667 | L98: 66.666667 | M98: 66.666667 | N98: 66.666667 | O98: 66.666667 | P98: 66.666667 | Q98: 66.666667 | R98: 66.666667 | S98: =SUM(G98:R98) -> 800 | U98: =SUM(S98:T98) -> 800
A99: =_xlfn.XLOOKUP(B99,'Reference '!J:J,'Reference '!K:K) -> Roger Plummer | B99: 0580_DSI_CORP,FIN&HR | C99: 612520 | D99: GENERAL | E99: Genetec development for extended use @ THIF sites | F99: GENERAL | G99: 7267.5625 | H99: 7267.5625 | I99: 7267.5625 | J99: 7267.5625 | K99: 7267.5625 | L99: 7267.5625 | M99: 7267.5625 | N99: 7267.5625 | O99: 7267.5625 | P99: 7267.5625 | Q99: 7267.5625 | R99: 7267.5625 | S99: =SUM(G99:R99) -> 87210.75 | U99: =SUM(S99:T99) -> 87210.75
A100: =_xlfn.XLOOKUP(B100,'Reference '!J:J,'Reference '!K:K) -> Roger Plummer | B100: 0580_DSI_CORP,FIN&HR | C100: 612520 | D100: GENERAL | E100: Edicom - E-Invoicing tool - Licence & Maintenance | F100: GENERAL | G100: 1916.6667 | H100: 1916.6667 | I100: 1916.6667 | J100: 1916.6667 | K100: 1916.6667 | L100: 1916.6667 | M100: 1916.6667 | N100: 1916.6667 | O100: 1916.6667 | P100: 1916.6667 | Q100: 1916.6667 | R100: 1916.6667 | S100: =SUM(G100:R100) -> 23000 | U100: =SUM(S100:T100) -> 23000
...

Sheet 3.2 THIF COS
R1: Total | S1: =SUBTOTAL(9,S3:S9) -> 4122434.5
A2: Account | B2: Level Code | C2: Compte_Général Code | D2: Type de tiers Code | E2: Type de tiers Name | F2: Projet Code | G2: 46023 | H2: 46054 | I2: 46082 | J2: 46113 | K2: 46143 | L2: 46174 | M2: 46204 | N2: 46235 | O2: 46266 | P2: 46296 | Q2: 46327 | R2: 46357 | S2: Total
A3: MontantCharge | B3: 0080_DISTRI_DAF | C3: 613000 | D3: SNCF-GLI76 | E3: Sqills | F3: GENERAL | G3: 272795.35 | H3: 209747.23 | I3: 288898.65 | J3: 349595.12 | K3: 370251.96 | L3: 346009.78 | M3: 318283.53 | N3: 291423.62 | O3: 276775.03 | P3: 242626.93 | Q3: 216569.55 | R3: 167395.57 | S3: =SUM(G3:R3) -> 3350372.3
A4: MontantCharge | B4: 0080_DISTRI_DAF | C4: 613000 | D4: SNCF-GLI76 | E4: PAO carrier | F4: GENERAL | G4: 28729.126 | H4: 20252.822 | I4: 21110.141 | J4: 20547.305 | K4: 21761.402 | L4: 20336.578 | M4: 18706.98 | N4: 17128.3 | O4: 23484.611 | P4: 23427.628 | Q4: 20911.573 | R4: 16163.42 | S4: =SUM(G4:R4) -> 252559.89
A5: MontantCharge | B5: 0080_DISTRI_DAF | C5: 613001 | D5: SNCF-GLI76 | E5: THIF Amadeus Segment charges | F5: GENERAL | G5: 2323.3119 | H5: 1786.8296 | I5: 1834.8221 | J5: 1784.8792 | K5: 1894.4622 | L5: 1751.9644 | M5: 1609.4026 | N5: 1485.9184 | O5: 2075.9689 | P5: 2051.0668 | Q5: 1839.557 | R5: 1427.5584 | S5: =SUM(G5:R5) -> 21865.741
A6: MontantCharge | B6: 0080_DISTRI_DAF | C6: 613001 | D6: SNCF-GLI76 | E6: THIF Sabre Segment charges | F6: GENERAL | G6: 3523.1752 | H6: 2709.6291 | I6: 2782.4071 | J6: 2706.6715 | K6: 2872.8481 | L6: 2656.758 | M6: 2440.5709 | N6: 2253.3139 | O6: 3148.093 | P6: 3110.3303 | Q6: 2789.5873 | R6: 2164.8141 | S6: =SUM(G6:R6) -> 33158.199
A7: MontantCharge | B7: 0080_DISTRI_DAF | C7: 613001 | D7: SNCF-GLI76 | E7: THIF Travelport Segment charges | F7: GENERAL | G7: 1886.1143 | H7: 1450.5864 | I7: 1489.5478 | J7: 1449.0031 | K7: 1537.9649 | L7: 1422.2821 | M7: 1306.5475 | N7: 1206.3004 | O7: 1685.3159 | P7: 1665.0999 | Q7: 1493.3917 | R7: 1158.9224 | S7: =SUM(G7:R7) -> 17751.076
A8: MontantCharge | B8: 0080_DISTRI_DAF | C8: 613001 | D8: SNCF-GLI76 | E8: AWS | F8: GENERAL | G8: 30727.273 | H8: 30727.273 | I8: 30727.273 | J8: 30727.273 | K8: 30727.273 | L8: 30727.273 | M8: 30727.273 | N8: 30727.273 | O8: 30727.273 | P8: 30727.273 | Q8: 30727.273 | R8: 30727.273 | S8: =SUM(G8:R8) -> 368727.27
A9: MontantCharge | B9: 0080_DISTRI_DAF | C9: 613001 | D9: SNCF-GLI76 | E9: Other software tools | F9: GENERAL | G9: 6500 | H9: 6500 | I9: 6500 | J9: 6500 | K9: 6500 | L9: 6500 | M9: 6500 | N9: 6500 | O9: 6500 | P9: 6500 | Q9: 6500 | R9: 6500 | S9: =SUM(G9:R9) -> 78000

Sheet 3.3 THIF Capex
F2: =SUBTOTAL(9,F4:F28) -> 4269000
B3: Owner | C3: Entity | D3: Function | E3: Description | F3: Amount | L3: Funtion | M3: Total Amount
B4: Paolo Rodeghiero | C4: THIF | D4: Data Middleware | E4: 2024 Leftover - Data Hub extensions for Stations & OnBoard tools (multiple projects) | F4: 485000 | L4: IS sales systems | M4: =#REF! -> #REF!
B5: Paolo Rodeghiero | C5: THIF | D5: Data Middleware | E5: 2024 Leftover - Fraud Detection - AI Integration | F5: 97000 | L5: Grand Total | M5: =SUM(M4:M4) -> #REF! | N5: ='[75]Summary per function (2)'!$N$144*1000 -> 30357500 | O5: =N5-M5 -> #REF! | U5: Owner | V5: Entity | W5: Function | X5: Description | Y5: Amount
B6: Valerie Veyt | C6: THIF | D6: IS Operations | E6: [ICOMERA] Router Upgrade x61 to 7 | F6: 812000 | V6: THIF | W6: Data Middleware | X6: 2024 Leftover - Fraud Detection - AI Integration | Y6: 97000 | AD6: EIL | AE6: Data Middleware | AF6: Thapaas Evolutions | AG6: 320000
B7: Valerie Veyt | C7: THIF | D7: IS Operations | E7: [Gauthier De Lavenne] IS Supervision manager 2026 | F7: 200000 | V7: THIF | W7: IS Operations | X7: [ICOMERA] Router Upgrade x61 to 7 | Y7: 812000 | AD7: EIL | AE7: Data Middleware | AF7: Enablers Evolutions | AG7: 320000
B8: Valerie Veyt | C8: THIF | D8: IS Operations | E8: [Samy Benhalla] BA/PM - Fiche Train 2026 | F8: 180000 | V8: THIF | W8: IS Operations | X8: [Gauthier De Lavenne] IS Supervision manager 2026 | Y8: 200000 | AD8: EIL | AE8: Data Middleware | AF8: DataHub Platform Roadmap | AG8: 450000
B9: Valerie Veyt | C9: THIF | D9: IS Operations | E9: Enchainements | F9: 50000 | V9: THIF | W9: IS Operations | X9: [Samy Benhalla] BA/PM - Fiche Train 2026 | Y9: 180000 | AD9: EIL | AE9: Data Middleware | AF9: Datalakehouse Platform Roadmap | AG9: 195000
B10: Valerie Veyt | C10: THIF | D10: IS Operations | E10: RNE migration | F10: 50000 | V10: THIF | W10: IS Operations | X10: Enchainements | Y10: 50000 | AD10: EIL | AE10: Data Middleware | AF10: Rolling Stock - OpsAPI Refactoring & DataHub Integration (Including NIS2 Activity) | AG10: 240000
