Workbook
Name _20EURRATE: #REF!
Name Account_codes: #REF!
Name archCost: #REF!
Name AshfordLeaseAssetCfProfile: #REF!
Name AshfordLeaseCurrentAssetCfProfile: #REF!
Name AshfordLeaseLongTermCreditorCfProfile: #REF!
Name AshfordLeaseNonCurrentAssetCfProfile: #REF!
Name AshfordLeaseShortTermCreditorCfProfile: #REF!
Name AuditFailsStructural: #REF!
Name Bud_Exch_Rate: #REF!
Name Bud_exch_rateUSD: #REF!
Name BudExRate: 1.37
Name budExRateUSD: 1.5
Name budRate: #REF!
Name BusinessDevelopment_Integration: 'System List'!$AT$5:$AT$10
Name capexMonths: #REF!
Name CashManagementActionsEUR: #REF!
Name CashManagementActionsGBP: #REF!
Name CashManagementActionsUSD: #REF!
Name CHANGE_Impact_Score: 'System List'!$S$4:$T$115
Name Commercial: 'System List'!$AD$5:$AD$12
Name Communication_DI: 'System List'!$AX$5:$AX$7
Name CostSalesTicketVariableAllEURPctIn: #REF!
Name CostSalesTicketVariableAllGBPPctIn: #REF!
Name CostSalesTicketVariableAllUSDPctIn: #REF!
Name CostSalesTicketVariableEILEURPctIn: #REF!
Name CostSalesTicketVariableEILGBPPctIn: #REF!
Name CostSalesTicketVariableEILUSDPctIn: #REF!
Name CostSalesTicketVariableOtherEURPctIn: #REF!
Name CostSalesTicketVariableOtherGBPPctIn: #REF!
Name CostSalesTicketVariableOtherUSDPctIn: #REF!
Name CostTrainLeasesProfileEUR: #REF!
Name CostTrainLeasesProfileGBP: #REF!
Name Counterparties: #REF!
Name dataCharERR: "ERR"
Name dataCharOK: "ok"
Name dataCharWARN: "WARN"
Name DateActualsEnd: #REF!
Name Days360: #REF!
Name Days365: #REF!
Name DaysInYear: 365
Name DaysPaymentsOutstanding: #REF!
Name DaysSalesOutstanding: #REF!
Name dbaCost: #REF!
Name dc5YPend: #REF!
Name dc5YPstart: #REF!
Name dcActualsMonth: #REF!
Name dcActualsYear: #REF!
Name dcAMSe320min: #REF!
Name dcBalSheetTol: 0.2
Name dcBEAMAlabourIndexApr14: #REF!
Name dcBEAMAmaterialsIndexApr14: #REF!
Name dcBEprepayEC4T: #REF!
Name dcBEprepayTAC: #REF!
Name dcBStol: #REF!
Name dcBudgetMode: #REF!
Name dcCashAdjustSwitch: #REF!
Name dcCurrentYear: #REF!
Name dcCurrentYearText: #REF!
Name dcDateFirstOptionUnit: #REF!

Sheet Instructions
A1: 2025 Synchro Plan - Step 1 - Value/Effort Instruction
A6: We recommend you to open the file in the desktop app for a better experience | C6: >>>
A8: Tab | B8: Description
A9: Input | B9: This is the most important tab where we are gathering your input in term of: - Project Deliverables - Project Start and End Dates - Project Value and contribution toward Group Strategic KPI - High Level Resource estimations by project and by departements: Low, Medium, High (when a department is not impacted, please, leave the cell blank) - High Level Change Impact estimations by project and by departements: Low, Medium, High (when a department is not impacted, please, leave the cell blank) A description of each column will apear when you hover your mouse on the column title (only if open on desktop app) + you will have indication on how to score Low (L), Medium (M) and High (H) on top of each section. If you want to modify the name of a project - please do it directly and re-word as you see fit If you want to split a specific line in 2 or several projects -> you can add line at the bottom of the list (you will not be able to insert a line) If you want to remove a project - delete the content of the line (leave it blank) Any questions / issues - please do not hesitate to contact us: nicolas.madier@eurostar.com lucie.jeunemaitre@eurostar.com
A10: Checklist | B10: This are few elements to take into account when estimating in the Resources and Change impact of your project
A11: Project Map Benefits - Effort | B11: This is an automated chart where projects will be ploted according to Value score and Effort Score
A12: Heat Map Change | B12: This is an automated table, a heat map showing when each department will be most impacted in term of changes.
A13: Heat Map Workload | B13: This is an automated table, a heat map showing when each department will be the most solicited by project delivery

Sheet Checklist
B1: CHECK List Have you thought about…?
C4: HR
C5: Will your project impact the roles & responsibilities, ways of working, working conditions of other colleagues? if yes on any of this, make sure you consult our HR team to check if Union Consultation is required and/or job descriptions must evolve Might you need additional resources, recruitment to deliver the project - therefore, might you need HR to do so?
C8: Communication interne
C9: Might your project involved several departments and might need to have internal communication support? Might you need communication material to be sent group wise?
C12: External Communication / Customer Comms / Marketing / Press
C13: Will you project requires to be communicated to Customers (will it need to be "commercially launched")? Will you project requires to be communicated to Shareholders?
C16: Finance & Procurement
C17: Will you need specific budget for your project? Will you need to go through the commitment board: >50K for consultancy & >250k for Project total cost if so - you will need Finance Support
C20: IS
C21: Will your project lead to improvement or creation of IS tools; if yes, have you already discuss your ambition with the IT/IS teams? Is is already on the IS/IT pipeline?

Sheet Input
B1: TPO Portfolio | G1: see in PowerBI | N1: VALUE SCORING L = Small Contribution to Strategic KPI M = Significant Contribution to Strategic KPI H = Big Contribution to Strategic KPI | V1: Estimation of Workload per Team No resources needed = leave Blank L = Less than 1 FTE needed for the length of the project (light contribution e.g. for workshop / follow up) M = Between 1 and 2 FTE needed for the length of the project (actively contributed to the project) H = More than 2 FTE needed for the length of the project (significant resource needed for the project) | AG1: Estimation on CHANGE IMPACT per Department when delivered L = Small changes on processes / tool for a small number of colleagues (<10 people) M = Significant changes for small number of colleagues OR small changes impacting high number colleagues H = Significant changes on processes / tools for high number colleagues OR any organisational changes | AS1: =VLOOKUP([@Duration];Duration;2;FALSE)+[@[Resource Score]]+[@[CHANGE Impact Score]] | AZ1: 1.1364 | BA1: 1.1364 | BC1: 1.1364 | BF1: CALCULATION | BH1: Change Impact SCORE | BT1: Resource Impact Score | CX1: ='System List'!$AB$5 -> CORPHRFIN | CY1: ='System List'!$AB$5 -> CORPHRFIN | CZ1: ='System List'!$AB$5 -> CORPHRFIN | DA1: ='System List'!$AB$5 -> CORPHRFIN | DB1: ='System List'!$AB$5 -> CORPHRFIN | DC1: ='System List'!$AB$5 -> CORPHRFIN | DD1: ='System List'!$AB$5 -> CORPHRFIN | DE1: ='System List'!$AB$5 -> CORPHRFIN | DF1: ='System List'!$AB$5 -> CORPHRFIN | DH1: ='System List'!$AB$6 -> CUST | DI1: ='System List'!$AB$6 -> CUST | DJ1: ='System List'!$AB$6 -> CUST | DK1: ='System List'!$AB$6 -> CUST | DL1: ='System List'!$AB$6 -> CUST | DM1: ='System List'!$AB$6 -> CUST | DN1: ='System List'!$AB$6 -> CUST | DO1: ='System List'!$AB$6 -> CUST | DP1: ='System List'!$AB$6 -> CUST | DR1: ='System List'!$AB$7 -> CYBER | DS1: ='System List'!$AB$7 -> CYBER | DT1: ='System List'!$AB$7 -> CYBER | DU1: ='System List'!$AB$7 -> CYBER | DV1: ='System List'!$AB$7 -> CYBER | DW1: ='System List'!$AB$7 -> CYBER | DX1: ='System List'!$AB$7 -> CYBER | DY1: ='System List'!$AB$7 -> CYBER | DZ1: ='System List'!$AB$7 -> CYBER | EB1: ='System List'!$AB$8 -> DATA | EC1: ='System List'!$AB$8 -> DATA | ED1: ='System List'!$AB$8 -> DATA | EE1: ='System List'!$AB$8 -> DATA | EF1: ='System List'!$AB$8 -> DATA | EG1: ='System List'!$AB$8 -> DATA | EH1: ='System List'!$AB$8 -> DATA | EI1: ='System List'!$AB$8 -> DATA | EJ1: ='System List'!$AB$8 -> DATA | EL1: ='System List'!$AB$10 -> INFRA | EM1: ='System List'!$AB$10 -> INFRA | EN1: ='System List'!$AB$10 -> INFRA | EO1: ='System List'!$AB$10 -> INFRA | EP1: ='System List'!$AB$10 -> INFRA | EQ1: ='System List'!$AB$10 -> INFRA | ER1: ='System List'!$AB$10 -> INFRA | ES1: ='System List'!$AB$10 -> INFRA | ET1: ='System List'!$AB$10 -> INFRA | EV1: ='System List'!$AB$11 -> OPERATIONS | EW1: ='System List'!$AB$11 -> OPERATIONS | EX1: ='System List'!$AB$11 -> OPERATIONS | EY1: ='System List'!$AB$11 -> OPERATIONS | EZ1: ='System List'!$AB$11 -> OPERATIONS | FA1: ='System List'!$AB$11 -> OPERATIONS | FB1: ='System List'!$AB$11 -> OPERATIONS | FC1: ='System List'!$AB$11 -> OPERATIONS | FD1: ='System List'!$AB$11 -> OPERATIONS | FF1: ='System List'!$AB$12 -> PMO | FG1: ='System List'!$AB$12 -> PMO | FH1: ='System List'!$AB$12 -> PMO | FI1: ='System List'!$AB$12 -> PMO | FJ1: ='System List'!$AB$12 -> PMO | FK1: ='System List'!$AB$12 -> PMO | FL1: ='System List'!$AB$12 -> PMO | FM1: ='System List'!$AB$12 -> PMO | FN1: ='System List'!$AB$12 -> PMO | FP1: ='System List'!#REF! -> #REF! | FQ1: ='System List'!#REF! -> #REF! | FR1: ='System List'!#REF! -> #REF! | FS1: ='System List'!#REF! -> #REF! | FT1: ='System List'!#REF! -> #REF! | FU1: ='System List'!#REF! -> #REF! | FV1: ='System List'!#REF! -> #REF! | FW1: ='System List'!#REF! -> #REF! | FX1: ='System List'!#REF! -> #REF! | GB1: =BH2 -> Impact on - CIAL | GC1: =GB1 -> Impact on - CIAL | GD1: =GC1 -> Impact on - CIAL | GE1: =GD1 -> Impact on - CIAL | GF1: =GE1 -> Impact on - CIAL | GG1: =GF1 -> Impact on - CIAL | GH1: =GG1 -> Impact on - CIAL | GI1: =GH1 -> Impact on - CIAL | GJ1: =GI1 -> Impact on - CIAL | GL1: =BI2 -> Impact on - COM | GM1: =GL1 -> Impact on - COM | GN1: =GM1 -> Impact on - COM | GO1: =GN1 -> Impact on - COM | GP1: =GO1 -> Impact on - COM | GQ1: =GP1 -> Impact on - COM | GR1: =GQ1 -> Impact on - COM | GS1: =GR1 -> Impact on - COM | GT1: =GS1 -> Impact on - COM | GV1: =BJ2 -> Impact on - FIN | GW1: =GV1 -> Impact on - FIN | GX1: =GW1 -> Impact on - FIN | GY1: =GX1 -> Impact on - FIN | GZ1: =GY1 -> Impact on - FIN | HA1: =GZ1 -> Impact on - FIN | HB1: =HA1 -> Impact on - FIN | HC1: =HB1 -> Impact on - FIN | HD1: =HC1 -> Impact on - FIN | HF1: =BK2 -> Impact on - GEN SEC | HG1: =HF1 -> Impact on - GEN SEC | HH1: =HG1 -> Impact on - GEN SEC | HI1: =HH1 -> Impact on - GEN SEC | HJ1: =HI1 -> Impact on - GEN SEC | HK1: =HJ1 -> Impact on - GEN SEC | HL1: =HK1 -> Impact on - GEN SEC | HM1: =HL1 -> Impact on - GEN SEC | HN1: =HM1 -> Impact on - GEN SEC | HP1: =BL2 -> Impact on - HR | HQ1: =HP1 -> Impact on - HR | HR1: =HQ1 -> Impact on - HR | HS1: =HR1 -> Impact on - HR | HT1: =HS1 -> Impact on - HR | HU1: =HT1 -> Impact on - HR | HV1: =HU1 -> Impact on - HR | HW1: =HV1 -> Impact on - HR | HX1: =HW1 -> Impact on - HR | HZ1: =BM2 -> Impact on - IS | IA1: =HZ1 -> Impact on - IS | IB1: =IA1 -> Impact on - IS | IC1: =IB1 -> Impact on - IS | ID1: =IC1 -> Impact on - IS | IE1: =ID1 -> Impact on - IS | IF1: =IE1 -> Impact on - IS | IG1: =IF1 -> Impact on - IS | IH1: =IG1 -> Impact on - IS | IJ1: =BN2 -> Impact on - OPS | IK1: =IJ1 -> Impact on - OPS | IL1: =IK1 -> Impact on - OPS | IM1: =IL1 -> Impact on - OPS | IN1: =IM1 -> Impact on - OPS | IO1: =IN1 -> Impact on - OPS | IP1: =IO1 -> Impact on - OPS | IQ1: =IP1 -> Impact on - OPS | IR1: =IQ1 -> Impact on - OPS | IT1: =BO2 -> Impact on - ROLL STOCK | IU1: =IT1 -> Impact on - ROLL STOCK | IV1: =IU1 -> Impact on - ROLL STOCK | IW1: =IV1 -> Impact on - ROLL STOCK | IX1: =IW1 -> Impact on - ROLL STOCK | IY1: =IX1 -> Impact on - ROLL STOCK | IZ1: =IY1 -> Impact on - ROLL STOCK | JA1: =IZ1 -> Impact on - ROLL STOCK | JB1: =JA1 -> Impact on - ROLL STOCK | JD1: =BP2 -> Impact on - SAFETY | JE1: =JD1 -> Impact on - SAFETY | JF1: =JE1 -> Impact on - SAFETY | JG1: =JF1 -> Impact on - SAFETY | JH1: =JG1 -> Impact on - SAFETY | JI1: =JH1 -> Impact on - SAFETY | JJ1: =JI1 -> Impact on - SAFETY | JK1: =JJ1 -> Impact on - SAFETY | JL1: =JK1 -> Impact on - SAFETY | JN1: =BQ2 -> Impact on - STATION | JO1: =JN1 -> Impact on - STATION | JP1: =JO1 -> Impact on - STATION | JQ1: =JP1 -> Impact on - STATION | JR1: =JQ1 -> Impact on - STATION | JS1: =JR1 -> Impact on - STATION | JT1: =JS1 -> Impact on - STATION | JU1: =JT1 -> Impact on - STATION | JV1: =JU1 -> Impact on - STATION | JX1: =BR2 -> Impact on - STRAT | JY1: =JX1 -> Impact on - STRAT | JZ1: =JY1 -> Impact on - STRAT | KA1: =JZ1 -> Impact on - STRAT | KB1: =KA1 -> Impact on - STRAT | KC1: =KB1 -> Impact on - STRAT | KD1: =KC1 -> Impact on - STRAT | KE1: =KD1 -> Impact on - STRAT | KF1: =KE1 -> Impact on - STRAT
A2: main 2025 Strategic Pillar 2025 | B2: Status | C2: Team | D2: IS Portfolio Ref ID | E2: Project | F2: eurostar dpt Owner | G2: Starting Date | H2: Level of Certainty on Start Date | I2: Delivery Date | J2: IS 2025 Priority | K2: Duration | L2: Duration Score | M2: #Simplify | N2: Safety | O2: NPS cust. Satisfaction | P2: Punctuality T15 | Q2: People Engagement | R2: EBITDA | S2: Regulatory | T2: Value Score | U2: Column2 | V2: CORPHRFIN | W2: CUST | X2: CYBER | Y2: DATA | Z2: INFRA | AA2: OPERATIONS | AB2: PMO | AC2: SALES | AD2: Number of Team Involved | AE2: Resource Score | AF2: Column3 | AG2: Impact on - CIAL | AH2: Impact on - COM | AI2: Impact on - FIN | AJ2: Impact on - GEN SEC | AK2: Impact on - HR | AL2: Impact on - IS | AM2: Impact on - OPS | AN2: Impact on - ROLL STOCK | AO2: Impact on - SAFETY | AP2: Impact on - STATION | AQ2: Impact on - STRAT | AR2: CHANGE Impact Score | AS2: EFFORT SCORE | AT2: Overall Effort Score | AU2: Ratio - Benefit / Effort | AV2: Project ID | AW2: Name of IS owner | AX2: OK comBoard | AY2: ORACLE/NAV/Fin project code | AZ2: Opex IS Budget (full project) | BA2: Capex IS Budget (full project) | BB2: mainly OPEX or CAPEX | BC2: Total IS Budget (full project) | BD2: Nb IS Employees implicated | BE2: Nb IS Contractors implicated | BH2: =InputTable[[#Headers],[Impact on - CIAL]] -> Impact on - CIAL | BI2: =InputTable[[#Headers],[Impact on - COM]] -> Impact on - COM | BJ2: =InputTable[[#Headers],[Impact on - FIN]] -> Impact on - FIN | BK2: =InputTable[[#Headers],[Impact on - GEN SEC]] -> Impact on - GEN SEC | BL2: =InputTable[[#Headers],[Impact on - HR]] -> Impact on - HR | BM2: =InputTable[[#Headers],[Impact on - IS]] -> Impact on - IS | BN2: =InputTable[[#Headers],[Impact on - OPS]] -> Impact on - OPS | BO2: =InputTable[[#Headers],[Impact on - ROLL STOCK]] -> Impact on - ROLL STOCK | BP2: =InputTable[[#Headers],[Impact on - SAFETY]] -> Impact on - SAFETY | BQ2: =InputTable[[#Headers],[Impact on - STATION]] -> Impact on - STATION | BR2: =InputTable[[#Headers],[Impact on - STRAT]] -> Impact on - STRAT | BT2: =InputTable[[#Headers],[CORPHRFIN]] -> CORPHRFIN | BU2: =InputTable[[#Headers],[CUST]] -> CUST | BV2: =InputTable[[#Headers],[CYBER]] -> CYBER | BW2: =InputTable[[#Headers],[DATA]] -> DATA | BX2: =InputTable[[#Headers],[INFRA]] -> INFRA | BY2: =InputTable[[#Headers],[OPERATIONS]] -> OPERATIONS | BZ2: =InputTable[[#Headers],[PMO]] -> PMO | CA2: =InputTable[[#Headers],[SALES]] -> SALES | CC2: ='System List'!#REF! -> #REF! | CD2: {=TRANSPOSE('System List'!D5:D12)} -> Q4 2024 | CE2: Q1 2025 | CF2: Q2 2025 | CG2: Q3 2025 | CH2: Q4 2025 | CI2: 2026 | CJ2: 2027 | CK2: 2028 + | CN2: ='System List'!#REF! -> #REF! | CO2: ='System List'!$B$5 -> 2024 | CP2: ='System List'!$B$6 -> 2025 Q1 | CQ2: ='System List'!$B$7 -> 2025 Q2 | CR2: ='System List'!$B$8 -> 2025 Q3 | CS2: ='System List'!$B$9 -> 2025 Q4 | CT2: ='System List'!$B$14 -> 2026 Q4 | CU2: ='System List'!$B$15 -> 2027 | CV2: ='System List'!$B$16 -> 2028 + | CX2: ='System List'!#REF! -> #REF! | CY2: ='System List'!$B$5 -> 2024 | CZ2: ='System List'!$B$6 -> 2025 Q1 | DA2: ='System List'!$B$7 -> 2025 Q2 | DB2: ='System List'!$B$8 -> 2025 Q3 | DC2: ='System List'!$B$9 -> 2025 Q4 | DD2: ='System List'!$B$14 -> 2026 Q4 | DE2: ='System List'!$B$15 -> 2027 | DF2: ='System List'!$B$16 -> 2028 + | DH2: ='System List'!#REF! -> #REF! | DI2: ='System List'!$B$5 -> 2024 | DJ2: ='System List'!$B$6 -> 2025 Q1 | DK2: ='System List'!$B$7 -> 2025 Q2 | DL2: ='System List'!$B$8 -> 2025 Q3 | DM2: ='System List'!$B$9 -> 2025 Q4 | DN2: ='System List'!$B$14 -> 2026 Q4 | DO2: ='System List'!$B$15 -> 2027 | DP2: ='System List'!$B$16 -> 2028 + | DR2: ='System List'!#REF! -> #REF! | DS2: ='System List'!$B$5 -> 2024 | DT2: ='System List'!$B$6 -> 2025 Q1 | DU2: ='System List'!$B$7 -> 2025 Q2 | DV2: ='System List'!$B$8 -> 2025 Q3 | DW2: ='System List'!$B$9 -> 2025 Q4 | DX2: ='System List'!$B$14 -> 2026 Q4 | DY2: ='System List'!$B$15 -> 2027 | DZ2: ='System List'!$B$16 -> 2028 + | EB2: ='System List'!#REF! -> #REF! | EC2: ='System List'!$B$5 -> 2024 | ED2: ='System List'!$B$6 -> 2025 Q1 | EE2: ='System List'!$B$7 -> 2025 Q2 | EF2: ='System List'!$B$8 -> 2025 Q3 | EG2: ='System List'!$B$9 -> 2025 Q4 | EH2: ='System List'!$B$14 -> 2026 Q4 | EI2: ='System List'!$B$15 -> 2027 | EJ2: ='System List'!$B$16 -> 2028 + | EL2: ='System List'!#REF! -> #REF! | EM2: ='System List'!$B$5 -> 2024 | EN2: ='System List'!$B$6 -> 2025 Q1 | EO2: ='System List'!$B$7 -> 2025 Q2 | EP2: ='System List'!$B$8 -> 2025 Q3 | EQ2: ='System List'!$B$9 -> 2025 Q4 | ER2: ='System List'!$B$14 -> 2026 Q4 | ES2: ='System List'!$B$15 -> 2027 | ET2: ='System List'!$B$16 -> 2028 + | EV2: ='System List'!#REF! -> #REF! | EW2: ='System List'!$B$5 -> 2024 | EX2: ='System List'!$B$6 -> 2025 Q1 | EY2: ='System List'!$B$7 -> 2025 Q2 | EZ2: ='System List'!$B$8 -> 2025 Q3 | FA2: ='System List'!$B$9 -> 2025 Q4 | FB2: ='System List'!$B$14 -> 2026 Q4 | FC2: ='System List'!$B$15 -> 2027 | FD2: ='System List'!$B$16 -> 2028 + | FF2: ='System List'!#REF! -> #REF! | FG2: ='System List'!$B$5 -> 2024 | FH2: ='System List'!$B$6 -> 2025 Q1 | FI2: ='System List'!$B$7 -> 2025 Q2 | FJ2: ='System List'!$B$8 -> 2025 Q3 | FK2: ='System List'!$B$9 -> 2025 Q4 | FL2: ='System List'!$B$14 -> 2026 Q4 | FM2: ='System List'!$B$15 -> 2027 | FN2: ='System List'!$B$16 -> 2028 + | FP2: ='System List'!#REF! -> #REF! | FQ2: ='System List'!$B$5 -> 2024 | FR2: ='System List'!$B$6 -> 2025 Q1 | FS2: ='System List'!$B$7 -> 2025 Q2 | FT2: ='System List'!$B$8 -> 2025 Q3 | FU2: ='System List'!$B$9 -> 2025 Q4 | FV2: ='System List'!$B$14 -> 2026 Q4 | FW2: ='System List'!$B$15 -> 2027 | FX2: ='System List'!$B$16 -> 2028 + | GB2: ='System List'!#REF! -> #REF! | GC2: ='System List'!$B$5 -> 2024 | GD2: ='System List'!$B$6 -> 2025 Q1 | GE2: ='System List'!$B$7 -> 2025 Q2 | GF2: ='System List'!$B$8 -> 2025 Q3 | GG2: ='System List'!$B$9 -> 2025 Q4 | GH2: ='System List'!$B$14 -> 2026 Q4 | GI2: ='System List'!$B$15 -> 2027 | GJ2: ='System List'!$B$16 -> 2028 + | GL2: ='System List'!#REF! -> #REF! | GM2: ='System List'!$B$5 -> 2024 | GN2: ='System List'!$B$6 -> 2025 Q1 | GO2: ='System List'!$B$7 -> 2025 Q2 | GP2: ='System List'!$B$8 -> 2025 Q3 | GQ2: ='System List'!$B$9 -> 2025 Q4 | GR2: ='System List'!$B$14 -> 2026 Q4 | GS2: ='System List'!$B$15 -> 2027 | GT2: ='System List'!$B$16 -> 2028 + | GV2: ='System List'!#REF! -> #REF! | GW2: ='System List'!$B$5 -> 2024 | GX2: ='System List'!$B$6 -> 2025 Q1 | GY2: ='System List'!$B$7 -> 2025 Q2 | GZ2: ='System List'!$B$8 -> 2025 Q3 | HA2: ='System List'!$B$9 -> 2025 Q4 | HB2: ='System List'!$B$14 -> 2026 Q4 | HC2: ='System List'!$B$15 -> 2027 | HD2: ='System List'!$B$16 -> 2028 + | HF2: ='System List'!#REF! -> #REF! | HG2: ='System List'!$B$5 -> 2024 | HH2: ='System List'!$B$6 -> 2025 Q1 | HI2: ='System List'!$B$7 -> 2025 Q2 | HJ2: ='System List'!$B$8 -> 2025 Q3 | HK2: ='System List'!$B$9 -> 2025 Q4 | HL2: ='System List'!$B$14 -> 2026 Q4 | HM2: ='System List'!$B$15 -> 2027 | HN2: ='System List'!$B$16 -> 2028 + | HP2: ='System List'!#REF! -> #REF! | HQ2: ='System List'!$B$5 -> 2024 | HR2: ='System List'!$B$6 -> 2025 Q1 | HS2: ='System List'!$B$7 -> 2025 Q2 | HT2: ='System List'!$B$8 -> 2025 Q3 | HU2: ='System List'!$B$9 -> 2025 Q4 | HV2: ='System List'!$B$14 -> 2026 Q4 | HW2: ='System List'!$B$15 -> 2027 | HX2: ='System List'!$B$16 -> 2028 + | HZ2: ='System List'!#REF! -> #REF! | IA2: ='System List'!$B$5 -> 2024 | IB2: ='System List'!$B$6 -> 2025 Q1 | IC2: ='System List'!$B$7 -> 2025 Q2 | ID2: ='System List'!$B$8 -> 2025 Q3 | IE2: ='System List'!$B$9 -> 2025 Q4 | IF2: ='System List'!$B$14 -> 2026 Q4 | IG2: ='System List'!$B$15 -> 2027 | IH2: ='System List'!$B$16 -> 2028 + | IJ2: ='System List'!#REF! -> #REF! | IK2: ='System List'!$B$5 -> 2024 | IL2: ='System List'!$B$6 -> 2025 Q1 | IM2: ='System List'!$B$7 -> 2025 Q2 | IN2: ='System List'!$B$8 -> 2025 Q3 | IO2: ='System List'!$B$9 -> 2025 Q4 | IP2: ='System List'!$B$14 -> 2026 Q4 | IQ2: ='System List'!$B$15 -> 2027 | IR2: ='System List'!$B$16 -> 2028 + | IT2: ='System List'!#REF! -> #REF! | IU2: ='System List'!$B$5 -> 2024 | IV2: ='System List'!$B$6 -> 2025 Q1 | IW2: ='System List'!$B$7 -> 2025 Q2 | IX2: ='System List'!$B$8 -> 2025 Q3 | IY2: ='System List'!$B$9 -> 2025 Q4 | IZ2: ='System List'!$B$14 -> 2026 Q4 | JA2: ='System List'!$B$15 -> 2027 | JB2: ='System List'!$B$16 -> 2028 + | JD2: ='System List'!#REF! -> #REF! | JE2: ='System List'!$B$5 -> 2024 | JF2: ='System List'!$B$6 -> 2025 Q1 | JG2: ='System List'!$B$7 -> 2025 Q2 | JH2: ='System List'!$B$8 -> 2025 Q3 | JI2: ='System List'!$B$9 -> 2025 Q4 | JJ2: ='System List'!$B$14 -> 2026 Q4 | JK2: ='System List'!$B$15 -> 2027 | JL2: ='System List'!$B$16 -> 2028 + | JN2: ='System List'!#REF! -> #REF! | JO2: ='System List'!$B$5 -> 2024 | JP2: ='System List'!$B$6 -> 2025 Q1 | JQ2: ='System List'!$B$7 -> 2025 Q2 | JR2: ='System List'!$B$8 -> 2025 Q3 | JS2: ='System List'!$B$9 -> 2025 Q4 | JT2: ='System List'!$B$14 -> 2026 Q4 | JU2: ='System List'!$B$15 -> 2027 | JV2: ='System List'!$B$16 -> 2028 + | JX2: ='System List'!#REF! -> #REF! | JY2: ='System List'!$B$5 -> 2024 | JZ2: ='System List'!$B$6 -> 2025 Q1 | KA2: ='System List'!$B$7 -> 2025 Q2 | KB2: ='System List'!$B$8 -> 2025 Q3 | KC2: ='System List'!$B$9 -> 2025 Q4 | KD2: ='System List'!$B$14 -> 2026 Q4 | KE2: ='System List'!$B$15 -> 2027 | KF2: ='System List'!$B$16 -> 2028 +
B3: Complete | C3: DIGITAL TECH | D3: ISPRJ-1 | E3: Digital Roadmap 2025 (Increase website and app conversion + indirect sales) | F3: COMMERCIAL | G3: 2025 Q1 | I3: 2025 Q4 | J3: TOP10 $$$ | K3: =VLOOKUP((InputTable[[#This Row],[Starting Date]]& " - " &InputTable[[#This Row],[Delivery Date]]),'System List'!$F$40:$H$83,2,FALSE) -> #N/A | L3: =VLOOKUP(InputTable[[#This Row],[Duration]],Duration,2,FALSE) -> #N/A | O3: H | R3: H | T3: {=SUM( _xlfn.XLOOKUP(InputTable[[#This Row],[Safety]:[Regulatory]], 'System List'!$F$4:$F$7, 'System List'!$G$4:$G$7, 0) * _xlfn.XLOOKUP(InputTable[[#Headers],[Safety]:[Regulatory]], 'System List'!$Y$4:$Y$10, 'System List'!$Z$4:$Z$10, 0) )} -> 6.5 | AD3: =COUNTA(InputTable[[#This Row],[CORPHRFIN]:[SALES]]) -> 0 | AE3: {=SUM( _xlfn.XLOOKUP(InputTable[[#This Row],[CORPHRFIN]:[SALES]],'System List'!$F$4:$F$7,'System List'!$H$4:$H$7,0))} -> 0 | AR3: {=SUM( _xlfn.XLOOKUP(InputTable[[#This Row],[Impact on - CIAL]:[Impact on - STRAT]],'System List'!$F$4:$F$7,'System List'!$H$4:$H$7,0))} -> 0 | AS3: =VLOOKUP(InputTable[[#This Row],[Duration]],Duration,2,FALSE)+InputTable[[#This Row],[Resource Score]] -> #N/A | AT3: =(( VLOOKUP(InputTable[[#This Row],[Duration]],'System List'!$J$5:$K$10,2,FALSE)*VLOOKUP(InputTable[[#Headers],[Duration]],'System List'!$V$5:$W$8,2,FALSE) + VLOOKUP(InputTable[[#This Row],[Number of Team Involved]],'System List'!$M$5:$N$13,2,FALSE)*VLOOKUP(InputTable[[#Headers],[Number of Team Involved]],'System List'!$V$5:$W$8,2,FALSE) + VLOOKUP(InputTable[[#This Row],[Resource Score]],Resource_Score,2,FALSE)*VLOOKUP(InputTable[[#Headers],[Resource Score]],'System List'!$V$5:$W$8,2,FALSE) + VLOOKUP(InputTable[[#This Row],[CHANGE Impact Score]],CHANGE_Impact_Score,2,FALSE)*VLOOKUP(InputTable[[#Headers],[CHANGE Impact Score]],'System List'!$V$5:$W$8,2,FALSE)) * 100) / 13 -> #N/A | AU3: =InputTable[[#This Row],[Value Score]]/InputTable[[#This Row],[EFFORT SCORE]]*100 -> #N/A | AV3: =InputTable[[#This Row],[IS Portfolio Ref ID]] -> ISPRJ-1 | AW3: Xavier ROMANET | AX3: approved in Digital BC | AY3: 1840 | BA3: =9500000*$BA$1 -> 10795800 | BB3: full CAPEX | BC3: =InputTable[[#This Row],[Capex IS Budget (full project)]]+InputTable[[#This Row],[Opex IS Budget (full project)]] -> 10795800 | BD3: 18 | BE3: 76 | BH3: =IFERROR(VLOOKUP(InputTable[[#This Row],[Impact on - CIAL]],'System List'!$F$4:$H$7,3,FALSE),0) -> 0 | BI3: =IFERROR(VLOOKUP(InputTable[[#This Row],[Impact on - COM]],'System List'!$F$4:$H$7,3,FALSE),0) -> 0 | BJ3: =IFERROR(VLOOKUP(InputTable[[#This Row],[Impact on - FIN]],'System List'!$F$4:$H$7,3,FALSE),0) -> 0 | BK3: =IFERROR(VLOOKUP(InputTable[[#This Row],[Impact on - GEN SEC]],'System List'!$F$4:$H$7,3,FALSE),0) -> 0 | BL3: =IFERROR(VLOOKUP(InputTable[[#This Row],[Impact on - HR]],'System List'!$F$4:$H$7,3,FALSE),0) -> 0 | BM3: =IFERROR(VLOOKUP(InputTable[[#This Row],[Impact on - IS]],'System List'!$F$4:$H$7,3,FALSE),0) -> 0 | BN3: =IFERROR(VLOOKUP(InputTable[[#This Row],[Impact on - OPS]],'System List'!$F$4:$H$7,3,FALSE),0) -> 0 | BO3: =IFERROR(VLOOKUP(InputTable[[#This Row],[Impact on - ROLL STOCK]],'System List'!$F$4:$H$7,3,FALSE),0) -> 0 | BP3: =IFERROR(VLOOKUP(InputTable[[#This Row],[Impact on - SAFETY]],'System List'!$F$4:$H$7,3,FALSE),0) -> 0 | BQ3: =IFERROR(VLOOKUP(InputTable[[#This Row],[Impact on - STATION]],'System List'!$F$4:$H$7,3,FALSE),0) -> 0 | BR3: =IFERROR(VLOOKUP(InputTable[[#This Row],[Impact on - STRAT]],'System List'!$F$4:$H$7,3,FALSE),0) -> 0 | BT3: =IFERROR(VLOOKUP(InputTable[[#This Row],[CORPHRFIN]],'System List'!$F$4:$H$7,3,FALSE),0) -> 0 | BU3: =IFERROR(VLOOKUP(InputTable[[#This Row],[CUST]],'System List'!$F$4:$H$7,3,FALSE),0) -> 0 | BV3: =IFERROR(VLOOKUP(InputTable[[#This Row],[CYBER]],'System List'!$F$4:$H$7,3,FALSE),0) -> 0 | BW3: =IFERROR(VLOOKUP(InputTable[[#This Row],[DATA]],'System List'!$F$4:$H$7,3,FALSE),0) -> 0 | BX3: =IFERROR(VLOOKUP(InputTable[[#This Row],[INFRA]],'System List'!$F$4:$H$7,3,FALSE),0) -> 0 | BY3: =IFERROR(VLOOKUP(InputTable[[#This Row],[OPERATIONS]],'System List'!$F$4:$H$7,3,FALSE),0) -> 0 | BZ3: =IFERROR(VLOOKUP(InputTable[[#This Row],[PMO]],'System List'!$F$4:$H$7,3,FALSE),0) -> 0 | CA3: =IFERROR(VLOOKUP(InputTable[[#This Row],[SALES]],'System List'!$F$4:$H$7,3,FALSE),0) -> 0 | CC3: {=IFERROR( IF( AND( MATCH(InputTable[[#This Row],[Starting Date]],'System List'!$B$5:$B$16,0)<=MATCH(Input!CC$2,'System List'!$B$5:$B$16,0), MATCH(Input!CC$2,'System List'!$B$5:$B$16<=MATCH(InputTable[[#This Row],[Delivery Date]],'System List'!$B$5:$B$16,0))),1,0), )} -> 0 | CD3: {=IFERROR( IF( AND( MATCH(InputTable[[#This Row],[Starting Date]],'System List'!$B$5:$B$16,0)<=MATCH(Input!CD$2,'System List'!$B$5:$B$16,0), MATCH(Input!CD$2,'System List'!$B$5:$B$16<=MATCH(InputTable[[#This Row],[Delivery Date]],'System List'!$B$5:$B$16,0))),1,0), )} -> 0 | CE3: {=IFERROR( IF( AND( MATCH(InputTable[[#This Row],[Starting Date]],'System List'!$B$5:$B$16,0)<=MATCH(Input!CE$2,'System List'!$B$5:$B$16,0), MATCH(Input!CE$2,'System List'!$B$5:$B$16<=MATCH(InputTable[[#This Row],[Delivery Date]],'System List'!$B$5:$B$16,0))),1,0), )} -> 0 | CF3: {=IFERROR( IF( AND( MATCH(InputTable[[#This Row],[Starting Date]],'System List'!$B$5:$B$16,0)<=MATCH(Input!CF$2,'System List'!$B$5:$B$16,0), MATCH(Input!CF$2,'System List'!$B$5:$B$16<=MATCH(InputTable[[#This Row],[Delivery Date]],'System List'!$B$5:$B$16,0))),1,0), )} -> 0 | CG3: {=IFERROR( IF( AND( MATCH(InputTable[[#This Row],[Starting Date]],'System List'!$B$5:$B$16,0)<=MATCH(Input!CG$2,'System List'!$B$5:$B$16,0), MATCH(Input!CG$2,'System List'!$B$5:$B$16<=MATCH(InputTable[[#This Row],[Delivery Date]],'System List'!$B$5:$B$16,0))),1,0), )} -> 0 | CH3: {=IFERROR( IF( AND( MATCH(InputTable[[#This Row],[Starting Date]],'System List'!$B$5:$B$16,0)<=MATCH(Input!CH$2,'System List'!$B$5:$B$16,0), MATCH(Input!CH$2,'System List'!$B$5:$B$16<=MATCH(InputTable[[#This Row],[Delivery Date]],'System List'!$B$5:$B$16,0))),1,0), )} -> 0 | CI3: {=IFERROR( IF( AND( MATCH(InputTable[[#This Row],[Starting Date]],'System List'!$B$5:$B$16,0)<=MATCH(Input!CI$2,'System List'!$B$5:$B$16,0), MATCH(Input!CI$2,'System List'!$B$5:$B$16<=MATCH(InputTable[[#This Row],[Delivery Date]],'System List'!$B$5:$B$16,0))),1,0), )} -> 0 | CJ3: {=IFERROR( IF( AND( MATCH(InputTable[[#This Row],[Starting Date]],'System List'!$B$5:$B$16,0)<=MATCH(Input!CJ$2,'System List'!$B$5:$B$16,0), MATCH(Input!CJ$2,'System List'!$B$5:$B$16<=MATCH(InputTable[[#This Row],[Delivery Date]],'System List'!$B$5:$B$16,0))),1,0), )} -> 0 | CK3: {=IFERROR( IF( AND( MATCH(InputTable[[#This Row],[Starting Date]],'System List'!$B$5:$B$16,0)<=MATCH(Input!CK$2,'System List'!$B$5:$B$16,0), MATCH(Input!CK$2,'System List'!$B$5:$B$16<=MATCH(InputTable[[#This Row],[Delivery Date]],'System List'!$B$5:$B$16,0))),1,0), )} -> 0 | CN3: =IFERROR( IF(AND( MATCH(InputTable[[#This Row],[Starting Date]],'System List'!$B$5:$B$16,0)<=MATCH(CN$2,'System List'!$B$5:$B$16,0), MATCH(CN$2,'System List'!$B$5:$B$16,0)<=MATCH(InputTable[[#This Row],[Delivery Date]],'System List'!$B$5:$B$16,0)),1,0),0) -> 0 | CO3: =IFERROR( IF(AND( MATCH(InputTable[[#This Row],[Starting Date]],'System List'!$B$5:$B$16,0)<=MATCH(CO$2,'System List'!$B$5:$B$16,0), MATCH(CO$2,'System List'!$B$5:$B$16,0)<=MATCH(InputTable[[#This Row],[Delivery Date]],'System List'!$B$5:$B$16,0)),1,0),0) -> 0 | CP3: =IFERROR( IF(AND( MATCH(InputTable[[#This Row],[Starting Date]],'System List'!$B$5:$B$16,0)<=MATCH(CP$2,'System List'!$B$5:$B$16,0), MATCH(CP$2,'System List'!$B$5:$B$16,0)<=MATCH(InputTable[[#This Row],[Delivery Date]],'System List'!$B$5:$B$16,0)),1,0),0) -> 1 | CQ3: =IFERROR( IF(AND( MATCH(InputTable[[#This Row],[Starting Date]],'System List'!$B$5:$B$16,0)<=MATCH(CQ$2,'System List'!$B$5:$B$16,0), MATCH(CQ$2,'System List'!$B$5:$B$16,0)<=MATCH(InputTable[[#This Row],[Delivery Date]],'System List'!$B$5:$B$16,0)),1,0),0) -> 1 | CR3: =IFERROR( IF(AND( MATCH(InputTable[[#This Row],[Starting Date]],'System List'!$B$5:$B$16,0)<=MATCH(CR$2,'System List'!$B$5:$B$16,0), MATCH(CR$2,'System List'!$B$5:$B$16,0)<=MATCH(InputTable[[#This Row],[Delivery Date]],'System List'!$B$5:$B$16,0)),1,0),0) -> 1 | CS3: =IFERROR( IF(AND( MATCH(InputTable[[#This Row],[Starting Date]],'System List'!$B$5:$B$16,0)<=MATCH(CS$2,'System List'!$B$5:$B$16,0), MATCH(CS$2,'System List'!$B$5:$B$16,0)<=MATCH(InputTable[[#This Row],[Delivery Date]],'System List'!$B$5:$B$16,0)),1,0),0) -> 1 | CT3: =IFERROR( IF(AND( MATCH(InputTable[[#This Row],[Starting Date]],'System List'!$B$5:$B$16,0)<=MATCH(CT$2,'System List'!$B$5:$B$16,0), MATCH(CT$2,'System List'!$B$5:$B$16,0)<=MATCH(InputTable[[#This Row],[Delivery Date]],'System List'!$B$5:$B$16,0)),1,0),0) -> 0 | CU3: =IFERROR( IF(AND( MATCH(InputTable[[#This Row],[Starting Date]],'System List'!$B$5:$B$16,0)<=MATCH(CU$2,'System List'!$B$5:$B$16,0), MATCH(CU$2,'System List'!$B$5:$B$16,0)<=MATCH(InputTable[[#This Row],[Delivery Date]],'System List'!$B$5:$B$16,0)),1,0),0) -> 0 | CV3: =IFERROR( IF(AND( MATCH(InputTable[[#This Row],[Starting Date]],'System List'!$B$5:$B$16,0)<=MATCH(CV$2,'System List'!$B$5:$B$16,0), MATCH(CV$2,'System List'!$B$5:$B$16,0)<=MATCH(InputTable[[#This Row],[Delivery Date]],'System List'!$B$5:$B$16,0)),1,0),0) -> 0 | CX3: =$CN3*_xlfn.XLOOKUP(CX$1,$BT$2:$CA$2,$BT3:$CA3,0) -> 0 | CY3: =$CO3*_xlfn.XLOOKUP(CY$1,$BT$2:$CA$2,$BT3:$CA3,0) -> 0 | CZ3: =$CP3*_xlfn.XLOOKUP(CZ$1,$BT$2:$CA$2,$BT3:$CA3,0) -> 0 | DA3: =$CQ3*_xlfn.XLOOKUP(DA$1,$BT$2:$CA$2,$BT3:$CA3,0) -> 0 | DB3: =$CR3*_xlfn.XLOOKUP(DB$1,$BT$2:$CA$2,$BT3:$CA3,0) -> 0 | DC3: =$CS3*_xlfn.XLOOKUP(DC$1,$BT$2:$CA$2,$BT3:$CA3,0) -> 0 | DD3: =$CT3*_xlfn.XLOOKUP(DD$1,$BT$2:$CA$2,$BT3:$CA3,0) -> 0 | DE3: =$CU3*_xlfn.XLOOKUP(DE$1,$BT$2:$CA$2,$BT3:$CA3,0) -> 0 | DF3: =$CV3*_xlfn.XLOOKUP(DF$1,$BT$2:$CA$2,$BT3:$CA3,0) -> 0 | DH3: =$CN3*_xlfn.XLOOKUP(DH$1,$BT$2:$CA$2,$BT3:$CA3,0) -> 0 | DI3: =$CO3*_xlfn.XLOOKUP(DI$1,$BT$2:$CA$2,$BT3:$CA3,0) -> 0 | DJ3: =$CP3*_xlfn.XLOOKUP(DJ$1,$BT$2:$CA$2,$BT3:$CA3,0) -> 0 | DK3: =$CQ3*_xlfn.XLOOKUP(DK$1,$BT$2:$CA$2,$BT3:$CA3,0) -> 0 | DL3: =$CR3*_xlfn.XLOOKUP(DL$1,$BT$2:$CA$2,$BT3:$CA3,0) -> 0 | DM3: =$CS3*_xlfn.XLOOKUP(DM$1,$BT$2:$CA$2,$BT3:$CA3,0) -> 0 | DN3: =$CT3*_xlfn.XLOOKUP(DN$1,$BT$2:$CA$2,$BT3:$CA3,0) -> 0 | DO3: =$CU3*_xlfn.XLOOKUP(DO$1,$BT$2:$CA$2,$BT3:$CA3,0) -> 0 | DP3: =$CV3*_xlfn.XLOOKUP(DP$1,$BT$2:$CA$2,$BT3:$CA3,0) -> 0 | DR3: =$CN3*_xlfn.XLOOKUP(DR$1,$BT$2:$CA$2,$BT3:$CA3,0) -> 0 | DS3: =$CO3*_xlfn.XLOOKUP(DS$1,$BT$2:$CA$2,$BT3:$CA3,0) -> 0 | DT3: =$CP3*_xlfn.XLOOKUP(DT$1,$BT$2:$CA$2,$BT3:$CA3,0) -> 0 | DU3: =$CQ3*_xlfn.XLOOKUP(DU$1,$BT$2:$CA$2,$BT3:$CA3,0) -> 0 | DV3: =$CR3*_xlfn.XLOOKUP(DV$1,$BT$2:$CA$2,$BT3:$CA3,0) -> 0 | DW3: =$CS3*_xlfn.XLOOKUP(DW$1,$BT$2:$CA$2,$BT3:$CA3,0) -> 0 | DX3: =$CT3*_xlfn.XLOOKUP(DX$1,$BT$2:$CA$2,$BT3:$CA3,0) -> 0 | DY3: =$CU3*_xlfn.XLOOKUP(DY$1,$BT$2:$CA$2,$BT3:$CA3,0) -> 0 | DZ3: =$CV3*_xlfn.XLOOKUP(DZ$1,$BT$2:$CA$2,$BT3:$CA3,0) -> 0 | EB3: =$CN3*_xlfn.XLOOKUP(EB$1,$BT$2:$CA$2,$BT3:$CA3,0) -> 0 | EC3: =$CO3*_xlfn.XLOOKUP(EC$1,$BT$2:$CA$2,$BT3:$CA3,0) -> 0 | ED3: =$CP3*_xlfn.XLOOKUP(ED$1,$BT$2:$CA$2,$BT3:$CA3,0) -> 0 | EE3: =$CQ3*_xlfn.XLOOKUP(EE$1,$BT$2:$CA$2,$BT3:$CA3,0) -> 0 | EF3: =$CR3*_xlfn.XLOOKUP(EF$1,$BT$2:$CA$2,$BT3:$CA3,0) -> 0 | EG3: =$CS3*_xlfn.XLOOKUP(EG$1,$BT$2:$CA$2,$BT3:$CA3,0) -> 0 | EH3: =$CT3*_xlfn.XLOOKUP(EH$1,$BT$2:$CA$2,$BT3:$CA3,0) -> 0 | EI3: =$CU3*_xlfn.XLOOKUP(EI$1,$BT$2:$CA$2,$BT3:$CA3,0) -> 0 | EJ3: =$CV3*_xlfn.XLOOKUP(EJ$1,$BT$2:$CA$2,$BT3:$CA3,0) -> 0 | EL3: =$CN3*_xlfn.XLOOKUP(EL$1,$BT$2:$CA$2,$BT3:$CA3,0) -> 0 | EM3: =$CO3*_xlfn.XLOOKUP(EM$1,$BT$2:$CA$2,$BT3:$CA3,0) -> 0 | EN3: =$CP3*_xlfn.XLOOKUP(EN$1,$BT$2:$CA$2,$BT3:$CA3,0) -> 0 | EO3: =$CQ3*_xlfn.XLOOKUP(EO$1,$BT$2:$CA$2,$BT3:$CA3,0) -> 0 | EP3: =$CR3*_xlfn.XLOOKUP(EP$1,$BT$2:$CA$2,$BT3:$CA3,0) -> 0 | EQ3: =$CS3*_xlfn.XLOOKUP(EQ$1,$BT$2:$CA$2,$BT3:$CA3,0) -> 0 | ER3: =$CT3*_xlfn.XLOOKUP(ER$1,$BT$2:$CA$2,$BT3:$CA3,0) -> 0 | ES3: =$CU3*_xlfn.XLOOKUP(ES$1,$BT$2:$CA$2,$BT3:$CA3,0) -> 0 | ET3: =$CV3*_xlfn.XLOOKUP(ET$1,$BT$2:$CA$2,$BT3:$CA3,0) -> 0 | EV3: =$CN3*_xlfn.XLOOKUP(EV$1,$BT$2:$CA$2,$BT3:$CA3,0) -> 0 | EW3: =$CO3*_xlfn.XLOOKUP(EW$1,$BT$2:$CA$2,$BT3:$CA3,0) -> 0 | EX3: =$CP3*_xlfn.XLOOKUP(EX$1,$BT$2:$CA$2,$BT3:$CA3,0) -> 0 | EY3: =$CQ3*_xlfn.XLOOKUP(EY$1,$BT$2:$CA$2,$BT3:$CA3,0) -> 0 | EZ3: =$CR3*_xlfn.XLOOKUP(EZ$1,$BT$2:$CA$2,$BT3:$CA3,0) -> 0 | FA3: =$CS3*_xlfn.XLOOKUP(FA$1,$BT$2:$CA$2,$BT3:$CA3,0) -> 0 | FB3: =$CT3*_xlfn.XLOOKUP(FB$1,$BT$2:$CA$2,$BT3:$CA3,0) -> 0 | FC3: =$CU3*_xlfn.XLOOKUP(FC$1,$BT$2:$CA$2,$BT3:$CA3,0) -> 0 | FD3: =$CV3*_xlfn.XLOOKUP(FD$1,$BT$2:$CA$2,$BT3:$CA3,0) -> 0 | FF3: =$CN3*_xlfn.XLOOKUP(FF$1,$BT$2:$CA$2,$BT3:$CA3,0) -> 0 | FG3: =$CO3*_xlfn.XLOOKUP(FG$1,$BT$2:$CA$2,$BT3:$CA3,0) -> 0 | FH3: =$CP3*_xlfn.XLOOKUP(FH$1,$BT$2:$CA$2,$BT3:$CA3,0) -> 0 | FI3: =$CQ3*_xlfn.XLOOKUP(FI$1,$BT$2:$CA$2,$BT3:$CA3,0) -> 0 | FJ3: =$CR3*_xlfn.XLOOKUP(FJ$1,$BT$2:$CA$2,$BT3:$CA3,0) -> 0 | FK3: =$CS3*_xlfn.XLOOKUP(FK$1,$BT$2:$CA$2,$BT3:$CA3,0) -> 0 | FL3: =$CT3*_xlfn.XLOOKUP(FL$1,$BT$2:$CA$2,$BT3:$CA3,0) -> 0 | FM3: =$CU3*_xlfn.XLOOKUP(FM$1,$BT$2:$CA$2,$BT3:$CA3,0) -> 0 | FN3: =$CV3*_xlfn.XLOOKUP(FN$1,$BT$2:$CA$2,$BT3:$CA3,0) -> 0 | FP3: =$CN3*_xlfn.XLOOKUP(FP$1,$BT$2:$CA$2,$BT3:$CA3,0) -> #REF! | FQ3: =$CO3*_xlfn.XLOOKUP(FQ$1,$BT$2:$CA$2,$BT3:$CA3,0) -> #REF! | FR3: =$CP3*_xlfn.XLOOKUP(FR$1,$BT$2:$CA$2,$BT3:$CA3,0) -> #REF! | FS3: =$CQ3*_xlfn.XLOOKUP(FS$1,$BT$2:$CA$2,$BT3:$CA3,0) -> #REF! | FT3: =$CR3*_xlfn.XLOOKUP(FT$1,$BT$2:$CA$2,$BT3:$CA3,0) -> #REF! | FU3: =$CS3*_xlfn.XLOOKUP(FU$1,$BT$2:$CA$2,$BT3:$CA3,0) -> #REF! | FV3: =$CT3*_xlfn.XLOOKUP(FV$1,$BT$2:$CA$2,$BT3:$CA3,0) -> #REF! | FW3: =$CU3*_xlfn.XLOOKUP(FW$1,$BT$2:$CA$2,$BT3:$CA3,0) -> #REF! | FX3: =$CV3*_xlfn.XLOOKUP(FX$1,$BT$2:$CA$2,$BT3:$CA3,0) -> #REF! | GB3: =IF(GB$2=InputTable[[#This Row],[Delivery Date]],_xlfn.XLOOKUP(GB$1,$BH$2:$BR$2,$BH3:$BR3,0),0) -> #REF! | GC3: =IF(GC$2=InputTable[[#This Row],[Delivery Date]],_xlfn.XLOOKUP(GC$1,$BH$2:$BR$2,$BH3:$BR3,0),0) -> 0 | GD3: =IF(GD$2=InputTable[[#This Row],[Delivery Date]],_xlfn.XLOOKUP(GD$1,$BH$2:$BR$2,$BH3:$BR3,0),0) -> 0 | GE3: =IF(GE$2=InputTable[[#This Row],[Delivery Date]],_xlfn.XLOOKUP(GE$1,$BH$2:$BR$2,$BH3:$BR3,0),0) -> 0 | GF3: =IF(GF$2=InputTable[[#This Row],[Delivery Date]],_xlfn.XLOOKUP(GF$1,$BH$2:$BR$2,$BH3:$BR3,0),0) -> 0 | GG3: =IF(GG$2=InputTable[[#This Row],[Delivery Date]],_xlfn.XLOOKUP(GG$1,$BH$2:$BR$2,$BH3:$BR3,0),0) -> 0 | GH3: =IF(GH$2=InputTable[[#This Row],[Delivery Date]],_xlfn.XLOOKUP(GH$1,$BH$2:$BR$2,$BH3:$BR3,0),0) -> 0 | GI3: =IF(GI$2=InputTable[[#This Row],[Delivery Date]],_xlfn.XLOOKUP(GI$1,$BH$2:$BR$2,$BH3:$BR3,0),0) -> 0 | GJ3: =IF(GJ$2=InputTable[[#This Row],[Delivery Date]],_xlfn.XLOOKUP(GJ$1,$BH$2:$BR$2,$BH3:$BR3,0),0) -> 0 | GL3: =IF(GL$2=InputTable[[#This Row],[Delivery Date]],_xlfn.XLOOKUP(GL$1,$BH$2:$BR$2,$BH3:$BR3,0),0) -> #REF! | GM3: =IF(GM$2=InputTable[[#This Row],[Delivery Date]],_xlfn.XLOOKUP(GM$1,$BH$2:$BR$2,$BH3:$BR3,0),0) -> 0 | GN3: =IF(GN$2=InputTable[[#This Row],[Delivery Date]],_xlfn.XLOOKUP(GN$1,$BH$2:$BR$2,$BH3:$BR3,0),0) -> 0 | GO3: =IF(GO$2=InputTable[[#This Row],[Delivery Date]],_xlfn.XLOOKUP(GO$1,$BH$2:$BR$2,$BH3:$BR3,0),0) -> 0 | GP3: =IF(GP$2=InputTable[[#This Row],[Delivery Date]],_xlfn.XLOOKUP(GP$1,$BH$2:$BR$2,$BH3:$BR3,0),0) -> 0 | GQ3: =IF(GQ$2=InputTable[[#This Row],[Delivery Date]],_xlfn.XLOOKUP(GQ$1,$BH$2:$BR$2,$BH3:$BR3,0),0) -> 0 | GR3: =IF(GR$2=InputTable[[#This Row],[Delivery Date]],_xlfn.XLOOKUP(GR$1,$BH$2:$BR$2,$BH3:$BR3,0),0) -> 0 | GS3: =IF(GS$2=InputTable[[#This Row],[Delivery Date]],_xlfn.XLOOKUP(GS$1,$BH$2:$BR$2,$BH3:$BR3,0),0) -> 0 | GT3: =IF(GT$2=InputTable[[#This Row],[Delivery Date]],_xlfn.XLOOKUP(GT$1,$BH$2:$BR$2,$BH3:$BR3,0),0) -> 0 | GV3: =IF(GV$2=InputTable[[#This Row],[Delivery Date]],_xlfn.XLOOKUP(GV$1,$BH$2:$BR$2,$BH3:$BR3,0),0) -> #REF! | GW3: =IF(GW$2=InputTable[[#This Row],[Delivery Date]],_xlfn.XLOOKUP(GW$1,$BH$2:$BR$2,$BH3:$BR3,0),0) -> 0 | GX3: =IF(GX$2=InputTable[[#This Row],[Delivery Date]],_xlfn.XLOOKUP(GX$1,$BH$2:$BR$2,$BH3:$BR3,0),0) -> 0 | GY3: =IF(GY$2=InputTable[[#This Row],[Delivery Date]],_xlfn.XLOOKUP(GY$1,$BH$2:$BR$2,$BH3:$BR3,0),0) -> 0 | GZ3: =IF(GZ$2=InputTable[[#This Row],[Delivery Date]],_xlfn.XLOOKUP(GZ$1,$BH$2:$BR$2,$BH3:$BR3,0),0) -> 0 | HA3: =IF(HA$2=InputTable[[#This Row],[Delivery Date]],_xlfn.XLOOKUP(HA$1,$BH$2:$BR$2,$BH3:$BR3,0),0) -> 0 | HB3: =IF(HB$2=InputTable[[#This Row],[Delivery Date]],_xlfn.XLOOKUP(HB$1,$BH$2:$BR$2,$BH3:$BR3,0),0) -> 0 | HC3: =IF(HC$2=InputTable[[#This Row],[Delivery Date]],_xlfn.XLOOKUP(HC$1,$BH$2:$BR$2,$BH3:$BR3,0),0) -> 0 | HD3: =IF(HD$2=InputTable[[#This Row],[Delivery Date]],_xlfn.XLOOKUP(HD$1,$BH$2:$BR$2,$BH3:$BR3,0),0) -> 0 | HF3: =IF(HF$2=InputTable[[#This Row],[Delivery Date]],_xlfn.XLOOKUP(HF$1,$BH$2:$BR$2,$BH3:$BR3,0),0) -> #REF! | HG3: =IF(HG$2=InputTable[[#This Row],[Delivery Date]],_xlfn.XLOOKUP(HG$1,$BH$2:$BR$2,$BH3:$BR3,0),0) -> 0 | HH3: =IF(HH$2=InputTable[[#This Row],[Delivery Date]],_xlfn.XLOOKUP(HH$1,$BH$2:$BR$2,$BH3:$BR3,0),0) -> 0 | HI3: =IF(HI$2=InputTable[[#This Row],[Delivery Date]],_xlfn.XLOOKUP(HI$1,$BH$2:$BR$2,$BH3:$BR3,0),0) -> 0 | HJ3: =IF(HJ$2=InputTable[[#This Row],[Delivery Date]],_xlfn.XLOOKUP(HJ$1,$BH$2:$BR$2,$BH3:$BR3,0),0) -> 0 | HK3: =IF(HK$2=InputTable[[#This Row],[Delivery Date]],_xlfn.XLOOKUP(HK$1,$BH$2:$BR$2,$BH3:$BR3,0),0) -> 0 | HL3: =IF(HL$2=InputTable[[#This Row],[Delivery Date]],_xlfn.XLOOKUP(HL$1,$BH$2:$BR$2,$BH3:$BR3,0),0) -> 0 | HM3: =IF(HM$2=InputTable[[#This Row],[Delivery Date]],_xlfn.XLOOKUP(HM$1,$BH$2:$BR$2,$BH3:$BR3,0),0) -> 0 | HN3: =IF(HN$2=InputTable[[#This Row],[Delivery Date]],_xlfn.XLOOKUP(HN$1,$BH$2:$BR$2,$BH3:$BR3,0),0) -> 0 | HP3: =IF(HP$2=InputTable[[#This Row],[Delivery Date]],_xlfn.XLOOKUP(HP$1,$BH$2:$BR$2,$BH3:$BR3,0),0) -> #REF! | HQ3: =IF(HQ$2=InputTable[[#This Row],[Delivery Date]],_xlfn.XLOOKUP(HQ$1,$BH$2:$BR$2,$BH3:$BR3,0),0) -> 0 | HR3: =IF(HR$2=InputTable[[#This Row],[Delivery Date]],_xlfn.XLOOKUP(HR$1,$BH$2:$BR$2,$BH3:$BR3,0),0) -> 0 | HS3: =IF(HS$2=InputTable[[#This Row],[Delivery Date]],_xlfn.XLOOKUP(HS$1,$BH$2:$BR$2,$BH3:$BR3,0),0) -> 0 | HT3: =IF(HT$2=InputTable[[#This Row],[Delivery Date]],_xlfn.XLOOKUP(HT$1,$BH$2:$BR$2,$BH3:$BR3,0),0) -> 0 | HU3: =IF(HU$2=InputTable[[#This Row],[Delivery Date]],_xlfn.XLOOKUP(HU$1,$BH$2:$BR$2,$BH3:$BR3,0),0) -> 0 | HV3: =IF(HV$2=InputTable[[#This Row],[Delivery Date]],_xlfn.XLOOKUP(HV$1,$BH$2:$BR$2,$BH3:$BR3,0),0) -> 0 | HW3: =IF(HW$2=InputTable[[#This Row],[Delivery Date]],_xlfn.XLOOKUP(HW$1,$BH$2:$BR$2,$BH3:$BR3,0),0) -> 0 | HX3: =IF(HX$2=InputTable[[#This Row],[Delivery Date]],_xlfn.XLOOKUP(HX$1,$BH$2:$BR$2,$BH3:$BR3,0),0) -> 0 | HZ3: =IF(HZ$2=InputTable[[#This Row],[Delivery Date]],_xlfn.XLOOKUP(HZ$1,$BH$2:$BR$2,$BH3:$BR3,0),0) -> #REF! | IA3: =IF(IA$2=InputTable[[#This Row],[Delivery Date]],_xlfn.XLOOKUP(IA$1,$BH$2:$BR$2,$BH3:$BR3,0),0) -> 0 | IB3: =IF(IB$2=InputTable[[#This Row],[Delivery Date]],_xlfn.XLOOKUP(IB$1,$BH$2:$BR$2,$BH3:$BR3,0),0) -> 0 | IC3: =IF(IC$2=InputTable[[#This Row],[Delivery Date]],_xlfn.XLOOKUP(IC$1,$BH$2:$BR$2,$BH3:$BR3,0),0) -> 0 | ID3: =IF(ID$2=InputTable[[#This Row],[Delivery Date]],_xlfn.XLOOKUP(ID$1,$BH$2:$BR$2,$BH3:$BR3,0),0) -> 0 | IE3: =IF(IE$2=InputTable[[#This Row],[Delivery Date]],_xlfn.XLOOKUP(IE$1,$BH$2:$BR$2,$BH3:$BR3,0),0) -> 0 | IF3: =IF(IF$2=InputTable[[#This Row],[Delivery Date]],_xlfn.XLOOKUP(IF$1,$BH$2:$BR$2,$BH3:$BR3,0),0) -> 0 | IG3: =IF(IG$2=InputTable[[#This Row],[Delivery Date]],_xlfn.XLOOKUP(IG$1,$BH$2:$BR$2,$BH3:$BR3,0),0) -> 0 | IH3: =IF(IH$2=InputTable[[#This Row],[Delivery Date]],_xlfn.XLOOKUP(IH$1,$BH$2:$BR$2,$BH3:$BR3,0),0) -> 0 | IJ3: =IF(IJ$2=InputTable[[#This Row],[Delivery Date]],_xlfn.XLOOKUP(IJ$1,$BH$2:$BR$2,$BH3:$BR3,0),0) -> #REF! | IK3: =IF(IK$2=InputTable[[#This Row],[Delivery Date]],_xlfn.XLOOKUP(IK$1,$BH$2:$BR$2,$BH3:$BR3,0),0) -> 0 | IL3: =IF(IL$2=InputTable[[#This Row],[Delivery Date]],_xlfn.XLOOKUP(IL$1,$BH$2:$BR$2,$BH3:$BR3,0),0) -> 0 | IM3: =IF(IM$2=InputTable[[#This Row],[Delivery Date]],_xlfn.XLOOKUP(IM$1,$BH$2:$BR$2,$BH3:$BR3,0),0) -> 0 | IN3: =IF(IN$2=InputTable[[#This Row],[Delivery Date]],_xlfn.XLOOKUP(IN$1,$BH$2:$BR$2,$BH3:$BR3,0),0) -> 0 | IO3: =IF(IO$2=InputTable[[#This Row],[Delivery Date]],_xlfn.XLOOKUP(IO$1,$BH$2:$BR$2,$BH3:$BR3,0),0) -> 0 | IP3: =IF(IP$2=InputTable[[#This Row],[Delivery Date]],_xlfn.XLOOKUP(IP$1,$BH$2:$BR$2,$BH3:$BR3,0),0) -> 0 | IQ3: =IF(IQ$2=InputTable[[#This Row],[Delivery Date]],_xlfn.XLOOKUP(IQ$1,$BH$2:$BR$2,$BH3:$BR3,0),0) -> 0 | IR3: =IF(IR$2=InputTable[[#This Row],[Delivery Date]],_xlfn.XLOOKUP(IR$1,$BH$2:$BR$2,$BH3:$BR3,0),0) -> 0 | IT3: =IF(IT$2=InputTable[[#This Row],[Delivery Date]],_xlfn.XLOOKUP(IT$1,$BH$2:$BR$2,$BH3:$BR3,0),0) -> #REF! | IU3: =IF(IU$2=InputTable[[#This Row],[Delivery Date]],_xlfn.XLOOKUP(IU$1,$BH$2:$BR$2,$BH3:$BR3,0),0) -> 0 | IV3: =IF(IV$2=InputTable[[#This Row],[Delivery Date]],_xlfn.XLOOKUP(IV$1,$BH$2:$BR$2,$BH3:$BR3,0),0) -> 0 | IW3: =IF(IW$2=InputTable[[#This Row],[Delivery Date]],_xlfn.XLOOKUP(IW$1,$BH$2:$BR$2,$BH3:$BR3,0),0) -> 0 | IX3: =IF(IX$2=InputTable[[#This Row],[Delivery Date]],_xlfn.XLOOKUP(IX$1,$BH$2:$BR$2,$BH3:$BR3,0),0) -> 0 | IY3: =IF(IY$2=InputTable[[#This Row],[Delivery Date]],_xlfn.XLOOKUP(IY$1,$BH$2:$BR$2,$BH3:$BR3,0),0) -> 0 | IZ3: =IF(IZ$2=InputTable[[#This Row],[Delivery Date]],_xlfn.XLOOKUP(IZ$1,$BH$2:$BR$2,$BH3:$BR3,0),0) -> 0 | JA3: =IF(JA$2=InputTable[[#This Row],[Delivery Date]],_xlfn.XLOOKUP(JA$1,$BH$2:$BR$2,$BH3:$BR3,0),0) -> 0 | JB3: =IF(JB$2=InputTable[[#This Row],[Delivery Date]],_xlfn.XLOOKUP(JB$1,$BH$2:$BR$2,$BH3:$BR3,0),0) -> 0 | JD3: =IF(JD$2=InputTable[[#This Row],[Delivery Date]],_xlfn.XLOOKUP(JD$1,$BH$2:$BR$2,$BH3:$BR3,0),0) -> #REF! | JE3: =IF(JE$2=InputTable[[#This Row],[Delivery Date]],_xlfn.XLOOKUP(JE$1,$BH$2:$BR$2,$BH3:$BR3,0),0) -> 0 | JF3: =IF(JF$2=InputTable[[#This Row],[Delivery Date]],_xlfn.XLOOKUP(JF$1,$BH$2:$BR$2,$BH3:$BR3,0),0) -> 0 | JG3: =IF(JG$2=InputTable[[#This Row],[Delivery Date]],_xlfn.XLOOKUP(JG$1,$BH$2:$BR$2,$BH3:$BR3,0),0) -> 0 | JH3: =IF(JH$2=InputTable[[#This Row],[Delivery Date]],_xlfn.XLOOKUP(JH$1,$BH$2:$BR$2,$BH3:$BR3,0),0) -> 0 | JI3: =IF(JI$2=InputTable[[#This Row],[Delivery Date]],_xlfn.XLOOKUP(JI$1,$BH$2:$BR$2,$BH3:$BR3,0),0) -> 0 | JJ3: =IF(JJ$2=InputTable[[#This Row],[Delivery Date]],_xlfn.XLOOKUP(JJ$1,$BH$2:$BR$2,$BH3:$BR3,0),0) -> 0 | JK3: =IF(JK$2=InputTable[[#This Row],[Delivery Date]],_xlfn.XLOOKUP(JK$1,$BH$2:$BR$2,$BH3:$BR3,0),0) -> 0 | JL3: =IF(JL$2=InputTable[[#This Row],[Delivery Date]],_xlfn.XLOOKUP(JL$1,$BH$2:$BR$2,$BH3:$BR3,0),0) -> 0 | JN3: =IF(JN$2=InputTable[[#This Row],[Delivery Date]],_xlfn.XLOOKUP(JN$1,$BH$2:$BR$2,$BH3:$BR3,0),0) -> #REF! | JO3: =IF(JO$2=InputTable[[#This Row],[Delivery Date]],_xlfn.XLOOKUP(JO$1,$BH$2:$BR$2,$BH3:$BR3,0),0) -> 0 | JP3: =IF(JP$2=InputTable[[#This Row],[Delivery Date]],_xlfn.XLOOKUP(JP$1,$BH$2:$BR$2,$BH3:$BR3,0),0) -> 0 | JQ3: =IF(JQ$2=InputTable[[#This Row],[Delivery Date]],_xlfn.XLOOKUP(JQ$1,$BH$2:$BR$2,$BH3:$BR3,0),0) -> 0 | JR3: =IF(JR$2=InputTable[[#This Row],[Delivery Date]],_xlfn.XLOOKUP(JR$1,$BH$2:$BR$2,$BH3:$BR3,0),0) -> 0 | JS3: =IF(JS$2=InputTable[[#This Row],[Delivery Date]],_xlfn.XLOOKUP(JS$1,$BH$2:$BR$2,$BH3:$BR3,0),0) -> 0 | JT3: =IF(JT$2=InputTable[[#This Row],[Delivery Date]],_xlfn.XLOOKUP(JT$1,$BH$2:$BR$2,$BH3:$BR3,0),0) -> 0 | JU3: =IF(JU$2=InputTable[[#This Row],[Delivery Date]],_xlfn.XLOOKUP(JU$1,$BH$2:$BR$2,$BH3:$BR3,0),0) -> 0 | JV3: =IF(JV$2=InputTable[[#This Row],[Delivery Date]],_xlfn.XLOOKUP(JV$1,$BH$2:$BR$2,$BH3:$BR3,0),0) -> 0 | JX3: =IF(JX$2=InputTable[[#This Row],[Delivery Date]],_xlfn.XLOOKUP(JX$1,$BH$2:$BR$2,$BH3:$BR3,0),0) -> #REF! | JY3: =IF(JY$2=InputTable[[#This Row],[Delivery Date]],_xlfn.XLOOKUP(JY$1,$BH$2:$BR$2,$BH3:$BR3,0),0) -> 0 | JZ3: =IF(JZ$2=InputTable[[#This Row],[Delivery Date]],_xlfn.XLOOKUP(JZ$1,$BH$2:$BR$2,$BH3:$BR3,0),0) -> 0 | KA3: =IF(KA$2=InputTable[[#This Row],[Delivery Date]],_xlfn.XLOOKUP(KA$1,$BH$2:$BR$2,$BH3:$BR3,0),0) -> 0 | KB3: =IF(KB$2=InputTable[[#This Row],[Delivery Date]],_xlfn.XLOOKUP(KB$1,$BH$2:$BR$2,$BH3:$BR3,0),0) -> 0 | KC3: =IF(KC$2=InputTable[[#This Row],[Delivery Date]],_xlfn.XLOOKUP(KC$1,$BH$2:$BR$2,$BH3:$BR3,0),0) -> 0 | KD3: =IF(KD$2=InputTable[[#This Row],[Delivery Date]],_xlfn.XLOOKUP(KD$1,$BH$2:$BR$2,$BH3:$BR3,0),0) -> 0 | KE3: =IF(KE$2=InputTable[[#This Row],[Delivery Date]],_xlfn.XLOOKUP(KE$1,$BH$2:$BR$2,$BH3:$BR3,0),0) -> 0 | KF3: =IF(KF$2=InputTable[[#This Row],[Delivery Date]],_xlfn.XLOOKUP(KF$1,$BH$2:$BR$2,$BH3:$BR3,0),0) -> 0
B4: On Track | C4: DIGITAL TECH | D4: ISPRJ-85 | E4: Digital Roadmap 2026 | F4: COMMERCIAL | G4: 2026 | I4: 2026 | K4: =VLOOKUP((InputTable[[#This Row],[Starting Date]]& " - " &InputTable[[#This Row],[Delivery Date]]),'System List'!$F$40:$H$83,2,FALSE) -> 1 to 2 years | L4: =VLOOKUP(InputTable[[#This Row],[Duration]],Duration,2,FALSE) -> 8 | O4: H | R4: H | T4: {=SUM( _xlfn.XLOOKUP(InputTable[[#This Row],[Safety]:[Regulatory]], 'System List'!$F$4:$F$7, 'System List'!$G$4:$G$7, 0) * _xlfn.XLOOKUP(InputTable[[#Headers],[Safety]:[Regulatory]], 'System List'!$Y$4:$Y$10, 'System List'!$Z$4:$Z$10, 0) )} -> 6.5 | AD4: =COUNTA(InputTable[[#This Row],[CORPHRFIN]:[SALES]]) -> 0 | AE4: {=SUM( _xlfn.XLOOKUP(InputTable[[#This Row],[CORPHRFIN]:[SALES]],'System List'!$F$4:$F$7,'System List'!$H$4:$H$7,0))} -> 0 | AR4: {=SUM( _xlfn.XLOOKUP(InputTable[[#This Row],[Impact on - CIAL]:[Impact on - STRAT]],'System List'!$F$4:$F$7,'System List'!$H$4:$H$7,0))} -> 0 | AS4: =VLOOKUP(InputTable[[#This Row],[Duration]],Duration,2,FALSE)+InputTable[[#This Row],[Resource Score]] -> 8 | AT4: =(( VLOOKUP(InputTable[[#This Row],[Duration]],'System List'!$J$5:$K$10,2,FALSE)*VLOOKUP(InputTable[[#Headers],[Duration]],'System List'!$V$5:$W$8,2,FALSE) + VLOOKUP(InputTable[[#This Row],[Number of Team Involved]],'System List'!$M$5:$N$13,2,FALSE)*VLOOKUP(InputTable[[#Headers],[Number of Team Involved]],'System List'!$V$5:$W$8,2,FALSE) + VLOOKUP(InputTable[[#This Row],[Resource Score]],Resource_Score,2,FALSE)*VLOOKUP(InputTable[[#Headers],[Resource Score]],'System List'!$V$5:$W$8,2,FALSE) + VLOOKUP(InputTable[[#This Row],[CHANGE Impact Score]],CHANGE_Impact_Score,2,FALSE)*VLOOKUP(InputTable[[#Headers],[CHANGE Impact Score]],'System List'!$V$5:$W$8,2,FALSE)) * 100) / 13 -> #N/A | AU4: =InputTable[[#This Row],[Value Score]]/InputTable[[#This Row],[EFFORT SCORE]]*100 -> 81.25 | AW4: Xavier ROMANET | AZ4: 0 | BA4: 0 | BC4: 10000000 | BH4: =IFERROR(VLOOKUP(InputTable[[#This Row],[Impact on - CIAL]],'System List'!$F$4:$H$7,3,FALSE),0) -> 0 | BI4: =IFERROR(VLOOKUP(InputTable[[#This Row],[Impact on - COM]],'System List'!$F$4:$H$7,3,FALSE),0) -> 0 | BJ4: =IFERROR(VLOOKUP(InputTable[[#This Row],[Impact on - FIN]],'System List'!$F$4:$H$7,3,FALSE),0) -> 0 | BK4: =IFERROR(VLOOKUP(InputTable[[#This Row],[Impact on - GEN SEC]],'System List'!$F$4:$H$7,3,FALSE),0) -> 0 | BL4: =IFERROR(VLOOKUP(InputTable[[#This Row],[Impact on - HR]],'System List'!$F$4:$H$7,3,FALSE),0) -> 0 | BM4: =IFERROR(VLOOKUP(InputTable[[#This Row],[Impact on - IS]],'System List'!$F$4:$H$7,3,FALSE),0) -> 0 | BN4: =IFERROR(VLOOKUP(InputTable[[#This Row],[Impact on - OPS]],'System List'!$F$4:$H$7,3,FALSE),0) -> 0 | BO4: =IFERROR(VLOOKUP(InputTable[[#This Row],[Impact on - ROLL STOCK]],'System List'!$F$4:$H$7,3,FALSE),0) -> 0 | BP4: =IFERROR(VLOOKUP(InputTable[[#This Row],[Impact on - SAFETY]],'System List'!$F$4:$H$7,3,FALSE),0) -> 0 | BQ4: =IFERROR(VLOOKUP(InputTable[[#This Row],[Impact on - STATION]],'System List'!$F$4:$H$7,3,FALSE),0) -> 0 | BR4: =IFERROR(VLOOKUP(InputTable[[#This Row],[Impact on - STRAT]],'System List'!$F$4:$H$7,3,FALSE),0) -> 0 | BT4: =IFERROR(VLOOKUP(InputTable[[#This Row],[CORPHRFIN]],'System List'!$F$4:$H$7,3,FALSE),0) -> 0 | BU4: =IFERROR(VLOOKUP(InputTable[[#This Row],[CUST]],'System List'!$F$4:$H$7,3,FALSE),0) -> 0 | BV4: =IFERROR(VLOOKUP(InputTable[[#This Row],[CYBER]],'System List'!$F$4:$H$7,3,FALSE),0) -> 0 | BW4: =IFERROR(VLOOKUP(InputTable[[#This Row],[DATA]],'System List'!$F$4:$H$7,3,FALSE),0) -> 0 | BX4: =IFERROR(VLOOKUP(InputTable[[#This Row],[INFRA]],'System List'!$F$4:$H$7,3,FALSE),0) -> 0 | BY4: =IFERROR(VLOOKUP(InputTable[[#This Row],[OPERATIONS]],'System List'!$F$4:$H$7,3,FALSE),0) -> 0 | BZ4: =IFERROR(VLOOKUP(InputTable[[#This Row],[PMO]],'System List'!$F$4:$H$7,3,FALSE),0) -> 0 | CA4: =IFERROR(VLOOKUP(InputTable[[#This Row],[SALES]],'System List'!$F$4:$H$7,3,FALSE),0) -> 0 | CC4: {=IFERROR( IF( AND( MATCH(InputTable[[#This Row],[Starting Date]],'System List'!$B$5:$B$16,0)<=MATCH(Input!CC$2,'System List'!$B$5:$B$16,0), MATCH(Input!CC$2,'System List'!$B$5:$B$16<=MATCH(InputTable[[#This Row],[Delivery Date]],'System List'!$B$5:$B$16,0))),1,0), )} -> 0 | CD4: {=IFERROR( IF( AND( MATCH(InputTable[[#This Row],[Starting Date]],'System List'!$B$5:$B$16,0)<=MATCH(Input!CD$2,'System List'!$B$5:$B$16,0), MATCH(Input!CD$2,'System List'!$B$5:$B$16<=MATCH(InputTable[[#This Row],[Delivery Date]],'System List'!$B$5:$B$16,0))),1,0), )} -> 0 | CE4: {=IFERROR( IF( AND( MATCH(InputTable[[#This Row],[Starting Date]],'System List'!$B$5:$B$16,0)<=MATCH(Input!CE$2,'System List'!$B$5:$B$16,0), MATCH(Input!CE$2,'System List'!$B$5:$B$16<=MATCH(InputTable[[#This Row],[Delivery Date]],'System List'!$B$5:$B$16,0))),1,0), )} -> 0 | CF4: {=IFERROR( IF( AND( MATCH(InputTable[[#This Row],[Starting Date]],'System List'!$B$5:$B$16,0)<=MATCH(Input!CF$2,'System List'!$B$5:$B$16,0), MATCH(Input!CF$2,'System List'!$B$5:$B$16<=MATCH(InputTable[[#This Row],[Delivery Date]],'System List'!$B$5:$B$16,0))),1,0), )} -> 0 | CG4: {=IFERROR( IF( AND( MATCH(InputTable[[#This Row],[Starting Date]],'System List'!$B$5:$B$16,0)<=MATCH(Input!CG$2,'System List'!$B$5:$B$16,0), MATCH(Input!CG$2,'System List'!$B$5:$B$16<=MATCH(InputTable[[#This Row],[Delivery Date]],'System List'!$B$5:$B$16,0))),1,0), )} -> 0 | CH4: {=IFERROR( IF( AND( MATCH(InputTable[[#This Row],[Starting Date]],'System List'!$B$5:$B$16,0)<=MATCH(Input!CH$2,'System List'!$B$5:$B$16,0), MATCH(Input!CH$2,'System List'!$B$5:$B$16<=MATCH(InputTable[[#This Row],[Delivery Date]],'System List'!$B$5:$B$16,0))),1,0), )} -> 0 | CI4: {=IFERROR( IF( AND( MATCH(InputTable[[#This Row],[Starting Date]],'System List'!$B$5:$B$16,0)<=MATCH(Input!CI$2,'System List'!$B$5:$B$16,0), MATCH(Input!CI$2,'System List'!$B$5:$B$16<=MATCH(InputTable[[#This Row],[Delivery Date]],'System List'!$B$5:$B$16,0))),1,0), )} -> 0 | CJ4: {=IFERROR( IF( AND( MATCH(InputTable[[#This Row],[Starting Date]],'System List'!$B$5:$B$16,0)<=MATCH(Input!CJ$2,'System List'!$B$5:$B$16,0), MATCH(Input!CJ$2,'System List'!$B$5:$B$16<=MATCH(InputTable[[#This Row],[Delivery Date]],'System List'!$B$5:$B$16,0))),1,0), )} -> 0 | CK4: {=IFERROR( IF( AND( MATCH(InputTable[[#This Row],[Starting Date]],'System List'!$B$5:$B$16,0)<=MATCH(Input!CK$2,'System List'!$B$5:$B$16,0), MATCH(Input!CK$2,'System List'!$B$5:$B$16<=MATCH(InputTable[[#This Row],[Delivery Date]],'System List'!$B$5:$B$16,0))),1,0), )} -> 0 | CN4: =IFERROR( IF(AND( MATCH(InputTable[[#This Row],[Starting Date]],'System List'!$B$5:$B$16,0)<=MATCH(CN$2,'System List'!$B$5:$B$16,0), MATCH(CN$2,'System List'!$B$5:$B$16,0)<=MATCH(InputTable[[#This Row],[Delivery Date]],'System List'!$B$5:$B$16,0)),1,0),0) -> 0 | CO4: =IFERROR( IF(AND( MATCH(InputTable[[#This Row],[Starting Date]],'System List'!$B$5:$B$16,0)<=MATCH(CO$2,'System List'!$B$5:$B$16,0), MATCH(CO$2,'System List'!$B$5:$B$16,0)<=MATCH(InputTable[[#This Row],[Delivery Date]],'System List'!$B$5:$B$16,0)),1,0),0) -> 0 | CP4: =IFERROR( IF(AND( MATCH(InputTable[[#This Row],[Starting Date]],'System List'!$B$5:$B$16,0)<=MATCH(CP$2,'System List'!$B$5:$B$16,0), MATCH(CP$2,'System List'!$B$5:$B$16,0)<=MATCH(InputTable[[#This Row],[Delivery Date]],'System List'!$B$5:$B$16,0)),1,0),0) -> 0 | CQ4: =IFERROR( IF(AND( MATCH(InputTable[[#This Row],[Starting Date]],'System List'!$B$5:$B$16,0)<=MATCH(CQ$2,'System List'!$B$5:$B$16,0), MATCH(CQ$2,'System List'!$B$5:$B$16,0)<=MATCH(InputTable[[#This Row],[Delivery Date]],'System List'!$B$5:$B$16,0)),1,0),0) -> 0 | CR4: =IFERROR( IF(AND( MATCH(InputTable[[#This Row],[Starting Date]],'System List'!$B$5:$B$16,0)<=MATCH(CR$2,'System List'!$B$5:$B$16,0), MATCH(CR$2,'System List'!$B$5:$B$16,0)<=MATCH(InputTable[[#This Row],[Delivery Date]],'System List'!$B$5:$B$16,0)),1,0),0) -> 0 | CS4: =IFERROR( IF(AND( MATCH(InputTable[[#This Row],[Starting Date]],'System List'!$B$5:$B$16,0)<=MATCH(CS$2,'System List'!$B$5:$B$16,0), MATCH(CS$2,'System List'!$B$5:$B$16,0)<=MATCH(InputTable[[#This Row],[Delivery Date]],'System List'!$B$5:$B$16,0)),1,0),0) -> 0 | CT4: =IFERROR( IF(AND( MATCH(InputTable[[#This Row],[Starting Date]],'System List'!$B$5:$B$16,0)<=MATCH(CT$2,'System List'!$B$5:$B$16,0), MATCH(CT$2,'System List'!$B$5:$B$16,0)<=MATCH(InputTable[[#This Row],[Delivery Date]],'System List'!$B$5:$B$16,0)),1,0),0) -> 0 | CU4: =IFERROR( IF(AND( MATCH(InputTable[[#This Row],[Starting Date]],'System List'!$B$5:$B$16,0)<=MATCH(CU$2,'System List'!$B$5:$B$16,0), MATCH(CU$2,'System List'!$B$5:$B$16,0)<=MATCH(InputTable[[#This Row],[Delivery Date]],'System List'!$B$5:$B$16,0)),1,0),0) -> 0 | CV4: =IFERROR( IF(AND( MATCH(InputTable[[#This Row],[Starting Date]],'System List'!$B$5:$B$16,0)<=MATCH(CV$2,'System List'!$B$5:$B$16,0), MATCH(CV$2,'System List'!$B$5:$B$16,0)<=MATCH(InputTable[[#This Row],[Delivery Date]],'System List'!$B$5:$B$16,0)),1,0),0) -> 0 | CX4: =$CN4*_xlfn.XLOOKUP(CX$1,$BT$2:$CA$2,$BT4:$CA4,0) -> 0 | CY4: =$CO4*_xlfn.XLOOKUP(CY$1,$BT$2:$CA$2,$BT4:$CA4,0) -> 0 | CZ4: =$CP4*_xlfn.XLOOKUP(CZ$1,$BT$2:$CA$2,$BT4:$CA4,0) -> 0 | DA4: =$CQ4*_xlfn.XLOOKUP(DA$1,$BT$2:$CA$2,$BT4:$CA4,0) -> 0 | DB4: =$CR4*_xlfn.XLOOKUP(DB$1,$BT$2:$CA$2,$BT4:$CA4,0) -> 0 | DC4: =$CS4*_xlfn.XLOOKUP(DC$1,$BT$2:$CA$2,$BT4:$CA4,0) -> 0 | DD4: =$CT4*_xlfn.XLOOKUP(DD$1,$BT$2:$CA$2,$BT4:$CA4,0) -> 0 | DE4: =$CU4*_xlfn.XLOOKUP(DE$1,$BT$2:$CA$2,$BT4:$CA4,0) -> 0 | DF4: =$CV4*_xlfn.XLOOKUP(DF$1,$BT$2:$CA$2,$BT4:$CA4,0) -> 0 | DH4: =$CN4*_xlfn.XLOOKUP(DH$1,$BT$2:$CA$2,$BT4:$CA4,0) -> 0 | DI4: =$CO4*_xlfn.XLOOKUP(DI$1,$BT$2:$CA$2,$BT4:$CA4,0) -> 0 | DJ4: =$CP4*_xlfn.XLOOKUP(DJ$1,$BT$2:$CA$2,$BT4:$CA4,0) -> 0 | DK4: =$CQ4*_xlfn.XLOOKUP(DK$1,$BT$2:$CA$2,$BT4:$CA4,0) -> 0 | DL4: =$CR4*_xlfn.XLOOKUP(DL$1,$BT$2:$CA$2,$BT4:$CA4,0) -> 0 | DM4: =$CS4*_xlfn.XLOOKUP(DM$1,$BT$2:$CA$2,$BT4:$CA4,0) -> 0 | DN4: =$CT4*_xlfn.XLOOKUP(DN$1,$BT$2:$CA$2,$BT4:$CA4,0) -> 0 | DO4: =$CU4*_xlfn.XLOOKUP(DO$1,$BT$2:$CA$2,$BT4:$CA4,0) -> 0 | DP4: =$CV4*_xlfn.XLOOKUP(DP$1,$BT$2:$CA$2,$BT4:$CA4,0) -> 0 | DR4: =$CN4*_xlfn.XLOOKUP(DR$1,$BT$2:$CA$2,$BT4:$CA4,0) -> 0 | DS4: =$CO4*_xlfn.XLOOKUP(DS$1,$BT$2:$CA$2,$BT4:$CA4,0) -> 0 | DT4: =$CP4*_xlfn.XLOOKUP(DT$1,$BT$2:$CA$2,$BT4:$CA4,0) -> 0 | DU4: =$CQ4*_xlfn.XLOOKUP(DU$1,$BT$2:$CA$2,$BT4:$CA4,0) -> 0 | DV4: =$CR4*_xlfn.XLOOKUP(DV$1,$BT$2:$CA$2,$BT4:$CA4,0) -> 0 | DW4: =$CS4*_xlfn.XLOOKUP(DW$1,$BT$2:$CA$2,$BT4:$CA4,0) -> 0 | DX4: =$CT4*_xlfn.XLOOKUP(DX$1,$BT$2:$CA$2,$BT4:$CA4,0) -> 0 | DY4: =$CU4*_xlfn.XLOOKUP(DY$1,$BT$2:$CA$2,$BT4:$CA4,0) -> 0 | DZ4: =$CV4*_xlfn.XLOOKUP(DZ$1,$BT$2:$CA$2,$BT4:$CA4,0) -> 0 | EB4: =$CN4*_xlfn.XLOOKUP(EB$1,$BT$2:$CA$2,$BT4:$CA4,0) -> 0 | EC4: =$CO4*_xlfn.XLOOKUP(EC$1,$BT$2:$CA$2,$BT4:$CA4,0) -> 0 | ED4: =$CP4*_xlfn.XLOOKUP(ED$1,$BT$2:$CA$2,$BT4:$CA4,0) -> 0 | EE4: =$CQ4*_xlfn.XLOOKUP(EE$1,$BT$2:$CA$2,$BT4:$CA4,0) -> 0 | EF4: =$CR4*_xlfn.XLOOKUP(EF$1,$BT$2:$CA$2,$BT4:$CA4,0) -> 0 | EG4: =$CS4*_xlfn.XLOOKUP(EG$1,$BT$2:$CA$2,$BT4:$CA4,0) -> 0 | EH4: =$CT4*_xlfn.XLOOKUP(EH$1,$BT$2:$CA$2,$BT4:$CA4,0) -> 0 | EI4: =$CU4*_xlfn.XLOOKUP(EI$1,$BT$2:$CA$2,$BT4:$CA4,0) -> 0 | EJ4: =$CV4*_xlfn.XLOOKUP(EJ$1,$BT$2:$CA$2,$BT4:$CA4,0) -> 0 | EL4: =$CN4*_xlfn.XLOOKUP(EL$1,$BT$2:$CA$2,$BT4:$CA4,0) -> 0 | EM4: =$CO4*_xlfn.XLOOKUP(EM$1,$BT$2:$CA$2,$BT4:$CA4,0) -> 0 | EN4: =$CP4*_xlfn.XLOOKUP(EN$1,$BT$2:$CA$2,$BT4:$CA4,0) -> 0 | EO4: =$CQ4*_xlfn.XLOOKUP(EO$1,$BT$2:$CA$2,$BT4:$CA4,0) -> 0 | EP4: =$CR4*_xlfn.XLOOKUP(EP$1,$BT$2:$CA$2,$BT4:$CA4,0) -> 0 | EQ4: =$CS4*_xlfn.XLOOKUP(EQ$1,$BT$2:$CA$2,$BT4:$CA4,0) -> 0 | ER4: =$CT4*_xlfn.XLOOKUP(ER$1,$BT$2:$CA$2,$BT4:$CA4,0) -> 0 | ES4: =$CU4*_xlfn.XLOOKUP(ES$1,$BT$2:$CA$2,$BT4:$CA4,0) -> 0 | ET4: =$CV4*_xlfn.XLOOKUP(ET$1,$BT$2:$CA$2,$BT4:$CA4,0) -> 0 | EV4: =$CN4*_xlfn.XLOOKUP(EV$1,$BT$2:$CA$2,$BT4:$CA4,0) -> 0 | EW4: =$CO4*_xlfn.XLOOKUP(EW$1,$BT$2:$CA$2,$BT4:$CA4,0) -> 0 | EX4: =$CP4*_xlfn.XLOOKUP(EX$1,$BT$2:$CA$2,$BT4:$CA4,0) -> 0 | EY4: =$CQ4*_xlfn.XLOOKUP(EY$1,$BT$2:$CA$2,$BT4:$CA4,0) -> 0 | EZ4: =$CR4*_xlfn.XLOOKUP(EZ$1,$BT$2:$CA$2,$BT4:$CA4,0) -> 0 | FA4: =$CS4*_xlfn.XLOOKUP(FA$1,$BT$2:$CA$2,$BT4:$CA4,0) -> 0 | FB4: =$CT4*_xlfn.XLOOKUP(FB$1,$BT$2:$CA$2,$BT4:$CA4,0) -> 0 | FC4: =$CU4*_xlfn.XLOOKUP(FC$1,$BT$2:$CA$2,$BT4:$CA4,0) -> 0 | FD4: =$CV4*_xlfn.XLOOKUP(FD$1,$BT$2:$CA$2,$BT4:$CA4,0) -> 0 | FF4: =$CN4*_xlfn.XLOOKUP(FF$1,$BT$2:$CA$2,$BT4:$CA4,0) -> 0 | FG4: =$CO4*_xlfn.XLOOKUP(FG$1,$BT$2:$CA$2,$BT4:$CA4,0) -> 0 | FH4: =$CP4*_xlfn.XLOOKUP(FH$1,$BT$2:$CA$2,$BT4:$CA4,0) -> 0 | FI4: =$CQ4*_xlfn.XLOOKUP(FI$1,$BT$2:$CA$2,$BT4:$CA4,0) -> 0 | FJ4: =$CR4*_xlfn.XLOOKUP(FJ$1,$BT$2:$CA$2,$BT4:$CA4,0) -> 0 | FK4: =$CS4*_xlfn.XLOOKUP(FK$1,$BT$2:$CA$2,$BT4:$CA4,0) -> 0 | FL4: =$CT4*_xlfn.XLOOKUP(FL$1,$BT$2:$CA$2,$BT4:$CA4,0) -> 0 | FM4: =$CU4*_xlfn.XLOOKUP(FM$1,$BT$2:$CA$2,$BT4:$CA4,0) -> 0 | FN4: =$CV4*_xlfn.XLOOKUP(FN$1,$BT$2:$CA$2,$BT4:$CA4,0) -> 0 | FP4: =$CN4*_xlfn.XLOOKUP(FP$1,$BT$2:$CA$2,$BT4:$CA4,0) -> #REF! | FQ4: =$CO4*_xlfn.XLOOKUP(FQ$1,$BT$2:$CA$2,$BT4:$CA4,0) -> #REF! | FR4: =$CP4*_xlfn.XLOOKUP(FR$1,$BT$2:$CA$2,$BT4:$CA4,0) -> #REF! | FS4: =$CQ4*_xlfn.XLOOKUP(FS$1,$BT$2:$CA$2,$BT4:$CA4,0) -> #REF! | FT4: =$CR4*_xlfn.XLOOKUP(FT$1,$BT$2:$CA$2,$BT4:$CA4,0) -> #REF! | FU4: =$CS4*_xlfn.XLOOKUP(FU$1,$BT$2:$CA$2,$BT4:$CA4,0) -> #REF! | FV4: =$CT4*_xlfn.XLOOKUP(FV$1,$BT$2:$CA$2,$BT4:$CA4,0) -> #REF! | FW4: =$CU4*_xlfn.XLOOKUP(FW$1,$BT$2:$CA$2,$BT4:$CA4,0) -> #REF! | FX4: =$CV4*_xlfn.XLOOKUP(FX$1,$BT$2:$CA$2,$BT4:$CA4,0) -> #REF! | GB4: =IF(GB$2=InputTable[[#This Row],[Delivery Date]],_xlfn.XLOOKUP(GB$1,$BH$2:$BR$2,$BH4:$BR4,0),0) -> #REF! | GC4: =IF(GC$2=InputTable[[#This Row],[Delivery Date]],_xlfn.XLOOKUP(GC$1,$BH$2:$BR$2,$BH4:$BR4,0),0) -> 0 | GD4: =IF(GD$2=InputTable[[#This Row],[Delivery Date]],_xlfn.XLOOKUP(GD$1,$BH$2:$BR$2,$BH4:$BR4,0),0) -> 0 | GE4: =IF(GE$2=InputTable[[#This Row],[Delivery Date]],_xlfn.XLOOKUP(GE$1,$BH$2:$BR$2,$BH4:$BR4,0),0) -> 0 | GF4: =IF(GF$2=InputTable[[#This Row],[Delivery Date]],_xlfn.XLOOKUP(GF$1,$BH$2:$BR$2,$BH4:$BR4,0),0) -> 0 | GG4: =IF(GG$2=InputTable[[#This Row],[Delivery Date]],_xlfn.XLOOKUP(GG$1,$BH$2:$BR$2,$BH4:$BR4,0),0) -> 0 | GH4: =IF(GH$2=InputTable[[#This Row],[Delivery Date]],_xlfn.XLOOKUP(GH$1,$BH$2:$BR$2,$BH4:$BR4,0),0) -> 0 | GI4: =IF(GI$2=InputTable[[#This Row],[Delivery Date]],_xlfn.XLOOKUP(GI$1,$BH$2:$BR$2,$BH4:$BR4,0),0) -> 0 | GJ4: =IF(GJ$2=InputTable[[#This Row],[Delivery Date]],_xlfn.XLOOKUP(GJ$1,$BH$2:$BR$2,$BH4:$BR4,0),0) -> 0 | GL4: =IF(GL$2=InputTable[[#This Row],[Delivery Date]],_xlfn.XLOOKUP(GL$1,$BH$2:$BR$2,$BH4:$BR4,0),0) -> #REF! | GM4: =IF(GM$2=InputTable[[#This Row],[Delivery Date]],_xlfn.XLOOKUP(GM$1,$BH$2:$BR$2,$BH4:$BR4,0),0) -> 0 | GN4: =IF(GN$2=InputTable[[#This Row],[Delivery Date]],_xlfn.XLOOKUP(GN$1,$BH$2:$BR$2,$BH4:$BR4,0),0) -> 0 | GO4: =IF(GO$2=InputTable[[#This Row],[Delivery Date]],_xlfn.XLOOKUP(GO$1,$BH$2:$BR$2,$BH4:$BR4,0),0) -> 0 | GP4: =IF(GP$2=InputTable[[#This Row],[Delivery Date]],_xlfn.XLOOKUP(GP$1,$BH$2:$BR$2,$BH4:$BR4,0),0) -> 0 | GQ4: =IF(GQ$2=InputTable[[#This Row],[Delivery Date]],_xlfn.XLOOKUP(GQ$1,$BH$2:$BR$2,$BH4:$BR4,0),0) -> 0 | GR4: =IF(GR$2=InputTable[[#This Row],[Delivery Date]],_xlfn.XLOOKUP(GR$1,$BH$2:$BR$2,$BH4:$BR4,0),0) -> 0 | GS4: =IF(GS$2=InputTable[[#This Row],[Delivery Date]],_xlfn.XLOOKUP(GS$1,$BH$2:$BR$2,$BH4:$BR4,0),0) -> 0 | GT4: =IF(GT$2=InputTable[[#This Row],[Delivery Date]],_xlfn.XLOOKUP(GT$1,$BH$2:$BR$2,$BH4:$BR4,0),0) -> 0 | GV4: =IF(GV$2=InputTable[[#This Row],[Delivery Date]],_xlfn.XLOOKUP(GV$1,$BH$2:$BR$2,$BH4:$BR4,0),0) -> #REF! | GW4: =IF(GW$2=InputTable[[#This Row],[Delivery Date]],_xlfn.XLOOKUP(GW$1,$BH$2:$BR$2,$BH4:$BR4,0),0) -> 0 | GX4: =IF(GX$2=InputTable[[#This Row],[Delivery Date]],_xlfn.XLOOKUP(GX$1,$BH$2:$BR$2,$BH4:$BR4,0),0) -> 0 | GY4: =IF(GY$2=InputTable[[#This Row],[Delivery Date]],_xlfn.XLOOKUP(GY$1,$BH$2:$BR$2,$BH4:$BR4,0),0) -> 0 | GZ4: =IF(GZ$2=InputTable[[#This Row],[Delivery Date]],_xlfn.XLOOKUP(GZ$1,$BH$2:$BR$2,$BH4:$BR4,0),0) -> 0 | HA4: =IF(HA$2=InputTable[[#This Row],[Delivery Date]],_xlfn.XLOOKUP(HA$1,$BH$2:$BR$2,$BH4:$BR4,0),0) -> 0 | HB4: =IF(HB$2=InputTable[[#This Row],[Delivery Date]],_xlfn.XLOOKUP(HB$1,$BH$2:$BR$2,$BH4:$BR4,0),0) -> 0 | HC4: =IF(HC$2=InputTable[[#This Row],[Delivery Date]],_xlfn.XLOOKUP(HC$1,$BH$2:$BR$2,$BH4:$BR4,0),0) -> 0 | HD4: =IF(HD$2=InputTable[[#This Row],[Delivery Date]],_xlfn.XLOOKUP(HD$1,$BH$2:$BR$2,$BH4:$BR4,0),0) -> 0 | HF4: =IF(HF$2=InputTable[[#This Row],[Delivery Date]],_xlfn.XLOOKUP(HF$1,$BH$2:$BR$2,$BH4:$BR4,0),0) -> #REF! | HG4: =IF(HG$2=InputTable[[#This Row],[Delivery Date]],_xlfn.XLOOKUP(HG$1,$BH$2:$BR$2,$BH4:$BR4,0),0) -> 0 | HH4: =IF(HH$2=InputTable[[#This Row],[Delivery Date]],_xlfn.XLOOKUP(HH$1,$BH$2:$BR$2,$BH4:$BR4,0),0) -> 0 | HI4: =IF(HI$2=InputTable[[#This Row],[Delivery Date]],_xlfn.XLOOKUP(HI$1,$BH$2:$BR$2,$BH4:$BR4,0),0) -> 0 | HJ4: =IF(HJ$2=InputTable[[#This Row],[Delivery Date]],_xlfn.XLOOKUP(HJ$1,$BH$2:$BR$2,$BH4:$BR4,0),0) -> 0 | HK4: =IF(HK$2=InputTable[[#This Row],[Delivery Date]],_xlfn.XLOOKUP(HK$1,$BH$2:$BR$2,$BH4:$BR4,0),0) -> 0 | HL4: =IF(HL$2=InputTable[[#This Row],[Delivery Date]],_xlfn.XLOOKUP(HL$1,$BH$2:$BR$2,$BH4:$BR4,0),0) -> 0 | HM4: =IF(HM$2=InputTable[[#This Row],[Delivery Date]],_xlfn.XLOOKUP(HM$1,$BH$2:$BR$2,$BH4:$BR4,0),0) -> 0 | HN4: =IF(HN$2=InputTable[[#This Row],[Delivery Date]],_xlfn.XLOOKUP(HN$1,$BH$2:$BR$2,$BH4:$BR4,0),0) -> 0 | HP4: =IF(HP$2=InputTable[[#This Row],[Delivery Date]],_xlfn.XLOOKUP(HP$1,$BH$2:$BR$2,$BH4:$BR4,0),0) -> #REF! | HQ4: =IF(HQ$2=InputTable[[#This Row],[Delivery Date]],_xlfn.XLOOKUP(HQ$1,$BH$2:$BR$2,$BH4:$BR4,0),0) -> 0 | HR4: =IF(HR$2=InputTable[[#This Row],[Delivery Date]],_xlfn.XLOOKUP(HR$1,$BH$2:$BR$2,$BH4:$BR4,0),0) -> 0 | HS4: =IF(HS$2=InputTable[[#This Row],[Delivery Date]],_xlfn.XLOOKUP(HS$1,$BH$2:$BR$2,$BH4:$BR4,0),0) -> 0 | HT4: =IF(HT$2=InputTable[[#This Row],[Delivery Date]],_xlfn.XLOOKUP(HT$1,$BH$2:$BR$2,$BH4:$BR4,0),0) -> 0 | HU4: =IF(HU$2=InputTable[[#This Row],[Delivery Date]],_xlfn.XLOOKUP(HU$1,$BH$2:$BR$2,$BH4:$BR4,0),0) -> 0 | HV4: =IF(HV$2=InputTable[[#This Row],[Delivery Date]],_xlfn.XLOOKUP(HV$1,$BH$2:$BR$2,$BH4:$BR4,0),0) -> 0 | HW4: =IF(HW$2=InputTable[[#This Row],[Delivery Date]],_xlfn.XLOOKUP(HW$1,$BH$2:$BR$2,$BH4:$BR4,0),0) -> 0 | HX4: =IF(HX$2=InputTable[[#This Row],[Delivery Date]],_xlfn.XLOOKUP(HX$1,$BH$2:$BR$2,$BH4:$BR4,0),0) -> 0 | HZ4: =IF(HZ$2=InputTable[[#This Row],[Delivery Date]],_xlfn.XLOOKUP(HZ$1,$BH$2:$BR$2,$BH4:$BR4,0),0) -> #REF! | IA4: =IF(IA$2=InputTable[[#This Row],[Delivery Date]],_xlfn.XLOOKUP(IA$1,$BH$2:$BR$2,$BH4:$BR4,0),0) -> 0 | IB4: =IF(IB$2=InputTable[[#This Row],[Delivery Date]],_xlfn.XLOOKUP(IB$1,$BH$2:$BR$2,$BH4:$BR4,0),0) -> 0 | IC4: =IF(IC$2=InputTable[[#This Row],[Delivery Date]],_xlfn.XLOOKUP(IC$1,$BH$2:$BR$2,$BH4:$BR4,0),0) -> 0 | ID4: =IF(ID$2=InputTable[[#This Row],[Delivery Date]],_xlfn.XLOOKUP(ID$1,$BH$2:$BR$2,$BH4:$BR4,0),0) -> 0 | IE4: =IF(IE$2=InputTable[[#This Row],[Delivery Date]],_xlfn.XLOOKUP(IE$1,$BH$2:$BR$2,$BH4:$BR4,0),0) -> 0 | IF4: =IF(IF$2=InputTable[[#This Row],[Delivery Date]],_xlfn.XLOOKUP(IF$1,$BH$2:$BR$2,$BH4:$BR4,0),0) -> 0 | IG4: =IF(IG$2=InputTable[[#This Row],[Delivery Date]],_xlfn.XLOOKUP(IG$1,$BH$2:$BR$2,$BH4:$BR4,0),0) -> 0 | IH4: =IF(IH$2=InputTable[[#This Row],[Delivery Date]],_xlfn.XLOOKUP(IH$1,$BH$2:$BR$2,$BH4:$BR4,0),0) -> 0 | IJ4: =IF(IJ$2=InputTable[[#This Row],[Delivery Date]],_xlfn.XLOOKUP(IJ$1,$BH$2:$BR$2,$BH4:$BR4,0),0) -> #REF! | IK4: =IF(IK$2=InputTable[[#This Row],[Delivery Date]],_xlfn.XLOOKUP(IK$1,$BH$2:$BR$2,$BH4:$BR4,0),0) -> 0 | IL4: =IF(IL$2=InputTable[[#This Row],[Delivery Date]],_xlfn.XLOOKUP(IL$1,$BH$2:$BR$2,$BH4:$BR4,0),0) -> 0 | IM4: =IF(IM$2=InputTable[[#This Row],[Delivery Date]],_xlfn.XLOOKUP(IM$1,$BH$2:$BR$2,$BH4:$BR4,0),0) -> 0 | IN4: =IF(IN$2=InputTable[[#This Row],[Delivery Date]],_xlfn.XLOOKUP(IN$1,$BH$2:$BR$2,$BH4:$BR4,0),0) -> 0 | IO4: =IF(IO$2=InputTable[[#This Row],[Delivery Date]],_xlfn.XLOOKUP(IO$1,$BH$2:$BR$2,$BH4:$BR4,0),0) -> 0 | IP4: =IF(IP$2=InputTable[[#This Row],[Delivery Date]],_xlfn.XLOOKUP(IP$1,$BH$2:$BR$2,$BH4:$BR4,0),0) -> 0 | IQ4: =IF(IQ$2=InputTable[[#This Row],[Delivery Date]],_xlfn.XLOOKUP(IQ$1,$BH$2:$BR$2,$BH4:$BR4,0),0) -> 0 | IR4: =IF(IR$2=InputTable[[#This Row],[Delivery Date]],_xlfn.XLOOKUP(IR$1,$BH$2:$BR$2,$BH4:$BR4,0),0) -> 0 | IT4: =IF(IT$2=InputTable[[#This Row],[Delivery Date]],_xlfn.XLOOKUP(IT$1,$BH$2:$BR$2,$BH4:$BR4,0),0) -> #REF! | IU4: =IF(IU$2=InputTable[[#This Row],[Delivery Date]],_xlfn.XLOOKUP(IU$1,$BH$2:$BR$2,$BH4:$BR4,0),0) -> 0 | IV4: =IF(IV$2=InputTable[[#This Row],[Delivery Date]],_xlfn.XLOOKUP(IV$1,$BH$2:$BR$2,$BH4:$BR4,0),0) -> 0 | IW4: =IF(IW$2=InputTable[[#This Row],[Delivery Date]],_xlfn.XLOOKUP(IW$1,$BH$2:$BR$2,$BH4:$BR4,0),0) -> 0 | IX4: =IF(IX$2=InputTable[[#This Row],[Delivery Date]],_xlfn.XLOOKUP(IX$1,$BH$2:$BR$2,$BH4:$BR4,0),0) -> 0 | IY4: =IF(IY$2=InputTable[[#This Row],[Delivery Date]],_xlfn.XLOOKUP(IY$1,$BH$2:$BR$2,$BH4:$BR4,0),0) -> 0 | IZ4: =IF(IZ$2=InputTable[[#This Row],[Delivery Date]],_xlfn.XLOOKUP(IZ$1,$BH$2:$BR$2,$BH4:$BR4,0),0) -> 0 | JA4: =IF(JA$2=InputTable[[#This Row],[Delivery Date]],_xlfn.XLOOKUP(JA$1,$BH$2:$BR$2,$BH4:$BR4,0),0) -> 0 | JB4: =IF(JB$2=InputTable[[#This Row],[Delivery Date]],_xlfn.XLOOKUP(JB$1,$BH$2:$BR$2,$BH4:$BR4,0),0) -> 0 | JD4: =IF(JD$2=InputTable[[#This Row],[Delivery Date]],_xlfn.XLOOKUP(JD$1,$BH$2:$BR$2,$BH4:$BR4,0),0) -> #REF! | JE4: =IF(JE$2=InputTable[[#This Row],[Delivery Date]],_xlfn.XLOOKUP(JE$1,$BH$2:$BR$2,$BH4:$BR4,0),0) -> 0 | JF4: =IF(JF$2=InputTable[[#This Row],[Delivery Date]],_xlfn.XLOOKUP(JF$1,$BH$2:$BR$2,$BH4:$BR4,0),0) -> 0 | JG4: =IF(JG$2=InputTable[[#This Row],[Delivery Date]],_xlfn.XLOOKUP(JG$1,$BH$2:$BR$2,$BH4:$BR4,0),0) -> 0 | JH4: =IF(JH$2=InputTable[[#This Row],[Delivery Date]],_xlfn.XLOOKUP(JH$1,$BH$2:$BR$2,$BH4:$BR4,0),0) -> 0 | JI4: =IF(JI$2=InputTable[[#This Row],[Delivery Date]],_xlfn.XLOOKUP(JI$1,$BH$2:$BR$2,$BH4:$BR4,0),0) -> 0 | JJ4: =IF(JJ$2=InputTable[[#This Row],[Delivery Date]],_xlfn.XLOOKUP(JJ$1,$BH$2:$BR$2,$BH4:$BR4,0),0) -> 0 | JK4: =IF(JK$2=InputTable[[#This Row],[Delivery Date]],_xlfn.XLOOKUP(JK$1,$BH$2:$BR$2,$BH4:$BR4,0),0) -> 0 | JL4: =IF(JL$2=InputTable[[#This Row],[Delivery Date]],_xlfn.XLOOKUP(JL$1,$BH$2:$BR$2,$BH4:$BR4,0),0) -> 0 | JN4: =IF(JN$2=InputTable[[#This Row],[Delivery Date]],_xlfn.XLOOKUP(JN$1,$BH$2:$BR$2,$BH4:$BR4,0),0) -> #REF! | JO4: =IF(JO$2=InputTable[[#This Row],[Delivery Date]],_xlfn.XLOOKUP(JO$1,$BH$2:$BR$2,$BH4:$BR4,0),0) -> 0 | JP4: =IF(JP$2=InputTable[[#This Row],[Delivery Date]],_xlfn.XLOOKUP(JP$1,$BH$2:$BR$2,$BH4:$BR4,0),0) -> 0 | JQ4: =IF(JQ$2=InputTable[[#This Row],[Delivery Date]],_xlfn.XLOOKUP(JQ$1,$BH$2:$BR$2,$BH4:$BR4,0),0) -> 0 | JR4: =IF(JR$2=InputTable[[#This Row],[Delivery Date]],_xlfn.XLOOKUP(JR$1,$BH$2:$BR$2,$BH4:$BR4,0),0) -> 0 | JS4: =IF(JS$2=InputTable[[#This Row],[Delivery Date]],_xlfn.XLOOKUP(JS$1,$BH$2:$BR$2,$BH4:$BR4,0),0) -> 0 | JT4: =IF(JT$2=InputTable[[#This Row],[Delivery Date]],_xlfn.XLOOKUP(JT$1,$BH$2:$BR$2,$BH4:$BR4,0),0) -> 0 | JU4: =IF(JU$2=InputTable[[#This Row],[Delivery Date]],_xlfn.XLOOKUP(JU$1,$BH$2:$BR$2,$BH4:$BR4,0),0) -> 0 | JV4: =IF(JV$2=InputTable[[#This Row],[Delivery Date]],_xlfn.XLOOKUP(JV$1,$BH$2:$BR$2,$BH4:$BR4,0),0) -> 0 | JX4: =IF(JX$2=InputTable[[#This Row],[Delivery Date]],_xlfn.XLOOKUP(JX$1,$BH$2:$BR$2,$BH4:$BR4,0),0) -> #REF! | JY4: =IF(JY$2=InputTable[[#This Row],[Delivery Date]],_xlfn.XLOOKUP(JY$1,$BH$2:$BR$2,$BH4:$BR4,0),0) -> 0 | JZ4: =IF(JZ$2=InputTable[[#This Row],[Delivery Date]],_xlfn.XLOOKUP(JZ$1,$BH$2:$BR$2,$BH4:$BR4,0),0) -> 0 | KA4: =IF(KA$2=InputTable[[#This Row],[Delivery Date]],_xlfn.XLOOKUP(KA$1,$BH$2:$BR$2,$BH4:$BR4,0),0) -> 0 | KB4: =IF(KB$2=InputTable[[#This Row],[Delivery Date]],_xlfn.XLOOKUP(KB$1,$BH$2:$BR$2,$BH4:$BR4,0),0) -> 0 | KC4: =IF(KC$2=InputTable[[#This Row],[Delivery Date]],_xlfn.XLOOKUP(KC$1,$BH$2:$BR$2,$BH4:$BR4,0),0) -> 0 | KD4: =IF(KD$2=InputTable[[#This Row],[Delivery Date]],_xlfn.XLOOKUP(KD$1,$BH$2:$BR$2,$BH4:$BR4,0),0) -> 0 | KE4: =IF(KE$2=InputTable[[#This Row],[Delivery Date]],_xlfn.XLOOKUP(KE$1,$BH$2:$BR$2,$BH4:$BR4,0),0) -> 0 | KF4: =IF(KF$2=InputTable[[#This Row],[Delivery Date]],_xlfn.XLOOKUP(KF$1,$BH$2:$BR$2,$BH4:$BR4,0),0) -> 0
B5: Stopped in 2026 | C5: OPERATIONS | D5: ISPRJ-22 | E5: Onboarding Continental Teams to ACMS | F5: OPERATIONS | G5: 2025 Q4 | I5: 2026 | K5: =VLOOKUP((InputTable[[#This Row],[Starting Date]]& " - " &InputTable[[#This Row],[Delivery Date]]),'System List'!$F$40:$H$83,2,FALSE) -> #N/A | L5: =VLOOKUP(InputTable[[#This Row],[Duration]],Duration,2,FALSE) -> #N/A | M5: yes | R5: L | T5: {=SUM( _xlfn.XLOOKUP(InputTable[[#This Row],[Safety]:[Regulatory]], 'System List'!$F$4:$F$7, 'System List'!$G$4:$G$7, 0) * _xlfn.XLOOKUP(InputTable[[#Headers],[Safety]:[Regulatory]], 'System List'!$Y$4:$Y$10, 'System List'!$Z$4:$Z$10, 0) )} -> 1.5 | AD5: =COUNTA(InputTable[[#This Row],[CORPHRFIN]:[SALES]]) -> 0 | AE5: {=SUM( _xlfn.XLOOKUP(InputTable[[#This Row],[CORPHRFIN]:[SALES]],'System List'!$F$4:$F$7,'System List'!$H$4:$H$7,0))} -> 0 | AR5: {=SUM( _xlfn.XLOOKUP(InputTable[[#This Row],[Impact on - CIAL]:[Impact on - STRAT]],'System List'!$F$4:$F$7,'System List'!$H$4:$H$7,0))} -> 0 | AS5: =VLOOKUP(InputTable[[#This Row],[Duration]],Duration,2,FALSE)+InputTable[[#This Row],[Resource Score]] -> #N/A | AT5: =(( VLOOKUP(InputTable[[#This Row],[Duration]],'System List'!$J$5:$K$10,2,FALSE)*VLOOKUP(InputTable[[#Headers],[Duration]],'System List'!$V$5:$W$8,2,FALSE) + VLOOKUP(InputTable[[#This Row],[Number of Team Involved]],'System List'!$M$5:$N$13,2,FALSE)*VLOOKUP(InputTable[[#Headers],[Number of Team Involved]],'System List'!$V$5:$W$8,2,FALSE) + VLOOKUP(InputTable[[#This Row],[Resource Score]],Resource_Score,2,FALSE)*VLOOKUP(InputTable[[#Headers],[Resource Score]],'System List'!$V$5:$W$8,2,FALSE) + VLOOKUP(InputTable[[#This Row],[CHANGE Impact Score]],CHANGE_Impact_Score,2,FALSE)*VLOOKUP(InputTable[[#Headers],[CHANGE Impact Score]],'System List'!$V$5:$W$8,2,FALSE)) * 100) / 13 -> #N/A | AU5: =InputTable[[#This Row],[Value Score]]/InputTable[[#This Row],[EFFORT SCORE]]*100 -> #N/A | AW5: Eva Wruszczak | AX5: approved | BH5: =IFERROR(VLOOKUP(InputTable[[#This Row],[Impact on - CIAL]],'System List'!$F$4:$H$7,3,FALSE),0) -> 0 | BI5: =IFERROR(VLOOKUP(InputTable[[#This Row],[Impact on - COM]],'System List'!$F$4:$H$7,3,FALSE),0) -> 0 | BJ5: =IFERROR(VLOOKUP(InputTable[[#This Row],[Impact on - FIN]],'System List'!$F$4:$H$7,3,FALSE),0) -> 0 | BK5: =IFERROR(VLOOKUP(InputTable[[#This Row],[Impact on - GEN SEC]],'System List'!$F$4:$H$7,3,FALSE),0) -> 0 | BL5: =IFERROR(VLOOKUP(InputTable[[#This Row],[Impact on - HR]],'System List'!$F$4:$H$7,3,FALSE),0) -> 0 | BM5: =IFERROR(VLOOKUP(InputTable[[#This Row],[Impact on - IS]],'System List'!$F$4:$H$7,3,FALSE),0) -> 0 | BN5: =IFERROR(VLOOKUP(InputTable[[#This Row],[Impact on - OPS]],'System List'!$F$4:$H$7,3,FALSE),0) -> 0 | BO5: =IFERROR(VLOOKUP(InputTable[[#This Row],[Impact on - ROLL STOCK]],'System List'!$F$4:$H$7,3,FALSE),0) -> 0 | BP5: =IFERROR(VLOOKUP(InputTable[[#This Row],[Impact on - SAFETY]],'System List'!$F$4:$H$7,3,FALSE),0) -> 0 | BQ5: =IFERROR(VLOOKUP(InputTable[[#This Row],[Impact on - STATION]],'System List'!$F$4:$H$7,3,FALSE),0) -> 0 | BR5: =IFERROR(VLOOKUP(InputTable[[#This Row],[Impact on - STRAT]],'System List'!$F$4:$H$7,3,FALSE),0) -> 0 | BT5: =IFERROR(VLOOKUP(InputTable[[#This Row],[CORPHRFIN]],'System List'!$F$4:$H$7,3,FALSE),0) -> 0 | BU5: =IFERROR(VLOOKUP(InputTable[[#This Row],[CUST]],'System List'!$F$4:$H$7,3,FALSE),0) -> 0 | BV5: =IFERROR(VLOOKUP(InputTable[[#This Row],[CYBER]],'System List'!$F$4:$H$7,3,FALSE),0) -> 0 | BW5: =IFERROR(VLOOKUP(InputTable[[#This Row],[DATA]],'System List'!$F$4:$H$7,3,FALSE),0) -> 0 | BX5: =IFERROR(VLOOKUP(InputTable[[#This Row],[INFRA]],'System List'!$F$4:$H$7,3,FALSE),0) -> 0 | BY5: =IFERROR(VLOOKUP(InputTable[[#This Row],[OPERATIONS]],'System List'!$F$4:$H$7,3,FALSE),0) -> 0 | BZ5: =IFERROR(VLOOKUP(InputTable[[#This Row],[PMO]],'System List'!$F$4:$H$7,3,FALSE),0) -> 0 | CA5: =IFERROR(VLOOKUP(InputTable[[#This Row],[SALES]],'System List'!$F$4:$H$7,3,FALSE),0) -> 0 | CC5: {=IFERROR( IF( AND( MATCH(InputTable[[#This Row],[Starting Date]],'System List'!$B$5:$B$16,0)<=MATCH(Input!CC$2,'System List'!$B$5:$B$16,0), MATCH(Input!CC$2,'System List'!$B$5:$B$16<=MATCH(InputTable[[#This Row],[Delivery Date]],'System List'!$B$5:$B$16,0))),1,0), )} -> 0 | CD5: {=IFERROR( IF( AND( MATCH(InputTable[[#This Row],[Starting Date]],'System List'!$B$5:$B$16,0)<=MATCH(Input!CD$2,'System List'!$B$5:$B$16,0), MATCH(Input!CD$2,'System List'!$B$5:$B$16<=MATCH(InputTable[[#This Row],[Delivery Date]],'System List'!$B$5:$B$16,0))),1,0), )} -> 0 | CE5: {=IFERROR( IF( AND( MATCH(InputTable[[#This Row],[Starting Date]],'System List'!$B$5:$B$16,0)<=MATCH(Input!CE$2,'System List'!$B$5:$B$16,0), MATCH(Input!CE$2,'System List'!$B$5:$B$16<=MATCH(InputTable[[#This Row],[Delivery Date]],'System List'!$B$5:$B$16,0))),1,0), )} -> 0 | CF5: {=IFERROR( IF( AND( MATCH(InputTable[[#This Row],[Starting Date]],'System List'!$B$5:$B$16,0)<=MATCH(Input!CF$2,'System List'!$B$5:$B$16,0), MATCH(Input!CF$2,'System List'!$B$5:$B$16<=MATCH(InputTable[[#This Row],[Delivery Date]],'System List'!$B$5:$B$16,0))),1,0), )} -> 0 | CG5: {=IFERROR( IF( AND( MATCH(InputTable[[#This Row],[Starting Date]],'System List'!$B$5:$B$16,0)<=MATCH(Input!CG$2,'System List'!$B$5:$B$16,0), MATCH(Input!CG$2,'System List'!$B$5:$B$16<=MATCH(InputTable[[#This Row],[Delivery Date]],'System List'!$B$5:$B$16,0))),1,0), )} -> 0 | CH5: {=IFERROR( IF( AND( MATCH(InputTable[[#This Row],[Starting Date]],'System List'!$B$5:$B$16,0)<=MATCH(Input!CH$2,'System List'!$B$5:$B$16,0), MATCH(Input!CH$2,'System List'!$B$5:$B$16<=MATCH(InputTable[[#This Row],[Delivery Date]],'System List'!$B$5:$B$16,0))),1,0), )} -> 0 | CI5: {=IFERROR( IF( AND( MATCH(InputTable[[#This Row],[Starting Date]],'System List'!$B$5:$B$16,0)<=MATCH(Input!CI$2,'System List'!$B$5:$B$16,0), MATCH(Input!CI$2,'System List'!$B$5:$B$16<=MATCH(InputTable[[#This Row],[Delivery Date]],'System List'!$B$5:$B$16,0))),1,0), )} -> 0 | CJ5: {=IFERROR( IF( AND( MATCH(InputTable[[#This Row],[Starting Date]],'System List'!$B$5:$B$16,0)<=MATCH(Input!CJ$2,'System List'!$B$5:$B$16,0), MATCH(Input!CJ$2,'System List'!$B$5:$B$16<=MATCH(InputTable[[#This Row],[Delivery Date]],'System List'!$B$5:$B$16,0))),1,0), )} -> 0 | CK5: {=IFERROR( IF( AND( MATCH(InputTable[[#This Row],[Starting Date]],'System List'!$B$5:$B$16,0)<=MATCH(Input!CK$2,'System List'!$B$5:$B$16,0), MATCH(Input!CK$2,'System List'!$B$5:$B$16<=MATCH(InputTable[[#This Row],[Delivery Date]],'System List'!$B$5:$B$16,0))),1,0), )} -> 0 | CN5: =IFERROR( IF(AND( MATCH(InputTable[[#This Row],[Starting Date]],'System List'!$B$5:$B$16,0)<=MATCH(CN$2,'System List'!$B$5:$B$16,0), MATCH(CN$2,'System List'!$B$5:$B$16,0)<=MATCH(InputTable[[#This Row],[Delivery Date]],'System List'!$B$5:$B$16,0)),1,0),0) -> 0 | CO5: =IFERROR( IF(AND( MATCH(InputTable[[#This Row],[Starting Date]],'System List'!$B$5:$B$16,0)<=MATCH(CO$2,'System List'!$B$5:$B$16,0), MATCH(CO$2,'System List'!$B$5:$B$16,0)<=MATCH(InputTable[[#This Row],[Delivery Date]],'System List'!$B$5:$B$16,0)),1,0),0) -> 0 | CP5: =IFERROR( IF(AND( MATCH(InputTable[[#This Row],[Starting Date]],'System List'!$B$5:$B$16,0)<=MATCH(CP$2,'System List'!$B$5:$B$16,0), MATCH(CP$2,'System List'!$B$5:$B$16,0)<=MATCH(InputTable[[#This Row],[Delivery Date]],'System List'!$B$5:$B$16,0)),1,0),0) -> 0 | CQ5: =IFERROR( IF(AND( MATCH(InputTable[[#This Row],[Starting Date]],'System List'!$B$5:$B$16,0)<=MATCH(CQ$2,'System List'!$B$5:$B$16,0), MATCH(CQ$2,'System List'!$B$5:$B$16,0)<=MATCH(InputTable[[#This Row],[Delivery Date]],'System List'!$B$5:$B$16,0)),1,0),0) -> 0 | CR5: =IFERROR( IF(AND( MATCH(InputTable[[#This Row],[Starting Date]],'System List'!$B$5:$B$16,0)<=MATCH(CR$2,'System List'!$B$5:$B$16,0), MATCH(CR$2,'System List'!$B$5:$B$16,0)<=MATCH(InputTable[[#This Row],[Delivery Date]],'System List'!$B$5:$B$16,0)),1,0),0) -> 0 | CS5: =IFERROR( IF(AND( MATCH(InputTable[[#This Row],[Starting Date]],'System List'!$B$5:$B$16,0)<=MATCH(CS$2,'System List'!$B$5:$B$16,0), MATCH(CS$2,'System List'!$B$5:$B$16,0)<=MATCH(InputTable[[#This Row],[Delivery Date]],'System List'!$B$5:$B$16,0)),1,0),0) -> 1 | CT5: =IFERROR( IF(AND( MATCH(InputTable[[#This Row],[Starting Date]],'System List'!$B$5:$B$16,0)<=MATCH(CT$2,'System List'!$B$5:$B$16,0), MATCH(CT$2,'System List'!$B$5:$B$16,0)<=MATCH(InputTable[[#This Row],[Delivery Date]],'System List'!$B$5:$B$16,0)),1,0),0) -> 0 | CU5: =IFERROR( IF(AND( MATCH(InputTable[[#This Row],[Starting Date]],'System List'!$B$5:$B$16,0)<=MATCH(CU$2,'System List'!$B$5:$B$16,0), MATCH(CU$2,'System List'!$B$5:$B$16,0)<=MATCH(InputTable[[#This Row],[Delivery Date]],'System List'!$B$5:$B$16,0)),1,0),0) -> 0 | CV5: =IFERROR( IF(AND( MATCH(InputTable[[#This Row],[Starting Date]],'System List'!$B$5:$B$16,0)<=MATCH(CV$2,'System List'!$B$5:$B$16,0), MATCH(CV$2,'System List'!$B$5:$B$16,0)<=MATCH(InputTable[[#This Row],[Delivery Date]],'System List'!$B$5:$B$16,0)),1,0),0) -> 0 | CX5: =CN5*_xlfn.XLOOKUP(CX$1,$BT$2:$CA$2,$BT5:$CA5,0) -> 0 | CY5: =CO5*_xlfn.XLOOKUP(CY$1,$BT$2:$CA$2,$BT5:$CA5,0) -> 0 | CZ5: =CP5*_xlfn.XLOOKUP(CZ$1,$BT$2:$CA$2,$BT5:$CA5,0) -> 0 | DA5: =CQ5*_xlfn.XLOOKUP(DA$1,$BT$2:$CA$2,$BT5:$CA5,0) -> 0 | DB5: =CR5*_xlfn.XLOOKUP(DB$1,$BT$2:$CA$2,$BT5:$CA5,0) -> 0 | DC5: =CS5*_xlfn.XLOOKUP(DC$1,$BT$2:$CA$2,$BT5:$CA5,0) -> 0 | DD5: =CT5*_xlfn.XLOOKUP(DD$1,$BT$2:$CA$2,$BT5:$CA5,0) -> 0 | DE5: =CU5*_xlfn.XLOOKUP(DE$1,$BT$2:$CA$2,$BT5:$CA5,0) -> 0 | DF5: =CV5*_xlfn.XLOOKUP(DF$1,$BT$2:$CA$2,$BT5:$CA5,0) -> 0 | DH5: =$CN5*_xlfn.XLOOKUP(DH$1,$BT$2:$CA$2,$BT5:$CA5,0) -> 0 | DI5: =$CO5*_xlfn.XLOOKUP(DI$1,$BT$2:$CA$2,$BT5:$CA5,0) -> 0 | DJ5: =$CP5*_xlfn.XLOOKUP(DJ$1,$BT$2:$CA$2,$BT5:$CA5,0) -> 0 | DK5: =$CQ5*_xlfn.XLOOKUP(DK$1,$BT$2:$CA$2,$BT5:$CA5,0) -> 0 | DL5: =$CR5*_xlfn.XLOOKUP(DL$1,$BT$2:$CA$2,$BT5:$CA5,0) -> 0 | DM5: =$CS5*_xlfn.XLOOKUP(DM$1,$BT$2:$CA$2,$BT5:$CA5,0) -> 0 | DN5: =$CT5*_xlfn.XLOOKUP(DN$1,$BT$2:$CA$2,$BT5:$CA5,0) -> 0 | DO5: =$CU5*_xlfn.XLOOKUP(DO$1,$BT$2:$CA$2,$BT5:$CA5,0) -> 0 | DP5: =$CV5*_xlfn.XLOOKUP(DP$1,$BT$2:$CA$2,$BT5:$CA5,0) -> 0 | DR5: =$CN5*_xlfn.XLOOKUP(DR$1,$BT$2:$CA$2,$BT5:$CA5,0) -> 0 | DS5: =$CO5*_xlfn.XLOOKUP(DS$1,$BT$2:$CA$2,$BT5:$CA5,0) -> 0 | DT5: =$CP5*_xlfn.XLOOKUP(DT$1,$BT$2:$CA$2,$BT5:$CA5,0) -> 0 | DU5: =$CQ5*_xlfn.XLOOKUP(DU$1,$BT$2:$CA$2,$BT5:$CA5,0) -> 0 | DV5: =$CR5*_xlfn.XLOOKUP(DV$1,$BT$2:$CA$2,$BT5:$CA5,0) -> 0 | DW5: =$CS5*_xlfn.XLOOKUP(DW$1,$BT$2:$CA$2,$BT5:$CA5,0) -> 0 | DX5: =$CT5*_xlfn.XLOOKUP(DX$1,$BT$2:$CA$2,$BT5:$CA5,0) -> 0 | DY5: =$CU5*_xlfn.XLOOKUP(DY$1,$BT$2:$CA$2,$BT5:$CA5,0) -> 0 | DZ5: =$CV5*_xlfn.XLOOKUP(DZ$1,$BT$2:$CA$2,$BT5:$CA5,0) -> 0 | EB5: =$CN5*_xlfn.XLOOKUP(EB$1,$BT$2:$CA$2,$BT5:$CA5,0) -> 0 | EC5: =$CO5*_xlfn.XLOOKUP(EC$1,$BT$2:$CA$2,$BT5:$CA5,0) -> 0 | ED5: =$CP5*_xlfn.XLOOKUP(ED$1,$BT$2:$CA$2,$BT5:$CA5,0) -> 0 | EE5: =$CQ5*_xlfn.XLOOKUP(EE$1,$BT$2:$CA$2,$BT5:$CA5,0) -> 0 | EF5: =$CR5*_xlfn.XLOOKUP(EF$1,$BT$2:$CA$2,$BT5:$CA5,0) -> 0 | EG5: =$CS5*_xlfn.XLOOKUP(EG$1,$BT$2:$CA$2,$BT5:$CA5,0) -> 0 | EH5: =$CT5*_xlfn.XLOOKUP(EH$1,$BT$2:$CA$2,$BT5:$CA5,0) -> 0 | EI5: =$CU5*_xlfn.XLOOKUP(EI$1,$BT$2:$CA$2,$BT5:$CA5,0) -> 0 | EJ5: =$CV5*_xlfn.XLOOKUP(EJ$1,$BT$2:$CA$2,$BT5:$CA5,0) -> 0 | EL5: =$CN5*_xlfn.XLOOKUP(EL$1,$BT$2:$CA$2,$BT5:$CA5,0) -> 0 | EM5: =$CO5*_xlfn.XLOOKUP(EM$1,$BT$2:$CA$2,$BT5:$CA5,0) -> 0 | EN5: =$CP5*_xlfn.XLOOKUP(EN$1,$BT$2:$CA$2,$BT5:$CA5,0) -> 0 | EO5: =$CQ5*_xlfn.XLOOKUP(EO$1,$BT$2:$CA$2,$BT5:$CA5,0) -> 0 | EP5: =$CR5*_xlfn.XLOOKUP(EP$1,$BT$2:$CA$2,$BT5:$CA5,0) -> 0 | EQ5: =$CS5*_xlfn.XLOOKUP(EQ$1,$BT$2:$CA$2,$BT5:$CA5,0) -> 0 | ER5: =$CT5*_xlfn.XLOOKUP(ER$1,$BT$2:$CA$2,$BT5:$CA5,0) -> 0 | ES5: =$CU5*_xlfn.XLOOKUP(ES$1,$BT$2:$CA$2,$BT5:$CA5,0) -> 0 | ET5: =$CV5*_xlfn.XLOOKUP(ET$1,$BT$2:$CA$2,$BT5:$CA5,0) -> 0 | EV5: =$CN5*_xlfn.XLOOKUP(EV$1,$BT$2:$CA$2,$BT5:$CA5,0) -> 0 | EW5: =$CO5*_xlfn.XLOOKUP(EW$1,$BT$2:$CA$2,$BT5:$CA5,0) -> 0 | EX5: =$CP5*_xlfn.XLOOKUP(EX$1,$BT$2:$CA$2,$BT5:$CA5,0) -> 0 | EY5: =$CQ5*_xlfn.XLOOKUP(EY$1,$BT$2:$CA$2,$BT5:$CA5,0) -> 0 | EZ5: =$CR5*_xlfn.XLOOKUP(EZ$1,$BT$2:$CA$2,$BT5:$CA5,0) -> 0 | FA5: =$CS5*_xlfn.XLOOKUP(FA$1,$BT$2:$CA$2,$BT5:$CA5,0) -> 0 | FB5: =$CT5*_xlfn.XLOOKUP(FB$1,$BT$2:$CA$2,$BT5:$CA5,0) -> 0 | FC5: =$CU5*_xlfn.XLOOKUP(FC$1,$BT$2:$CA$2,$BT5:$CA5,0) -> 0 | FD5: =$CV5*_xlfn.XLOOKUP(FD$1,$BT$2:$CA$2,$BT5:$CA5,0) -> 0 | FF5: =$CN5*_xlfn.XLOOKUP(FF$1,$BT$2:$CA$2,$BT5:$CA5,0) -> 0 | FG5: =$CO5*_xlfn.XLOOKUP(FG$1,$BT$2:$CA$2,$BT5:$CA5,0) -> 0 | FH5: =$CP5*_xlfn.XLOOKUP(FH$1,$BT$2:$CA$2,$BT5:$CA5,0) -> 0 | FI5: =$CQ5*_xlfn.XLOOKUP(FI$1,$BT$2:$CA$2,$BT5:$CA5,0) -> 0 | FJ5: =$CR5*_xlfn.XLOOKUP(FJ$1,$BT$2:$CA$2,$BT5:$CA5,0) -> 0 | FK5: =$CS5*_xlfn.XLOOKUP(FK$1,$BT$2:$CA$2,$BT5:$CA5,0) -> 0 | FL5: =$CT5*_xlfn.XLOOKUP(FL$1,$BT$2:$CA$2,$BT5:$CA5,0) -> 0 | FM5: =$CU5*_xlfn.XLOOKUP(FM$1,$BT$2:$CA$2,$BT5:$CA5,0) -> 0 | FN5: =$CV5*_xlfn.XLOOKUP(FN$1,$BT$2:$CA$2,$BT5:$CA5,0) -> 0 | FP5: =$CN5*_xlfn.XLOOKUP(FP$1,$BT$2:$CA$2,$BT5:$CA5,0) -> #REF! | FQ5: =$CO5*_xlfn.XLOOKUP(FQ$1,$BT$2:$CA$2,$BT5:$CA5,0) -> #REF! | FR5: =$CP5*_xlfn.XLOOKUP(FR$1,$BT$2:$CA$2,$BT5:$CA5,0) -> #REF! | FS5: =$CQ5*_xlfn.XLOOKUP(FS$1,$BT$2:$CA$2,$BT5:$CA5,0) -> #REF! | FT5: =$CR5*_xlfn.XLOOKUP(FT$1,$BT$2:$CA$2,$BT5:$CA5,0) -> #REF! | FU5: =$CS5*_xlfn.XLOOKUP(FU$1,$BT$2:$CA$2,$BT5:$CA5,0) -> #REF! | FV5: =$CT5*_xlfn.XLOOKUP(FV$1,$BT$2:$CA$2,$BT5:$CA5,0) -> #REF! | FW5: =$CU5*_xlfn.XLOOKUP(FW$1,$BT$2:$CA$2,$BT5:$CA5,0) -> #REF! | FX5: =$CV5*_xlfn.XLOOKUP(FX$1,$BT$2:$CA$2,$BT5:$CA5,0) -> #REF! | GB5: =IF(GB$2=InputTable[[#This Row],[Delivery Date]],_xlfn.XLOOKUP(GB$1,$BH$2:$BR$2,$BH5:$BR5,0),0) -> #REF! | GC5: =IF(GC$2=InputTable[[#This Row],[Delivery Date]],_xlfn.XLOOKUP(GC$1,$BH$2:$BR$2,$BH5:$BR5,0),0) -> 0 | GD5: =IF(GD$2=InputTable[[#This Row],[Delivery Date]],_xlfn.XLOOKUP(GD$1,$BH$2:$BR$2,$BH5:$BR5,0),0) -> 0 | GE5: =IF(GE$2=InputTable[[#This Row],[Delivery Date]],_xlfn.XLOOKUP(GE$1,$BH$2:$BR$2,$BH5:$BR5,0),0) -> 0 | GF5: =IF(GF$2=InputTable[[#This Row],[Delivery Date]],_xlfn.XLOOKUP(GF$1,$BH$2:$BR$2,$BH5:$BR5,0),0) -> 0 | GG5: =IF(GG$2=InputTable[[#This Row],[Delivery Date]],_xlfn.XLOOKUP(GG$1,$BH$2:$BR$2,$BH5:$BR5,0),0) -> 0 | GH5: =IF(GH$2=InputTable[[#This Row],[Delivery Date]],_xlfn.XLOOKUP(GH$1,$BH$2:$BR$2,$BH5:$BR5,0),0) -> 0 | GI5: =IF(GI$2=InputTable[[#This Row],[Delivery Date]],_xlfn.XLOOKUP(GI$1,$BH$2:$BR$2,$BH5:$BR5,0),0) -> 0 | GJ5: =IF(GJ$2=InputTable[[#This Row],[Delivery Date]],_xlfn.XLOOKUP(GJ$1,$BH$2:$BR$2,$BH5:$BR5,0),0) -> 0 | GL5: =IF(GL$2=InputTable[[#This Row],[Delivery Date]],_xlfn.XLOOKUP(GL$1,$BH$2:$BR$2,$BH5:$BR5,0),0) -> #REF! | GM5: =IF(GM$2=InputTable[[#This Row],[Delivery Date]],_xlfn.XLOOKUP(GM$1,$BH$2:$BR$2,$BH5:$BR5,0),0) -> 0 | GN5: =IF(GN$2=InputTable[[#This Row],[Delivery Date]],_xlfn.XLOOKUP(GN$1,$BH$2:$BR$2,$BH5:$BR5,0),0) -> 0 | GO5: =IF(GO$2=InputTable[[#This Row],[Delivery Date]],_xlfn.XLOOKUP(GO$1,$BH$2:$BR$2,$BH5:$BR5,0),0) -> 0 | GP5: =IF(GP$2=InputTable[[#This Row],[Delivery Date]],_xlfn.XLOOKUP(GP$1,$BH$2:$BR$2,$BH5:$BR5,0),0) -> 0 | GQ5: =IF(GQ$2=InputTable[[#This Row],[Delivery Date]],_xlfn.XLOOKUP(GQ$1,$BH$2:$BR$2,$BH5:$BR5,0),0) -> 0 | GR5: =IF(GR$2=InputTable[[#This Row],[Delivery Date]],_xlfn.XLOOKUP(GR$1,$BH$2:$BR$2,$BH5:$BR5,0),0) -> 0 | GS5: =IF(GS$2=InputTable[[#This Row],[Delivery Date]],_xlfn.XLOOKUP(GS$1,$BH$2:$BR$2,$BH5:$BR5,0),0) -> 0 | GT5: =IF(GT$2=InputTable[[#This Row],[Delivery Date]],_xlfn.XLOOKUP(GT$1,$BH$2:$BR$2,$BH5:$BR5,0),0) -> 0 | GV5: =IF(GV$2=InputTable[[#This Row],[Delivery Date]],_xlfn.XLOOKUP(GV$1,$BH$2:$BR$2,$BH5:$BR5,0),0) -> #REF! | GW5: =IF(GW$2=InputTable[[#This Row],[Delivery Date]],_xlfn.XLOOKUP(GW$1,$BH$2:$BR$2,$BH5:$BR5,0),0) -> 0 | GX5: =IF(GX$2=InputTable[[#This Row],[Delivery Date]],_xlfn.XLOOKUP(GX$1,$BH$2:$BR$2,$BH5:$BR5,0),0) -> 0 | GY5: =IF(GY$2=InputTable[[#This Row],[Delivery Date]],_xlfn.XLOOKUP(GY$1,$BH$2:$BR$2,$BH5:$BR5,0),0) -> 0 | GZ5: =IF(GZ$2=InputTable[[#This Row],[Delivery Date]],_xlfn.XLOOKUP(GZ$1,$BH$2:$BR$2,$BH5:$BR5,0),0) -> 0 | HA5: =IF(HA$2=InputTable[[#This Row],[Delivery Date]],_xlfn.XLOOKUP(HA$1,$BH$2:$BR$2,$BH5:$BR5,0),0) -> 0 | HB5: =IF(HB$2=InputTable[[#This Row],[Delivery Date]],_xlfn.XLOOKUP(HB$1,$BH$2:$BR$2,$BH5:$BR5,0),0) -> 0 | HC5: =IF(HC$2=InputTable[[#This Row],[Delivery Date]],_xlfn.XLOOKUP(HC$1,$BH$2:$BR$2,$BH5:$BR5,0),0) -> 0 | HD5: =IF(HD$2=InputTable[[#This Row],[Delivery Date]],_xlfn.XLOOKUP(HD$1,$BH$2:$BR$2,$BH5:$BR5,0),0) -> 0 | HF5: =IF(HF$2=InputTable[[#This Row],[Delivery Date]],_xlfn.XLOOKUP(HF$1,$BH$2:$BR$2,$BH5:$BR5,0),0) -> #REF! | HG5: =IF(HG$2=InputTable[[#This Row],[Delivery Date]],_xlfn.XLOOKUP(HG$1,$BH$2:$BR$2,$BH5:$BR5,0),0) -> 0 | HH5: =IF(HH$2=InputTable[[#This Row],[Delivery Date]],_xlfn.XLOOKUP(HH$1,$BH$2:$BR$2,$BH5:$BR5,0),0) -> 0 | HI5: =IF(HI$2=InputTable[[#This Row],[Delivery Date]],_xlfn.XLOOKUP(HI$1,$BH$2:$BR$2,$BH5:$BR5,0),0) -> 0 | HJ5: =IF(HJ$2=InputTable[[#This Row],[Delivery Date]],_xlfn.XLOOKUP(HJ$1,$BH$2:$BR$2,$BH5:$BR5,0),0) -> 0 | HK5: =IF(HK$2=InputTable[[#This Row],[Delivery Date]],_xlfn.XLOOKUP(HK$1,$BH$2:$BR$2,$BH5:$BR5,0),0) -> 0 | HL5: =IF(HL$2=InputTable[[#This Row],[Delivery Date]],_xlfn.XLOOKUP(HL$1,$BH$2:$BR$2,$BH5:$BR5,0),0) -> 0 | HM5: =IF(HM$2=InputTable[[#This Row],[Delivery Date]],_xlfn.XLOOKUP(HM$1,$BH$2:$BR$2,$BH5:$BR5,0),0) -> 0 | HN5: =IF(HN$2=InputTable[[#This Row],[Delivery Date]],_xlfn.XLOOKUP(HN$1,$BH$2:$BR$2,$BH5:$BR5,0),0) -> 0 | HP5: =IF(HP$2=InputTable[[#This Row],[Delivery Date]],_xlfn.XLOOKUP(HP$1,$BH$2:$BR$2,$BH5:$BR5,0),0) -> #REF! | HQ5: =IF(HQ$2=InputTable[[#This Row],[Delivery Date]],_xlfn.XLOOKUP(HQ$1,$BH$2:$BR$2,$BH5:$BR5,0),0) -> 0 | HR5: =IF(HR$2=InputTable[[#This Row],[Delivery Date]],_xlfn.XLOOKUP(HR$1,$BH$2:$BR$2,$BH5:$BR5,0),0) -> 0 | HS5: =IF(HS$2=InputTable[[#This Row],[Delivery Date]],_xlfn.XLOOKUP(HS$1,$BH$2:$BR$2,$BH5:$BR5,0),0) -> 0 | HT5: =IF(HT$2=InputTable[[#This Row],[Delivery Date]],_xlfn.XLOOKUP(HT$1,$BH$2:$BR$2,$BH5:$BR5,0),0) -> 0 | HU5: =IF(HU$2=InputTable[[#This Row],[Delivery Date]],_xlfn.XLOOKUP(HU$1,$BH$2:$BR$2,$BH5:$BR5,0),0) -> 0 | HV5: =IF(HV$2=InputTable[[#This Row],[Delivery Date]],_xlfn.XLOOKUP(HV$1,$BH$2:$BR$2,$BH5:$BR5,0),0) -> 0 | HW5: =IF(HW$2=InputTable[[#This Row],[Delivery Date]],_xlfn.XLOOKUP(HW$1,$BH$2:$BR$2,$BH5:$BR5,0),0) -> 0 | HX5: =IF(HX$2=InputTable[[#This Row],[Delivery Date]],_xlfn.XLOOKUP(HX$1,$BH$2:$BR$2,$BH5:$BR5,0),0) -> 0 | HZ5: =IF(HZ$2=InputTable[[#This Row],[Delivery Date]],_xlfn.XLOOKUP(HZ$1,$BH$2:$BR$2,$BH5:$BR5,0),0) -> #REF! | IA5: =IF(IA$2=InputTable[[#This Row],[Delivery Date]],_xlfn.XLOOKUP(IA$1,$BH$2:$BR$2,$BH5:$BR5,0),0) -> 0 | IB5: =IF(IB$2=InputTable[[#This Row],[Delivery Date]],_xlfn.XLOOKUP(IB$1,$BH$2:$BR$2,$BH5:$BR5,0),0) -> 0 | IC5: =IF(IC$2=InputTable[[#This Row],[Delivery Date]],_xlfn.XLOOKUP(IC$1,$BH$2:$BR$2,$BH5:$BR5,0),0) -> 0 | ID5: =IF(ID$2=InputTable[[#This Row],[Delivery Date]],_xlfn.XLOOKUP(ID$1,$BH$2:$BR$2,$BH5:$BR5,0),0) -> 0 | IE5: =IF(IE$2=InputTable[[#This Row],[Delivery Date]],_xlfn.XLOOKUP(IE$1,$BH$2:$BR$2,$BH5:$BR5,0),0) -> 0 | IF5: =IF(IF$2=InputTable[[#This Row],[Delivery Date]],_xlfn.XLOOKUP(IF$1,$BH$2:$BR$2,$BH5:$BR5,0),0) -> 0 | IG5: =IF(IG$2=InputTable[[#This Row],[Delivery Date]],_xlfn.XLOOKUP(IG$1,$BH$2:$BR$2,$BH5:$BR5,0),0) -> 0 | IH5: =IF(IH$2=InputTable[[#This Row],[Delivery Date]],_xlfn.XLOOKUP(IH$1,$BH$2:$BR$2,$BH5:$BR5,0),0) -> 0 | IJ5: =IF(IJ$2=InputTable[[#This Row],[Delivery Date]],_xlfn.XLOOKUP(IJ$1,$BH$2:$BR$2,$BH5:$BR5,0),0) -> #REF! | IK5: =IF(IK$2=InputTable[[#This Row],[Delivery Date]],_xlfn.XLOOKUP(IK$1,$BH$2:$BR$2,$BH5:$BR5,0),0) -> 0 | IL5: =IF(IL$2=InputTable[[#This Row],[Delivery Date]],_xlfn.XLOOKUP(IL$1,$BH$2:$BR$2,$BH5:$BR5,0),0) -> 0 | IM5: =IF(IM$2=InputTable[[#This Row],[Delivery Date]],_xlfn.XLOOKUP(IM$1,$BH$2:$BR$2,$BH5:$BR5,0),0) -> 0 | IN5: =IF(IN$2=InputTable[[#This Row],[Delivery Date]],_xlfn.XLOOKUP(IN$1,$BH$2:$BR$2,$BH5:$BR5,0),0) -> 0 | IO5: =IF(IO$2=InputTable[[#This Row],[Delivery Date]],_xlfn.XLOOKUP(IO$1,$BH$2:$BR$2,$BH5:$BR5,0),0) -> 0 | IP5: =IF(IP$2=InputTable[[#This Row],[Delivery Date]],_xlfn.XLOOKUP(IP$1,$BH$2:$BR$2,$BH5:$BR5,0),0) -> 0 | IQ5: =IF(IQ$2=InputTable[[#This Row],[Delivery Date]],_xlfn.XLOOKUP(IQ$1,$BH$2:$BR$2,$BH5:$BR5,0),0) -> 0 | IR5: =IF(IR$2=InputTable[[#This Row],[Delivery Date]],_xlfn.XLOOKUP(IR$1,$BH$2:$BR$2,$BH5:$BR5,0),0) -> 0 | IT5: =IF(IT$2=InputTable[[#This Row],[Delivery Date]],_xlfn.XLOOKUP(IT$1,$BH$2:$BR$2,$BH5:$BR5,0),0) -> #REF! | IU5: =IF(IU$2=InputTable[[#This Row],[Delivery Date]],_xlfn.XLOOKUP(IU$1,$BH$2:$BR$2,$BH5:$BR5,0),0) -> 0 | IV5: =IF(IV$2=InputTable[[#This Row],[Delivery Date]],_xlfn.XLOOKUP(IV$1,$BH$2:$BR$2,$BH5:$BR5,0),0) -> 0 | IW5: =IF(IW$2=InputTable[[#This Row],[Delivery Date]],_xlfn.XLOOKUP(IW$1,$BH$2:$BR$2,$BH5:$BR5,0),0) -> 0 | IX5: =IF(IX$2=InputTable[[#This Row],[Delivery Date]],_xlfn.XLOOKUP(IX$1,$BH$2:$BR$2,$BH5:$BR5,0),0) -> 0 | IY5: =IF(IY$2=InputTable[[#This Row],[Delivery Date]],_xlfn.XLOOKUP(IY$1,$BH$2:$BR$2,$BH5:$BR5,0),0) -> 0 | IZ5: =IF(IZ$2=InputTable[[#This Row],[Delivery Date]],_xlfn.XLOOKUP(IZ$1,$BH$2:$BR$2,$BH5:$BR5,0),0) -> 0 | JA5: =IF(JA$2=InputTable[[#This Row],[Delivery Date]],_xlfn.XLOOKUP(JA$1,$BH$2:$BR$2,$BH5:$BR5,0),0) -> 0 | JB5: =IF(JB$2=InputTable[[#This Row],[Delivery Date]],_xlfn.XLOOKUP(JB$1,$BH$2:$BR$2,$BH5:$BR5,0),0) -> 0 | JD5: =IF(JD$2=InputTable[[#This Row],[Delivery Date]],_xlfn.XLOOKUP(JD$1,$BH$2:$BR$2,$BH5:$BR5,0),0) -> #REF! | JE5: =IF(JE$2=InputTable[[#This Row],[Delivery Date]],_xlfn.XLOOKUP(JE$1,$BH$2:$BR$2,$BH5:$BR5,0),0) -> 0 | JF5: =IF(JF$2=InputTable[[#This Row],[Delivery Date]],_xlfn.XLOOKUP(JF$1,$BH$2:$BR$2,$BH5:$BR5,0),0) -> 0 | JG5: =IF(JG$2=InputTable[[#This Row],[Delivery Date]],_xlfn.XLOOKUP(JG$1,$BH$2:$BR$2,$BH5:$BR5,0),0) -> 0 | JH5: =IF(JH$2=InputTable[[#This Row],[Delivery Date]],_xlfn.XLOOKUP(JH$1,$BH$2:$BR$2,$BH5:$BR5,0),0) -> 0 | JI5: =IF(JI$2=InputTable[[#This Row],[Delivery Date]],_xlfn.XLOOKUP(JI$1,$BH$2:$BR$2,$BH5:$BR5,0),0) -> 0 | JJ5: =IF(JJ$2=InputTable[[#This Row],[Delivery Date]],_xlfn.XLOOKUP(JJ$1,$BH$2:$BR$2,$BH5:$BR5,0),0) -> 0 | JK5: =IF(JK$2=InputTable[[#This Row],[Delivery Date]],_xlfn.XLOOKUP(JK$1,$BH$2:$BR$2,$BH5:$BR5,0),0) -> 0 | JL5: =IF(JL$2=InputTable[[#This Row],[Delivery Date]],_xlfn.XLOOKUP(JL$1,$BH$2:$BR$2,$BH5:$BR5,0),0) -> 0 | JN5: =IF(JN$2=InputTable[[#This Row],[Delivery Date]],_xlfn.XLOOKUP(JN$1,$BH$2:$BR$2,$BH5:$BR5,0),0) -> #REF! | JO5: =IF(JO$2=InputTable[[#This Row],[Delivery Date]],_xlfn.XLOOKUP(JO$1,$BH$2:$BR$2,$BH5:$BR5,0),0) -> 0 | JP5: =IF(JP$2=InputTable[[#This Row],[Delivery Date]],_xlfn.XLOOKUP(JP$1,$BH$2:$BR$2,$BH5:$BR5,0),0) -> 0 | JQ5: =IF(JQ$2=InputTable[[#This Row],[Delivery Date]],_xlfn.XLOOKUP(JQ$1,$BH$2:$BR$2,$BH5:$BR5,0),0) -> 0 | JR5: =IF(JR$2=InputTable[[#This Row],[Delivery Date]],_xlfn.XLOOKUP(JR$1,$BH$2:$BR$2,$BH5:$BR5,0),0) -> 0 | JS5: =IF(JS$2=InputTable[[#This Row],[Delivery Date]],_xlfn.XLOOKUP(JS$1,$BH$2:$BR$2,$BH5:$BR5,0),0) -> 0 | JT5: =IF(JT$2=InputTable[[#This Row],[Delivery Date]],_xlfn.XLOOKUP(JT$1,$BH$2:$BR$2,$BH5:$BR5,0),0) -> 0 | JU5: =IF(JU$2=InputTable[[#This Row],[Delivery Date]],_xlfn.XLOOKUP(JU$1,$BH$2:$BR$2,$BH5:$BR5,0),0) -> 0 | JV5: =IF(JV$2=InputTable[[#This Row],[Delivery Date]],_xlfn.XLOOKUP(JV$1,$BH$2:$BR$2,$BH5:$BR5,0),0) -> 0 | JX5: =IF(JX$2=InputTable[[#This Row],[Delivery Date]],_xlfn.XLOOKUP(JX$1,$BH$2:$BR$2,$BH5:$BR5,0),0) -> #REF! | JY5: =IF(JY$2=InputTable[[#This Row],[Delivery Date]],_xlfn.XLOOKUP(JY$1,$BH$2:$BR$2,$BH5:$BR5,0),0) -> 0 | JZ5: =IF(JZ$2=InputTable[[#This Row],[Delivery Date]],_xlfn.XLOOKUP(JZ$1,$BH$2:$BR$2,$BH5:$BR5,0),0) -> 0 | KA5: =IF(KA$2=InputTable[[#This Row],[Delivery Date]],_xlfn.XLOOKUP(KA$1,$BH$2:$BR$2,$BH5:$BR5,0),0) -> 0 | KB5: =IF(KB$2=InputTable[[#This Row],[Delivery Date]],_xlfn.XLOOKUP(KB$1,$BH$2:$BR$2,$BH5:$BR5,0),0) -> 0 | KC5: =IF(KC$2=InputTable[[#This Row],[Delivery Date]],_xlfn.XLOOKUP(KC$1,$BH$2:$BR$2,$BH5:$BR5,0),0) -> 0 | KD5: =IF(KD$2=InputTable[[#This Row],[Delivery Date]],_xlfn.XLOOKUP(KD$1,$BH$2:$BR$2,$BH5:$BR5,0),0) -> 0 | KE5: =IF(KE$2=InputTable[[#This Row],[Delivery Date]],_xlfn.XLOOKUP(KE$1,$BH$2:$BR$2,$BH5:$BR5,0),0) -> 0 | KF5: =IF(KF$2=InputTable[[#This Row],[Delivery Date]],_xlfn.XLOOKUP(KF$1,$BH$2:$BR$2,$BH5:$BR5,0),0) -> 0
B6: Stopped in 2025 | C6: DIGITAL TECH | D6: ISPRJ-100 | E6: Group sales automation | F6: COMMERCIAL | G6: 2025 Q1 | I6: 2025 Q4 | K6: =VLOOKUP((InputTable[[#This Row],[Starting Date]]& " - " &InputTable[[#This Row],[Delivery Date]]),'System List'!$F$40:$H$83,2,FALSE) -> #N/A | L6: =VLOOKUP(InputTable[[#This Row],[Duration]],Duration,2,FALSE) -> #N/A | M6: yes | R6: L | T6: {=SUM( _xlfn.XLOOKUP(InputTable[[#This Row],[Safety]:[Regulatory]], 'System List'!$F$4:$F$7, 'System List'!$G$4:$G$7, 0) * _xlfn.XLOOKUP(InputTable[[#Headers],[Safety]:[Regulatory]], 'System List'!$Y$4:$Y$10, 'System List'!$Z$4:$Z$10, 0) )} -> 1.5 | AD6: =COUNTA(InputTable[[#This Row],[CORPHRFIN]:[SALES]]) -> 0 | AE6: {=SUM( _xlfn.XLOOKUP(InputTable[[#This Row],[CORPHRFIN]:[SALES]],'System List'!$F$4:$F$7,'System List'!$H$4:$H$7,0))} -> 0 | AR6: {=SUM( _xlfn.XLOOKUP(InputTable[[#This Row],[Impact on - CIAL]:[Impact on - STRAT]],'System List'!$F$4:$F$7,'System List'!$H$4:$H$7,0))} -> 0 | AS6: =VLOOKUP(InputTable[[#This Row],[Duration]],Duration,2,FALSE)+InputTable[[#This Row],[Resource Score]] -> #N/A | AT6: =(( VLOOKUP(InputTable[[#This Row],[Duration]],'System List'!$J$5:$K$10,2,FALSE)*VLOOKUP(InputTable[[#Headers],[Duration]],'System List'!$V$5:$W$8,2,FALSE) + VLOOKUP(InputTable[[#This Row],[Number of Team Involved]],'System List'!$M$5:$N$13,2,FALSE)*VLOOKUP(InputTable[[#Headers],[Number of Team Involved]],'System List'!$V$5:$W$8,2,FALSE) + VLOOKUP(InputTable[[#This Row],[Resource Score]],Resource_Score,2,FALSE)*VLOOKUP(InputTable[[#Headers],[Resource Score]],'System List'!$V$5:$W$8,2,FALSE) + VLOOKUP(InputTable[[#This Row],[CHANGE Impact Score]],CHANGE_Impact_Score,2,FALSE)*VLOOKUP(InputTable[[#Headers],[CHANGE Impact Score]],'System List'!$V$5:$W$8,2,FALSE)) * 100) / 13 -> #N/A | AU6: =InputTable[[#This Row],[Value Score]]/InputTable[[#This Row],[EFFORT SCORE]]*100 -> #N/A | AW6: Xavier ROMANET | AZ6: 0 | BA6: 0 | BH6: =IFERROR(VLOOKUP(InputTable[[#This Row],[Impact on - CIAL]],'System List'!$F$4:$H$7,3,FALSE),0) -> 0 | BI6: =IFERROR(VLOOKUP(InputTable[[#This Row],[Impact on - COM]],'System List'!$F$4:$H$7,3,FALSE),0) -> 0 | BJ6: =IFERROR(VLOOKUP(InputTable[[#This Row],[Impact on - FIN]],'System List'!$F$4:$H$7,3,FALSE),0) -> 0 | BK6: =IFERROR(VLOOKUP(InputTable[[#This Row],[Impact on - GEN SEC]],'System List'!$F$4:$H$7,3,FALSE),0) -> 0 | BL6: =IFERROR(VLOOKUP(InputTable[[#This Row],[Impact on - HR]],'System List'!$F$4:$H$7,3,FALSE),0) -> 0 | BM6: =IFERROR(VLOOKUP(InputTable[[#This Row],[Impact on - IS]],'System List'!$F$4:$H$7,3,FALSE),0) -> 0 | BN6: =IFERROR(VLOOKUP(InputTable[[#This Row],[Impact on - OPS]],'System List'!$F$4:$H$7,3,FALSE),0) -> 0 | BO6: =IFERROR(VLOOKUP(InputTable[[#This Row],[Impact on - ROLL STOCK]],'System List'!$F$4:$H$7,3,FALSE),0) -> 0 | BP6: =IFERROR(VLOOKUP(InputTable[[#This Row],[Impact on - SAFETY]],'System List'!$F$4:$H$7,3,FALSE),0) -> 0 | BQ6: =IFERROR(VLOOKUP(InputTable[[#This Row],[Impact on - STATION]],'System List'!$F$4:$H$7,3,FALSE),0) -> 0 | BR6: =IFERROR(VLOOKUP(InputTable[[#This Row],[Impact on - STRAT]],'System List'!$F$4:$H$7,3,FALSE),0) -> 0 | BT6: =IFERROR(VLOOKUP(InputTable[[#This Row],[CORPHRFIN]],'System List'!$F$4:$H$7,3,FALSE),0) -> 0 | BU6: =IFERROR(VLOOKUP(InputTable[[#This Row],[CUST]],'System List'!$F$4:$H$7,3,FALSE),0) -> 0 | BV6: =IFERROR(VLOOKUP(InputTable[[#This Row],[CYBER]],'System List'!$F$4:$H$7,3,FALSE),0) -> 0 | BW6: =IFERROR(VLOOKUP(InputTable[[#This Row],[DATA]],'System List'!$F$4:$H$7,3,FALSE),0) -> 0 | BX6: =IFERROR(VLOOKUP(InputTable[[#This Row],[INFRA]],'System List'!$F$4:$H$7,3,FALSE),0) -> 0 | BY6: =IFERROR(VLOOKUP(InputTable[[#This Row],[OPERATIONS]],'System List'!$F$4:$H$7,3,FALSE),0) -> 0 | BZ6: =IFERROR(VLOOKUP(InputTable[[#This Row],[PMO]],'System List'!$F$4:$H$7,3,FALSE),0) -> 0 | CA6: =IFERROR(VLOOKUP(InputTable[[#This Row],[SALES]],'System List'!$F$4:$H$7,3,FALSE),0) -> 0 | CC6: {=IFERROR( IF( AND( MATCH(InputTable[[#This Row],[Starting Date]],'System List'!$B$5:$B$16,0)<=MATCH(Input!CC$2,'System List'!$B$5:$B$16,0), MATCH(Input!CC$2,'System List'!$B$5:$B$16<=MATCH(InputTable[[#This Row],[Delivery Date]],'System List'!$B$5:$B$16,0))),1,0), )} -> 0 | CD6: {=IFERROR( IF( AND( MATCH(InputTable[[#This Row],[Starting Date]],'System List'!$B$5:$B$16,0)<=MATCH(Input!CD$2,'System List'!$B$5:$B$16,0), MATCH(Input!CD$2,'System List'!$B$5:$B$16<=MATCH(InputTable[[#This Row],[Delivery Date]],'System List'!$B$5:$B$16,0))),1,0), )} -> 0 | CE6: {=IFERROR( IF( AND( MATCH(InputTable[[#This Row],[Starting Date]],'System List'!$B$5:$B$16,0)<=MATCH(Input!CE$2,'System List'!$B$5:$B$16,0), MATCH(Input!CE$2,'System List'!$B$5:$B$16<=MATCH(InputTable[[#This Row],[Delivery Date]],'System List'!$B$5:$B$16,0))),1,0), )} -> 0 | CF6: {=IFERROR( IF( AND( MATCH(InputTable[[#This Row],[Starting Date]],'System List'!$B$5:$B$16,0)<=MATCH(Input!CF$2,'System List'!$B$5:$B$16,0), MATCH(Input!CF$2,'System List'!$B$5:$B$16<=MATCH(InputTable[[#This Row],[Delivery Date]],'System List'!$B$5:$B$16,0))),1,0), )} -> 0 | CG6: {=IFERROR( IF( AND( MATCH(InputTable[[#This Row],[Starting Date]],'System List'!$B$5:$B$16,0)<=MATCH(Input!CG$2,'System List'!$B$5:$B$16,0), MATCH(Input!CG$2,'System List'!$B$5:$B$16<=MATCH(InputTable[[#This Row],[Delivery Date]],'System List'!$B$5:$B$16,0))),1,0), )} -> 0 | CH6: {=IFERROR( IF( AND( MATCH(InputTable[[#This Row],[Starting Date]],'System List'!$B$5:$B$16,0)<=MATCH(Input!CH$2,'System List'!$B$5:$B$16,0), MATCH(Input!CH$2,'System List'!$B$5:$B$16<=MATCH(InputTable[[#This Row],[Delivery Date]],'System List'!$B$5:$B$16,0))),1,0), )} -> 0 | CI6: {=IFERROR( IF( AND( MATCH(InputTable[[#This Row],[Starting Date]],'System List'!$B$5:$B$16,0)<=MATCH(Input!CI$2,'System List'!$B$5:$B$16,0), MATCH(Input!CI$2,'System List'!$B$5:$B$16<=MATCH(InputTable[[#This Row],[Delivery Date]],'System List'!$B$5:$B$16,0))),1,0), )} -> 0 | CJ6: {=IFERROR( IF( AND( MATCH(InputTable[[#This Row],[Starting Date]],'System List'!$B$5:$B$16,0)<=MATCH(Input!CJ$2,'System List'!$B$5:$B$16,0), MATCH(Input!CJ$2,'System List'!$B$5:$B$16<=MATCH(InputTable[[#This Row],[Delivery Date]],'System List'!$B$5:$B$16,0))),1,0), )} -> 0 | CK6: {=IFERROR( IF( AND( MATCH(InputTable[[#This Row],[Starting Date]],'System List'!$B$5:$B$16,0)<=MATCH(Input!CK$2,'System List'!$B$5:$B$16,0), MATCH(Input!CK$2,'System List'!$B$5:$B$16<=MATCH(InputTable[[#This Row],[Delivery Date]],'System List'!$B$5:$B$16,0))),1,0), )} -> 0 | CN6: =IFERROR( IF(AND( MATCH(InputTable[[#This Row],[Starting Date]],'System List'!$B$5:$B$16,0)<=MATCH(CN$2,'System List'!$B$5:$B$16,0), MATCH(CN$2,'System List'!$B$5:$B$16,0)<=MATCH(InputTable[[#This Row],[Delivery Date]],'System List'!$B$5:$B$16,0)),1,0),0) -> 0 | CO6: =IFERROR( IF(AND( MATCH(InputTable[[#This Row],[Starting Date]],'System List'!$B$5:$B$16,0)<=MATCH(CO$2,'System List'!$B$5:$B$16,0), MATCH(CO$2,'System List'!$B$5:$B$16,0)<=MATCH(InputTable[[#This Row],[Delivery Date]],'System List'!$B$5:$B$16,0)),1,0),0) -> 0 | CP6: =IFERROR( IF(AND( MATCH(InputTable[[#This Row],[Starting Date]],'System List'!$B$5:$B$16,0)<=MATCH(CP$2,'System List'!$B$5:$B$16,0), MATCH(CP$2,'System List'!$B$5:$B$16,0)<=MATCH(InputTable[[#This Row],[Delivery Date]],'System List'!$B$5:$B$16,0)),1,0),0) -> 1 | CQ6: =IFERROR( IF(AND( MATCH(InputTable[[#This Row],[Starting Date]],'System List'!$B$5:$B$16,0)<=MATCH(CQ$2,'System List'!$B$5:$B$16,0), MATCH(CQ$2,'System List'!$B$5:$B$16,0)<=MATCH(InputTable[[#This Row],[Delivery Date]],'System List'!$B$5:$B$16,0)),1,0),0) -> 1 | CR6: =IFERROR( IF(AND( MATCH(InputTable[[#This Row],[Starting Date]],'System List'!$B$5:$B$16,0)<=MATCH(CR$2,'System List'!$B$5:$B$16,0), MATCH(CR$2,'System List'!$B$5:$B$16,0)<=MATCH(InputTable[[#This Row],[Delivery Date]],'System List'!$B$5:$B$16,0)),1,0),0) -> 1 | CS6: =IFERROR( IF(AND( MATCH(InputTable[[#This Row],[Starting Date]],'System List'!$B$5:$B$16,0)<=MATCH(CS$2,'System List'!$B$5:$B$16,0), MATCH(CS$2,'System List'!$B$5:$B$16,0)<=MATCH(InputTable[[#This Row],[Delivery Date]],'System List'!$B$5:$B$16,0)),1,0),0) -> 1 | CT6: =IFERROR( IF(AND( MATCH(InputTable[[#This Row],[Starting Date]],'System List'!$B$5:$B$16,0)<=MATCH(CT$2,'System List'!$B$5:$B$16,0), MATCH(CT$2,'System List'!$B$5:$B$16,0)<=MATCH(InputTable[[#This Row],[Delivery Date]],'System List'!$B$5:$B$16,0)),1,0),0) -> 0 | CU6: =IFERROR( IF(AND( MATCH(InputTable[[#This Row],[Starting Date]],'System List'!$B$5:$B$16,0)<=MATCH(CU$2,'System List'!$B$5:$B$16,0), MATCH(CU$2,'System List'!$B$5:$B$16,0)<=MATCH(InputTable[[#This Row],[Delivery Date]],'System List'!$B$5:$B$16,0)),1,0),0) -> 0 | CV6: =IFERROR( IF(AND( MATCH(InputTable[[#This Row],[Starting Date]],'System List'!$B$5:$B$16,0)<=MATCH(CV$2,'System List'!$B$5:$B$16,0), MATCH(CV$2,'System List'!$B$5:$B$16,0)<=MATCH(InputTable[[#This Row],[Delivery Date]],'System List'!$B$5:$B$16,0)),1,0),0) -> 0 | CX6: =CN6*_xlfn.XLOOKUP(CX$1,$BT$2:$CA$2,$BT6:$CA6,0) -> 0 | CY6: =CO6*_xlfn.XLOOKUP(CY$1,$BT$2:$CA$2,$BT6:$CA6,0) -> 0 | CZ6: =CP6*_xlfn.XLOOKUP(CZ$1,$BT$2:$CA$2,$BT6:$CA6,0) -> 0 | DA6: =CQ6*_xlfn.XLOOKUP(DA$1,$BT$2:$CA$2,$BT6:$CA6,0) -> 0 | DB6: =CR6*_xlfn.XLOOKUP(DB$1,$BT$2:$CA$2,$BT6:$CA6,0) -> 0 | DC6: =CS6*_xlfn.XLOOKUP(DC$1,$BT$2:$CA$2,$BT6:$CA6,0) -> 0 | DD6: =CT6*_xlfn.XLOOKUP(DD$1,$BT$2:$CA$2,$BT6:$CA6,0) -> 0 | DE6: =CU6*_xlfn.XLOOKUP(DE$1,$BT$2:$CA$2,$BT6:$CA6,0) -> 0 | DF6: =CV6*_xlfn.XLOOKUP(DF$1,$BT$2:$CA$2,$BT6:$CA6,0) -> 0 | DH6: =$CN6*_xlfn.XLOOKUP(DH$1,$BT$2:$CA$2,$BT6:$CA6,0) -> 0 | DI6: =$CO6*_xlfn.XLOOKUP(DI$1,$BT$2:$CA$2,$BT6:$CA6,0) -> 0 | DJ6: =$CP6*_xlfn.XLOOKUP(DJ$1,$BT$2:$CA$2,$BT6:$CA6,0) -> 0 | DK6: =$CQ6*_xlfn.XLOOKUP(DK$1,$BT$2:$CA$2,$BT6:$CA6,0) -> 0 | DL6: =$CR6*_xlfn.XLOOKUP(DL$1,$BT$2:$CA$2,$BT6:$CA6,0) -> 0 | DM6: =$CS6*_xlfn.XLOOKUP(DM$1,$BT$2:$CA$2,$BT6:$CA6,0) -> 0 | DN6: =$CT6*_xlfn.XLOOKUP(DN$1,$BT$2:$CA$2,$BT6:$CA6,0) -> 0 | DO6: =$CU6*_xlfn.XLOOKUP(DO$1,$BT$2:$CA$2,$BT6:$CA6,0) -> 0 | DP6: =$CV6*_xlfn.XLOOKUP(DP$1,$BT$2:$CA$2,$BT6:$CA6,0) -> 0 | DR6: =$CN6*_xlfn.XLOOKUP(DR$1,$BT$2:$CA$2,$BT6:$CA6,0) -> 0 | DS6: =$CO6*_xlfn.XLOOKUP(DS$1,$BT$2:$CA$2,$BT6:$CA6,0) -> 0 | DT6: =$CP6*_xlfn.XLOOKUP(DT$1,$BT$2:$CA$2,$BT6:$CA6,0) -> 0 | DU6: =$CQ6*_xlfn.XLOOKUP(DU$1,$BT$2:$CA$2,$BT6:$CA6,0) -> 0 | DV6: =$CR6*_xlfn.XLOOKUP(DV$1,$BT$2:$CA$2,$BT6:$CA6,0) -> 0 | DW6: =$CS6*_xlfn.XLOOKUP(DW$1,$BT$2:$CA$2,$BT6:$CA6,0) -> 0 | DX6: =$CT6*_xlfn.XLOOKUP(DX$1,$BT$2:$CA$2,$BT6:$CA6,0) -> 0 | DY6: =$CU6*_xlfn.XLOOKUP(DY$1,$BT$2:$CA$2,$BT6:$CA6,0) -> 0 | DZ6: =$CV6*_xlfn.XLOOKUP(DZ$1,$BT$2:$CA$2,$BT6:$CA6,0) -> 0 | EB6: =$CN6*_xlfn.XLOOKUP(EB$1,$BT$2:$CA$2,$BT6:$CA6,0) -> 0 | EC6: =$CO6*_xlfn.XLOOKUP(EC$1,$BT$2:$CA$2,$BT6:$CA6,0) -> 0 | ED6: =$CP6*_xlfn.XLOOKUP(ED$1,$BT$2:$CA$2,$BT6:$CA6,0) -> 0 | EE6: =$CQ6*_xlfn.XLOOKUP(EE$1,$BT$2:$CA$2,$BT6:$CA6,0) -> 0 | EF6: =$CR6*_xlfn.XLOOKUP(EF$1,$BT$2:$CA$2,$BT6:$CA6,0) -> 0 | EG6: =$CS6*_xlfn.XLOOKUP(EG$1,$BT$2:$CA$2,$BT6:$CA6,0) -> 0 | EH6: =$CT6*_xlfn.XLOOKUP(EH$1,$BT$2:$CA$2,$BT6:$CA6,0) -> 0 | EI6: =$CU6*_xlfn.XLOOKUP(EI$1,$BT$2:$CA$2,$BT6:$CA6,0) -> 0 | EJ6: =$CV6*_xlfn.XLOOKUP(EJ$1,$BT$2:$CA$2,$BT6:$CA6,0) -> 0 | EL6: =$CN6*_xlfn.XLOOKUP(EL$1,$BT$2:$CA$2,$BT6:$CA6,0) -> 0 | EM6: =$CO6*_xlfn.XLOOKUP(EM$1,$BT$2:$CA$2,$BT6:$CA6,0) -> 0 | EN6: =$CP6*_xlfn.XLOOKUP(EN$1,$BT$2:$CA$2,$BT6:$CA6,0) -> 0 | EO6: =$CQ6*_xlfn.XLOOKUP(EO$1,$BT$2:$CA$2,$BT6:$CA6,0) -> 0 | EP6: =$CR6*_xlfn.XLOOKUP(EP$1,$BT$2:$CA$2,$BT6:$CA6,0) -> 0 | EQ6: =$CS6*_xlfn.XLOOKUP(EQ$1,$BT$2:$CA$2,$BT6:$CA6,0) -> 0 | ER6: =$CT6*_xlfn.XLOOKUP(ER$1,$BT$2:$CA$2,$BT6:$CA6,0) -> 0 | ES6: =$CU6*_xlfn.XLOOKUP(ES$1,$BT$2:$CA$2,$BT6:$CA6,0) -> 0 | ET6: =$CV6*_xlfn.XLOOKUP(ET$1,$BT$2:$CA$2,$BT6:$CA6,0) -> 0 | EV6: =$CN6*_xlfn.XLOOKUP(EV$1,$BT$2:$CA$2,$BT6:$CA6,0) -> 0 | EW6: =$CO6*_xlfn.XLOOKUP(EW$1,$BT$2:$CA$2,$BT6:$CA6,0) -> 0 | EX6: =$CP6*_xlfn.XLOOKUP(EX$1,$BT$2:$CA$2,$BT6:$CA6,0) -> 0 | EY6: =$CQ6*_xlfn.XLOOKUP(EY$1,$BT$2:$CA$2,$BT6:$CA6,0) -> 0 | EZ6: =$CR6*_xlfn.XLOOKUP(EZ$1,$BT$2:$CA$2,$BT6:$CA6,0) -> 0 | FA6: =$CS6*_xlfn.XLOOKUP(FA$1,$BT$2:$CA$2,$BT6:$CA6,0) -> 0 | FB6: =$CT6*_xlfn.XLOOKUP(FB$1,$BT$2:$CA$2,$BT6:$CA6,0) -> 0 | FC6: =$CU6*_xlfn.XLOOKUP(FC$1,$BT$2:$CA$2,$BT6:$CA6,0) -> 0 | FD6: =$CV6*_xlfn.XLOOKUP(FD$1,$BT$2:$CA$2,$BT6:$CA6,0) -> 0 | FF6: =$CN6*_xlfn.XLOOKUP(FF$1,$BT$2:$CA$2,$BT6:$CA6,0) -> 0 | FG6: =$CO6*_xlfn.XLOOKUP(FG$1,$BT$2:$CA$2,$BT6:$CA6,0) -> 0 | FH6: =$CP6*_xlfn.XLOOKUP(FH$1,$BT$2:$CA$2,$BT6:$CA6,0) -> 0 | FI6: =$CQ6*_xlfn.XLOOKUP(FI$1,$BT$2:$CA$2,$BT6:$CA6,0) -> 0 | FJ6: =$CR6*_xlfn.XLOOKUP(FJ$1,$BT$2:$CA$2,$BT6:$CA6,0) -> 0 | FK6: =$CS6*_xlfn.XLOOKUP(FK$1,$BT$2:$CA$2,$BT6:$CA6,0) -> 0 | FL6: =$CT6*_xlfn.XLOOKUP(FL$1,$BT$2:$CA$2,$BT6:$CA6,0) -> 0 | FM6: =$CU6*_xlfn.XLOOKUP(FM$1,$BT$2:$CA$2,$BT6:$CA6,0) -> 0 | FN6: =$CV6*_xlfn.XLOOKUP(FN$1,$BT$2:$CA$2,$BT6:$CA6,0) -> 0 | FP6: =$CN6*_xlfn.XLOOKUP(FP$1,$BT$2:$CA$2,$BT6:$CA6,0) -> #REF! | FQ6: =$CO6*_xlfn.XLOOKUP(FQ$1,$BT$2:$CA$2,$BT6:$CA6,0) -> #REF! | FR6: =$CP6*_xlfn.XLOOKUP(FR$1,$BT$2:$CA$2,$BT6:$CA6,0) -> #REF! | FS6: =$CQ6*_xlfn.XLOOKUP(FS$1,$BT$2:$CA$2,$BT6:$CA6,0) -> #REF! | FT6: =$CR6*_xlfn.XLOOKUP(FT$1,$BT$2:$CA$2,$BT6:$CA6,0) -> #REF! | FU6: =$CS6*_xlfn.XLOOKUP(FU$1,$BT$2:$CA$2,$BT6:$CA6,0) -> #REF! | FV6: =$CT6*_xlfn.XLOOKUP(FV$1,$BT$2:$CA$2,$BT6:$CA6,0) -> #REF! | FW6: =$CU6*_xlfn.XLOOKUP(FW$1,$BT$2:$CA$2,$BT6:$CA6,0) -> #REF! | FX6: =$CV6*_xlfn.XLOOKUP(FX$1,$BT$2:$CA$2,$BT6:$CA6,0) -> #REF! | GB6: =IF(GB$2=InputTable[[#This Row],[Delivery Date]],_xlfn.XLOOKUP(GB$1,$BH$2:$BR$2,$BH6:$BR6,0),0) -> #REF! | GC6: =IF(GC$2=InputTable[[#This Row],[Delivery Date]],_xlfn.XLOOKUP(GC$1,$BH$2:$BR$2,$BH6:$BR6,0),0) -> 0 | GD6: =IF(GD$2=InputTable[[#This Row],[Delivery Date]],_xlfn.XLOOKUP(GD$1,$BH$2:$BR$2,$BH6:$BR6,0),0) -> 0 | GE6: =IF(GE$2=InputTable[[#This Row],[Delivery Date]],_xlfn.XLOOKUP(GE$1,$BH$2:$BR$2,$BH6:$BR6,0),0) -> 0 | GF6: =IF(GF$2=InputTable[[#This Row],[Delivery Date]],_xlfn.XLOOKUP(GF$1,$BH$2:$BR$2,$BH6:$BR6,0),0) -> 0 | GG6: =IF(GG$2=InputTable[[#This Row],[Delivery Date]],_xlfn.XLOOKUP(GG$1,$BH$2:$BR$2,$BH6:$BR6,0),0) -> 0 | GH6: =IF(GH$2=InputTable[[#This Row],[Delivery Date]],_xlfn.XLOOKUP(GH$1,$BH$2:$BR$2,$BH6:$BR6,0),0) -> 0 | GI6: =IF(GI$2=InputTable[[#This Row],[Delivery Date]],_xlfn.XLOOKUP(GI$1,$BH$2:$BR$2,$BH6:$BR6,0),0) -> 0 | GJ6: =IF(GJ$2=InputTable[[#This Row],[Delivery Date]],_xlfn.XLOOKUP(GJ$1,$BH$2:$BR$2,$BH6:$BR6,0),0) -> 0 | GL6: =IF(GL$2=InputTable[[#This Row],[Delivery Date]],_xlfn.XLOOKUP(GL$1,$BH$2:$BR$2,$BH6:$BR6,0),0) -> #REF! | GM6: =IF(GM$2=InputTable[[#This Row],[Delivery Date]],_xlfn.XLOOKUP(GM$1,$BH$2:$BR$2,$BH6:$BR6,0),0) -> 0 | GN6: =IF(GN$2=InputTable[[#This Row],[Delivery Date]],_xlfn.XLOOKUP(GN$1,$BH$2:$BR$2,$BH6:$BR6,0),0) -> 0 | GO6: =IF(GO$2=InputTable[[#This Row],[Delivery Date]],_xlfn.XLOOKUP(GO$1,$BH$2:$BR$2,$BH6:$BR6,0),0) -> 0 | GP6: =IF(GP$2=InputTable[[#This Row],[Delivery Date]],_xlfn.XLOOKUP(GP$1,$BH$2:$BR$2,$BH6:$BR6,0),0) -> 0 | GQ6: =IF(GQ$2=InputTable[[#This Row],[Delivery Date]],_xlfn.XLOOKUP(GQ$1,$BH$2:$BR$2,$BH6:$BR6,0),0) -> 0 | GR6: =IF(GR$2=InputTable[[#This Row],[Delivery Date]],_xlfn.XLOOKUP(GR$1,$BH$2:$BR$2,$BH6:$BR6,0),0) -> 0 | GS6: =IF(GS$2=InputTable[[#This Row],[Delivery Date]],_xlfn.XLOOKUP(GS$1,$BH$2:$BR$2,$BH6:$BR6,0),0) -> 0 | GT6: =IF(GT$2=InputTable[[#This Row],[Delivery Date]],_xlfn.XLOOKUP(GT$1,$BH$2:$BR$2,$BH6:$BR6,0),0) -> 0 | GV6: =IF(GV$2=InputTable[[#This Row],[Delivery Date]],_xlfn.XLOOKUP(GV$1,$BH$2:$BR$2,$BH6:$BR6,0),0) -> #REF! | GW6: =IF(GW$2=InputTable[[#This Row],[Delivery Date]],_xlfn.XLOOKUP(GW$1,$BH$2:$BR$2,$BH6:$BR6,0),0) -> 0 | GX6: =IF(GX$2=InputTable[[#This Row],[Delivery Date]],_xlfn.XLOOKUP(GX$1,$BH$2:$BR$2,$BH6:$BR6,0),0) -> 0 | GY6: =IF(GY$2=InputTable[[#This Row],[Delivery Date]],_xlfn.XLOOKUP(GY$1,$BH$2:$BR$2,$BH6:$BR6,0),0) -> 0 | GZ6: =IF(GZ$2=InputTable[[#This Row],[Delivery Date]],_xlfn.XLOOKUP(GZ$1,$BH$2:$BR$2,$BH6:$BR6,0),0) -> 0 | HA6: =IF(HA$2=InputTable[[#This Row],[Delivery Date]],_xlfn.XLOOKUP(HA$1,$BH$2:$BR$2,$BH6:$BR6,0),0) -> 0 | HB6: =IF(HB$2=InputTable[[#This Row],[Delivery Date]],_xlfn.XLOOKUP(HB$1,$BH$2:$BR$2,$BH6:$BR6,0),0) -> 0 | HC6: =IF(HC$2=InputTable[[#This Row],[Delivery Date]],_xlfn.XLOOKUP(HC$1,$BH$2:$BR$2,$BH6:$BR6,0),0) -> 0 | HD6: =IF(HD$2=InputTable[[#This Row],[Delivery Date]],_xlfn.XLOOKUP(HD$1,$BH$2:$BR$2,$BH6:$BR6,0),0) -> 0 | HF6: =IF(HF$2=InputTable[[#This Row],[Delivery Date]],_xlfn.XLOOKUP(HF$1,$BH$2:$BR$2,$BH6:$BR6,0),0) -> #REF! | HG6: =IF(HG$2=InputTable[[#This Row],[Delivery Date]],_xlfn.XLOOKUP(HG$1,$BH$2:$BR$2,$BH6:$BR6,0),0) -> 0 | HH6: =IF(HH$2=InputTable[[#This Row],[Delivery Date]],_xlfn.XLOOKUP(HH$1,$BH$2:$BR$2,$BH6:$BR6,0),0) -> 0 | HI6: =IF(HI$2=InputTable[[#This Row],[Delivery Date]],_xlfn.XLOOKUP(HI$1,$BH$2:$BR$2,$BH6:$BR6,0),0) -> 0 | HJ6: =IF(HJ$2=InputTable[[#This Row],[Delivery Date]],_xlfn.XLOOKUP(HJ$1,$BH$2:$BR$2,$BH6:$BR6,0),0) -> 0 | HK6: =IF(HK$2=InputTable[[#This Row],[Delivery Date]],_xlfn.XLOOKUP(HK$1,$BH$2:$BR$2,$BH6:$BR6,0),0) -> 0 | HL6: =IF(HL$2=InputTable[[#This Row],[Delivery Date]],_xlfn.XLOOKUP(HL$1,$BH$2:$BR$2,$BH6:$BR6,0),0) -> 0 | HM6: =IF(HM$2=InputTable[[#This Row],[Delivery Date]],_xlfn.XLOOKUP(HM$1,$BH$2:$BR$2,$BH6:$BR6,0),0) -> 0 | HN6: =IF(HN$2=InputTable[[#This Row],[Delivery Date]],_xlfn.XLOOKUP(HN$1,$BH$2:$BR$2,$BH6:$BR6,0),0) -> 0 | HP6: =IF(HP$2=InputTable[[#This Row],[Delivery Date]],_xlfn.XLOOKUP(HP$1,$BH$2:$BR$2,$BH6:$BR6,0),0) -> #REF! | HQ6: =IF(HQ$2=InputTable[[#This Row],[Delivery Date]],_xlfn.XLOOKUP(HQ$1,$BH$2:$BR$2,$BH6:$BR6,0),0) -> 0 | HR6: =IF(HR$2=InputTable[[#This Row],[Delivery Date]],_xlfn.XLOOKUP(HR$1,$BH$2:$BR$2,$BH6:$BR6,0),0) -> 0 | HS6: =IF(HS$2=InputTable[[#This Row],[Delivery Date]],_xlfn.XLOOKUP(HS$1,$BH$2:$BR$2,$BH6:$BR6,0),0) -> 0 | HT6: =IF(HT$2=InputTable[[#This Row],[Delivery Date]],_xlfn.XLOOKUP(HT$1,$BH$2:$BR$2,$BH6:$BR6,0),0) -> 0 | HU6: =IF(HU$2=InputTable[[#This Row],[Delivery Date]],_xlfn.XLOOKUP(HU$1,$BH$2:$BR$2,$BH6:$BR6,0),0) -> 0 | HV6: =IF(HV$2=InputTable[[#This Row],[Delivery Date]],_xlfn.XLOOKUP(HV$1,$BH$2:$BR$2,$BH6:$BR6,0),0) -> 0 | HW6: =IF(HW$2=InputTable[[#This Row],[Delivery Date]],_xlfn.XLOOKUP(HW$1,$BH$2:$BR$2,$BH6:$BR6,0),0) -> 0 | HX6: =IF(HX$2=InputTable[[#This Row],[Delivery Date]],_xlfn.XLOOKUP(HX$1,$BH$2:$BR$2,$BH6:$BR6,0),0) -> 0 | HZ6: =IF(HZ$2=InputTable[[#This Row],[Delivery Date]],_xlfn.XLOOKUP(HZ$1,$BH$2:$BR$2,$BH6:$BR6,0),0) -> #REF! | IA6: =IF(IA$2=InputTable[[#This Row],[Delivery Date]],_xlfn.XLOOKUP(IA$1,$BH$2:$BR$2,$BH6:$BR6,0),0) -> 0 | IB6: =IF(IB$2=InputTable[[#This Row],[Delivery Date]],_xlfn.XLOOKUP(IB$1,$BH$2:$BR$2,$BH6:$BR6,0),0) -> 0 | IC6: =IF(IC$2=InputTable[[#This Row],[Delivery Date]],_xlfn.XLOOKUP(IC$1,$BH$2:$BR$2,$BH6:$BR6,0),0) -> 0 | ID6: =IF(ID$2=InputTable[[#This Row],[Delivery Date]],_xlfn.XLOOKUP(ID$1,$BH$2:$BR$2,$BH6:$BR6,0),0) -> 0 | IE6: =IF(IE$2=InputTable[[#This Row],[Delivery Date]],_xlfn.XLOOKUP(IE$1,$BH$2:$BR$2,$BH6:$BR6,0),0) -> 0 | IF6: =IF(IF$2=InputTable[[#This Row],[Delivery Date]],_xlfn.XLOOKUP(IF$1,$BH$2:$BR$2,$BH6:$BR6,0),0) -> 0 | IG6: =IF(IG$2=InputTable[[#This Row],[Delivery Date]],_xlfn.XLOOKUP(IG$1,$BH$2:$BR$2,$BH6:$BR6,0),0) -> 0 | IH6: =IF(IH$2=InputTable[[#This Row],[Delivery Date]],_xlfn.XLOOKUP(IH$1,$BH$2:$BR$2,$BH6:$BR6,0),0) -> 0 | IJ6: =IF(IJ$2=InputTable[[#This Row],[Delivery Date]],_xlfn.XLOOKUP(IJ$1,$BH$2:$BR$2,$BH6:$BR6,0),0) -> #REF! | IK6: =IF(IK$2=InputTable[[#This Row],[Delivery Date]],_xlfn.XLOOKUP(IK$1,$BH$2:$BR$2,$BH6:$BR6,0),0) -> 0 | IL6: =IF(IL$2=InputTable[[#This Row],[Delivery Date]],_xlfn.XLOOKUP(IL$1,$BH$2:$BR$2,$BH6:$BR6,0),0) -> 0 | IM6: =IF(IM$2=InputTable[[#This Row],[Delivery Date]],_xlfn.XLOOKUP(IM$1,$BH$2:$BR$2,$BH6:$BR6,0),0) -> 0 | IN6: =IF(IN$2=InputTable[[#This Row],[Delivery Date]],_xlfn.XLOOKUP(IN$1,$BH$2:$BR$2,$BH6:$BR6,0),0) -> 0 | IO6: =IF(IO$2=InputTable[[#This Row],[Delivery Date]],_xlfn.XLOOKUP(IO$1,$BH$2:$BR$2,$BH6:$BR6,0),0) -> 0 | IP6: =IF(IP$2=InputTable[[#This Row],[Delivery Date]],_xlfn.XLOOKUP(IP$1,$BH$2:$BR$2,$BH6:$BR6,0),0) -> 0 | IQ6: =IF(IQ$2=InputTable[[#This Row],[Delivery Date]],_xlfn.XLOOKUP(IQ$1,$BH$2:$BR$2,$BH6:$BR6,0),0) -> 0 | IR6: =IF(IR$2=InputTable[[#This Row],[Delivery Date]],_xlfn.XLOOKUP(IR$1,$BH$2:$BR$2,$BH6:$BR6,0),0) -> 0 | IT6: =IF(IT$2=InputTable[[#This Row],[Delivery Date]],_xlfn.XLOOKUP(IT$1,$BH$2:$BR$2,$BH6:$BR6,0),0) -> #REF! | IU6: =IF(IU$2=InputTable[[#This Row],[Delivery Date]],_xlfn.XLOOKUP(IU$1,$BH$2:$BR$2,$BH6:$BR6,0),0) -> 0 | IV6: =IF(IV$2=InputTable[[#This Row],[Delivery Date]],_xlfn.XLOOKUP(IV$1,$BH$2:$BR$2,$BH6:$BR6,0),0) -> 0 | IW6: =IF(IW$2=InputTable[[#This Row],[Delivery Date]],_xlfn.XLOOKUP(IW$1,$BH$2:$BR$2,$BH6:$BR6,0),0) -> 0 | IX6: =IF(IX$2=InputTable[[#This Row],[Delivery Date]],_xlfn.XLOOKUP(IX$1,$BH$2:$BR$2,$BH6:$BR6,0),0) -> 0 | IY6: =IF(IY$2=InputTable[[#This Row],[Delivery Date]],_xlfn.XLOOKUP(IY$1,$BH$2:$BR$2,$BH6:$BR6,0),0) -> 0 | IZ6: =IF(IZ$2=InputTable[[#This Row],[Delivery Date]],_xlfn.XLOOKUP(IZ$1,$BH$2:$BR$2,$BH6:$BR6,0),0) -> 0 | JA6: =IF(JA$2=InputTable[[#This Row],[Delivery Date]],_xlfn.XLOOKUP(JA$1,$BH$2:$BR$2,$BH6:$BR6,0),0) -> 0 | JB6: =IF(JB$2=InputTable[[#This Row],[Delivery Date]],_xlfn.XLOOKUP(JB$1,$BH$2:$BR$2,$BH6:$BR6,0),0) -> 0 | JD6: =IF(JD$2=InputTable[[#This Row],[Delivery Date]],_xlfn.XLOOKUP(JD$1,$BH$2:$BR$2,$BH6:$BR6,0),0) -> #REF! | JE6: =IF(JE$2=InputTable[[#This Row],[Delivery Date]],_xlfn.XLOOKUP(JE$1,$BH$2:$BR$2,$BH6:$BR6,0),0) -> 0 | JF6: =IF(JF$2=InputTable[[#This Row],[Delivery Date]],_xlfn.XLOOKUP(JF$1,$BH$2:$BR$2,$BH6:$BR6,0),0) -> 0 | JG6: =IF(JG$2=InputTable[[#This Row],[Delivery Date]],_xlfn.XLOOKUP(JG$1,$BH$2:$BR$2,$BH6:$BR6,0),0) -> 0 | JH6: =IF(JH$2=InputTable[[#This Row],[Delivery Date]],_xlfn.XLOOKUP(JH$1,$BH$2:$BR$2,$BH6:$BR6,0),0) -> 0 | JI6: =IF(JI$2=InputTable[[#This Row],[Delivery Date]],_xlfn.XLOOKUP(JI$1,$BH$2:$BR$2,$BH6:$BR6,0),0) -> 0 | JJ6: =IF(JJ$2=InputTable[[#This Row],[Delivery Date]],_xlfn.XLOOKUP(JJ$1,$BH$2:$BR$2,$BH6:$BR6,0),0) -> 0 | JK6: =IF(JK$2=InputTable[[#This Row],[Delivery Date]],_xlfn.XLOOKUP(JK$1,$BH$2:$BR$2,$BH6:$BR6,0),0) -> 0 | JL6: =IF(JL$2=InputTable[[#This Row],[Delivery Date]],_xlfn.XLOOKUP(JL$1,$BH$2:$BR$2,$BH6:$BR6,0),0) -> 0 | JN6: =IF(JN$2=InputTable[[#This Row],[Delivery Date]],_xlfn.XLOOKUP(JN$1,$BH$2:$BR$2,$BH6:$BR6,0),0) -> #REF! | JO6: =IF(JO$2=InputTable[[#This Row],[Delivery Date]],_xlfn.XLOOKUP(JO$1,$BH$2:$BR$2,$BH6:$BR6,0),0) -> 0 | JP6: =IF(JP$2=InputTable[[#This Row],[Delivery Date]],_xlfn.XLOOKUP(JP$1,$BH$2:$BR$2,$BH6:$BR6,0),0) -> 0 | JQ6: =IF(JQ$2=InputTable[[#This Row],[Delivery Date]],_xlfn.XLOOKUP(JQ$1,$BH$2:$BR$2,$BH6:$BR6,0),0) -> 0 | JR6: =IF(JR$2=InputTable[[#This Row],[Delivery Date]],_xlfn.XLOOKUP(JR$1,$BH$2:$BR$2,$BH6:$BR6,0),0) -> 0 | JS6: =IF(JS$2=InputTable[[#This Row],[Delivery Date]],_xlfn.XLOOKUP(JS$1,$BH$2:$BR$2,$BH6:$BR6,0),0) -> 0 | JT6: =IF(JT$2=InputTable[[#This Row],[Delivery Date]],_xlfn.XLOOKUP(JT$1,$BH$2:$BR$2,$BH6:$BR6,0),0) -> 0 | JU6: =IF(JU$2=InputTable[[#This Row],[Delivery Date]],_xlfn.XLOOKUP(JU$1,$BH$2:$BR$2,$BH6:$BR6,0),0) -> 0 | JV6: =IF(JV$2=InputTable[[#This Row],[Delivery Date]],_xlfn.XLOOKUP(JV$1,$BH$2:$BR$2,$BH6:$BR6,0),0) -> 0 | JX6: =IF(JX$2=InputTable[[#This Row],[Delivery Date]],_xlfn.XLOOKUP(JX$1,$BH$2:$BR$2,$BH6:$BR6,0),0) -> #REF! | JY6: =IF(JY$2=InputTable[[#This Row],[Delivery Date]],_xlfn.XLOOKUP(JY$1,$BH$2:$BR$2,$BH6:$BR6,0),0) -> 0 | JZ6: =IF(JZ$2=InputTable[[#This Row],[Delivery Date]],_xlfn.XLOOKUP(JZ$1,$BH$2:$BR$2,$BH6:$BR6,0),0) -> 0 | KA6: =IF(KA$2=InputTable[[#This Row],[Delivery Date]],_xlfn.XLOOKUP(KA$1,$BH$2:$BR$2,$BH6:$BR6,0),0) -> 0 | KB6: =IF(KB$2=InputTable[[#This Row],[Delivery Date]],_xlfn.XLOOKUP(KB$1,$BH$2:$BR$2,$BH6:$BR6,0),0) -> 0 | KC6: =IF(KC$2=InputTable[[#This Row],[Delivery Date]],_xlfn.XLOOKUP(KC$1,$BH$2:$BR$2,$BH6:$BR6,0),0) -> 0 | KD6: =IF(KD$2=InputTable[[#This Row],[Delivery Date]],_xlfn.XLOOKUP(KD$1,$BH$2:$BR$2,$BH6:$BR6,0),0) -> 0 | KE6: =IF(KE$2=InputTable[[#This Row],[Delivery Date]],_xlfn.XLOOKUP(KE$1,$BH$2:$BR$2,$BH6:$BR6,0),0) -> 0 | KF6: =IF(KF$2=InputTable[[#This Row],[Delivery Date]],_xlfn.XLOOKUP(KF$1,$BH$2:$BR$2,$BH6:$BR6,0),0) -> 0
B7: Stopped in 2025 | C7: DIGITAL TECH | D7: ISPRJ-101 | E7: Loyalty as a currency | F7: COMMERCIAL | G7: 2025 Q1 | I7: 2025 Q4 | K7: =VLOOKUP((InputTable[[#This Row],[Starting Date]]& " - " &InputTable[[#This Row],[Delivery Date]]),'System List'!$F$40:$H$83,2,FALSE) -> #N/A | L7: =VLOOKUP(InputTable[[#This Row],[Duration]],Duration,2,FALSE) -> #N/A | M7: yes | O7: L | T7: {=SUM( _xlfn.XLOOKUP(InputTable[[#This Row],[Safety]:[Regulatory]], 'System List'!$F$4:$F$7, 'System List'!$G$4:$G$7, 0) * _xlfn.XLOOKUP(InputTable[[#Headers],[Safety]:[Regulatory]], 'System List'!$Y$4:$Y$10, 'System List'!$Z$4:$Z$10, 0) )} -> 1 | AD7: =COUNTA(InputTable[[#This Row],[CORPHRFIN]:[SALES]]) -> 0 | AE7: {=SUM( _xlfn.XLOOKUP(InputTable[[#This Row],[CORPHRFIN]:[SALES]],'System List'!$F$4:$F$7,'System List'!$H$4:$H$7,0))} -> 0 | AR7: {=SUM( _xlfn.XLOOKUP(InputTable[[#This Row],[Impact on - CIAL]:[Impact on - STRAT]],'System List'!$F$4:$F$7,'System List'!$H$4:$H$7,0))} -> 0 | AS7: =VLOOKUP(InputTable[[#This Row],[Duration]],Duration,2,FALSE)+InputTable[[#This Row],[Resource Score]] -> #N/A | AT7: =(( VLOOKUP(InputTable[[#This Row],[Duration]],'System List'!$J$5:$K$10,2,FALSE)*VLOOKUP(InputTable[[#Headers],[Duration]],'System List'!$V$5:$W$8,2,FALSE) + VLOOKUP(InputTable[[#This Row],[Number of Team Involved]],'System List'!$M$5:$N$13,2,FALSE)*VLOOKUP(InputTable[[#Headers],[Number of Team Involved]],'System List'!$V$5:$W$8,2,FALSE) + VLOOKUP(InputTable[[#This Row],[Resource Score]],Resource_Score,2,FALSE)*VLOOKUP(InputTable[[#Headers],[Resource Score]],'System List'!$V$5:$W$8,2,FALSE) + VLOOKUP(InputTable[[#This Row],[CHANGE Impact Score]],CHANGE_Impact_Score,2,FALSE)*VLOOKUP(InputTable[[#Headers],[CHANGE Impact Score]],'System List'!$V$5:$W$8,2,FALSE)) * 100) / 13 -> #N/A | AU7: =InputTable[[#This Row],[Value Score]]/InputTable[[#This Row],[EFFORT SCORE]]*100 -> #N/A | AV7: =InputTable[[#This Row],[IS Portfolio Ref ID]] -> ISPRJ-101 | AW7: Xavier ROMANET | AZ7: 0 | BA7: 0 | BH7: =IFERROR(VLOOKUP(InputTable[[#This Row],[Impact on - CIAL]],'System List'!$F$4:$H$7,3,FALSE),0) -> 0 | BI7: =IFERROR(VLOOKUP(InputTable[[#This Row],[Impact on - COM]],'System List'!$F$4:$H$7,3,FALSE),0) -> 0 | BJ7: =IFERROR(VLOOKUP(InputTable[[#This Row],[Impact on - FIN]],'System List'!$F$4:$H$7,3,FALSE),0) -> 0 | BK7: =IFERROR(VLOOKUP(InputTable[[#This Row],[Impact on - GEN SEC]],'System List'!$F$4:$H$7,3,FALSE),0) -> 0 | BL7: =IFERROR(VLOOKUP(InputTable[[#This Row],[Impact on - HR]],'System List'!$F$4:$H$7,3,FALSE),0) -> 0 | BM7: =IFERROR(VLOOKUP(InputTable[[#This Row],[Impact on - IS]],'System List'!$F$4:$H$7,3,FALSE),0) -> 0 | BN7: =IFERROR(VLOOKUP(InputTable[[#This Row],[Impact on - OPS]],'System List'!$F$4:$H$7,3,FALSE),0) -> 0 | BO7: =IFERROR(VLOOKUP(InputTable[[#This Row],[Impact on - ROLL STOCK]],'System List'!$F$4:$H$7,3,FALSE),0) -> 0 | BP7: =IFERROR(VLOOKUP(InputTable[[#This Row],[Impact on - SAFETY]],'System List'!$F$4:$H$7,3,FALSE),0) -> 0 | BQ7: =IFERROR(VLOOKUP(InputTable[[#This Row],[Impact on - STATION]],'System List'!$F$4:$H$7,3,FALSE),0) -> 0 | BR7: =IFERROR(VLOOKUP(InputTable[[#This Row],[Impact on - STRAT]],'System List'!$F$4:$H$7,3,FALSE),0) -> 0 | BT7: =IFERROR(VLOOKUP(InputTable[[#This Row],[CORPHRFIN]],'System List'!$F$4:$H$7,3,FALSE),0) -> 0 | BU7: =IFERROR(VLOOKUP(InputTable[[#This Row],[CUST]],'System List'!$F$4:$H$7,3,FALSE),0) -> 0 | BV7: =IFERROR(VLOOKUP(InputTable[[#This Row],[CYBER]],'System List'!$F$4:$H$7,3,FALSE),0) -> 0 | BW7: =IFERROR(VLOOKUP(InputTable[[#This Row],[DATA]],'System List'!$F$4:$H$7,3,FALSE),0) -> 0 | BX7: =IFERROR(VLOOKUP(InputTable[[#This Row],[INFRA]],'System List'!$F$4:$H$7,3,FALSE),0) -> 0 | BY7: =IFERROR(VLOOKUP(InputTable[[#This Row],[OPERATIONS]],'System List'!$F$4:$H$7,3,FALSE),0) -> 0 | BZ7: =IFERROR(VLOOKUP(InputTable[[#This Row],[PMO]],'System List'!$F$4:$H$7,3,FALSE),0) -> 0 | CA7: =IFERROR(VLOOKUP(InputTable[[#This Row],[SALES]],'System List'!$F$4:$H$7,3,FALSE),0) -> 0 | CC7: {=IFERROR( IF( AND( MATCH(InputTable[[#This Row],[Starting Date]],'System List'!$B$5:$B$16,0)<=MATCH(Input!CC$2,'System List'!$B$5:$B$16,0), MATCH(Input!CC$2,'System List'!$B$5:$B$16<=MATCH(InputTable[[#This Row],[Delivery Date]],'System List'!$B$5:$B$16,0))),1,0), )} -> 0 | CD7: {=IFERROR( IF( AND( MATCH(InputTable[[#This Row],[Starting Date]],'System List'!$B$5:$B$16,0)<=MATCH(Input!CD$2,'System List'!$B$5:$B$16,0), MATCH(Input!CD$2,'System List'!$B$5:$B$16<=MATCH(InputTable[[#This Row],[Delivery Date]],'System List'!$B$5:$B$16,0))),1,0), )} -> 0 | CE7: {=IFERROR( IF( AND( MATCH(InputTable[[#This Row],[Starting Date]],'System List'!$B$5:$B$16,0)<=MATCH(Input!CE$2,'System List'!$B$5:$B$16,0), MATCH(Input!CE$2,'System List'!$B$5:$B$16<=MATCH(InputTable[[#This Row],[Delivery Date]],'System List'!$B$5:$B$16,0))),1,0), )} -> 0 | CF7: {=IFERROR( IF( AND( MATCH(InputTable[[#This Row],[Starting Date]],'System List'!$B$5:$B$16,0)<=MATCH(Input!CF$2,'System List'!$B$5:$B$16,0), MATCH(Input!CF$2,'System List'!$B$5:$B$16<=MATCH(InputTable[[#This Row],[Delivery Date]],'System List'!$B$5:$B$16,0))),1,0), )} -> 0 | CG7: {=IFERROR( IF( AND( MATCH(InputTable[[#This Row],[Starting Date]],'System List'!$B$5:$B$16,0)<=MATCH(Input!CG$2,'System List'!$B$5:$B$16,0), MATCH(Input!CG$2,'System List'!$B$5:$B$16<=MATCH(InputTable[[#This Row],[Delivery Date]],'System List'!$B$5:$B$16,0))),1,0), )} -> 0 | CH7: {=IFERROR( IF( AND( MATCH(InputTable[[#This Row],[Starting Date]],'System List'!$B$5:$B$16,0)<=MATCH(Input!CH$2,'System List'!$B$5:$B$16,0), MATCH(Input!CH$2,'System List'!$B$5:$B$16<=MATCH(InputTable[[#This Row],[Delivery Date]],'System List'!$B$5:$B$16,0))),1,0), )} -> 0 | CI7: {=IFERROR( IF( AND( MATCH(InputTable[[#This Row],[Starting Date]],'System List'!$B$5:$B$16,0)<=MATCH(Input!CI$2,'System List'!$B$5:$B$16,0), MATCH(Input!CI$2,'System List'!$B$5:$B$16<=MATCH(InputTable[[#This Row],[Delivery Date]],'System List'!$B$5:$B$16,0))),1,0), )} -> 0 | CJ7: {=IFERROR( IF( AND( MATCH(InputTable[[#This Row],[Starting Date]],'System List'!$B$5:$B$16,0)<=MATCH(Input!CJ$2,'System List'!$B$5:$B$16,0), MATCH(Input!CJ$2,'System List'!$B$5:$B$16<=MATCH(InputTable[[#This Row],[Delivery Date]],'System List'!$B$5:$B$16,0))),1,0), )} -> 0 | CK7: {=IFERROR( IF( AND( MATCH(InputTable[[#This Row],[Starting Date]],'System List'!$B$5:$B$16,0)<=MATCH(Input!CK$2,'System List'!$B$5:$B$16,0), MATCH(Input!CK$2,'System List'!$B$5:$B$16<=MATCH(InputTable[[#This Row],[Delivery Date]],'System List'!$B$5:$B$16,0))),1,0), )} -> 0 | CN7: =IFERROR( IF(AND( MATCH(InputTable[[#This Row],[Starting Date]],'System List'!$B$5:$B$16,0)<=MATCH(CN$2,'System List'!$B$5:$B$16,0), MATCH(CN$2,'System List'!$B$5:$B$16,0)<=MATCH(InputTable[[#This Row],[Delivery Date]],'System List'!$B$5:$B$16,0)),1,0),0) -> 0 | CO7: =IFERROR( IF(AND( MATCH(InputTable[[#This Row],[Starting Date]],'System List'!$B$5:$B$16,0)<=MATCH(CO$2,'System List'!$B$5:$B$16,0), MATCH(CO$2,'System List'!$B$5:$B$16,0)<=MATCH(InputTable[[#This Row],[Delivery Date]],'System List'!$B$5:$B$16,0)),1,0),0) -> 0 | CP7: =IFERROR( IF(AND( MATCH(InputTable[[#This Row],[Starting Date]],'System List'!$B$5:$B$16,0)<=MATCH(CP$2,'System List'!$B$5:$B$16,0), MATCH(CP$2,'System List'!$B$5:$B$16,0)<=MATCH(InputTable[[#This Row],[Delivery Date]],'System List'!$B$5:$B$16,0)),1,0),0) -> 1 | CQ7: =IFERROR( IF(AND( MATCH(InputTable[[#This Row],[Starting Date]],'System List'!$B$5:$B$16,0)<=MATCH(CQ$2,'System List'!$B$5:$B$16,0), MATCH(CQ$2,'System List'!$B$5:$B$16,0)<=MATCH(InputTable[[#This Row],[Delivery Date]],'System List'!$B$5:$B$16,0)),1,0),0) -> 1 | CR7: =IFERROR( IF(AND( MATCH(InputTable[[#This Row],[Starting Date]],'System List'!$B$5:$B$16,0)<=MATCH(CR$2,'System List'!$B$5:$B$16,0), MATCH(CR$2,'System List'!$B$5:$B$16,0)<=MATCH(InputTable[[#This Row],[Delivery Date]],'System List'!$B$5:$B$16,0)),1,0),0) -> 1 | CS7: =IFERROR( IF(AND( MATCH(InputTable[[#This Row],[Starting Date]],'System List'!$B$5:$B$16,0)<=MATCH(CS$2,'System List'!$B$5:$B$16,0), MATCH(CS$2,'System List'!$B$5:$B$16,0)<=MATCH(InputTable[[#This Row],[Delivery Date]],'System List'!$B$5:$B$16,0)),1,0),0) -> 1 | CT7: =IFERROR( IF(AND( MATCH(InputTable[[#This Row],[Starting Date]],'System List'!$B$5:$B$16,0)<=MATCH(CT$2,'System List'!$B$5:$B$16,0), MATCH(CT$2,'System List'!$B$5:$B$16,0)<=MATCH(InputTable[[#This Row],[Delivery Date]],'System List'!$B$5:$B$16,0)),1,0),0) -> 0 | CU7: =IFERROR( IF(AND( MATCH(InputTable[[#This Row],[Starting Date]],'System List'!$B$5:$B$16,0)<=MATCH(CU$2,'System List'!$B$5:$B$16,0), MATCH(CU$2,'System List'!$B$5:$B$16,0)<=MATCH(InputTable[[#This Row],[Delivery Date]],'System List'!$B$5:$B$16,0)),1,0),0) -> 0 | CV7: =IFERROR( IF(AND( MATCH(InputTable[[#This Row],[Starting Date]],'System List'!$B$5:$B$16,0)<=MATCH(CV$2,'System List'!$B$5:$B$16,0), MATCH(CV$2,'System List'!$B$5:$B$16,0)<=MATCH(InputTable[[#This Row],[Delivery Date]],'System List'!$B$5:$B$16,0)),1,0),0) -> 0 | CX7: =CN7*_xlfn.XLOOKUP(CX$1,$BT$2:$CA$2,$BT7:$CA7,0) -> 0 | CY7: =CO7*_xlfn.XLOOKUP(CY$1,$BT$2:$CA$2,$BT7:$CA7,0) -> 0 | CZ7: =CP7*_xlfn.XLOOKUP(CZ$1,$BT$2:$CA$2,$BT7:$CA7,0) -> 0 | DA7: =CQ7*_xlfn.XLOOKUP(DA$1,$BT$2:$CA$2,$BT7:$CA7,0) -> 0 | DB7: =CR7*_xlfn.XLOOKUP(DB$1,$BT$2:$CA$2,$BT7:$CA7,0) -> 0 | DC7: =CS7*_xlfn.XLOOKUP(DC$1,$BT$2:$CA$2,$BT7:$CA7,0) -> 0 | DD7: =CT7*_xlfn.XLOOKUP(DD$1,$BT$2:$CA$2,$BT7:$CA7,0) -> 0 | DE7: =CU7*_xlfn.XLOOKUP(DE$1,$BT$2:$CA$2,$BT7:$CA7,0) -> 0 | DF7: =CV7*_xlfn.XLOOKUP(DF$1,$BT$2:$CA$2,$BT7:$CA7,0) -> 0 | DH7: =$CN7*_xlfn.XLOOKUP(DH$1,$BT$2:$CA$2,$BT7:$CA7,0) -> 0 | DI7: =$CO7*_xlfn.XLOOKUP(DI$1,$BT$2:$CA$2,$BT7:$CA7,0) -> 0 | DJ7: =$CP7*_xlfn.XLOOKUP(DJ$1,$BT$2:$CA$2,$BT7:$CA7,0) -> 0 | DK7: =$CQ7*_xlfn.XLOOKUP(DK$1,$BT$2:$CA$2,$BT7:$CA7,0) -> 0 | DL7: =$CR7*_xlfn.XLOOKUP(DL$1,$BT$2:$CA$2,$BT7:$CA7,0) -> 0 | DM7: =$CS7*_xlfn.XLOOKUP(DM$1,$BT$2:$CA$2,$BT7:$CA7,0) -> 0 | DN7: =$CT7*_xlfn.XLOOKUP(DN$1,$BT$2:$CA$2,$BT7:$CA7,0) -> 0 | DO7: =$CU7*_xlfn.XLOOKUP(DO$1,$BT$2:$CA$2,$BT7:$CA7,0) -> 0 | DP7: =$CV7*_xlfn.XLOOKUP(DP$1,$BT$2:$CA$2,$BT7:$CA7,0) -> 0 | DR7: =$CN7*_xlfn.XLOOKUP(DR$1,$BT$2:$CA$2,$BT7:$CA7,0) -> 0 | DS7: =$CO7*_xlfn.XLOOKUP(DS$1,$BT$2:$CA$2,$BT7:$CA7,0) -> 0 | DT7: =$CP7*_xlfn.XLOOKUP(DT$1,$BT$2:$CA$2,$BT7:$CA7,0) -> 0 | DU7: =$CQ7*_xlfn.XLOOKUP(DU$1,$BT$2:$CA$2,$BT7:$CA7,0) -> 0 | DV7: =$CR7*_xlfn.XLOOKUP(DV$1,$BT$2:$CA$2,$BT7:$CA7,0) -> 0 | DW7: =$CS7*_xlfn.XLOOKUP(DW$1,$BT$2:$CA$2,$BT7:$CA7,0) -> 0 | DX7: =$CT7*_xlfn.XLOOKUP(DX$1,$BT$2:$CA$2,$BT7:$CA7,0) -> 0 | DY7: =$CU7*_xlfn.XLOOKUP(DY$1,$BT$2:$CA$2,$BT7:$CA7,0) -> 0 | DZ7: =$CV7*_xlfn.XLOOKUP(DZ$1,$BT$2:$CA$2,$BT7:$CA7,0) -> 0 | EB7: =$CN7*_xlfn.XLOOKUP(EB$1,$BT$2:$CA$2,$BT7:$CA7,0) -> 0 | EC7: =$CO7*_xlfn.XLOOKUP(EC$1,$BT$2:$CA$2,$BT7:$CA7,0) -> 0 | ED7: =$CP7*_xlfn.XLOOKUP(ED$1,$BT$2:$CA$2,$BT7:$CA7,0) -> 0 | EE7: =$CQ7*_xlfn.XLOOKUP(EE$1,$BT$2:$CA$2,$BT7:$CA7,0) -> 0 | EF7: =$CR7*_xlfn.XLOOKUP(EF$1,$BT$2:$CA$2,$BT7:$CA7,0) -> 0 | EG7: =$CS7*_xlfn.XLOOKUP(EG$1,$BT$2:$CA$2,$BT7:$CA7,0) -> 0 | EH7: =$CT7*_xlfn.XLOOKUP(EH$1,$BT$2:$CA$2,$BT7:$CA7,0) -> 0 | EI7: =$CU7*_xlfn.XLOOKUP(EI$1,$BT$2:$CA$2,$BT7:$CA7,0) -> 0 | EJ7: =$CV7*_xlfn.XLOOKUP(EJ$1,$BT$2:$CA$2,$BT7:$CA7,0) -> 0 | EL7: =$CN7*_xlfn.XLOOKUP(EL$1,$BT$2:$CA$2,$BT7:$CA7,0) -> 0 | EM7: =$CO7*_xlfn.XLOOKUP(EM$1,$BT$2:$CA$2,$BT7:$CA7,0) -> 0 | EN7: =$CP7*_xlfn.XLOOKUP(EN$1,$BT$2:$CA$2,$BT7:$CA7,0) -> 0 | EO7: =$CQ7*_xlfn.XLOOKUP(EO$1,$BT$2:$CA$2,$BT7:$CA7,0) -> 0 | EP7: =$CR7*_xlfn.XLOOKUP(EP$1,$BT$2:$CA$2,$BT7:$CA7,0) -> 0 | EQ7: =$CS7*_xlfn.XLOOKUP(EQ$1,$BT$2:$CA$2,$BT7:$CA7,0) -> 0 | ER7: =$CT7*_xlfn.XLOOKUP(ER$1,$BT$2:$CA$2,$BT7:$CA7,0) -> 0 | ES7: =$CU7*_xlfn.XLOOKUP(ES$1,$BT$2:$CA$2,$BT7:$CA7,0) -> 0 | ET7: =$CV7*_xlfn.XLOOKUP(ET$1,$BT$2:$CA$2,$BT7:$CA7,0) -> 0 | EV7: =$CN7*_xlfn.XLOOKUP(EV$1,$BT$2:$CA$2,$BT7:$CA7,0) -> 0 | EW7: =$CO7*_xlfn.XLOOKUP(EW$1,$BT$2:$CA$2,$BT7:$CA7,0) -> 0 | EX7: =$CP7*_xlfn.XLOOKUP(EX$1,$BT$2:$CA$2,$BT7:$CA7,0) -> 0 | EY7: =$CQ7*_xlfn.XLOOKUP(EY$1,$BT$2:$CA$2,$BT7:$CA7,0) -> 0 | EZ7: =$CR7*_xlfn.XLOOKUP(EZ$1,$BT$2:$CA$2,$BT7:$CA7,0) -> 0 | FA7: =$CS7*_xlfn.XLOOKUP(FA$1,$BT$2:$CA$2,$BT7:$CA7,0) -> 0 | FB7: =$CT7*_xlfn.XLOOKUP(FB$1,$BT$2:$CA$2,$BT7:$CA7,0) -> 0 | FC7: =$CU7*_xlfn.XLOOKUP(FC$1,$BT$2:$CA$2,$BT7:$CA7,0) -> 0 | FD7: =$CV7*_xlfn.XLOOKUP(FD$1,$BT$2:$CA$2,$BT7:$CA7,0) -> 0 | FF7: =$CN7*_xlfn.XLOOKUP(FF$1,$BT$2:$CA$2,$BT7:$CA7,0) -> 0 | FG7: =$CO7*_xlfn.XLOOKUP(FG$1,$BT$2:$CA$2,$BT7:$CA7,0) -> 0 | FH7: =$CP7*_xlfn.XLOOKUP(FH$1,$BT$2:$CA$2,$BT7:$CA7,0) -> 0 | FI7: =$CQ7*_xlfn.XLOOKUP(FI$1,$BT$2:$CA$2,$BT7:$CA7,0) -> 0 | FJ7: =$CR7*_xlfn.XLOOKUP(FJ$1,$BT$2:$CA$2,$BT7:$CA7,0) -> 0 | FK7: =$CS7*_xlfn.XLOOKUP(FK$1,$BT$2:$CA$2,$BT7:$CA7,0) -> 0 | FL7: =$CT7*_xlfn.XLOOKUP(FL$1,$BT$2:$CA$2,$BT7:$CA7,0) -> 0 | FM7: =$CU7*_xlfn.XLOOKUP(FM$1,$BT$2:$CA$2,$BT7:$CA7,0) -> 0 | FN7: =$CV7*_xlfn.XLOOKUP(FN$1,$BT$2:$CA$2,$BT7:$CA7,0) -> 0 | FP7: =$CN7*_xlfn.XLOOKUP(FP$1,$BT$2:$CA$2,$BT7:$CA7,0) -> #REF! | FQ7: =$CO7*_xlfn.XLOOKUP(FQ$1,$BT$2:$CA$2,$BT7:$CA7,0) -> #REF! | FR7: =$CP7*_xlfn.XLOOKUP(FR$1,$BT$2:$CA$2,$BT7:$CA7,0) -> #REF! | FS7: =$CQ7*_xlfn.XLOOKUP(FS$1,$BT$2:$CA$2,$BT7:$CA7,0) -> #REF! | FT7: =$CR7*_xlfn.XLOOKUP(FT$1,$BT$2:$CA$2,$BT7:$CA7,0) -> #REF! | FU7: =$CS7*_xlfn.XLOOKUP(FU$1,$BT$2:$CA$2,$BT7:$CA7,0) -> #REF! | FV7: =$CT7*_xlfn.XLOOKUP(FV$1,$BT$2:$CA$2,$BT7:$CA7,0) -> #REF! | FW7: =$CU7*_xlfn.XLOOKUP(FW$1,$BT$2:$CA$2,$BT7:$CA7,0) -> #REF! | FX7: =$CV7*_xlfn.XLOOKUP(FX$1,$BT$2:$CA$2,$BT7:$CA7,0) -> #REF! | GB7: =IF(GB$2=InputTable[[#This Row],[Delivery Date]],_xlfn.XLOOKUP(GB$1,$BH$2:$BR$2,$BH7:$BR7,0),0) -> #REF! | GC7: =IF(GC$2=InputTable[[#This Row],[Delivery Date]],_xlfn.XLOOKUP(GC$1,$BH$2:$BR$2,$BH7:$BR7,0),0) -> 0 | GD7: =IF(GD$2=InputTable[[#This Row],[Delivery Date]],_xlfn.XLOOKUP(GD$1,$BH$2:$BR$2,$BH7:$BR7,0),0) -> 0 | GE7: =IF(GE$2=InputTable[[#This Row],[Delivery Date]],_xlfn.XLOOKUP(GE$1,$BH$2:$BR$2,$BH7:$BR7,0),0) -> 0 | GF7: =IF(GF$2=InputTable[[#This Row],[Delivery Date]],_xlfn.XLOOKUP(GF$1,$BH$2:$BR$2,$BH7:$BR7,0),0) -> 0 | GG7: =IF(GG$2=InputTable[[#This Row],[Delivery Date]],_xlfn.XLOOKUP(GG$1,$BH$2:$BR$2,$BH7:$BR7,0),0) -> 0 | GH7: =IF(GH$2=InputTable[[#This Row],[Delivery Date]],_xlfn.XLOOKUP(GH$1,$BH$2:$BR$2,$BH7:$BR7,0),0) -> 0 | GI7: =IF(GI$2=InputTable[[#This Row],[Delivery Date]],_xlfn.XLOOKUP(GI$1,$BH$2:$BR$2,$BH7:$BR7,0),0) -> 0 | GJ7: =IF(GJ$2=InputTable[[#This Row],[Delivery Date]],_xlfn.XLOOKUP(GJ$1,$BH$2:$BR$2,$BH7:$BR7,0),0) -> 0 | GL7: =IF(GL$2=InputTable[[#This Row],[Delivery Date]],_xlfn.XLOOKUP(GL$1,$BH$2:$BR$2,$BH7:$BR7,0),0) -> #REF! | GM7: =IF(GM$2=InputTable[[#This Row],[Delivery Date]],_xlfn.XLOOKUP(GM$1,$BH$2:$BR$2,$BH7:$BR7,0),0) -> 0 | GN7: =IF(GN$2=InputTable[[#This Row],[Delivery Date]],_xlfn.XLOOKUP(GN$1,$BH$2:$BR$2,$BH7:$BR7,0),0) -> 0 | GO7: =IF(GO$2=InputTable[[#This Row],[Delivery Date]],_xlfn.XLOOKUP(GO$1,$BH$2:$BR$2,$BH7:$BR7,0),0) -> 0 | GP7: =IF(GP$2=InputTable[[#This Row],[Delivery Date]],_xlfn.XLOOKUP(GP$1,$BH$2:$BR$2,$BH7:$BR7,0),0) -> 0 | GQ7: =IF(GQ$2=InputTable[[#This Row],[Delivery Date]],_xlfn.XLOOKUP(GQ$1,$BH$2:$BR$2,$BH7:$BR7,0),0) -> 0 | GR7: =IF(GR$2=InputTable[[#This Row],[Delivery Date]],_xlfn.XLOOKUP(GR$1,$BH$2:$BR$2,$BH7:$BR7,0),0) -> 0 | GS7: =IF(GS$2=InputTable[[#This Row],[Delivery Date]],_xlfn.XLOOKUP(GS$1,$BH$2:$BR$2,$BH7:$BR7,0),0) -> 0 | GT7: =IF(GT$2=InputTable[[#This Row],[Delivery Date]],_xlfn.XLOOKUP(GT$1,$BH$2:$BR$2,$BH7:$BR7,0),0) -> 0 | GV7: =IF(GV$2=InputTable[[#This Row],[Delivery Date]],_xlfn.XLOOKUP(GV$1,$BH$2:$BR$2,$BH7:$BR7,0),0) -> #REF! | GW7: =IF(GW$2=InputTable[[#This Row],[Delivery Date]],_xlfn.XLOOKUP(GW$1,$BH$2:$BR$2,$BH7:$BR7,0),0) -> 0 | GX7: =IF(GX$2=InputTable[[#This Row],[Delivery Date]],_xlfn.XLOOKUP(GX$1,$BH$2:$BR$2,$BH7:$BR7,0),0) -> 0 | GY7: =IF(GY$2=InputTable[[#This Row],[Delivery Date]],_xlfn.XLOOKUP(GY$1,$BH$2:$BR$2,$BH7:$BR7,0),0) -> 0 | GZ7: =IF(GZ$2=InputTable[[#This Row],[Delivery Date]],_xlfn.XLOOKUP(GZ$1,$BH$2:$BR$2,$BH7:$BR7,0),0) -> 0 | HA7: =IF(HA$2=InputTable[[#This Row],[Delivery Date]],_xlfn.XLOOKUP(HA$1,$BH$2:$BR$2,$BH7:$BR7,0),0) -> 0 | HB7: =IF(HB$2=InputTable[[#This Row],[Delivery Date]],_xlfn.XLOOKUP(HB$1,$BH$2:$BR$2,$BH7:$BR7,0),0) -> 0 | HC7: =IF(HC$2=InputTable[[#This Row],[Delivery Date]],_xlfn.XLOOKUP(HC$1,$BH$2:$BR$2,$BH7:$BR7,0),0) -> 0 | HD7: =IF(HD$2=InputTable[[#This Row],[Delivery Date]],_xlfn.XLOOKUP(HD$1,$BH$2:$BR$2,$BH7:$BR7,0),0) -> 0 | HF7: =IF(HF$2=InputTable[[#This Row],[Delivery Date]],_xlfn.XLOOKUP(HF$1,$BH$2:$BR$2,$BH7:$BR7,0),0) -> #REF! | HG7: =IF(HG$2=InputTable[[#This Row],[Delivery Date]],_xlfn.XLOOKUP(HG$1,$BH$2:$BR$2,$BH7:$BR7,0),0) -> 0 | HH7: =IF(HH$2=InputTable[[#This Row],[Delivery Date]],_xlfn.XLOOKUP(HH$1,$BH$2:$BR$2,$BH7:$BR7,0),0) -> 0 | HI7: =IF(HI$2=InputTable[[#This Row],[Delivery Date]],_xlfn.XLOOKUP(HI$1,$BH$2:$BR$2,$BH7:$BR7,0),0) -> 0 | HJ7: =IF(HJ$2=InputTable[[#This Row],[Delivery Date]],_xlfn.XLOOKUP(HJ$1,$BH$2:$BR$2,$BH7:$BR7,0),0) -> 0 | HK7: =IF(HK$2=InputTable[[#This Row],[Delivery Date]],_xlfn.XLOOKUP(HK$1,$BH$2:$BR$2,$BH7:$BR7,0),0) -> 0 | HL7: =IF(HL$2=InputTable[[#This Row],[Delivery Date]],_xlfn.XLOOKUP(HL$1,$BH$2:$BR$2,$BH7:$BR7,0),0) -> 0 | HM7: =IF(HM$2=InputTable[[#This Row],[Delivery Date]],_xlfn.XLOOKUP(HM$1,$BH$2:$BR$2,$BH7:$BR7,0),0) -> 0 | HN7: =IF(HN$2=InputTable[[#This Row],[Delivery Date]],_xlfn.XLOOKUP(HN$1,$BH$2:$BR$2,$BH7:$BR7,0),0) -> 0 | HP7: =IF(HP$2=InputTable[[#This Row],[Delivery Date]],_xlfn.XLOOKUP(HP$1,$BH$2:$BR$2,$BH7:$BR7,0),0) -> #REF! | HQ7: =IF(HQ$2=InputTable[[#This Row],[Delivery Date]],_xlfn.XLOOKUP(HQ$1,$BH$2:$BR$2,$BH7:$BR7,0),0) -> 0 | HR7: =IF(HR$2=InputTable[[#This Row],[Delivery Date]],_xlfn.XLOOKUP(HR$1,$BH$2:$BR$2,$BH7:$BR7,0),0) -> 0 | HS7: =IF(HS$2=InputTable[[#This Row],[Delivery Date]],_xlfn.XLOOKUP(HS$1,$BH$2:$BR$2,$BH7:$BR7,0),0) -> 0 | HT7: =IF(HT$2=InputTable[[#This Row],[Delivery Date]],_xlfn.XLOOKUP(HT$1,$BH$2:$BR$2,$BH7:$BR7,0),0) -> 0 | HU7: =IF(HU$2=InputTable[[#This Row],[Delivery Date]],_xlfn.XLOOKUP(HU$1,$BH$2:$BR$2,$BH7:$BR7,0),0) -> 0 | HV7: =IF(HV$2=InputTable[[#This Row],[Delivery Date]],_xlfn.XLOOKUP(HV$1,$BH$2:$BR$2,$BH7:$BR7,0),0) -> 0 | HW7: =IF(HW$2=InputTable[[#This Row],[Delivery Date]],_xlfn.XLOOKUP(HW$1,$BH$2:$BR$2,$BH7:$BR7,0),0) -> 0 | HX7: =IF(HX$2=InputTable[[#This Row],[Delivery Date]],_xlfn.XLOOKUP(HX$1,$BH$2:$BR$2,$BH7:$BR7,0),0) -> 0 | HZ7: =IF(HZ$2=InputTable[[#This Row],[Delivery Date]],_xlfn.XLOOKUP(HZ$1,$BH$2:$BR$2,$BH7:$BR7,0),0) -> #REF! | IA7: =IF(IA$2=InputTable[[#This Row],[Delivery Date]],_xlfn.XLOOKUP(IA$1,$BH$2:$BR$2,$BH7:$BR7,0),0) -> 0 | IB7: =IF(IB$2=InputTable[[#This Row],[Delivery Date]],_xlfn.XLOOKUP(IB$1,$BH$2:$BR$2,$BH7:$BR7,0),0) -> 0 | IC7: =IF(IC$2=InputTable[[#This Row],[Delivery Date]],_xlfn.XLOOKUP(IC$1,$BH$2:$BR$2,$BH7:$BR7,0),0) -> 0 | ID7: =IF(ID$2=InputTable[[#This Row],[Delivery Date]],_xlfn.XLOOKUP(ID$1,$BH$2:$BR$2,$BH7:$BR7,0),0) -> 0 | IE7: =IF(IE$2=InputTable[[#This Row],[Delivery Date]],_xlfn.XLOOKUP(IE$1,$BH$2:$BR$2,$BH7:$BR7,0),0) -> 0 | IF7: =IF(IF$2=InputTable[[#This Row],[Delivery Date]],_xlfn.XLOOKUP(IF$1,$BH$2:$BR$2,$BH7:$BR7,0),0) -> 0 | IG7: =IF(IG$2=InputTable[[#This Row],[Delivery Date]],_xlfn.XLOOKUP(IG$1,$BH$2:$BR$2,$BH7:$BR7,0),0) -> 0 | IH7: =IF(IH$2=InputTable[[#This Row],[Delivery Date]],_xlfn.XLOOKUP(IH$1,$BH$2:$BR$2,$BH7:$BR7,0),0) -> 0 | IJ7: =IF(IJ$2=InputTable[[#This Row],[Delivery Date]],_xlfn.XLOOKUP(IJ$1,$BH$2:$BR$2,$BH7:$BR7,0),0) -> #REF! | IK7: =IF(IK$2=InputTable[[#This Row],[Delivery Date]],_xlfn.XLOOKUP(IK$1,$BH$2:$BR$2,$BH7:$BR7,0),0) -> 0 | IL7: =IF(IL$2=InputTable[[#This Row],[Delivery Date]],_xlfn.XLOOKUP(IL$1,$BH$2:$BR$2,$BH7:$BR7,0),0) -> 0 | IM7: =IF(IM$2=InputTable[[#This Row],[Delivery Date]],_xlfn.XLOOKUP(IM$1,$BH$2:$BR$2,$BH7:$BR7,0),0) -> 0 | IN7: =IF(IN$2=InputTable[[#This Row],[Delivery Date]],_xlfn.XLOOKUP(IN$1,$BH$2:$BR$2,$BH7:$BR7,0),0) -> 0 | IO7: =IF(IO$2=InputTable[[#This Row],[Delivery Date]],_xlfn.XLOOKUP(IO$1,$BH$2:$BR$2,$BH7:$BR7,0),0) -> 0 | IP7: =IF(IP$2=InputTable[[#This Row],[Delivery Date]],_xlfn.XLOOKUP(IP$1,$BH$2:$BR$2,$BH7:$BR7,0),0) -> 0 | IQ7: =IF(IQ$2=InputTable[[#This Row],[Delivery Date]],_xlfn.XLOOKUP(IQ$1,$BH$2:$BR$2,$BH7:$BR7,0),0) -> 0 | IR7: =IF(IR$2=InputTable[[#This Row],[Delivery Date]],_xlfn.XLOOKUP(IR$1,$BH$2:$BR$2,$BH7:$BR7,0),0) -> 0 | IT7: =IF(IT$2=InputTable[[#This Row],[Delivery Date]],_xlfn.XLOOKUP(IT$1,$BH$2:$BR$2,$BH7:$BR7,0),0) -> #REF! | IU7: =IF(IU$2=InputTable[[#This Row],[Delivery Date]],_xlfn.XLOOKUP(IU$1,$BH$2:$BR$2,$BH7:$BR7,0),0) -> 0 | IV7: =IF(IV$2=InputTable[[#This Row],[Delivery Date]],_xlfn.XLOOKUP(IV$1,$BH$2:$BR$2,$BH7:$BR7,0),0) -> 0 | IW7: =IF(IW$2=InputTable[[#This Row],[Delivery Date]],_xlfn.XLOOKUP(IW$1,$BH$2:$BR$2,$BH7:$BR7,0),0) -> 0 | IX7: =IF(IX$2=InputTable[[#This Row],[Delivery Date]],_xlfn.XLOOKUP(IX$1,$BH$2:$BR$2,$BH7:$BR7,0),0) -> 0 | IY7: =IF(IY$2=InputTable[[#This Row],[Delivery Date]],_xlfn.XLOOKUP(IY$1,$BH$2:$BR$2,$BH7:$BR7,0),0) -> 0 | IZ7: =IF(IZ$2=InputTable[[#This Row],[Delivery Date]],_xlfn.XLOOKUP(IZ$1,$BH$2:$BR$2,$BH7:$BR7,0),0) -> 0 | JA7: =IF(JA$2=InputTable[[#This Row],[Delivery Date]],_xlfn.XLOOKUP(JA$1,$BH$2:$BR$2,$BH7:$BR7,0),0) -> 0 | JB7: =IF(JB$2=InputTable[[#This Row],[Delivery Date]],_xlfn.XLOOKUP(JB$1,$BH$2:$BR$2,$BH7:$BR7,0),0) -> 0 | JD7: =IF(JD$2=InputTable[[#This Row],[Delivery Date]],_xlfn.XLOOKUP(JD$1,$BH$2:$BR$2,$BH7:$BR7,0),0) -> #REF! | JE7: =IF(JE$2=InputTable[[#This Row],[Delivery Date]],_xlfn.XLOOKUP(JE$1,$BH$2:$BR$2,$BH7:$BR7,0),0) -> 0 | JF7: =IF(JF$2=InputTable[[#This Row],[Delivery Date]],_xlfn.XLOOKUP(JF$1,$BH$2:$BR$2,$BH7:$BR7,0),0) -> 0 | JG7: =IF(JG$2=InputTable[[#This Row],[Delivery Date]],_xlfn.XLOOKUP(JG$1,$BH$2:$BR$2,$BH7:$BR7,0),0) -> 0 | JH7: =IF(JH$2=InputTable[[#This Row],[Delivery Date]],_xlfn.XLOOKUP(JH$1,$BH$2:$BR$2,$BH7:$BR7,0),0) -> 0 | JI7: =IF(JI$2=InputTable[[#This Row],[Delivery Date]],_xlfn.XLOOKUP(JI$1,$BH$2:$BR$2,$BH7:$BR7,0),0) -> 0 | JJ7: =IF(JJ$2=InputTable[[#This Row],[Delivery Date]],_xlfn.XLOOKUP(JJ$1,$BH$2:$BR$2,$BH7:$BR7,0),0) -> 0 | JK7: =IF(JK$2=InputTable[[#This Row],[Delivery Date]],_xlfn.XLOOKUP(JK$1,$BH$2:$BR$2,$BH7:$BR7,0),0) -> 0 | JL7: =IF(JL$2=InputTable[[#This Row],[Delivery Date]],_xlfn.XLOOKUP(JL$1,$BH$2:$BR$2,$BH7:$BR7,0),0) -> 0 | JN7: =IF(JN$2=InputTable[[#This Row],[Delivery Date]],_xlfn.XLOOKUP(JN$1,$BH$2:$BR$2,$BH7:$BR7,0),0) -> #REF! | JO7: =IF(JO$2=InputTable[[#This Row],[Delivery Date]],_xlfn.XLOOKUP(JO$1,$BH$2:$BR$2,$BH7:$BR7,0),0) -> 0 | JP7: =IF(JP$2=InputTable[[#This Row],[Delivery Date]],_xlfn.XLOOKUP(JP$1,$BH$2:$BR$2,$BH7:$BR7,0),0) -> 0 | JQ7: =IF(JQ$2=InputTable[[#This Row],[Delivery Date]],_xlfn.XLOOKUP(JQ$1,$BH$2:$BR$2,$BH7:$BR7,0),0) -> 0 | JR7: =IF(JR$2=InputTable[[#This Row],[Delivery Date]],_xlfn.XLOOKUP(JR$1,$BH$2:$BR$2,$BH7:$BR7,0),0) -> 0 | JS7: =IF(JS$2=InputTable[[#This Row],[Delivery Date]],_xlfn.XLOOKUP(JS$1,$BH$2:$BR$2,$BH7:$BR7,0),0) -> 0 | JT7: =IF(JT$2=InputTable[[#This Row],[Delivery Date]],_xlfn.XLOOKUP(JT$1,$BH$2:$BR$2,$BH7:$BR7,0),0) -> 0 | JU7: =IF(JU$2=InputTable[[#This Row],[Delivery Date]],_xlfn.XLOOKUP(JU$1,$BH$2:$BR$2,$BH7:$BR7,0),0) -> 0 | JV7: =IF(JV$2=InputTable[[#This Row],[Delivery Date]],_xlfn.XLOOKUP(JV$1,$BH$2:$BR$2,$BH7:$BR7,0),0) -> 0 | JX7: =IF(JX$2=InputTable[[#This Row],[Delivery Date]],_xlfn.XLOOKUP(JX$1,$BH$2:$BR$2,$BH7:$BR7,0),0) -> #REF! | JY7: =IF(JY$2=InputTable[[#This Row],[Delivery Date]],_xlfn.XLOOKUP(JY$1,$BH$2:$BR$2,$BH7:$BR7,0),0) -> 0 | JZ7: =IF(JZ$2=InputTable[[#This Row],[Delivery Date]],_xlfn.XLOOKUP(JZ$1,$BH$2:$BR$2,$BH7:$BR7,0),0) -> 0 | KA7: =IF(KA$2=InputTable[[#This Row],[Delivery Date]],_xlfn.XLOOKUP(KA$1,$BH$2:$BR$2,$BH7:$BR7,0),0) -> 0 | KB7: =IF(KB$2=InputTable[[#This Row],[Delivery Date]],_xlfn.XLOOKUP(KB$1,$BH$2:$BR$2,$BH7:$BR7,0),0) -> 0 | KC7: =IF(KC$2=InputTable[[#This Row],[Delivery Date]],_xlfn.XLOOKUP(KC$1,$BH$2:$BR$2,$BH7:$BR7,0),0) -> 0 | KD7: =IF(KD$2=InputTable[[#This Row],[Delivery Date]],_xlfn.XLOOKUP(KD$1,$BH$2:$BR$2,$BH7:$BR7,0),0) -> 0 | KE7: =IF(KE$2=InputTable[[#This Row],[Delivery Date]],_xlfn.XLOOKUP(KE$1,$BH$2:$BR$2,$BH7:$BR7,0),0) -> 0 | KF7: =IF(KF$2=InputTable[[#This Row],[Delivery Date]],_xlfn.XLOOKUP(KF$1,$BH$2:$BR$2,$BH7:$BR7,0),0) -> 0
B8: Stopped in 2025 | C8: DIGITAL TECH | D8: ISPRJ-102 | E8: Check out (Paypal NL+FR, WERO) | F8: COMMERCIAL | G8: 2025 Q1 | I8: 2025 Q4 | K8: =VLOOKUP((InputTable[[#This Row],[Starting Date]]& " - " &InputTable[[#This Row],[Delivery Date]]),'System List'!$F$40:$H$83,2,FALSE) -> #N/A | L8: =VLOOKUP(InputTable[[#This Row],[Duration]],Duration,2,FALSE) -> #N/A | M8: yes | O8: L | T8: {=SUM( _xlfn.XLOOKUP(InputTable[[#This Row],[Safety]:[Regulatory]], 'System List'!$F$4:$F$7, 'System List'!$G$4:$G$7, 0) * _xlfn.XLOOKUP(InputTable[[#Headers],[Safety]:[Regulatory]], 'System List'!$Y$4:$Y$10, 'System List'!$Z$4:$Z$10, 0) )} -> 1 | AD8: =COUNTA(InputTable[[#This Row],[CORPHRFIN]:[SALES]]) -> 0 | AE8: {=SUM( _xlfn.XLOOKUP(InputTable[[#This Row],[CORPHRFIN]:[SALES]],'System List'!$F$4:$F$7,'System List'!$H$4:$H$7,0))} -> 0 | AR8: {=SUM( _xlfn.XLOOKUP(InputTable[[#This Row],[Impact on - CIAL]:[Impact on - STRAT]],'System List'!$F$4:$F$7,'System List'!$H$4:$H$7,0))} -> 0 | AS8: =VLOOKUP(InputTable[[#This Row],[Duration]],Duration,2,FALSE)+InputTable[[#This Row],[Resource Score]] -> #N/A | AT8: =(( VLOOKUP(InputTable[[#This Row],[Duration]],'System List'!$J$5:$K$10,2,FALSE)*VLOOKUP(InputTable[[#Headers],[Duration]],'System List'!$V$5:$W$8,2,FALSE) + VLOOKUP(InputTable[[#This Row],[Number of Team Involved]],'System List'!$M$5:$N$13,2,FALSE)*VLOOKUP(InputTable[[#Headers],[Number of Team Involved]],'System List'!$V$5:$W$8,2,FALSE) + VLOOKUP(InputTable[[#This Row],[Resource Score]],Resource_Score,2,FALSE)*VLOOKUP(InputTable[[#Headers],[Resource Score]],'System List'!$V$5:$W$8,2,FALSE) + VLOOKUP(InputTable[[#This Row],[CHANGE Impact Score]],CHANGE_Impact_Score,2,FALSE)*VLOOKUP(InputTable[[#Headers],[CHANGE Impact Score]],'System List'!$V$5:$W$8,2,FALSE)) * 100) / 13 -> #N/A | AU8: =InputTable[[#This Row],[Value Score]]/InputTable[[#This Row],[EFFORT SCORE]]*100 -> #N/A | AW8: Xavier ROMANET | AZ8: 0 | BA8: 0 | BH8: =IFERROR(VLOOKUP(InputTable[[#This Row],[Impact on - CIAL]],'System List'!$F$4:$H$7,3,FALSE),0) -> 0 | BI8: =IFERROR(VLOOKUP(InputTable[[#This Row],[Impact on - COM]],'System List'!$F$4:$H$7,3,FALSE),0) -> 0 | BJ8: =IFERROR(VLOOKUP(InputTable[[#This Row],[Impact on - FIN]],'System List'!$F$4:$H$7,3,FALSE),0) -> 0 | BK8: =IFERROR(VLOOKUP(InputTable[[#This Row],[Impact on - GEN SEC]],'System List'!$F$4:$H$7,3,FALSE),0) -> 0 | BL8: =IFERROR(VLOOKUP(InputTable[[#This Row],[Impact on - HR]],'System List'!$F$4:$H$7,3,FALSE),0) -> 0 | BM8: =IFERROR(VLOOKUP(InputTable[[#This Row],[Impact on - IS]],'System List'!$F$4:$H$7,3,FALSE),0) -> 0 | BN8: =IFERROR(VLOOKUP(InputTable[[#This Row],[Impact on - OPS]],'System List'!$F$4:$H$7,3,FALSE),0) -> 0 | BO8: =IFERROR(VLOOKUP(InputTable[[#This Row],[Impact on - ROLL STOCK]],'System List'!$F$4:$H$7,3,FALSE),0) -> 0 | BP8: =IFERROR(VLOOKUP(InputTable[[#This Row],[Impact on - SAFETY]],'System List'!$F$4:$H$7,3,FALSE),0) -> 0 | BQ8: =IFERROR(VLOOKUP(InputTable[[#This Row],[Impact on - STATION]],'System List'!$F$4:$H$7,3,FALSE),0) -> 0 | BR8: =IFERROR(VLOOKUP(InputTable[[#This Row],[Impact on - STRAT]],'System List'!$F$4:$H$7,3,FALSE),0) -> 0 | BT8: =IFERROR(VLOOKUP(InputTable[[#This Row],[CORPHRFIN]],'System List'!$F$4:$H$7,3,FALSE),0) -> 0 | BU8: =IFERROR(VLOOKUP(InputTable[[#This Row],[CUST]],'System List'!$F$4:$H$7,3,FALSE),0) -> 0 | BV8: =IFERROR(VLOOKUP(InputTable[[#This Row],[CYBER]],'System List'!$F$4:$H$7,3,FALSE),0) -> 0 | BW8: =IFERROR(VLOOKUP(InputTable[[#This Row],[DATA]],'System List'!$F$4:$H$7,3,FALSE),0) -> 0 | BX8: =IFERROR(VLOOKUP(InputTable[[#This Row],[INFRA]],'System List'!$F$4:$H$7,3,FALSE),0) -> 0 | BY8: =IFERROR(VLOOKUP(InputTable[[#This Row],[OPERATIONS]],'System List'!$F$4:$H$7,3,FALSE),0) -> 0 | BZ8: =IFERROR(VLOOKUP(InputTable[[#This Row],[PMO]],'System List'!$F$4:$H$7,3,FALSE),0) -> 0 | CA8: =IFERROR(VLOOKUP(InputTable[[#This Row],[SALES]],'System List'!$F$4:$H$7,3,FALSE),0) -> 0 | CC8: {=IFERROR( IF( AND( MATCH(InputTable[[#This Row],[Starting Date]],'System List'!$B$5:$B$16,0)<=MATCH(Input!CC$2,'System List'!$B$5:$B$16,0), MATCH(Input!CC$2,'System List'!$B$5:$B$16<=MATCH(InputTable[[#This Row],[Delivery Date]],'System List'!$B$5:$B$16,0))),1,0), )} -> 0 | CD8: {=IFERROR( IF( AND( MATCH(InputTable[[#This Row],[Starting Date]],'System List'!$B$5:$B$16,0)<=MATCH(Input!CD$2,'System List'!$B$5:$B$16,0), MATCH(Input!CD$2,'System List'!$B$5:$B$16<=MATCH(InputTable[[#This Row],[Delivery Date]],'System List'!$B$5:$B$16,0))),1,0), )} -> 0 | CE8: {=IFERROR( IF( AND( MATCH(InputTable[[#This Row],[Starting Date]],'System List'!$B$5:$B$16,0)<=MATCH(Input!CE$2,'System List'!$B$5:$B$16,0), MATCH(Input!CE$2,'System List'!$B$5:$B$16<=MATCH(InputTable[[#This Row],[Delivery Date]],'System List'!$B$5:$B$16,0))),1,0), )} -> 0 | CF8: {=IFERROR( IF( AND( MATCH(InputTable[[#This Row],[Starting Date]],'System List'!$B$5:$B$16,0)<=MATCH(Input!CF$2,'System List'!$B$5:$B$16,0), MATCH(Input!CF$2,'System List'!$B$5:$B$16<=MATCH(InputTable[[#This Row],[Delivery Date]],'System List'!$B$5:$B$16,0))),1,0), )} -> 0 | CG8: {=IFERROR( IF( AND( MATCH(InputTable[[#This Row],[Starting Date]],'System List'!$B$5:$B$16,0)<=MATCH(Input!CG$2,'System List'!$B$5:$B$16,0), MATCH(Input!CG$2,'System List'!$B$5:$B$16<=MATCH(InputTable[[#This Row],[Delivery Date]],'System List'!$B$5:$B$16,0))),1,0), )} -> 0 | CH8: {=IFERROR( IF( AND( MATCH(InputTable[[#This Row],[Starting Date]],'System List'!$B$5:$B$16,0)<=MATCH(Input!CH$2,'System List'!$B$5:$B$16,0), MATCH(Input!CH$2,'System List'!$B$5:$B$16<=MATCH(InputTable[[#This Row],[Delivery Date]],'System List'!$B$5:$B$16,0))),1,0), )} -> 0 | CI8: {=IFERROR( IF( AND( MATCH(InputTable[[#This Row],[Starting Date]],'System List'!$B$5:$B$16,0)<=MATCH(Input!CI$2,'System List'!$B$5:$B$16,0), MATCH(Input!CI$2,'System List'!$B$5:$B$16<=MATCH(InputTable[[#This Row],[Delivery Date]],'System List'!$B$5:$B$16,0))),1,0), )} -> 0 | CJ8: {=IFERROR( IF( AND( MATCH(InputTable[[#This Row],[Starting Date]],'System List'!$B$5:$B$16,0)<=MATCH(Input!CJ$2,'System List'!$B$5:$B$16,0), MATCH(Input!CJ$2,'System List'!$B$5:$B$16<=MATCH(InputTable[[#This Row],[Delivery Date]],'System List'!$B$5:$B$16,0))),1,0), )} -> 0 | CK8: {=IFERROR( IF( AND( MATCH(InputTable[[#This Row],[Starting Date]],'System List'!$B$5:$B$16,0)<=MATCH(Input!CK$2,'System List'!$B$5:$B$16,0), MATCH(Input!CK$2,'System List'!$B$5:$B$16<=MATCH(InputTable[[#This Row],[Delivery Date]],'System List'!$B$5:$B$16,0))),1,0), )} -> 0 | CN8: =IFERROR( IF(AND( MATCH(InputTable[[#This Row],[Starting Date]],'System List'!$B$5:$B$16,0)<=MATCH(CN$2,'System List'!$B$5:$B$16,0), MATCH(CN$2,'System List'!$B$5:$B$16,0)<=MATCH(InputTable[[#This Row],[Delivery Date]],'System List'!$B$5:$B$16,0)),1,0),0) -> 0 | CO8: =IFERROR( IF(AND( MATCH(InputTable[[#This Row],[Starting Date]],'System List'!$B$5:$B$16,0)<=MATCH(CO$2,'System List'!$B$5:$B$16,0), MATCH(CO$2,'System List'!$B$5:$B$16,0)<=MATCH(InputTable[[#This Row],[Delivery Date]],'System List'!$B$5:$B$16,0)),1,0),0) -> 0 | CP8: =IFERROR( IF(AND( MATCH(InputTable[[#This Row],[Starting Date]],'System List'!$B$5:$B$16,0)<=MATCH(CP$2,'System List'!$B$5:$B$16,0), MATCH(CP$2,'System List'!$B$5:$B$16,0)<=MATCH(InputTable[[#This Row],[Delivery Date]],'System List'!$B$5:$B$16,0)),1,0),0) -> 1 | CQ8: =IFERROR( IF(AND( MATCH(InputTable[[#This Row],[Starting Date]],'System List'!$B$5:$B$16,0)<=MATCH(CQ$2,'System List'!$B$5:$B$16,0), MATCH(CQ$2,'System List'!$B$5:$B$16,0)<=MATCH(InputTable[[#This Row],[Delivery Date]],'System List'!$B$5:$B$16,0)),1,0),0) -> 1 | CR8: =IFERROR( IF(AND( MATCH(InputTable[[#This Row],[Starting Date]],'System List'!$B$5:$B$16,0)<=MATCH(CR$2,'System List'!$B$5:$B$16,0), MATCH(CR$2,'System List'!$B$5:$B$16,0)<=MATCH(InputTable[[#This Row],[Delivery Date]],'System List'!$B$5:$B$16,0)),1,0),0) -> 1 | CS8: =IFERROR( IF(AND( MATCH(InputTable[[#This Row],[Starting Date]],'System List'!$B$5:$B$16,0)<=MATCH(CS$2,'System List'!$B$5:$B$16,0), MATCH(CS$2,'System List'!$B$5:$B$16,0)<=MATCH(InputTable[[#This Row],[Delivery Date]],'System List'!$B$5:$B$16,0)),1,0),0) -> 1 | CT8: =IFERROR( IF(AND( MATCH(InputTable[[#This Row],[Starting Date]],'System List'!$B$5:$B$16,0)<=MATCH(CT$2,'System List'!$B$5:$B$16,0), MATCH(CT$2,'System List'!$B$5:$B$16,0)<=MATCH(InputTable[[#This Row],[Delivery Date]],'System List'!$B$5:$B$16,0)),1,0),0) -> 0 | CU8: =IFERROR( IF(AND( MATCH(InputTable[[#This Row],[Starting Date]],'System List'!$B$5:$B$16,0)<=MATCH(CU$2,'System List'!$B$5:$B$16,0), MATCH(CU$2,'System List'!$B$5:$B$16,0)<=MATCH(InputTable[[#This Row],[Delivery Date]],'System List'!$B$5:$B$16,0)),1,0),0) -> 0 | CV8: =IFERROR( IF(AND( MATCH(InputTable[[#This Row],[Starting Date]],'System List'!$B$5:$B$16,0)<=MATCH(CV$2,'System List'!$B$5:$B$16,0), MATCH(CV$2,'System List'!$B$5:$B$16,0)<=MATCH(InputTable[[#This Row],[Delivery Date]],'System List'!$B$5:$B$16,0)),1,0),0) -> 0 | CX8: =CN8*_xlfn.XLOOKUP(CX$1,$BT$2:$CA$2,$BT8:$CA8,0) -> 0 | CY8: =CO8*_xlfn.XLOOKUP(CY$1,$BT$2:$CA$2,$BT8:$CA8,0) -> 0 | CZ8: =CP8*_xlfn.XLOOKUP(CZ$1,$BT$2:$CA$2,$BT8:$CA8,0) -> 0 | DA8: =CQ8*_xlfn.XLOOKUP(DA$1,$BT$2:$CA$2,$BT8:$CA8,0) -> 0 | DB8: =CR8*_xlfn.XLOOKUP(DB$1,$BT$2:$CA$2,$BT8:$CA8,0) -> 0 | DC8: =CS8*_xlfn.XLOOKUP(DC$1,$BT$2:$CA$2,$BT8:$CA8,0) -> 0 | DD8: =CT8*_xlfn.XLOOKUP(DD$1,$BT$2:$CA$2,$BT8:$CA8,0) -> 0 | DE8: =CU8*_xlfn.XLOOKUP(DE$1,$BT$2:$CA$2,$BT8:$CA8,0) -> 0 | DF8: =CV8*_xlfn.XLOOKUP(DF$1,$BT$2:$CA$2,$BT8:$CA8,0) -> 0 | DH8: =$CN8*_xlfn.XLOOKUP(DH$1,$BT$2:$CA$2,$BT8:$CA8,0) -> 0 | DI8: =$CO8*_xlfn.XLOOKUP(DI$1,$BT$2:$CA$2,$BT8:$CA8,0) -> 0 | DJ8: =$CP8*_xlfn.XLOOKUP(DJ$1,$BT$2:$CA$2,$BT8:$CA8,0) -> 0 | DK8: =$CQ8*_xlfn.XLOOKUP(DK$1,$BT$2:$CA$2,$BT8:$CA8,0) -> 0 | DL8: =$CR8*_xlfn.XLOOKUP(DL$1,$BT$2:$CA$2,$BT8:$CA8,0) -> 0 | DM8: =$CS8*_xlfn.XLOOKUP(DM$1,$BT$2:$CA$2,$BT8:$CA8,0) -> 0 | DN8: =$CT8*_xlfn.XLOOKUP(DN$1,$BT$2:$CA$2,$BT8:$CA8,0) -> 0 | DO8: =$CU8*_xlfn.XLOOKUP(DO$1,$BT$2:$CA$2,$BT8:$CA8,0) -> 0 | DP8: =$CV8*_xlfn.XLOOKUP(DP$1,$BT$2:$CA$2,$BT8:$CA8,0) -> 0 | DR8: =$CN8*_xlfn.XLOOKUP(DR$1,$BT$2:$CA$2,$BT8:$CA8,0) -> 0 | DS8: =$CO8*_xlfn.XLOOKUP(DS$1,$BT$2:$CA$2,$BT8:$CA8,0) -> 0 | DT8: =$CP8*_xlfn.XLOOKUP(DT$1,$BT$2:$CA$2,$BT8:$CA8,0) -> 0 | DU8: =$CQ8*_xlfn.XLOOKUP(DU$1,$BT$2:$CA$2,$BT8:$CA8,0) -> 0 | DV8: =$CR8*_xlfn.XLOOKUP(DV$1,$BT$2:$CA$2,$BT8:$CA8,0) -> 0 | DW8: =$CS8*_xlfn.XLOOKUP(DW$1,$BT$2:$CA$2,$BT8:$CA8,0) -> 0 | DX8: =$CT8*_xlfn.XLOOKUP(DX$1,$BT$2:$CA$2,$BT8:$CA8,0) -> 0 | DY8: =$CU8*_xlfn.XLOOKUP(DY$1,$BT$2:$CA$2,$BT8:$CA8,0) -> 0 | DZ8: =$CV8*_xlfn.XLOOKUP(DZ$1,$BT$2:$CA$2,$BT8:$CA8,0) -> 0 | EB8: =$CN8*_xlfn.XLOOKUP(EB$1,$BT$2:$CA$2,$BT8:$CA8,0) -> 0 | EC8: =$CO8*_xlfn.XLOOKUP(EC$1,$BT$2:$CA$2,$BT8:$CA8,0) -> 0 | ED8: =$CP8*_xlfn.XLOOKUP(ED$1,$BT$2:$CA$2,$BT8:$CA8,0) -> 0 | EE8: =$CQ8*_xlfn.XLOOKUP(EE$1,$BT$2:$CA$2,$BT8:$CA8,0) -> 0 | EF8: =$CR8*_xlfn.XLOOKUP(EF$1,$BT$2:$CA$2,$BT8:$CA8,0) -> 0 | EG8: =$CS8*_xlfn.XLOOKUP(EG$1,$BT$2:$CA$2,$BT8:$CA8,0) -> 0 | EH8: =$CT8*_xlfn.XLOOKUP(EH$1,$BT$2:$CA$2,$BT8:$CA8,0) -> 0 | EI8: =$CU8*_xlfn.XLOOKUP(EI$1,$BT$2:$CA$2,$BT8:$CA8,0) -> 0 | EJ8: =$CV8*_xlfn.XLOOKUP(EJ$1,$BT$2:$CA$2,$BT8:$CA8,0) -> 0 | EL8: =$CN8*_xlfn.XLOOKUP(EL$1,$BT$2:$CA$2,$BT8:$CA8,0) -> 0 | EM8: =$CO8*_xlfn.XLOOKUP(EM$1,$BT$2:$CA$2,$BT8:$CA8,0) -> 0 | EN8: =$CP8*_xlfn.XLOOKUP(EN$1,$BT$2:$CA$2,$BT8:$CA8,0) -> 0 | EO8: =$CQ8*_xlfn.XLOOKUP(EO$1,$BT$2:$CA$2,$BT8:$CA8,0) -> 0 | EP8: =$CR8*_xlfn.XLOOKUP(EP$1,$BT$2:$CA$2,$BT8:$CA8,0) -> 0 | EQ8: =$CS8*_xlfn.XLOOKUP(EQ$1,$BT$2:$CA$2,$BT8:$CA8,0) -> 0 | ER8: =$CT8*_xlfn.XLOOKUP(ER$1,$BT$2:$CA$2,$BT8:$CA8,0) -> 0 | ES8: =$CU8*_xlfn.XLOOKUP(ES$1,$BT$2:$CA$2,$BT8:$CA8,0) -> 0 | ET8: =$CV8*_xlfn.XLOOKUP(ET$1,$BT$2:$CA$2,$BT8:$CA8,0) -> 0 | EV8: =$CN8*_xlfn.XLOOKUP(EV$1,$BT$2:$CA$2,$BT8:$CA8,0) -> 0 | EW8: =$CO8*_xlfn.XLOOKUP(EW$1,$BT$2:$CA$2,$BT8:$CA8,0) -> 0 | EX8: =$CP8*_xlfn.XLOOKUP(EX$1,$BT$2:$CA$2,$BT8:$CA8,0) -> 0 | EY8: =$CQ8*_xlfn.XLOOKUP(EY$1,$BT$2:$CA$2,$BT8:$CA8,0) -> 0 | EZ8: =$CR8*_xlfn.XLOOKUP(EZ$1,$BT$2:$CA$2,$BT8:$CA8,0) -> 0 | FA8: =$CS8*_xlfn.XLOOKUP(FA$1,$BT$2:$CA$2,$BT8:$CA8,0) -> 0 | FB8: =$CT8*_xlfn.XLOOKUP(FB$1,$BT$2:$CA$2,$BT8:$CA8,0) -> 0 | FC8: =$CU8*_xlfn.XLOOKUP(FC$1,$BT$2:$CA$2,$BT8:$CA8,0) -> 0 | FD8: =$CV8*_xlfn.XLOOKUP(FD$1,$BT$2:$CA$2,$BT8:$CA8,0) -> 0 | FF8: =$CN8*_xlfn.XLOOKUP(FF$1,$BT$2:$CA$2,$BT8:$CA8,0) -> 0 | FG8: =$CO8*_xlfn.XLOOKUP(FG$1,$BT$2:$CA$2,$BT8:$CA8,0) -> 0 | FH8: =$CP8*_xlfn.XLOOKUP(FH$1,$BT$2:$CA$2,$BT8:$CA8,0) -> 0 | FI8: =$CQ8*_xlfn.XLOOKUP(FI$1,$BT$2:$CA$2,$BT8:$CA8,0) -> 0 | FJ8: =$CR8*_xlfn.XLOOKUP(FJ$1,$BT$2:$CA$2,$BT8:$CA8,0) -> 0 | FK8: =$CS8*_xlfn.XLOOKUP(FK$1,$BT$2:$CA$2,$BT8:$CA8,0) -> 0 | FL8: =$CT8*_xlfn.XLOOKUP(FL$1,$BT$2:$CA$2,$BT8:$CA8,0) -> 0 | FM8: =$CU8*_xlfn.XLOOKUP(FM$1,$BT$2:$CA$2,$BT8:$CA8,0) -> 0 | FN8: =$CV8*_xlfn.XLOOKUP(FN$1,$BT$2:$CA$2,$BT8:$CA8,0) -> 0 | FP8: =$CN8*_xlfn.XLOOKUP(FP$1,$BT$2:$CA$2,$BT8:$CA8,0) -> #REF! | FQ8: =$CO8*_xlfn.XLOOKUP(FQ$1,$BT$2:$CA$2,$BT8:$CA8,0) -> #REF! | FR8: =$CP8*_xlfn.XLOOKUP(FR$1,$BT$2:$CA$2,$BT8:$CA8,0) -> #REF! | FS8: =$CQ8*_xlfn.XLOOKUP(FS$1,$BT$2:$CA$2,$BT8:$CA8,0) -> #REF! | FT8: =$CR8*_xlfn.XLOOKUP(FT$1,$BT$2:$CA$2,$BT8:$CA8,0) -> #REF! | FU8: =$CS8*_xlfn.XLOOKUP(FU$1,$BT$2:$CA$2,$BT8:$CA8,0) -> #REF! | FV8: =$CT8*_xlfn.XLOOKUP(FV$1,$BT$2:$CA$2,$BT8:$CA8,0) -> #REF! | FW8: =$CU8*_xlfn.XLOOKUP(FW$1,$BT$2:$CA$2,$BT8:$CA8,0) -> #REF! | FX8: =$CV8*_xlfn.XLOOKUP(FX$1,$BT$2:$CA$2,$BT8:$CA8,0) -> #REF! | GB8: =IF(GB$2=InputTable[[#This Row],[Delivery Date]],_xlfn.XLOOKUP(GB$1,$BH$2:$BR$2,$BH8:$BR8,0),0) -> #REF! | GC8: =IF(GC$2=InputTable[[#This Row],[Delivery Date]],_xlfn.XLOOKUP(GC$1,$BH$2:$BR$2,$BH8:$BR8,0),0) -> 0 | GD8: =IF(GD$2=InputTable[[#This Row],[Delivery Date]],_xlfn.XLOOKUP(GD$1,$BH$2:$BR$2,$BH8:$BR8,0),0) -> 0 | GE8: =IF(GE$2=InputTable[[#This Row],[Delivery Date]],_xlfn.XLOOKUP(GE$1,$BH$2:$BR$2,$BH8:$BR8,0),0) -> 0 | GF8: =IF(GF$2=InputTable[[#This Row],[Delivery Date]],_xlfn.XLOOKUP(GF$1,$BH$2:$BR$2,$BH8:$BR8,0),0) -> 0 | GG8: =IF(GG$2=InputTable[[#This Row],[Delivery Date]],_xlfn.XLOOKUP(GG$1,$BH$2:$BR$2,$BH8:$BR8,0),0) -> 0 | GH8: =IF(GH$2=InputTable[[#This Row],[Delivery Date]],_xlfn.XLOOKUP(GH$1,$BH$2:$BR$2,$BH8:$BR8,0),0) -> 0 | GI8: =IF(GI$2=InputTable[[#This Row],[Delivery Date]],_xlfn.XLOOKUP(GI$1,$BH$2:$BR$2,$BH8:$BR8,0),0) -> 0 | GJ8: =IF(GJ$2=InputTable[[#This Row],[Delivery Date]],_xlfn.XLOOKUP(GJ$1,$BH$2:$BR$2,$BH8:$BR8,0),0) -> 0 | GL8: =IF(GL$2=InputTable[[#This Row],[Delivery Date]],_xlfn.XLOOKUP(GL$1,$BH$2:$BR$2,$BH8:$BR8,0),0) -> #REF! | GM8: =IF(GM$2=InputTable[[#This Row],[Delivery Date]],_xlfn.XLOOKUP(GM$1,$BH$2:$BR$2,$BH8:$BR8,0),0) -> 0 | GN8: =IF(GN$2=InputTable[[#This Row],[Delivery Date]],_xlfn.XLOOKUP(GN$1,$BH$2:$BR$2,$BH8:$BR8,0),0) -> 0 | GO8: =IF(GO$2=InputTable[[#This Row],[Delivery Date]],_xlfn.XLOOKUP(GO$1,$BH$2:$BR$2,$BH8:$BR8,0),0) -> 0 | GP8: =IF(GP$2=InputTable[[#This Row],[Delivery Date]],_xlfn.XLOOKUP(GP$1,$BH$2:$BR$2,$BH8:$BR8,0),0) -> 0 | GQ8: =IF(GQ$2=InputTable[[#This Row],[Delivery Date]],_xlfn.XLOOKUP(GQ$1,$BH$2:$BR$2,$BH8:$BR8,0),0) -> 0 | GR8: =IF(GR$2=InputTable[[#This Row],[Delivery Date]],_xlfn.XLOOKUP(GR$1,$BH$2:$BR$2,$BH8:$BR8,0),0) -> 0 | GS8: =IF(GS$2=InputTable[[#This Row],[Delivery Date]],_xlfn.XLOOKUP(GS$1,$BH$2:$BR$2,$BH8:$BR8,0),0) -> 0 | GT8: =IF(GT$2=InputTable[[#This Row],[Delivery Date]],_xlfn.XLOOKUP(GT$1,$BH$2:$BR$2,$BH8:$BR8,0),0) -> 0 | GV8: =IF(GV$2=InputTable[[#This Row],[Delivery Date]],_xlfn.XLOOKUP(GV$1,$BH$2:$BR$2,$BH8:$BR8,0),0) -> #REF! | GW8: =IF(GW$2=InputTable[[#This Row],[Delivery Date]],_xlfn.XLOOKUP(GW$1,$BH$2:$BR$2,$BH8:$BR8,0),0) -> 0 | GX8: =IF(GX$2=InputTable[[#This Row],[Delivery Date]],_xlfn.XLOOKUP(GX$1,$BH$2:$BR$2,$BH8:$BR8,0),0) -> 0 | GY8: =IF(GY$2=InputTable[[#This Row],[Delivery Date]],_xlfn.XLOOKUP(GY$1,$BH$2:$BR$2,$BH8:$BR8,0),0) -> 0 | GZ8: =IF(GZ$2=InputTable[[#This Row],[Delivery Date]],_xlfn.XLOOKUP(GZ$1,$BH$2:$BR$2,$BH8:$BR8,0),0) -> 0 | HA8: =IF(HA$2=InputTable[[#This Row],[Delivery Date]],_xlfn.XLOOKUP(HA$1,$BH$2:$BR$2,$BH8:$BR8,0),0) -> 0 | HB8: =IF(HB$2=InputTable[[#This Row],[Delivery Date]],_xlfn.XLOOKUP(HB$1,$BH$2:$BR$2,$BH8:$BR8,0),0) -> 0 | HC8: =IF(HC$2=InputTable[[#This Row],[Delivery Date]],_xlfn.XLOOKUP(HC$1,$BH$2:$BR$2,$BH8:$BR8,0),0) -> 0 | HD8: =IF(HD$2=InputTable[[#This Row],[Delivery Date]],_xlfn.XLOOKUP(HD$1,$BH$2:$BR$2,$BH8:$BR8,0),0) -> 0 | HF8: =IF(HF$2=InputTable[[#This Row],[Delivery Date]],_xlfn.XLOOKUP(HF$1,$BH$2:$BR$2,$BH8:$BR8,0),0) -> #REF! | HG8: =IF(HG$2=InputTable[[#This Row],[Delivery Date]],_xlfn.XLOOKUP(HG$1,$BH$2:$BR$2,$BH8:$BR8,0),0) -> 0 | HH8: =IF(HH$2=InputTable[[#This Row],[Delivery Date]],_xlfn.XLOOKUP(HH$1,$BH$2:$BR$2,$BH8:$BR8,0),0) -> 0 | HI8: =IF(HI$2=InputTable[[#This Row],[Delivery Date]],_xlfn.XLOOKUP(HI$1,$BH$2:$BR$2,$BH8:$BR8,0),0) -> 0 | HJ8: =IF(HJ$2=InputTable[[#This Row],[Delivery Date]],_xlfn.XLOOKUP(HJ$1,$BH$2:$BR$2,$BH8:$BR8,0),0) -> 0 | HK8: =IF(HK$2=InputTable[[#This Row],[Delivery Date]],_xlfn.XLOOKUP(HK$1,$BH$2:$BR$2,$BH8:$BR8,0),0) -> 0 | HL8: =IF(HL$2=InputTable[[#This Row],[Delivery Date]],_xlfn.XLOOKUP(HL$1,$BH$2:$BR$2,$BH8:$BR8,0),0) -> 0 | HM8: =IF(HM$2=InputTable[[#This Row],[Delivery Date]],_xlfn.XLOOKUP(HM$1,$BH$2:$BR$2,$BH8:$BR8,0),0) -> 0 | HN8: =IF(HN$2=InputTable[[#This Row],[Delivery Date]],_xlfn.XLOOKUP(HN$1,$BH$2:$BR$2,$BH8:$BR8,0),0) -> 0 | HP8: =IF(HP$2=InputTable[[#This Row],[Delivery Date]],_xlfn.XLOOKUP(HP$1,$BH$2:$BR$2,$BH8:$BR8,0),0) -> #REF! | HQ8: =IF(HQ$2=InputTable[[#This Row],[Delivery Date]],_xlfn.XLOOKUP(HQ$1,$BH$2:$BR$2,$BH8:$BR8,0),0) -> 0 | HR8: =IF(HR$2=InputTable[[#This Row],[Delivery Date]],_xlfn.XLOOKUP(HR$1,$BH$2:$BR$2,$BH8:$BR8,0),0) -> 0 | HS8: =IF(HS$2=InputTable[[#This Row],[Delivery Date]],_xlfn.XLOOKUP(HS$1,$BH$2:$BR$2,$BH8:$BR8,0),0) -> 0 | HT8: =IF(HT$2=InputTable[[#This Row],[Delivery Date]],_xlfn.XLOOKUP(HT$1,$BH$2:$BR$2,$BH8:$BR8,0),0) -> 0 | HU8: =IF(HU$2=InputTable[[#This Row],[Delivery Date]],_xlfn.XLOOKUP(HU$1,$BH$2:$BR$2,$BH8:$BR8,0),0) -> 0 | HV8: =IF(HV$2=InputTable[[#This Row],[Delivery Date]],_xlfn.XLOOKUP(HV$1,$BH$2:$BR$2,$BH8:$BR8,0),0) -> 0 | HW8: =IF(HW$2=InputTable[[#This Row],[Delivery Date]],_xlfn.XLOOKUP(HW$1,$BH$2:$BR$2,$BH8:$BR8,0),0) -> 0 | HX8: =IF(HX$2=InputTable[[#This Row],[Delivery Date]],_xlfn.XLOOKUP(HX$1,$BH$2:$BR$2,$BH8:$BR8,0),0) -> 0 | HZ8: =IF(HZ$2=InputTable[[#This Row],[Delivery Date]],_xlfn.XLOOKUP(HZ$1,$BH$2:$BR$2,$BH8:$BR8,0),0) -> #REF! | IA8: =IF(IA$2=InputTable[[#This Row],[Delivery Date]],_xlfn.XLOOKUP(IA$1,$BH$2:$BR$2,$BH8:$BR8,0),0) -> 0 | IB8: =IF(IB$2=InputTable[[#This Row],[Delivery Date]],_xlfn.XLOOKUP(IB$1,$BH$2:$BR$2,$BH8:$BR8,0),0) -> 0 | IC8: =IF(IC$2=InputTable[[#This Row],[Delivery Date]],_xlfn.XLOOKUP(IC$1,$BH$2:$BR$2,$BH8:$BR8,0),0) -> 0 | ID8: =IF(ID$2=InputTable[[#This Row],[Delivery Date]],_xlfn.XLOOKUP(ID$1,$BH$2:$BR$2,$BH8:$BR8,0),0) -> 0 | IE8: =IF(IE$2=InputTable[[#This Row],[Delivery Date]],_xlfn.XLOOKUP(IE$1,$BH$2:$BR$2,$BH8:$BR8,0),0) -> 0 | IF8: =IF(IF$2=InputTable[[#This Row],[Delivery Date]],_xlfn.XLOOKUP(IF$1,$BH$2:$BR$2,$BH8:$BR8,0),0) -> 0 | IG8: =IF(IG$2=InputTable[[#This Row],[Delivery Date]],_xlfn.XLOOKUP(IG$1,$BH$2:$BR$2,$BH8:$BR8,0),0) -> 0 | IH8: =IF(IH$2=InputTable[[#This Row],[Delivery Date]],_xlfn.XLOOKUP(IH$1,$BH$2:$BR$2,$BH8:$BR8,0),0) -> 0 | IJ8: =IF(IJ$2=InputTable[[#This Row],[Delivery Date]],_xlfn.XLOOKUP(IJ$1,$BH$2:$BR$2,$BH8:$BR8,0),0) -> #REF! | IK8: =IF(IK$2=InputTable[[#This Row],[Delivery Date]],_xlfn.XLOOKUP(IK$1,$BH$2:$BR$2,$BH8:$BR8,0),0) -> 0 | IL8: =IF(IL$2=InputTable[[#This Row],[Delivery Date]],_xlfn.XLOOKUP(IL$1,$BH$2:$BR$2,$BH8:$BR8,0),0) -> 0 | IM8: =IF(IM$2=InputTable[[#This Row],[Delivery Date]],_xlfn.XLOOKUP(IM$1,$BH$2:$BR$2,$BH8:$BR8,0),0) -> 0 | IN8: =IF(IN$2=InputTable[[#This Row],[Delivery Date]],_xlfn.XLOOKUP(IN$1,$BH$2:$BR$2,$BH8:$BR8,0),0) -> 0 | IO8: =IF(IO$2=InputTable[[#This Row],[Delivery Date]],_xlfn.XLOOKUP(IO$1,$BH$2:$BR$2,$BH8:$BR8,0),0) -> 0 | IP8: =IF(IP$2=InputTable[[#This Row],[Delivery Date]],_xlfn.XLOOKUP(IP$1,$BH$2:$BR$2,$BH8:$BR8,0),0) -> 0 | IQ8: =IF(IQ$2=InputTable[[#This Row],[Delivery Date]],_xlfn.XLOOKUP(IQ$1,$BH$2:$BR$2,$BH8:$BR8,0),0) -> 0 | IR8: =IF(IR$2=InputTable[[#This Row],[Delivery Date]],_xlfn.XLOOKUP(IR$1,$BH$2:$BR$2,$BH8:$BR8,0),0) -> 0 | IT8: =IF(IT$2=InputTable[[#This Row],[Delivery Date]],_xlfn.XLOOKUP(IT$1,$BH$2:$BR$2,$BH8:$BR8,0),0) -> #REF! | IU8: =IF(IU$2=InputTable[[#This Row],[Delivery Date]],_xlfn.XLOOKUP(IU$1,$BH$2:$BR$2,$BH8:$BR8,0),0) -> 0 | IV8: =IF(IV$2=InputTable[[#This Row],[Delivery Date]],_xlfn.XLOOKUP(IV$1,$BH$2:$BR$2,$BH8:$BR8,0),0) -> 0 | IW8: =IF(IW$2=InputTable[[#This Row],[Delivery Date]],_xlfn.XLOOKUP(IW$1,$BH$2:$BR$2,$BH8:$BR8,0),0) -> 0 | IX8: =IF(IX$2=InputTable[[#This Row],[Delivery Date]],_xlfn.XLOOKUP(IX$1,$BH$2:$BR$2,$BH8:$BR8,0),0) -> 0 | IY8: =IF(IY$2=InputTable[[#This Row],[Delivery Date]],_xlfn.XLOOKUP(IY$1,$BH$2:$BR$2,$BH8:$BR8,0),0) -> 0 | IZ8: =IF(IZ$2=InputTable[[#This Row],[Delivery Date]],_xlfn.XLOOKUP(IZ$1,$BH$2:$BR$2,$BH8:$BR8,0),0) -> 0 | JA8: =IF(JA$2=InputTable[[#This Row],[Delivery Date]],_xlfn.XLOOKUP(JA$1,$BH$2:$BR$2,$BH8:$BR8,0),0) -> 0 | JB8: =IF(JB$2=InputTable[[#This Row],[Delivery Date]],_xlfn.XLOOKUP(JB$1,$BH$2:$BR$2,$BH8:$BR8,0),0) -> 0 | JD8: =IF(JD$2=InputTable[[#This Row],[Delivery Date]],_xlfn.XLOOKUP(JD$1,$BH$2:$BR$2,$BH8:$BR8,0),0) -> #REF! | JE8: =IF(JE$2=InputTable[[#This Row],[Delivery Date]],_xlfn.XLOOKUP(JE$1,$BH$2:$BR$2,$BH8:$BR8,0),0) -> 0 | JF8: =IF(JF$2=InputTable[[#This Row],[Delivery Date]],_xlfn.XLOOKUP(JF$1,$BH$2:$BR$2,$BH8:$BR8,0),0) -> 0 | JG8: =IF(JG$2=InputTable[[#This Row],[Delivery Date]],_xlfn.XLOOKUP(JG$1,$BH$2:$BR$2,$BH8:$BR8,0),0) -> 0 | JH8: =IF(JH$2=InputTable[[#This Row],[Delivery Date]],_xlfn.XLOOKUP(JH$1,$BH$2:$BR$2,$BH8:$BR8,0),0) -> 0 | JI8: =IF(JI$2=InputTable[[#This Row],[Delivery Date]],_xlfn.XLOOKUP(JI$1,$BH$2:$BR$2,$BH8:$BR8,0),0) -> 0 | JJ8: =IF(JJ$2=InputTable[[#This Row],[Delivery Date]],_xlfn.XLOOKUP(JJ$1,$BH$2:$BR$2,$BH8:$BR8,0),0) -> 0 | JK8: =IF(JK$2=InputTable[[#This Row],[Delivery Date]],_xlfn.XLOOKUP(JK$1,$BH$2:$BR$2,$BH8:$BR8,0),0) -> 0 | JL8: =IF(JL$2=InputTable[[#This Row],[Delivery Date]],_xlfn.XLOOKUP(JL$1,$BH$2:$BR$2,$BH8:$BR8,0),0) -> 0 | JN8: =IF(JN$2=InputTable[[#This Row],[Delivery Date]],_xlfn.XLOOKUP(JN$1,$BH$2:$BR$2,$BH8:$BR8,0),0) -> #REF! | JO8: =IF(JO$2=InputTable[[#This Row],[Delivery Date]],_xlfn.XLOOKUP(JO$1,$BH$2:$BR$2,$BH8:$BR8,0),0) -> 0 | JP8: =IF(JP$2=InputTable[[#This Row],[Delivery Date]],_xlfn.XLOOKUP(JP$1,$BH$2:$BR$2,$BH8:$BR8,0),0) -> 0 | JQ8: =IF(JQ$2=InputTable[[#This Row],[Delivery Date]],_xlfn.XLOOKUP(JQ$1,$BH$2:$BR$2,$BH8:$BR8,0),0) -> 0 | JR8: =IF(JR$2=InputTable[[#This Row],[Delivery Date]],_xlfn.XLOOKUP(JR$1,$BH$2:$BR$2,$BH8:$BR8,0),0) -> 0 | JS8: =IF(JS$2=InputTable[[#This Row],[Delivery Date]],_xlfn.XLOOKUP(JS$1,$BH$2:$BR$2,$BH8:$BR8,0),0) -> 0 | JT8: =IF(JT$2=InputTable[[#This Row],[Delivery Date]],_xlfn.XLOOKUP(JT$1,$BH$2:$BR$2,$BH8:$BR8,0),0) -> 0 | JU8: =IF(JU$2=InputTable[[#This Row],[Delivery Date]],_xlfn.XLOOKUP(JU$1,$BH$2:$BR$2,$BH8:$BR8,0),0) -> 0 | JV8: =IF(JV$2=InputTable[[#This Row],[Delivery Date]],_xlfn.XLOOKUP(JV$1,$BH$2:$BR$2,$BH8:$BR8,0),0) -> 0 | JX8: =IF(JX$2=InputTable[[#This Row],[Delivery Date]],_xlfn.XLOOKUP(JX$1,$BH$2:$BR$2,$BH8:$BR8,0),0) -> #REF! | JY8: =IF(JY$2=InputTable[[#This Row],[Delivery Date]],_xlfn.XLOOKUP(JY$1,$BH$2:$BR$2,$BH8:$BR8,0),0) -> 0 | JZ8: =IF(JZ$2=InputTable[[#This Row],[Delivery Date]],_xlfn.XLOOKUP(JZ$1,$BH$2:$BR$2,$BH8:$BR8,0),0) -> 0 | KA8: =IF(KA$2=InputTable[[#This Row],[Delivery Date]],_xlfn.XLOOKUP(KA$1,$BH$2:$BR$2,$BH8:$BR8,0),0) -> 0 | KB8: =IF(KB$2=InputTable[[#This Row],[Delivery Date]],_xlfn.XLOOKUP(KB$1,$BH$2:$BR$2,$BH8:$BR8,0),0) -> 0 | KC8: =IF(KC$2=InputTable[[#This Row],[Delivery Date]],_xlfn.XLOOKUP(KC$1,$BH$2:$BR$2,$BH8:$BR8,0),0) -> 0 | KD8: =IF(KD$2=InputTable[[#This Row],[Delivery Date]],_xlfn.XLOOKUP(KD$1,$BH$2:$BR$2,$BH8:$BR8,0),0) -> 0 | KE8: =IF(KE$2=InputTable[[#This Row],[Delivery Date]],_xlfn.XLOOKUP(KE$1,$BH$2:$BR$2,$BH8:$BR8,0),0) -> 0 | KF8: =IF(KF$2=InputTable[[#This Row],[Delivery Date]],_xlfn.XLOOKUP(KF$1,$BH$2:$BR$2,$BH8:$BR8,0),0) -> 0
B9: Stopped in 2025 | C9: DIGITAL TECH | D9: ISPRJ-103 | E9: MYB : upgrade optimisation, assistance aftersales, meal pref… | F9: COMMERCIAL | G9: 2025 Q1 | H9: Q4 2025 | I9: 2025 Q4 | K9: =VLOOKUP((InputTable[[#This Row],[Starting Date]]& " - " &InputTable[[#This Row],[Delivery Date]]),'System List'!$F$40:$H$83,2,FALSE) -> #N/A | L9: =VLOOKUP(InputTable[[#This Row],[Duration]],Duration,2,FALSE) -> #N/A | M9: yes | O9: L | T9: {=SUM( _xlfn.XLOOKUP(InputTable[[#This Row],[Safety]:[Regulatory]], 'System List'!$F$4:$F$7, 'System List'!$G$4:$G$7, 0) * _xlfn.XLOOKUP(InputTable[[#Headers],[Safety]:[Regulatory]], 'System List'!$Y$4:$Y$10, 'System List'!$Z$4:$Z$10, 0) )} -> 1 | AD9: =COUNTA(InputTable[[#This Row],[CORPHRFIN]:[SALES]]) -> 0 | AE9: {=SUM( _xlfn.XLOOKUP(InputTable[[#This Row],[CORPHRFIN]:[SALES]],'System List'!$F$4:$F$7,'System List'!$H$4:$H$7,0))} -> 0 | AR9: {=SUM( _xlfn.XLOOKUP(InputTable[[#This Row],[Impact on - CIAL]:[Impact on - STRAT]],'System List'!$F$4:$F$7,'System List'!$H$4:$H$7,0))} -> 0 | AS9: =VLOOKUP(InputTable[[#This Row],[Duration]],Duration,2,FALSE)+InputTable[[#This Row],[Resource Score]] -> #N/A | AT9: =(( VLOOKUP(InputTable[[#This Row],[Duration]],'System List'!$J$5:$K$10,2,FALSE)*VLOOKUP(InputTable[[#Headers],[Duration]],'System List'!$V$5:$W$8,2,FALSE) + VLOOKUP(InputTable[[#This Row],[Number of Team Involved]],'System List'!$M$5:$N$13,2,FALSE)*VLOOKUP(InputTable[[#Headers],[Number of Team Involved]],'System List'!$V$5:$W$8,2,FALSE) + VLOOKUP(InputTable[[#This Row],[Resource Score]],Resource_Score,2,FALSE)*VLOOKUP(InputTable[[#Headers],[Resource Score]],'System List'!$V$5:$W$8,2,FALSE) + VLOOKUP(InputTable[[#This Row],[CHANGE Impact Score]],CHANGE_Impact_Score,2,FALSE)*VLOOKUP(InputTable[[#Headers],[CHANGE Impact Score]],'System List'!$V$5:$W$8,2,FALSE)) * 100) / 13 -> #N/A | AU9: =InputTable[[#This Row],[Value Score]]/InputTable[[#This Row],[EFFORT SCORE]]*100 -> #N/A | AW9: Xavier ROMANET | AZ9: 0 | BA9: 0
B10: Stopped in 2025 | C10: DIGITAL TECH | D10: ISPRJ-104 | E10: E4B dashboard/invoices | F10: COMMERCIAL | G10: 2025 Q1 | I10: 2025 Q4 | K10: =VLOOKUP((InputTable[[#This Row],[Starting Date]]& " - " &InputTable[[#This Row],[Delivery Date]]),'System List'!$F$40:$H$83,2,FALSE) -> #N/A | L10: =VLOOKUP(InputTable[[#This Row],[Duration]],Duration,2,FALSE) -> #N/A | M10: yes | O10: L | T10: {=SUM( _xlfn.XLOOKUP(InputTable[[#This Row],[Safety]:[Regulatory]], 'System List'!$F$4:$F$7, 'System List'!$G$4:$G$7, 0) * _xlfn.XLOOKUP(InputTable[[#Headers],[Safety]:[Regulatory]], 'System List'!$Y$4:$Y$10, 'System List'!$Z$4:$Z$10, 0) )} -> 1 | AD10: =COUNTA(InputTable[[#This Row],[CORPHRFIN]:[SALES]]) -> 0 | AE10: {=SUM( _xlfn.XLOOKUP(InputTable[[#This Row],[CORPHRFIN]:[SALES]],'System List'!$F$4:$F$7,'System List'!$H$4:$H$7,0))} -> 0 | AR10: {=SUM( _xlfn.XLOOKUP(InputTable[[#This Row],[Impact on - CIAL]:[Impact on - STRAT]],'System List'!$F$4:$F$7,'System List'!$H$4:$H$7,0))} -> 0 | AS10: =VLOOKUP(InputTable[[#This Row],[Duration]],Duration,2,FALSE)+InputTable[[#This Row],[Resource Score]] -> #N/A | AT10: =(( VLOOKUP(InputTable[[#This Row],[Duration]],'System List'!$J$5:$K$10,2,FALSE)*VLOOKUP(InputTable[[#Headers],[Duration]],'System List'!$V$5:$W$8,2,FALSE) + VLOOKUP(InputTable[[#This Row],[Number of Team Involved]],'System List'!$M$5:$N$13,2,FALSE)*VLOOKUP(InputTable[[#Headers],[Number of Team Involved]],'System List'!$V$5:$W$8,2,FALSE) + VLOOKUP(InputTable[[#This Row],[Resource Score]],Resource_Score,2,FALSE)*VLOOKUP(InputTable[[#Headers],[Resource Score]],'System List'!$V$5:$W$8,2,FALSE) + VLOOKUP(InputTable[[#This Row],[CHANGE Impact Score]],CHANGE_Impact_Score,2,FALSE)*VLOOKUP(InputTable[[#Headers],[CHANGE Impact Score]],'System List'!$V$5:$W$8,2,FALSE)) * 100) / 13 -> #N/A | AU10: =InputTable[[#This Row],[Value Score]]/InputTable[[#This Row],[EFFORT SCORE]]*100 -> #N/A | AW10: Xavier ROMANET | AZ10: 0 | BA10: 0 | BH10: =IFERROR(VLOOKUP(InputTable[[#This Row],[Impact on - CIAL]],'System List'!$F$4:$H$7,3,FALSE),0) -> 0 | BI10: =IFERROR(VLOOKUP(InputTable[[#This Row],[Impact on - COM]],'System List'!$F$4:$H$7,3,FALSE),0) -> 0 | BJ10: =IFERROR(VLOOKUP(InputTable[[#This Row],[Impact on - FIN]],'System List'!$F$4:$H$7,3,FALSE),0) -> 0 | BK10: =IFERROR(VLOOKUP(InputTable[[#This Row],[Impact on - GEN SEC]],'System List'!$F$4:$H$7,3,FALSE),0) -> 0 | BL10: =IFERROR(VLOOKUP(InputTable[[#This Row],[Impact on - HR]],'System List'!$F$4:$H$7,3,FALSE),0) -> 0 | BM10: =IFERROR(VLOOKUP(InputTable[[#This Row],[Impact on - IS]],'System List'!$F$4:$H$7,3,FALSE),0) -> 0 | BN10: =IFERROR(VLOOKUP(InputTable[[#This Row],[Impact on - OPS]],'System List'!$F$4:$H$7,3,FALSE),0) -> 0 | BO10: =IFERROR(VLOOKUP(InputTable[[#This Row],[Impact on - ROLL STOCK]],'System List'!$F$4:$H$7,3,FALSE),0) -> 0 | BP10: =IFERROR(VLOOKUP(InputTable[[#This Row],[Impact on - SAFETY]],'System List'!$F$4:$H$7,3,FALSE),0) -> 0 | BQ10: =IFERROR(VLOOKUP(InputTable[[#This Row],[Impact on - STATION]],'System List'!$F$4:$H$7,3,FALSE),0) -> 0 | BR10: =IFERROR(VLOOKUP(InputTable[[#This Row],[Impact on - STRAT]],'System List'!$F$4:$H$7,3,FALSE),0) -> 0 | BT10: =IFERROR(VLOOKUP(InputTable[[#This Row],[CORPHRFIN]],'System List'!$F$4:$H$7,3,FALSE),0) -> 0 | BU10: =IFERROR(VLOOKUP(InputTable[[#This Row],[CUST]],'System List'!$F$4:$H$7,3,FALSE),0) -> 0 | BV10: =IFERROR(VLOOKUP(InputTable[[#This Row],[CYBER]],'System List'!$F$4:$H$7,3,FALSE),0) -> 0 | BW10: =IFERROR(VLOOKUP(InputTable[[#This Row],[DATA]],'System List'!$F$4:$H$7,3,FALSE),0) -> 0 | BX10: =IFERROR(VLOOKUP(InputTable[[#This Row],[INFRA]],'System List'!$F$4:$H$7,3,FALSE),0) -> 0 | BY10: =IFERROR(VLOOKUP(InputTable[[#This Row],[OPERATIONS]],'System List'!$F$4:$H$7,3,FALSE),0) -> 0 | BZ10: =IFERROR(VLOOKUP(InputTable[[#This Row],[PMO]],'System List'!$F$4:$H$7,3,FALSE),0) -> 0 | CA10: =IFERROR(VLOOKUP(InputTable[[#This Row],[SALES]],'System List'!$F$4:$H$7,3,FALSE),0) -> 0 | CC10: {=IFERROR( IF( AND( MATCH(InputTable[[#This Row],[Starting Date]],'System List'!$B$5:$B$16,0)<=MATCH(Input!CC$2,'System List'!$B$5:$B$16,0), MATCH(Input!CC$2,'System List'!$B$5:$B$16<=MATCH(InputTable[[#This Row],[Delivery Date]],'System List'!$B$5:$B$16,0))),1,0), )} -> 0 | CD10: {=IFERROR( IF( AND( MATCH(InputTable[[#This Row],[Starting Date]],'System List'!$B$5:$B$16,0)<=MATCH(Input!CD$2,'System List'!$B$5:$B$16,0), MATCH(Input!CD$2,'System List'!$B$5:$B$16<=MATCH(InputTable[[#This Row],[Delivery Date]],'System List'!$B$5:$B$16,0))),1,0), )} -> 0 | CE10: {=IFERROR( IF( AND( MATCH(InputTable[[#This Row],[Starting Date]],'System List'!$B$5:$B$16,0)<=MATCH(Input!CE$2,'System List'!$B$5:$B$16,0), MATCH(Input!CE$2,'System List'!$B$5:$B$16<=MATCH(InputTable[[#This Row],[Delivery Date]],'System List'!$B$5:$B$16,0))),1,0), )} -> 0 | CF10: {=IFERROR( IF( AND( MATCH(InputTable[[#This Row],[Starting Date]],'System List'!$B$5:$B$16,0)<=MATCH(Input!CF$2,'System List'!$B$5:$B$16,0), MATCH(Input!CF$2,'System List'!$B$5:$B$16<=MATCH(InputTable[[#This Row],[Delivery Date]],'System List'!$B$5:$B$16,0))),1,0), )} -> 0 | CG10: {=IFERROR( IF( AND( MATCH(InputTable[[#This Row],[Starting Date]],'System List'!$B$5:$B$16,0)<=MATCH(Input!CG$2,'System List'!$B$5:$B$16,0), MATCH(Input!CG$2,'System List'!$B$5:$B$16<=MATCH(InputTable[[#This Row],[Delivery Date]],'System List'!$B$5:$B$16,0))),1,0), )} -> 0 | CH10: {=IFERROR( IF( AND( MATCH(InputTable[[#This Row],[Starting Date]],'System List'!$B$5:$B$16,0)<=MATCH(Input!CH$2,'System List'!$B$5:$B$16,0), MATCH(Input!CH$2,'System List'!$B$5:$B$16<=MATCH(InputTable[[#This Row],[Delivery Date]],'System List'!$B$5:$B$16,0))),1,0), )} -> 0 | CI10: {=IFERROR( IF( AND( MATCH(InputTable[[#This Row],[Starting Date]],'System List'!$B$5:$B$16,0)<=MATCH(Input!CI$2,'System List'!$B$5:$B$16,0), MATCH(Input!CI$2,'System List'!$B$5:$B$16<=MATCH(InputTable[[#This Row],[Delivery Date]],'System List'!$B$5:$B$16,0))),1,0), )} -> 0 | CJ10: {=IFERROR( IF( AND( MATCH(InputTable[[#This Row],[Starting Date]],'System List'!$B$5:$B$16,0)<=MATCH(Input!CJ$2,'System List'!$B$5:$B$16,0), MATCH(Input!CJ$2,'System List'!$B$5:$B$16<=MATCH(InputTable[[#This Row],[Delivery Date]],'System List'!$B$5:$B$16,0))),1,0), )} -> 0 | CK10: {=IFERROR( IF( AND( MATCH(InputTable[[#This Row],[Starting Date]],'System List'!$B$5:$B$16,0)<=MATCH(Input!CK$2,'System List'!$B$5:$B$16,0), MATCH(Input!CK$2,'System List'!$B$5:$B$16<=MATCH(InputTable[[#This Row],[Delivery Date]],'System List'!$B$5:$B$16,0))),1,0), )} -> 0 | CN10: =IFERROR( IF(AND( MATCH(InputTable[[#This Row],[Starting Date]],'System List'!$B$5:$B$16,0)<=MATCH(CN$2,'System List'!$B$5:$B$16,0), MATCH(CN$2,'System List'!$B$5:$B$16,0)<=MATCH(InputTable[[#This Row],[Delivery Date]],'System List'!$B$5:$B$16,0)),1,0),0) -> 0 | CO10: =IFERROR( IF(AND( MATCH(InputTable[[#This Row],[Starting Date]],'System List'!$B$5:$B$16,0)<=MATCH(CO$2,'System List'!$B$5:$B$16,0), MATCH(CO$2,'System List'!$B$5:$B$16,0)<=MATCH(InputTable[[#This Row],[Delivery Date]],'System List'!$B$5:$B$16,0)),1,0),0) -> 0 | CP10: =IFERROR( IF(AND( MATCH(InputTable[[#This Row],[Starting Date]],'System List'!$B$5:$B$16,0)<=MATCH(CP$2,'System List'!$B$5:$B$16,0), MATCH(CP$2,'System List'!$B$5:$B$16,0)<=MATCH(InputTable[[#This Row],[Delivery Date]],'System List'!$B$5:$B$16,0)),1,0),0) -> 1 | CQ10: =IFERROR( IF(AND( MATCH(InputTable[[#This Row],[Starting Date]],'System List'!$B$5:$B$16,0)<=MATCH(CQ$2,'System List'!$B$5:$B$16,0), MATCH(CQ$2,'System List'!$B$5:$B$16,0)<=MATCH(InputTable[[#This Row],[Delivery Date]],'System List'!$B$5:$B$16,0)),1,0),0) -> 1 | CR10: =IFERROR( IF(AND( MATCH(InputTable[[#This Row],[Starting Date]],'System List'!$B$5:$B$16,0)<=MATCH(CR$2,'System List'!$B$5:$B$16,0), MATCH(CR$2,'System List'!$B$5:$B$16,0)<=MATCH(InputTable[[#This Row],[Delivery Date]],'System List'!$B$5:$B$16,0)),1,0),0) -> 1 | CS10: =IFERROR( IF(AND( MATCH(InputTable[[#This Row],[Starting Date]],'System List'!$B$5:$B$16,0)<=MATCH(CS$2,'System List'!$B$5:$B$16,0), MATCH(CS$2,'System List'!$B$5:$B$16,0)<=MATCH(InputTable[[#This Row],[Delivery Date]],'System List'!$B$5:$B$16,0)),1,0),0) -> 1 | CT10: =IFERROR( IF(AND( MATCH(InputTable[[#This Row],[Starting Date]],'System List'!$B$5:$B$16,0)<=MATCH(CT$2,'System List'!$B$5:$B$16,0), MATCH(CT$2,'System List'!$B$5:$B$16,0)<=MATCH(InputTable[[#This Row],[Delivery Date]],'System List'!$B$5:$B$16,0)),1,0),0) -> 0 | CU10: =IFERROR( IF(AND( MATCH(InputTable[[#This Row],[Starting Date]],'System List'!$B$5:$B$16,0)<=MATCH(CU$2,'System List'!$B$5:$B$16,0), MATCH(CU$2,'System List'!$B$5:$B$16,0)<=MATCH(InputTable[[#This Row],[Delivery Date]],'System List'!$B$5:$B$16,0)),1,0),0) -> 0 | CV10: =IFERROR( IF(AND( MATCH(InputTable[[#This Row],[Starting Date]],'System List'!$B$5:$B$16,0)<=MATCH(CV$2,'System List'!$B$5:$B$16,0), MATCH(CV$2,'System List'!$B$5:$B$16,0)<=MATCH(InputTable[[#This Row],[Delivery Date]],'System List'!$B$5:$B$16,0)),1,0),0) -> 0 | CX10: =CN10*_xlfn.XLOOKUP(CX$1,$BT$2:$CA$2,$BT10:$CA10,0) -> 0 | CY10: =CO10*_xlfn.XLOOKUP(CY$1,$BT$2:$CA$2,$BT10:$CA10,0) -> 0 | CZ10: =CP10*_xlfn.XLOOKUP(CZ$1,$BT$2:$CA$2,$BT10:$CA10,0) -> 0 | DA10: =CQ10*_xlfn.XLOOKUP(DA$1,$BT$2:$CA$2,$BT10:$CA10,0) -> 0 | DB10: =CR10*_xlfn.XLOOKUP(DB$1,$BT$2:$CA$2,$BT10:$CA10,0) -> 0 | DC10: =CS10*_xlfn.XLOOKUP(DC$1,$BT$2:$CA$2,$BT10:$CA10,0) -> 0 | DD10: =CT10*_xlfn.XLOOKUP(DD$1,$BT$2:$CA$2,$BT10:$CA10,0) -> 0 | DE10: =CU10*_xlfn.XLOOKUP(DE$1,$BT$2:$CA$2,$BT10:$CA10,0) -> 0 | DF10: =CV10*_xlfn.XLOOKUP(DF$1,$BT$2:$CA$2,$BT10:$CA10,0) -> 0 | DH10: =$CN10*_xlfn.XLOOKUP(DH$1,$BT$2:$CA$2,$BT10:$CA10,0) -> 0 | DI10: =$CO10*_xlfn.XLOOKUP(DI$1,$BT$2:$CA$2,$BT10:$CA10,0) -> 0 | DJ10: =$CP10*_xlfn.XLOOKUP(DJ$1,$BT$2:$CA$2,$BT10:$CA10,0) -> 0 | DK10: =$CQ10*_xlfn.XLOOKUP(DK$1,$BT$2:$CA$2,$BT10:$CA10,0) -> 0 | DL10: =$CR10*_xlfn.XLOOKUP(DL$1,$BT$2:$CA$2,$BT10:$CA10,0) -> 0 | DM10: =$CS10*_xlfn.XLOOKUP(DM$1,$BT$2:$CA$2,$BT10:$CA10,0) -> 0 | DN10: =$CT10*_xlfn.XLOOKUP(DN$1,$BT$2:$CA$2,$BT10:$CA10,0) -> 0 | DO10: =$CU10*_xlfn.XLOOKUP(DO$1,$BT$2:$CA$2,$BT10:$CA10,0) -> 0 | DP10: =$CV10*_xlfn.XLOOKUP(DP$1,$BT$2:$CA$2,$BT10:$CA10,0) -> 0 | DR10: =$CN10*_xlfn.XLOOKUP(DR$1,$BT$2:$CA$2,$BT10:$CA10,0) -> 0 | DS10: =$CO10*_xlfn.XLOOKUP(DS$1,$BT$2:$CA$2,$BT10:$CA10,0) -> 0 | DT10: =$CP10*_xlfn.XLOOKUP(DT$1,$BT$2:$CA$2,$BT10:$CA10,0) -> 0 | DU10: =$CQ10*_xlfn.XLOOKUP(DU$1,$BT$2:$CA$2,$BT10:$CA10,0) -> 0 | DV10: =$CR10*_xlfn.XLOOKUP(DV$1,$BT$2:$CA$2,$BT10:$CA10,0) -> 0 | DW10: =$CS10*_xlfn.XLOOKUP(DW$1,$BT$2:$CA$2,$BT10:$CA10,0) -> 0 | DX10: =$CT10*_xlfn.XLOOKUP(DX$1,$BT$2:$CA$2,$BT10:$CA10,0) -> 0 | DY10: =$CU10*_xlfn.XLOOKUP(DY$1,$BT$2:$CA$2,$BT10:$CA10,0) -> 0 | DZ10: =$CV10*_xlfn.XLOOKUP(DZ$1,$BT$2:$CA$2,$BT10:$CA10,0) -> 0 | EB10: =$CN10*_xlfn.XLOOKUP(EB$1,$BT$2:$CA$2,$BT10:$CA10,0) -> 0 | EC10: =$CO10*_xlfn.XLOOKUP(EC$1,$BT$2:$CA$2,$BT10:$CA10,0) -> 0 | ED10: =$CP10*_xlfn.XLOOKUP(ED$1,$BT$2:$CA$2,$BT10:$CA10,0) -> 0 | EE10: =$CQ10*_xlfn.XLOOKUP(EE$1,$BT$2:$CA$2,$BT10:$CA10,0) -> 0 | EF10: =$CR10*_xlfn.XLOOKUP(EF$1,$BT$2:$CA$2,$BT10:$CA10,0) -> 0 | EG10: =$CS10*_xlfn.XLOOKUP(EG$1,$BT$2:$CA$2,$BT10:$CA10,0) -> 0 | EH10: =$CT10*_xlfn.XLOOKUP(EH$1,$BT$2:$CA$2,$BT10:$CA10,0) -> 0 | EI10: =$CU10*_xlfn.XLOOKUP(EI$1,$BT$2:$CA$2,$BT10:$CA10,0) -> 0 | EJ10: =$CV10*_xlfn.XLOOKUP(EJ$1,$BT$2:$CA$2,$BT10:$CA10,0) -> 0 | EL10: =$CN10*_xlfn.XLOOKUP(EL$1,$BT$2:$CA$2,$BT10:$CA10,0) -> 0 | EM10: =$CO10*_xlfn.XLOOKUP(EM$1,$BT$2:$CA$2,$BT10:$CA10,0) -> 0 | EN10: =$CP10*_xlfn.XLOOKUP(EN$1,$BT$2:$CA$2,$BT10:$CA10,0) -> 0 | EO10: =$CQ10*_xlfn.XLOOKUP(EO$1,$BT$2:$CA$2,$BT10:$CA10,0) -> 0 | EP10: =$CR10*_xlfn.XLOOKUP(EP$1,$BT$2:$CA$2,$BT10:$CA10,0) -> 0 | EQ10: =$CS10*_xlfn.XLOOKUP(EQ$1,$BT$2:$CA$2,$BT10:$CA10,0) -> 0 | ER10: =$CT10*_xlfn.XLOOKUP(ER$1,$BT$2:$CA$2,$BT10:$CA10,0) -> 0 | ES10: =$CU10*_xlfn.XLOOKUP(ES$1,$BT$2:$CA$2,$BT10:$CA10,0) -> 0 | ET10: =$CV10*_xlfn.XLOOKUP(ET$1,$BT$2:$CA$2,$BT10:$CA10,0) -> 0 | EV10: =$CN10*_xlfn.XLOOKUP(EV$1,$BT$2:$CA$2,$BT10:$CA10,0) -> 0 | EW10: =$CO10*_xlfn.XLOOKUP(EW$1,$BT$2:$CA$2,$BT10:$CA10,0) -> 0 | EX10: =$CP10*_xlfn.XLOOKUP(EX$1,$BT$2:$CA$2,$BT10:$CA10,0) -> 0 | EY10: =$CQ10*_xlfn.XLOOKUP(EY$1,$BT$2:$CA$2,$BT10:$CA10,0) -> 0 | EZ10: =$CR10*_xlfn.XLOOKUP(EZ$1,$BT$2:$CA$2,$BT10:$CA10,0) -> 0 | FA10: =$CS10*_xlfn.XLOOKUP(FA$1,$BT$2:$CA$2,$BT10:$CA10,0) -> 0 | FB10: =$CT10*_xlfn.XLOOKUP(FB$1,$BT$2:$CA$2,$BT10:$CA10,0) -> 0 | FC10: =$CU10*_xlfn.XLOOKUP(FC$1,$BT$2:$CA$2,$BT10:$CA10,0) -> 0 | FD10: =$CV10*_xlfn.XLOOKUP(FD$1,$BT$2:$CA$2,$BT10:$CA10,0) -> 0 | FF10: =$CN10*_xlfn.XLOOKUP(FF$1,$BT$2:$CA$2,$BT10:$CA10,0) -> 0 | FG10: =$CO10*_xlfn.XLOOKUP(FG$1,$BT$2:$CA$2,$BT10:$CA10,0) -> 0 | FH10: =$CP10*_xlfn.XLOOKUP(FH$1,$BT$2:$CA$2,$BT10:$CA10,0) -> 0 | FI10: =$CQ10*_xlfn.XLOOKUP(FI$1,$BT$2:$CA$2,$BT10:$CA10,0) -> 0 | FJ10: =$CR10*_xlfn.XLOOKUP(FJ$1,$BT$2:$CA$2,$BT10:$CA10,0) -> 0 | FK10: =$CS10*_xlfn.XLOOKUP(FK$1,$BT$2:$CA$2,$BT10:$CA10,0) -> 0 | FL10: =$CT10*_xlfn.XLOOKUP(FL$1,$BT$2:$CA$2,$BT10:$CA10,0) -> 0 | FM10: =$CU10*_xlfn.XLOOKUP(FM$1,$BT$2:$CA$2,$BT10:$CA10,0) -> 0 | FN10: =$CV10*_xlfn.XLOOKUP(FN$1,$BT$2:$CA$2,$BT10:$CA10,0) -> 0 | FP10: =$CN10*_xlfn.XLOOKUP(FP$1,$BT$2:$CA$2,$BT10:$CA10,0) -> #REF! | FQ10: =$CO10*_xlfn.XLOOKUP(FQ$1,$BT$2:$CA$2,$BT10:$CA10,0) -> #REF! | FR10: =$CP10*_xlfn.XLOOKUP(FR$1,$BT$2:$CA$2,$BT10:$CA10,0) -> #REF! | FS10: =$CQ10*_xlfn.XLOOKUP(FS$1,$BT$2:$CA$2,$BT10:$CA10,0) -> #REF! | FT10: =$CR10*_xlfn.XLOOKUP(FT$1,$BT$2:$CA$2,$BT10:$CA10,0) -> #REF! | FU10: =$CS10*_xlfn.XLOOKUP(FU$1,$BT$2:$CA$2,$BT10:$CA10,0) -> #REF! | FV10: =$CT10*_xlfn.XLOOKUP(FV$1,$BT$2:$CA$2,$BT10:$CA10,0) -> #REF! | FW10: =$CU10*_xlfn.XLOOKUP(FW$1,$BT$2:$CA$2,$BT10:$CA10,0) -> #REF! | FX10: =$CV10*_xlfn.XLOOKUP(FX$1,$BT$2:$CA$2,$BT10:$CA10,0) -> #REF! | GB10: =IF(GB$2=InputTable[[#This Row],[Delivery Date]],_xlfn.XLOOKUP(GB$1,$BH$2:$BR$2,$BH10:$BR10,0),0) -> #REF! | GC10: =IF(GC$2=InputTable[[#This Row],[Delivery Date]],_xlfn.XLOOKUP(GC$1,$BH$2:$BR$2,$BH10:$BR10,0),0) -> 0 | GD10: =IF(GD$2=InputTable[[#This Row],[Delivery Date]],_xlfn.XLOOKUP(GD$1,$BH$2:$BR$2,$BH10:$BR10,0),0) -> 0 | GE10: =IF(GE$2=InputTable[[#This Row],[Delivery Date]],_xlfn.XLOOKUP(GE$1,$BH$2:$BR$2,$BH10:$BR10,0),0) -> 0 | GF10: =IF(GF$2=InputTable[[#This Row],[Delivery Date]],_xlfn.XLOOKUP(GF$1,$BH$2:$BR$2,$BH10:$BR10,0),0) -> 0 | GG10: =IF(GG$2=InputTable[[#This Row],[Delivery Date]],_xlfn.XLOOKUP(GG$1,$BH$2:$BR$2,$BH10:$BR10,0),0) -> 0 | GH10: =IF(GH$2=InputTable[[#This Row],[Delivery Date]],_xlfn.XLOOKUP(GH$1,$BH$2:$BR$2,$BH10:$BR10,0),0) -> 0 | GI10: =IF(GI$2=InputTable[[#This Row],[Delivery Date]],_xlfn.XLOOKUP(GI$1,$BH$2:$BR$2,$BH10:$BR10,0),0) -> 0 | GJ10: =IF(GJ$2=InputTable[[#This Row],[Delivery Date]],_xlfn.XLOOKUP(GJ$1,$BH$2:$BR$2,$BH10:$BR10,0),0) -> 0 | GL10: =IF(GL$2=InputTable[[#This Row],[Delivery Date]],_xlfn.XLOOKUP(GL$1,$BH$2:$BR$2,$BH10:$BR10,0),0) -> #REF! | GM10: =IF(GM$2=InputTable[[#This Row],[Delivery Date]],_xlfn.XLOOKUP(GM$1,$BH$2:$BR$2,$BH10:$BR10,0),0) -> 0 | GN10: =IF(GN$2=InputTable[[#This Row],[Delivery Date]],_xlfn.XLOOKUP(GN$1,$BH$2:$BR$2,$BH10:$BR10,0),0) -> 0 | GO10: =IF(GO$2=InputTable[[#This Row],[Delivery Date]],_xlfn.XLOOKUP(GO$1,$BH$2:$BR$2,$BH10:$BR10,0),0) -> 0 | GP10: =IF(GP$2=InputTable[[#This Row],[Delivery Date]],_xlfn.XLOOKUP(GP$1,$BH$2:$BR$2,$BH10:$BR10,0),0) -> 0 | GQ10: =IF(GQ$2=InputTable[[#This Row],[Delivery Date]],_xlfn.XLOOKUP(GQ$1,$BH$2:$BR$2,$BH10:$BR10,0),0) -> 0 | GR10: =IF(GR$2=InputTable[[#This Row],[Delivery Date]],_xlfn.XLOOKUP(GR$1,$BH$2:$BR$2,$BH10:$BR10,0),0) -> 0 | GS10: =IF(GS$2=InputTable[[#This Row],[Delivery Date]],_xlfn.XLOOKUP(GS$1,$BH$2:$BR$2,$BH10:$BR10,0),0) -> 0 | GT10: =IF(GT$2=InputTable[[#This Row],[Delivery Date]],_xlfn.XLOOKUP(GT$1,$BH$2:$BR$2,$BH10:$BR10,0),0) -> 0 | GV10: =IF(GV$2=InputTable[[#This Row],[Delivery Date]],_xlfn.XLOOKUP(GV$1,$BH$2:$BR$2,$BH10:$BR10,0),0) -> #REF! | GW10: =IF(GW$2=InputTable[[#This Row],[Delivery Date]],_xlfn.XLOOKUP(GW$1,$BH$2:$BR$2,$BH10:$BR10,0),0) -> 0 | GX10: =IF(GX$2=InputTable[[#This Row],[Delivery Date]],_xlfn.XLOOKUP(GX$1,$BH$2:$BR$2,$BH10:$BR10,0),0) -> 0 | GY10: =IF(GY$2=InputTable[[#This Row],[Delivery Date]],_xlfn.XLOOKUP(GY$1,$BH$2:$BR$2,$BH10:$BR10,0),0) -> 0 | GZ10: =IF(GZ$2=InputTable[[#This Row],[Delivery Date]],_xlfn.XLOOKUP(GZ$1,$BH$2:$BR$2,$BH10:$BR10,0),0) -> 0 | HA10: =IF(HA$2=InputTable[[#This Row],[Delivery Date]],_xlfn.XLOOKUP(HA$1,$BH$2:$BR$2,$BH10:$BR10,0),0) -> 0 | HB10: =IF(HB$2=InputTable[[#This Row],[Delivery Date]],_xlfn.XLOOKUP(HB$1,$BH$2:$BR$2,$BH10:$BR10,0),0) -> 0 | HC10: =IF(HC$2=InputTable[[#This Row],[Delivery Date]],_xlfn.XLOOKUP(HC$1,$BH$2:$BR$2,$BH10:$BR10,0),0) -> 0 | HD10: =IF(HD$2=InputTable[[#This Row],[Delivery Date]],_xlfn.XLOOKUP(HD$1,$BH$2:$BR$2,$BH10:$BR10,0),0) -> 0 | HF10: =IF(HF$2=InputTable[[#This Row],[Delivery Date]],_xlfn.XLOOKUP(HF$1,$BH$2:$BR$2,$BH10:$BR10,0),0) -> #REF! | HG10: =IF(HG$2=InputTable[[#This Row],[Delivery Date]],_xlfn.XLOOKUP(HG$1,$BH$2:$BR$2,$BH10:$BR10,0),0) -> 0 | HH10: =IF(HH$2=InputTable[[#This Row],[Delivery Date]],_xlfn.XLOOKUP(HH$1,$BH$2:$BR$2,$BH10:$BR10,0),0) -> 0 | HI10: =IF(HI$2=InputTable[[#This Row],[Delivery Date]],_xlfn.XLOOKUP(HI$1,$BH$2:$BR$2,$BH10:$BR10,0),0) -> 0 | HJ10: =IF(HJ$2=InputTable[[#This Row],[Delivery Date]],_xlfn.XLOOKUP(HJ$1,$BH$2:$BR$2,$BH10:$BR10,0),0) -> 0 | HK10: =IF(HK$2=InputTable[[#This Row],[Delivery Date]],_xlfn.XLOOKUP(HK$1,$BH$2:$BR$2,$BH10:$BR10,0),0) -> 0 | HL10: =IF(HL$2=InputTable[[#This Row],[Delivery Date]],_xlfn.XLOOKUP(HL$1,$BH$2:$BR$2,$BH10:$BR10,0),0) -> 0 | HM10: =IF(HM$2=InputTable[[#This Row],[Delivery Date]],_xlfn.XLOOKUP(HM$1,$BH$2:$BR$2,$BH10:$BR10,0),0) -> 0 | HN10: =IF(HN$2=InputTable[[#This Row],[Delivery Date]],_xlfn.XLOOKUP(HN$1,$BH$2:$BR$2,$BH10:$BR10,0),0) -> 0 | HP10: =IF(HP$2=InputTable[[#This Row],[Delivery Date]],_xlfn.XLOOKUP(HP$1,$BH$2:$BR$2,$BH10:$BR10,0),0) -> #REF! | HQ10: =IF(HQ$2=InputTable[[#This Row],[Delivery Date]],_xlfn.XLOOKUP(HQ$1,$BH$2:$BR$2,$BH10:$BR10,0),0) -> 0 | HR10: =IF(HR$2=InputTable[[#This Row],[Delivery Date]],_xlfn.XLOOKUP(HR$1,$BH$2:$BR$2,$BH10:$BR10,0),0) -> 0 | HS10: =IF(HS$2=InputTable[[#This Row],[Delivery Date]],_xlfn.XLOOKUP(HS$1,$BH$2:$BR$2,$BH10:$BR10,0),0) -> 0 | HT10: =IF(HT$2=InputTable[[#This Row],[Delivery Date]],_xlfn.XLOOKUP(HT$1,$BH$2:$BR$2,$BH10:$BR10,0),0) -> 0 | HU10: =IF(HU$2=InputTable[[#This Row],[Delivery Date]],_xlfn.XLOOKUP(HU$1,$BH$2:$BR$2,$BH10:$BR10,0),0) -> 0 | HV10: =IF(HV$2=InputTable[[#This Row],[Delivery Date]],_xlfn.XLOOKUP(HV$1,$BH$2:$BR$2,$BH10:$BR10,0),0) -> 0 | HW10: =IF(HW$2=InputTable[[#This Row],[Delivery Date]],_xlfn.XLOOKUP(HW$1,$BH$2:$BR$2,$BH10:$BR10,0),0) -> 0 | HX10: =IF(HX$2=InputTable[[#This Row],[Delivery Date]],_xlfn.XLOOKUP(HX$1,$BH$2:$BR$2,$BH10:$BR10,0),0) -> 0 | HZ10: =IF(HZ$2=InputTable[[#This Row],[Delivery Date]],_xlfn.XLOOKUP(HZ$1,$BH$2:$BR$2,$BH10:$BR10,0),0) -> #REF! | IA10: =IF(IA$2=InputTable[[#This Row],[Delivery Date]],_xlfn.XLOOKUP(IA$1,$BH$2:$BR$2,$BH10:$BR10,0),0) -> 0 | IB10: =IF(IB$2=InputTable[[#This Row],[Delivery Date]],_xlfn.XLOOKUP(IB$1,$BH$2:$BR$2,$BH10:$BR10,0),0) -> 0 | IC10: =IF(IC$2=InputTable[[#This Row],[Delivery Date]],_xlfn.XLOOKUP(IC$1,$BH$2:$BR$2,$BH10:$BR10,0),0) -> 0 | ID10: =IF(ID$2=InputTable[[#This Row],[Delivery Date]],_xlfn.XLOOKUP(ID$1,$BH$2:$BR$2,$BH10:$BR10,0),0) -> 0 | IE10: =IF(IE$2=InputTable[[#This Row],[Delivery Date]],_xlfn.XLOOKUP(IE$1,$BH$2:$BR$2,$BH10:$BR10,0),0) -> 0 | IF10: =IF(IF$2=InputTable[[#This Row],[Delivery Date]],_xlfn.XLOOKUP(IF$1,$BH$2:$BR$2,$BH10:$BR10,0),0) -> 0 | IG10: =IF(IG$2=InputTable[[#This Row],[Delivery Date]],_xlfn.XLOOKUP(IG$1,$BH$2:$BR$2,$BH10:$BR10,0),0) -> 0 | IH10: =IF(IH$2=InputTable[[#This Row],[Delivery Date]],_xlfn.XLOOKUP(IH$1,$BH$2:$BR$2,$BH10:$BR10,0),0) -> 0 | IJ10: =IF(IJ$2=InputTable[[#This Row],[Delivery Date]],_xlfn.XLOOKUP(IJ$1,$BH$2:$BR$2,$BH10:$BR10,0),0) -> #REF! | IK10: =IF(IK$2=InputTable[[#This Row],[Delivery Date]],_xlfn.XLOOKUP(IK$1,$BH$2:$BR$2,$BH10:$BR10,0),0) -> 0 | IL10: =IF(IL$2=InputTable[[#This Row],[Delivery Date]],_xlfn.XLOOKUP(IL$1,$BH$2:$BR$2,$BH10:$BR10,0),0) -> 0 | IM10: =IF(IM$2=InputTable[[#This Row],[Delivery Date]],_xlfn.XLOOKUP(IM$1,$BH$2:$BR$2,$BH10:$BR10,0),0) -> 0 | IN10: =IF(IN$2=InputTable[[#This Row],[Delivery Date]],_xlfn.XLOOKUP(IN$1,$BH$2:$BR$2,$BH10:$BR10,0),0) -> 0 | IO10: =IF(IO$2=InputTable[[#This Row],[Delivery Date]],_xlfn.XLOOKUP(IO$1,$BH$2:$BR$2,$BH10:$BR10,0),0) -> 0 | IP10: =IF(IP$2=InputTable[[#This Row],[Delivery Date]],_xlfn.XLOOKUP(IP$1,$BH$2:$BR$2,$BH10:$BR10,0),0) -> 0 | IQ10: =IF(IQ$2=InputTable[[#This Row],[Delivery Date]],_xlfn.XLOOKUP(IQ$1,$BH$2:$BR$2,$BH10:$BR10,0),0) -> 0 | IR10: =IF(IR$2=InputTable[[#This Row],[Delivery Date]],_xlfn.XLOOKUP(IR$1,$BH$2:$BR$2,$BH10:$BR10,0),0) -> 0 | IT10: =IF(IT$2=InputTable[[#This Row],[Delivery Date]],_xlfn.XLOOKUP(IT$1,$BH$2:$BR$2,$BH10:$BR10,0),0) -> #REF! | IU10: =IF(IU$2=InputTable[[#This Row],[Delivery Date]],_xlfn.XLOOKUP(IU$1,$BH$2:$BR$2,$BH10:$BR10,0),0) -> 0 | IV10: =IF(IV$2=InputTable[[#This Row],[Delivery Date]],_xlfn.XLOOKUP(IV$1,$BH$2:$BR$2,$BH10:$BR10,0),0) -> 0 | IW10: =IF(IW$2=InputTable[[#This Row],[Delivery Date]],_xlfn.XLOOKUP(IW$1,$BH$2:$BR$2,$BH10:$BR10,0),0) -> 0 | IX10: =IF(IX$2=InputTable[[#This Row],[Delivery Date]],_xlfn.XLOOKUP(IX$1,$BH$2:$BR$2,$BH10:$BR10,0),0) -> 0 | IY10: =IF(IY$2=InputTable[[#This Row],[Delivery Date]],_xlfn.XLOOKUP(IY$1,$BH$2:$BR$2,$BH10:$BR10,0),0) -> 0 | IZ10: =IF(IZ$2=InputTable[[#This Row],[Delivery Date]],_xlfn.XLOOKUP(IZ$1,$BH$2:$BR$2,$BH10:$BR10,0),0) -> 0 | JA10: =IF(JA$2=InputTable[[#This Row],[Delivery Date]],_xlfn.XLOOKUP(JA$1,$BH$2:$BR$2,$BH10:$BR10,0),0) -> 0 | JB10: =IF(JB$2=InputTable[[#This Row],[Delivery Date]],_xlfn.XLOOKUP(JB$1,$BH$2:$BR$2,$BH10:$BR10,0),0) -> 0 | JD10: =IF(JD$2=InputTable[[#This Row],[Delivery Date]],_xlfn.XLOOKUP(JD$1,$BH$2:$BR$2,$BH10:$BR10,0),0) -> #REF! | JE10: =IF(JE$2=InputTable[[#This Row],[Delivery Date]],_xlfn.XLOOKUP(JE$1,$BH$2:$BR$2,$BH10:$BR10,0),0) -> 0 | JF10: =IF(JF$2=InputTable[[#This Row],[Delivery Date]],_xlfn.XLOOKUP(JF$1,$BH$2:$BR$2,$BH10:$BR10,0),0) -> 0 | JG10: =IF(JG$2=InputTable[[#This Row],[Delivery Date]],_xlfn.XLOOKUP(JG$1,$BH$2:$BR$2,$BH10:$BR10,0),0) -> 0 | JH10: =IF(JH$2=InputTable[[#This Row],[Delivery Date]],_xlfn.XLOOKUP(JH$1,$BH$2:$BR$2,$BH10:$BR10,0),0) -> 0 | JI10: =IF(JI$2=InputTable[[#This Row],[Delivery Date]],_xlfn.XLOOKUP(JI$1,$BH$2:$BR$2,$BH10:$BR10,0),0) -> 0 | JJ10: =IF(JJ$2=InputTable[[#This Row],[Delivery Date]],_xlfn.XLOOKUP(JJ$1,$BH$2:$BR$2,$BH10:$BR10,0),0) -> 0 | JK10: =IF(JK$2=InputTable[[#This Row],[Delivery Date]],_xlfn.XLOOKUP(JK$1,$BH$2:$BR$2,$BH10:$BR10,0),0) -> 0 | JL10: =IF(JL$2=InputTable[[#This Row],[Delivery Date]],_xlfn.XLOOKUP(JL$1,$BH$2:$BR$2,$BH10:$BR10,0),0) -> 0 | JN10: =IF(JN$2=InputTable[[#This Row],[Delivery Date]],_xlfn.XLOOKUP(JN$1,$BH$2:$BR$2,$BH10:$BR10,0),0) -> #REF! | JO10: =IF(JO$2=InputTable[[#This Row],[Delivery Date]],_xlfn.XLOOKUP(JO$1,$BH$2:$BR$2,$BH10:$BR10,0),0) -> 0 | JP10: =IF(JP$2=InputTable[[#This Row],[Delivery Date]],_xlfn.XLOOKUP(JP$1,$BH$2:$BR$2,$BH10:$BR10,0),0) -> 0 | JQ10: =IF(JQ$2=InputTable[[#This Row],[Delivery Date]],_xlfn.XLOOKUP(JQ$1,$BH$2:$BR$2,$BH10:$BR10,0),0) -> 0 | JR10: =IF(JR$2=InputTable[[#This Row],[Delivery Date]],_xlfn.XLOOKUP(JR$1,$BH$2:$BR$2,$BH10:$BR10,0),0) -> 0 | JS10: =IF(JS$2=InputTable[[#This Row],[Delivery Date]],_xlfn.XLOOKUP(JS$1,$BH$2:$BR$2,$BH10:$BR10,0),0) -> 0 | JT10: =IF(JT$2=InputTable[[#This Row],[Delivery Date]],_xlfn.XLOOKUP(JT$1,$BH$2:$BR$2,$BH10:$BR10,0),0) -> 0 | JU10: =IF(JU$2=InputTable[[#This Row],[Delivery Date]],_xlfn.XLOOKUP(JU$1,$BH$2:$BR$2,$BH10:$BR10,0),0) -> 0 | JV10: =IF(JV$2=InputTable[[#This Row],[Delivery Date]],_xlfn.XLOOKUP(JV$1,$BH$2:$BR$2,$BH10:$BR10,0),0) -> 0 | JX10: =IF(JX$2=InputTable[[#This Row],[Delivery Date]],_xlfn.XLOOKUP(JX$1,$BH$2:$BR$2,$BH10:$BR10,0),0) -> #REF! | JY10: =IF(JY$2=InputTable[[#This Row],[Delivery Date]],_xlfn.XLOOKUP(JY$1,$BH$2:$BR$2,$BH10:$BR10,0),0) -> 0 | JZ10: =IF(JZ$2=InputTable[[#This Row],[Delivery Date]],_xlfn.XLOOKUP(JZ$1,$BH$2:$BR$2,$BH10:$BR10,0),0) -> 0 | KA10: =IF(KA$2=InputTable[[#This Row],[Delivery Date]],_xlfn.XLOOKUP(KA$1,$BH$2:$BR$2,$BH10:$BR10,0),0) -> 0 | KB10: =IF(KB$2=InputTable[[#This Row],[Delivery Date]],_xlfn.XLOOKUP(KB$1,$BH$2:$BR$2,$BH10:$BR10,0),0) -> 0 | KC10: =IF(KC$2=InputTable[[#This Row],[Delivery Date]],_xlfn.XLOOKUP(KC$1,$BH$2:$BR$2,$BH10:$BR10,0),0) -> 0 | KD10: =IF(KD$2=InputTable[[#This Row],[Delivery Date]],_xlfn.XLOOKUP(KD$1,$BH$2:$BR$2,$BH10:$BR10,0),0) -> 0 | KE10: =IF(KE$2=InputTable[[#This Row],[Delivery Date]],_xlfn.XLOOKUP(KE$1,$BH$2:$BR$2,$BH10:$BR10,0),0) -> 0 | KF10: =IF(KF$2=InputTable[[#This Row],[Delivery Date]],_xlfn.XLOOKUP(KF$1,$BH$2:$BR$2,$BH10:$BR10,0),0) -> 0
